Workbook

Sheet original
A1: Une fois les chiffres extraits dans un CSV à l'aide de Tabula, on met le CSV sur Google Drive afin de l'ouvrir avec Google Sheets. Une fois ouvert dans le premier onglet, deux étapes: 1. Je renomme l'onglet pour clarifier que ce sont les données d'origine (que je ne vais pas toucher) 2. Je change l'affichage du texte pour qu'il s'adapte à la taille des cellules et qu'il y ait un retour à la ligne. Cela facilite une exploration visuelle des données. 3. Dès cette étape, si les montants présents dans la colonne B sont reconnus comme des chiffres, je peux vérifier que le total correspond au PDF source. A noter: vous ne savez jamais si le PDF originel sera toujours à l'adresse où vous l'avez trouvé. Il vaut mieux donc le mettre dans le même dossier Google Drive que le CSV, de façon à avoir tous vos documents source au même endroit.
A2: "BAMBINO BERTHELOT" ASSOCIATION DE PARENTS D'ELEVES DE | B2: 0,00 | C2: Locaux
A3: L'ECOLE MATERNELLE BERTHELOT A BORDEAUX
A4: 1001 JEUNES BORDELAIS | B4: 0,00 | C4: Matériel pour manifestations
A5: 2AA | B5: 0,00 | C5: Locaux
A6: 2SI2LA | B6: 0,00 | C6: Locaux
A7: 4 CATS | B7: 0,00 | C7: Locaux
A8: 5UN7 | B8: 1 000,00
A9: 60 000 REBONDS | B9: 1 800,00
A10: 9-33 | B10: 19 000,00 | C10: Communication, locaux
A11: A L EAU MUSIC | B11: 500,00
A12: A PART ENTIERE | B12: 2 000,00
A13: A PETIT PAS | B13: 3 000,00
A14: A TRAVERS CHANT | B14: 0,00 | C14: Locaux
A15: A2RUNNING | B15: 0,00 | C15: Locaux
A16: ABALONE CHASSE BORDEAUX | B16: 0,00 | C16: Locaux, équipements sportifs
A17: ABEILLES BORDELAISES | B17: 0,00 | C17: Locaux
A18: ACADEMIE BUSHIKAI KARATE DO | B18: 0,00 | C18: Equipements sportifs
A19: ACADEMIE DES SCIENCES, BELLES LETTRES ET ARTS DE | B19: 7 600,00 | C19: Locaux, matériel pour manifestations
A20: BORDEAUX
A21: ACADEMIE PROSPECTIVE NOUVELLES TECHNOLOGIES | B21: 0,00 | C21: Locaux
A22: ACADEMIE YOUNUS | B22: 22 000,00 | C22: Locaux, équipements sportifs, matériel pour
C23: manifestations
A24: ACCOMPAGNEMENT ET RECHERCHE PSYCHO-SOCIO EDUCATIFS | B24: 0,00 | C24: Locaux
A25: POUR LES JEUNES (ARPEJE)
A26: ACCOMPAGNEMENT PSYCHOLOGIQUE ET MEDIATION | B26: 5 000,00
A27: INTERCULTURELLE - AMI
A28: ACCOMPAGNER CONDUIRE TRANSMETTRE - ACT | B28: 300,00 | C28: Locaux
A29: ACCORDERIE BORDEAUX SUD | B29: 4 500,00 | C29: Locaux
A30: ACHATS GROUPES ASSOCIATIF POUR L'ECONOMIE SOLIDAIRE DE | B30: 0,00 | C30: Locaux
A31: BORDEAUX - AGAPES
A32: ACIDD, ASSOCIATION COMMUNICATION ET INFORMATION POUR LE | B32: 10 000,00 | C32: Locaux
A33: DEVELOPPEMENT DURABLE
A34: ACINQBYS_ESPACE 29 A5BIS | B34: 22 000,00
A35: ACTA GIRONDE - AGIR CONTRE LA TORTURE DES ANIMAUX | B35: 0,00 | C35: Locaux
A36: ACTIFS 33 | B36: 2 400,00
A37: ACTIMAGE | B37: 6 500,00
A38: ACTION CONTRE LA FAIM | B38: 0,00 | C38: Locaux
A39: ACTION INTERNATIONALE POUR LA PAIX ET LE DEVELOPPEMENT | B39: 0,00 | C39: Locaux
A40: AD LUCEM THEATRE | B40: 0,00 | C40: Locaux
A41: ADDAH 33 | B41: 500,00
A42: ADORA | B42: 5 000,00 | C42: Locaux
A43: ADRIA | B43: 1 500,00
A44: AEP SAINT PROJET | B44: 0,00 | C44: Matériel pour manifestations
A45: AFRICAFRANCE | B45: 1 500,00
A46: AGENCE D'URBANISME BORDEAUX METROPOLE AQUITAINE | B46: 60 000,00
A47: (A'URBA)
A48: AGENCE LOCALE DE L'ENERGIE ET DU CLIMAT (ALEC) | B48: 6 000,00 | C48: Locaux
A49: AGENCE REGIONALE DE SANTE NOUVELLE AQUITAINE | B49: 0,00 | C49: Matériel pour manifestations
A50: AGIR POUR UN COMMERE EQUITABLE ET SOLIDAIRE EN AQUITAINE - | B50: 500,00
A51: ACESA
A52: AGORA DES ARTS | B52: 5 000,00 | C52: Matériel pour manifestations
A53: AIDE AUX AIDANTS DU PAVILLON | B53: 2 000,00
A54: AIDES AQUITAINE | B54: 5 500,00
A55: AIGUILLES ET CALAME | B55: 0,00 | C55: Locaux
A56: AIKIDO BORDEAUX BASTIDE | B56: 2 000,00 | C56: Equipements sportifs
A57: AIM ACTIONS INTER MEDIATION | B57: 20 060,00
A58: AIR ROLLER (ATTENTION INERTIE RENOUVELABLE) | B58: 11 000,00 | C58: Locaux, équipements sportifs
A59: ALAM AMIS DU LIVRE ANCIEN ET MODERNE | B59: 0,00 | C59: Locaux, matériel pour manifestations
A60: ALGERIENS DE L'AQUITAINE | B60: 0,00 | C60: Locaux
A61: ALLIANCE DEPARTEMENT 33, JUSQU'AU BOUT ACCOMPAGNER LA | B61: 4 500,00 | C61: Locaux
A62: VIE...
A63: ALLIANCE FRANCAISE DE BORDEAUX AQUITAINE | B63: 0,00 | C63: Locaux
A64: ALPTIS | B64: 0,00 | C64: Locaux
A65: ALTER INSERTION | B65: 0,00 | C65: Matériel pour manifestations
A66: AMADEUS | B66: 1 000,00
A67: AMBASSADE REGIONALE DES CONFRERIES DE PRODUITS DE | B67: 500,00
A68: TERROIR ET DU GOUT
A69: AMELIORATION DES CONDITIONS DE VIE DES ENFANTS | B69: 571,00
A70: ADOLESCENTS HOSPITALISES
A71: AMEPI | B71: 0,00 | C71: Locaux
A72: AMICALE BORDELAISE TRACTION AVANT CITROEN | B72: 0,00 | C72: Locaux
A73: AMICALE COMORIENNE DE BORDEAUX | B73: 0,00 | C73: Locaux
A74: AMICALE DE LA RESIDENCE DU LAC | B74: 0,00 | C74: Locaux
A75: AMICALE DES ANCIENS DE LA LEGION ETRANGERE | B75: 1 000,00
A76: AMICALE DES ANCIENS DE MARIE-BRIZARD - AAMB | B76: 0,00 | C76: Locaux
A77: AMICALE DES ANCIENS DES NOUVELLES GALERIES DE BORDEAUX | B77: 0,00 | C77: Locaux
A78: AMICALE DES ANCIENS DES TROUPES DE MARINE DE BORDEAUX ET | B78: 500,00
A79: D'AQUITAINE
A80: AMICALE DES ANCIENS GUERILLEROS ESPAGNOLS EN FRANCE-FFI - | B80: 0,00 | C80: Locaux
A81: SECTION DE LA GIRONDE
A82: AMICALE DES AVEYRONNAIS DE BORDEAUX ET GIRONDE | B82: 0,00 | C82: Locaux
A83: AMICALE DES ETABLISSEMENTS SCOLAIRES LAIQUES DE BACALAN - | B83: 82 238,00 | C83: Locaux, équipements sportifs, matériel pour
A84: ALB | C84: manifestations
A85: AMICALE DES LOCATAIRES DU PORT DE LA LUNE | B85: 4 000,00
A86: AMICALE DES PARACHUTISTES DU SUD-OUEST | B86: 300,00
A87: AMICALE DES PARENTS D'ELEVES DE L'ECOLE STEHELIN | B87: 8 605,00
A88: AMICALE DES PHILIPPEVILLOIS, CONSTANTINOIS ET LEURS AMIS - | B88: 0,00 | C88: Locaux
A89: APCA
A90: AMICALE DES RETRAITES U.G.R.R. - I.S.I.C.A. DE BORDEAUX | B90: 0,00 | C90: Locaux
A91: AMICALE DU PATRONAGE LAIQUE ET DU CONSEIL DE PARENTS | B91: 1 000,00 | C91: Matériel pour manifestations
A92: D'ELEVES DU GROUPE SCOLAIRE NUYENS
A93: AMICALE LAIQUE BORDEAUX CENTRE | B93: 2 500,00 | C93: Locaux, équipements sportifs
A94: AMICALE LAIQUE DAVID JOHNSTON LAGRANGE ALBERT BARRAUD | B94: 450 195,00 | C94: Equipements sportifs
A95: NAUJAC
A96: AMICALE LAIQUE DU GROUPE SCOLAIRE LEONARD-LENOIR - | B96: 0,00 | C96: Equipements sportifs
A97: MONTAUD - NUITS
A98: AMICALE LAIQUE LEONARD LENOIR | B98: 0,00 | C98: Locaux
A99: AMICALE NATIONALE DES RETRAITES DE L'AUDIOVISUEL | B99: 0,00 | C99: Locaux
A100: AMIS D'ARS ET FIDES BORDEAUX | B100: 2 000,00 | C100: Locaux
...

Sheet etape1
A1: Nous voici dans la première étape de transformation des données. Après avoir observé dans les données de départ que certains noms étaient coupés en deux, il s'agit d'identifier l'ampleur du problème. Pour cela nous avons d'abord dupliqué le premier onglet de la feulle de calcul afin de ne pas travailler sur les données originelles. 1. Le nouvel onglet est renommé etape1. 2. On utilise la formule =isblank() dans la colonne D afin d'identifier les cellules vides de la colonne B, qui semblent résulter d'un nom coupé en deux. 3. on applique une mise en forme conditionnelle à la colonne D afin d'identifier visuellement les noms coupés en deux. 4. (optionnel) Dans mon cas, les montants ne sont pas reconnus en tant que chiffres car mon compte est configuré en anglais. Il s'attend donc à voir des chiffres mis en forme à l'anglaise (1,000.00) plutôt qu'à la française (1 000,00). Pour remédier à cela, je fais un simple recherche et remplacer dans la colonne B, en remplaçant les espaces par rien du tout (ce qui les supprime) et en remplaçant les virgules par des points. Cela me permet de vérifier dès cette étape que le montant total correspond bien à celui affiché dans le PDF source.
A2: "BAMBINO BERTHELOT" ASSOCIATION DE PARENTS D'ELEVES DE | B2: 0 | C2: Locaux | D2: =ISBLANK(B2) -> FALSE
A3: L'ECOLE MATERNELLE BERTHELOT A BORDEAUX | D3: =ISBLANK(B3) -> TRUE
A4: 1001 JEUNES BORDELAIS | B4: 0 | C4: Matériel pour manifestations | D4: =ISBLANK(B4) -> FALSE
A5: 2AA | B5: 0 | C5: Locaux | D5: =ISBLANK(B5) -> FALSE
A6: 2SI2LA | B6: 0 | C6: Locaux | D6: =ISBLANK(B6) -> FALSE
A7: 4 CATS | B7: 0 | C7: Locaux | D7: =ISBLANK(B7) -> FALSE
A8: 5UN7 | B8: 1000 | D8: =ISBLANK(B8) -> FALSE
A9: 60 000 REBONDS | B9: 1800 | D9: =ISBLANK(B9) -> FALSE
A10: 9-33 | B10: 19000 | C10: Communication, locaux | D10: =ISBLANK(B10) -> FALSE
A11: A L EAU MUSIC | B11: 500 | D11: =ISBLANK(B11) -> FALSE
A12: A PART ENTIERE | B12: 2000 | D12: =ISBLANK(B12) -> FALSE
A13: A PETIT PAS | B13: 3000 | D13: =ISBLANK(B13) -> FALSE
A14: A TRAVERS CHANT | B14: 0 | C14: Locaux | D14: =ISBLANK(B14) -> FALSE
A15: A2RUNNING | B15: 0 | C15: Locaux | D15: =ISBLANK(B15) -> FALSE
A16: ABALONE CHASSE BORDEAUX | B16: 0 | C16: Locaux, équipements sportifs | D16: =ISBLANK(B16) -> FALSE
A17: ABEILLES BORDELAISES | B17: 0 | C17: Locaux | D17: =ISBLANK(B17) -> FALSE
A18: ACADEMIE BUSHIKAI KARATE DO | B18: 0 | C18: Equipements sportifs | D18: =ISBLANK(B18) -> FALSE
A19: ACADEMIE DES SCIENCES, BELLES LETTRES ET ARTS DE | B19: 7600 | C19: Locaux, matériel pour manifestations | D19: =ISBLANK(B19) -> FALSE
A20: BORDEAUX | D20: =ISBLANK(B20) -> TRUE
A21: ACADEMIE PROSPECTIVE NOUVELLES TECHNOLOGIES | B21: 0 | C21: Locaux | D21: =ISBLANK(B21) -> FALSE
A22: ACADEMIE YOUNUS | B22: 22000 | C22: Locaux, équipements sportifs, matériel pour | D22: =ISBLANK(B22) -> FALSE
C23: manifestations | D23: =ISBLANK(B23) -> TRUE
A24: ACCOMPAGNEMENT ET RECHERCHE PSYCHO-SOCIO EDUCATIFS | B24: 0 | C24: Locaux | D24: =ISBLANK(B24) -> FALSE
A25: POUR LES JEUNES (ARPEJE) | D25: =ISBLANK(B25) -> TRUE
A26: ACCOMPAGNEMENT PSYCHOLOGIQUE ET MEDIATION | B26: 5000 | D26: =ISBLANK(B26) -> FALSE
A27: INTERCULTURELLE - AMI | D27: =ISBLANK(B27) -> TRUE
A28: ACCOMPAGNER CONDUIRE TRANSMETTRE - ACT | B28: 300 | C28: Locaux | D28: =ISBLANK(B28) -> FALSE
A29: ACCORDERIE BORDEAUX SUD | B29: 4500 | C29: Locaux | D29: =ISBLANK(B29) -> FALSE
A30: ACHATS GROUPES ASSOCIATIF POUR L'ECONOMIE SOLIDAIRE DE | B30: 0 | C30: Locaux | D30: =ISBLANK(B30) -> FALSE
A31: BORDEAUX - AGAPES | D31: =ISBLANK(B31) -> TRUE
A32: ACIDD, ASSOCIATION COMMUNICATION ET INFORMATION POUR LE | B32: 10000 | C32: Locaux | D32: =ISBLANK(B32) -> FALSE
A33: DEVELOPPEMENT DURABLE | D33: =ISBLANK(B33) -> TRUE
A34: ACINQBYS_ESPACE 29 A5BIS | B34: 22000 | D34: =ISBLANK(B34) -> FALSE
A35: ACTA GIRONDE - AGIR CONTRE LA TORTURE DES ANIMAUX | B35: 0 | C35: Locaux | D35: =ISBLANK(B35) -> FALSE
A36: ACTIFS 33 | B36: 2400 | D36: =ISBLANK(B36) -> FALSE
A37: ACTIMAGE | B37: 6500 | D37: =ISBLANK(B37) -> FALSE
A38: ACTION CONTRE LA FAIM | B38: 0 | C38: Locaux | D38: =ISBLANK(B38) -> FALSE
A39: ACTION INTERNATIONALE POUR LA PAIX ET LE DEVELOPPEMENT | B39: 0 | C39: Locaux | D39: =ISBLANK(B39) -> FALSE
A40: AD LUCEM THEATRE | B40: 0 | C40: Locaux | D40: =ISBLANK(B40) -> FALSE
A41: ADDAH 33 | B41: 500 | D41: =ISBLANK(B41) -> FALSE
A42: ADORA | B42: 5000 | C42: Locaux | D42: =ISBLANK(B42) -> FALSE
A43: ADRIA | B43: 1500 | D43: =ISBLANK(B43) -> FALSE
A44: AEP SAINT PROJET | B44: 0 | C44: Matériel pour manifestations | D44: =ISBLANK(B44) -> FALSE
A45: AFRICAFRANCE | B45: 1500 | D45: =ISBLANK(B45) -> FALSE
A46: AGENCE D'URBANISME BORDEAUX METROPOLE AQUITAINE | B46: 60000 | D46: =ISBLANK(B46) -> FALSE
A47: (A'URBA) | D47: =ISBLANK(B47) -> TRUE
A48: AGENCE LOCALE DE L'ENERGIE ET DU CLIMAT (ALEC) | B48: 6000 | C48: Locaux | D48: =ISBLANK(B48) -> FALSE
A49: AGENCE REGIONALE DE SANTE NOUVELLE AQUITAINE | B49: 0 | C49: Matériel pour manifestations | D49: =ISBLANK(B49) -> FALSE
A50: AGIR POUR UN COMMERE EQUITABLE ET SOLIDAIRE EN AQUITAINE - | B50: 500 | D50: =ISBLANK(B50) -> FALSE
A51: ACESA | D51: =ISBLANK(B51) -> TRUE
A52: AGORA DES ARTS | B52: 5000 | C52: Matériel pour manifestations | D52: =ISBLANK(B52) -> FALSE
A53: AIDE AUX AIDANTS DU PAVILLON | B53: 2000 | D53: =ISBLANK(B53) -> FALSE
A54: AIDES AQUITAINE | B54: 5500 | D54: =ISBLANK(B54) -> FALSE
A55: AIGUILLES ET CALAME | B55: 0 | C55: Locaux | D55: =ISBLANK(B55) -> FALSE
A56: AIKIDO BORDEAUX BASTIDE | B56: 2000 | C56: Equipements sportifs | D56: =ISBLANK(B56) -> FALSE
A57: AIM ACTIONS INTER MEDIATION | B57: 20060 | D57: =ISBLANK(B57) -> FALSE
A58: AIR ROLLER (ATTENTION INERTIE RENOUVELABLE) | B58: 11000 | C58: Locaux, équipements sportifs | D58: =ISBLANK(B58) -> FALSE
A59: ALAM AMIS DU LIVRE ANCIEN ET MODERNE | B59: 0 | C59: Locaux, matériel pour manifestations | D59: =ISBLANK(B59) -> FALSE
A60: ALGERIENS DE L'AQUITAINE | B60: 0 | C60: Locaux | D60: =ISBLANK(B60) -> FALSE
A61: ALLIANCE DEPARTEMENT 33, JUSQU'AU BOUT ACCOMPAGNER LA | B61: 4500 | C61: Locaux | D61: =ISBLANK(B61) -> FALSE
A62: VIE... | D62: =ISBLANK(B62) -> TRUE
A63: ALLIANCE FRANCAISE DE BORDEAUX AQUITAINE | B63: 0 | C63: Locaux | D63: =ISBLANK(B63) -> FALSE
A64: ALPTIS | B64: 0 | C64: Locaux | D64: =ISBLANK(B64) -> FALSE
A65: ALTER INSERTION | B65: 0 | C65: Matériel pour manifestations | D65: =ISBLANK(B65) -> FALSE
A66: AMADEUS | B66: 1000 | D66: =ISBLANK(B66) -> FALSE
A67: AMBASSADE REGIONALE DES CONFRERIES DE PRODUITS DE | B67: 500 | D67: =ISBLANK(B67) -> FALSE
A68: TERROIR ET DU GOUT | D68: =ISBLANK(B68) -> TRUE
A69: AMELIORATION DES CONDITIONS DE VIE DES ENFANTS | B69: 571 | D69: =ISBLANK(B69) -> FALSE
A70: ADOLESCENTS HOSPITALISES | D70: =ISBLANK(B70) -> TRUE
A71: AMEPI | B71: 0 | C71: Locaux | D71: =ISBLANK(B71) -> FALSE
A72: AMICALE BORDELAISE TRACTION AVANT CITROEN | B72: 0 | C72: Locaux | D72: =ISBLANK(B72) -> FALSE
A73: AMICALE COMORIENNE DE BORDEAUX | B73: 0 | C73: Locaux | D73: =ISBLANK(B73) -> FALSE
A74: AMICALE DE LA RESIDENCE DU LAC | B74: 0 | C74: Locaux | D74: =ISBLANK(B74) -> FALSE
A75: AMICALE DES ANCIENS DE LA LEGION ETRANGERE | B75: 1000 | D75: =ISBLANK(B75) -> FALSE
A76: AMICALE DES ANCIENS DE MARIE-BRIZARD - AAMB | B76: 0 | C76: Locaux | D76: =ISBLANK(B76) -> FALSE
A77: AMICALE DES ANCIENS DES NOUVELLES GALERIES DE BORDEAUX | B77: 0 | C77: Locaux | D77: =ISBLANK(B77) -> FALSE
A78: AMICALE DES ANCIENS DES TROUPES DE MARINE DE BORDEAUX ET | B78: 500 | D78: =ISBLANK(B78) -> FALSE
A79: D'AQUITAINE | D79: =ISBLANK(B79) -> TRUE
A80: AMICALE DES ANCIENS GUERILLEROS ESPAGNOLS EN FRANCE-FFI - | B80: 0 | C80: Locaux | D80: =ISBLANK(B80) -> FALSE
A81: SECTION DE LA GIRONDE | D81: =ISBLANK(B81) -> TRUE
A82: AMICALE DES AVEYRONNAIS DE BORDEAUX ET GIRONDE | B82: 0 | C82: Locaux | D82: =ISBLANK(B82) -> FALSE
A83: AMICALE DES ETABLISSEMENTS SCOLAIRES LAIQUES DE BACALAN - | B83: 82238 | C83: Locaux, équipements sportifs, matériel pour | D83: =ISBLANK(B83) -> FALSE
A84: ALB | C84: manifestations | D84: =ISBLANK(B84) -> TRUE
A85: AMICALE DES LOCATAIRES DU PORT DE LA LUNE | B85: 4000 | D85: =ISBLANK(B85) -> FALSE
A86: AMICALE DES PARACHUTISTES DU SUD-OUEST | B86: 300 | D86: =ISBLANK(B86) -> FALSE
A87: AMICALE DES PARENTS D'ELEVES DE L'ECOLE STEHELIN | B87: 8605 | D87: =ISBLANK(B87) -> FALSE
A88: AMICALE DES PHILIPPEVILLOIS, CONSTANTINOIS ET LEURS AMIS - | B88: 0 | C88: Locaux | D88: =ISBLANK(B88) -> FALSE
A89: APCA | D89: =ISBLANK(B89) -> TRUE
A90: AMICALE DES RETRAITES U.G.R.R. - I.S.I.C.A. DE BORDEAUX | B90: 0 | C90: Locaux | D90: =ISBLANK(B90) -> FALSE
A91: AMICALE DU PATRONAGE LAIQUE ET DU CONSEIL DE PARENTS | B91: 1000 | C91: Matériel pour manifestations | D91: =ISBLANK(B91) -> FALSE
A92: D'ELEVES DU GROUPE SCOLAIRE NUYENS | D92: =ISBLANK(B92) -> TRUE
A93: AMICALE LAIQUE BORDEAUX CENTRE | B93: 2500 | C93: Locaux, équipements sportifs | D93: =ISBLANK(B93) -> FALSE
A94: AMICALE LAIQUE DAVID JOHNSTON LAGRANGE ALBERT BARRAUD | B94: 450195 | C94: Equipements sportifs | D94: =ISBLANK(B94) -> FALSE
A95: NAUJAC | D95: =ISBLANK(B95) -> TRUE
A96: AMICALE LAIQUE DU GROUPE SCOLAIRE LEONARD-LENOIR - | B96: 0 | C96: Equipements sportifs | D96: =ISBLANK(B96) -> FALSE
A97: MONTAUD - NUITS | D97: =ISBLANK(B97) -> TRUE
A98: AMICALE LAIQUE LEONARD LENOIR | B98: 0 | C98: Locaux | D98: =ISBLANK(B98) -> FALSE
A99: AMICALE NATIONALE DES RETRAITES DE L'AUDIOVISUEL | B99: 0 | C99: Locaux | D99: =ISBLANK(B99) -> FALSE
A100: AMIS D'ARS ET FIDES BORDEAUX | B100: 2000 | C100: Locaux | D100: =ISBLANK(B100) -> FALSE
...

Sheet etape2
A1: L'étape précédent nous a fait découvrir l'ampleur du problème. Au vu du nombre de noms affectés, il est nécessaire de passer par des formules pour automatiser la résolution du problème. Notre problème est donc que certains noms sont sur deux lignes. grâce à nos étapes précédentes, on a pu faire apparaitre TRUE (ou VRAI si votre logiciel est en Français) sur la même que la seconde partie de noms coupés en deux. Par conséquent, on sait que si TRUE apparait sur une ligne, on va trouver, sur la même ligne, la deuxième partie d'un nom coupé en deux, et sur la ligne précédente la première partie de ce nom. Cette logique fonctionne pour tous les TRUE, ce qui veut dire qu'on peut l'utiliser pour recréer les noms : Si dans la ligne 10 de la colonne D je trouve TRUE, alors je veux fusionner le contenu de la ligne 9 de la colonne A et de la ligne 10 de la colonne A. En formule, cela donne: IF(D10 = TRUE, CONCATENATE(A9,A10)) Plutôt que d'essayer de changer la colonne avec le texte existant et s'embrouiller les pinceaux, on va utiliser la colonne E, qui est vide, pour recréer les noms. En faisant commencer cette formule avec D2, A1 et A2, et en l'appliquand sur toute la colonne, on arrive en effet à fusionner les noms coupés en deux. Mais il deux points sont encore à régler : 1. Il manque un espace entre les morceaux de noms fusionnés. Pas de souci, il faut juste s'assurer que la formule rajoute cet espace: IF(D10 = TRUE, CONCATENATE(A9," ",A10)) 2. La colonne D est rempli de FALSE pour toutes les fois où la formule ne tombe pas sur un nom découpé. Dans ce cas, plutôt que un FALSE, on veut le nom original. On modifie alors la formule pour rajouter la condition finale au IF : IF(D10 = TRUE, CONCATENATE(A9," ",A10),A10) Donc si D10 est TRUE, la formule va fusionner A9 et A10 en rajoutant un espace entre les deux. Mais si D10 est FALSE, alors la formule va simplement recopier le contenu de A10.
A2: "BAMBINO BERTHELOT" ASSOCIATION DE PARENTS D'ELEVES DE | B2: 0 | C2: Locaux | D2: =ISBLANK(B2) -> FALSE | E2: =if(D3=TRUE, CONCATENATE(A2," ",A3),A2) -> "BAMBINO BERTHELOT" ASSOCIATION DE PARENTS D'ELEVES DE L'ECOLE MATERNELLE BERTHELOT A BORDEAUX
A3: L'ECOLE MATERNELLE BERTHELOT A BORDEAUX | D3: =ISBLANK(B3) -> TRUE | E3: =if(D4=TRUE, CONCATENATE(A3," ",A4),A3) -> L'ECOLE MATERNELLE BERTHELOT A BORDEAUX
A4: 1001 JEUNES BORDELAIS | B4: 0 | C4: Matériel pour manifestations | D4: =ISBLANK(B4) -> FALSE | E4: =if(D5=TRUE, CONCATENATE(A4," ",A5),A4) -> 1001 JEUNES BORDELAIS
A5: 2AA | B5: 0 | C5: Locaux | D5: =ISBLANK(B5) -> FALSE | E5: =if(D6=TRUE, CONCATENATE(A5," ",A6),A5) -> 2AA
A6: 2SI2LA | B6: 0 | C6: Locaux | D6: =ISBLANK(B6) -> FALSE | E6: =if(D7=TRUE, CONCATENATE(A6," ",A7),A6) -> 2SI2LA
A7: 4 CATS | B7: 0 | C7: Locaux | D7: =ISBLANK(B7) -> FALSE | E7: =if(D8=TRUE, CONCATENATE(A7," ",A8),A7) -> 4 CATS
A8: 5UN7 | B8: 1000 | D8: =ISBLANK(B8) -> FALSE | E8: =if(D9=TRUE, CONCATENATE(A8," ",A9),A8) -> 5UN7
A9: 60 000 REBONDS | B9: 1800 | D9: =ISBLANK(B9) -> FALSE | E9: =if(D10=TRUE, CONCATENATE(A9," ",A10),A9) -> 60 000 REBONDS
A10: 9-33 | B10: 19000 | C10: Communication, locaux | D10: =ISBLANK(B10) -> FALSE | E10: =if(D11=TRUE, CONCATENATE(A10," ",A11),A10) -> 9-33
A11: A L EAU MUSIC | B11: 500 | D11: =ISBLANK(B11) -> FALSE | E11: =if(D12=TRUE, CONCATENATE(A11," ",A12),A11) -> A L EAU MUSIC
A12: A PART ENTIERE | B12: 2000 | D12: =ISBLANK(B12) -> FALSE | E12: =if(D13=TRUE, CONCATENATE(A12," ",A13),A12) -> A PART ENTIERE
A13: A PETIT PAS | B13: 3000 | D13: =ISBLANK(B13) -> FALSE | E13: =if(D14=TRUE, CONCATENATE(A13," ",A14),A13) -> A PETIT PAS
A14: A TRAVERS CHANT | B14: 0 | C14: Locaux | D14: =ISBLANK(B14) -> FALSE | E14: =if(D15=TRUE, CONCATENATE(A14," ",A15),A14) -> A TRAVERS CHANT
A15: A2RUNNING | B15: 0 | C15: Locaux | D15: =ISBLANK(B15) -> FALSE | E15: =if(D16=TRUE, CONCATENATE(A15," ",A16),A15) -> A2RUNNING
A16: ABALONE CHASSE BORDEAUX | B16: 0 | C16: Locaux, équipements sportifs | D16: =ISBLANK(B16) -> FALSE | E16: =if(D17=TRUE, CONCATENATE(A16," ",A17),A16) -> ABALONE CHASSE BORDEAUX
A17: ABEILLES BORDELAISES | B17: 0 | C17: Locaux | D17: =ISBLANK(B17) -> FALSE | E17: =if(D18=TRUE, CONCATENATE(A17," ",A18),A17) -> ABEILLES BORDELAISES
A18: ACADEMIE BUSHIKAI KARATE DO | B18: 0 | C18: Equipements sportifs | D18: =ISBLANK(B18) -> FALSE | E18: =if(D19=TRUE, CONCATENATE(A18," ",A19),A18) -> ACADEMIE BUSHIKAI KARATE DO
A19: ACADEMIE DES SCIENCES, BELLES LETTRES ET ARTS DE | B19: 7600 | C19: Locaux, matériel pour manifestations | D19: =ISBLANK(B19) -> FALSE | E19: =if(D20=TRUE, CONCATENATE(A19," ",A20),A19) -> ACADEMIE DES SCIENCES, BELLES LETTRES ET ARTS DE BORDEAUX
A20: BORDEAUX | D20: =ISBLANK(B20) -> TRUE | E20: =if(D21=TRUE, CONCATENATE(A20," ",A21),A20) -> BORDEAUX
A21: ACADEMIE PROSPECTIVE NOUVELLES TECHNOLOGIES | B21: 0 | C21: Locaux | D21: =ISBLANK(B21) -> FALSE | E21: =if(D22=TRUE, CONCATENATE(A21," ",A22),A21) -> ACADEMIE PROSPECTIVE NOUVELLES TECHNOLOGIES
A22: ACADEMIE YOUNUS | B22: 22000 | C22: Locaux, équipements sportifs, matériel pour | D22: =ISBLANK(B22) -> FALSE | E22: =if(D23=TRUE, CONCATENATE(A22," ",A23),A22) -> ACADEMIE YOUNUS
C23: manifestations | D23: =ISBLANK(B23) -> TRUE | E23: =if(D24=TRUE, CONCATENATE(A23," ",A24),A23)
A24: ACCOMPAGNEMENT ET RECHERCHE PSYCHO-SOCIO EDUCATIFS | B24: 0 | C24: Locaux | D24: =ISBLANK(B24) -> FALSE | E24: =if(D25=TRUE, CONCATENATE(A24," ",A25),A24) -> ACCOMPAGNEMENT ET RECHERCHE PSYCHO-SOCIO EDUCATIFS POUR LES JEUNES (ARPEJE)
A25: POUR LES JEUNES (ARPEJE) | D25: =ISBLANK(B25) -> TRUE | E25: =if(D26=TRUE, CONCATENATE(A25," ",A26),A25) -> POUR LES JEUNES (ARPEJE)
A26: ACCOMPAGNEMENT PSYCHOLOGIQUE ET MEDIATION | B26: 5000 | D26: =ISBLANK(B26) -> FALSE | E26: =if(D27=TRUE, CONCATENATE(A26," ",A27),A26) -> ACCOMPAGNEMENT PSYCHOLOGIQUE ET MEDIATION INTERCULTURELLE - AMI
A27: INTERCULTURELLE - AMI | D27: =ISBLANK(B27) -> TRUE | E27: =if(D28=TRUE, CONCATENATE(A27," ",A28),A27) -> INTERCULTURELLE - AMI
A28: ACCOMPAGNER CONDUIRE TRANSMETTRE - ACT | B28: 300 | C28: Locaux | D28: =ISBLANK(B28) -> FALSE | E28: =if(D29=TRUE, CONCATENATE(A28," ",A29),A28) -> ACCOMPAGNER CONDUIRE TRANSMETTRE - ACT
A29: ACCORDERIE BORDEAUX SUD | B29: 4500 | C29: Locaux | D29: =ISBLANK(B29) -> FALSE | E29: =if(D30=TRUE, CONCATENATE(A29," ",A30),A29) -> ACCORDERIE BORDEAUX SUD
A30: ACHATS GROUPES ASSOCIATIF POUR L'ECONOMIE SOLIDAIRE DE | B30: 0 | C30: Locaux | D30: =ISBLANK(B30) -> FALSE | E30: =if(D31=TRUE, CONCATENATE(A30," ",A31),A30) -> ACHATS GROUPES ASSOCIATIF POUR L'ECONOMIE SOLIDAIRE DE BORDEAUX - AGAPES
A31: BORDEAUX - AGAPES | D31: =ISBLANK(B31) -> TRUE | E31: =if(D32=TRUE, CONCATENATE(A31," ",A32),A31) -> BORDEAUX - AGAPES
A32: ACIDD, ASSOCIATION COMMUNICATION ET INFORMATION POUR LE | B32: 10000 | C32: Locaux | D32: =ISBLANK(B32) -> FALSE | E32: =if(D33=TRUE, CONCATENATE(A32," ",A33),A32) -> ACIDD, ASSOCIATION COMMUNICATION ET INFORMATION POUR LE DEVELOPPEMENT DURABLE
A33: DEVELOPPEMENT DURABLE | D33: =ISBLANK(B33) -> TRUE | E33: =if(D34=TRUE, CONCATENATE(A33," ",A34),A33) -> DEVELOPPEMENT DURABLE
A34: ACINQBYS_ESPACE 29 A5BIS | B34: 22000 | D34: =ISBLANK(B34) -> FALSE | E34: =if(D35=TRUE, CONCATENATE(A34," ",A35),A34) -> ACINQBYS_ESPACE 29 A5BIS
A35: ACTA GIRONDE - AGIR CONTRE LA TORTURE DES ANIMAUX | B35: 0 | C35: Locaux | D35: =ISBLANK(B35) -> FALSE | E35: =if(D36=TRUE, CONCATENATE(A35," ",A36),A35) -> ACTA GIRONDE - AGIR CONTRE LA TORTURE DES ANIMAUX
A36: ACTIFS 33 | B36: 2400 | D36: =ISBLANK(B36) -> FALSE | E36: =if(D37=TRUE, CONCATENATE(A36," ",A37),A36) -> ACTIFS 33
A37: ACTIMAGE | B37: 6500 | D37: =ISBLANK(B37) -> FALSE | E37: =if(D38=TRUE, CONCATENATE(A37," ",A38),A37) -> ACTIMAGE
A38: ACTION CONTRE LA FAIM | B38: 0 | C38: Locaux | D38: =ISBLANK(B38) -> FALSE | E38: =if(D39=TRUE, CONCATENATE(A38," ",A39),A38) -> ACTION CONTRE LA FAIM
A39: ACTION INTERNATIONALE POUR LA PAIX ET LE DEVELOPPEMENT | B39: 0 | C39: Locaux | D39: =ISBLANK(B39) -> FALSE | E39: =if(D40=TRUE, CONCATENATE(A39," ",A40),A39) -> ACTION INTERNATIONALE POUR LA PAIX ET LE DEVELOPPEMENT
A40: AD LUCEM THEATRE | B40: 0 | C40: Locaux | D40: =ISBLANK(B40) -> FALSE | E40: =if(D41=TRUE, CONCATENATE(A40," ",A41),A40) -> AD LUCEM THEATRE
A41: ADDAH 33 | B41: 500 | D41: =ISBLANK(B41) -> FALSE | E41: =if(D42=TRUE, CONCATENATE(A41," ",A42),A41) -> ADDAH 33
A42: ADORA | B42: 5000 | C42: Locaux | D42: =ISBLANK(B42) -> FALSE | E42: =if(D43=TRUE, CONCATENATE(A42," ",A43),A42) -> ADORA
A43: ADRIA | B43: 1500 | D43: =ISBLANK(B43) -> FALSE | E43: =if(D44=TRUE, CONCATENATE(A43," ",A44),A43) -> ADRIA
A44: AEP SAINT PROJET | B44: 0 | C44: Matériel pour manifestations | D44: =ISBLANK(B44) -> FALSE | E44: =if(D45=TRUE, CONCATENATE(A44," ",A45),A44) -> AEP SAINT PROJET
A45: AFRICAFRANCE | B45: 1500 | D45: =ISBLANK(B45) -> FALSE | E45: =if(D46=TRUE, CONCATENATE(A45," ",A46),A45) -> AFRICAFRANCE
A46: AGENCE D'URBANISME BORDEAUX METROPOLE AQUITAINE | B46: 60000 | D46: =ISBLANK(B46) -> FALSE | E46: =if(D47=TRUE, CONCATENATE(A46," ",A47),A46) -> AGENCE D'URBANISME BORDEAUX METROPOLE AQUITAINE (A'URBA)
A47: (A'URBA) | D47: =ISBLANK(B47) -> TRUE | E47: =if(D48=TRUE, CONCATENATE(A47," ",A48),A47) -> (A'URBA)
A48: AGENCE LOCALE DE L'ENERGIE ET DU CLIMAT (ALEC) | B48: 6000 | C48: Locaux | D48: =ISBLANK(B48) -> FALSE | E48: =if(D49=TRUE, CONCATENATE(A48," ",A49),A48) -> AGENCE LOCALE DE L'ENERGIE ET DU CLIMAT (ALEC)
A49: AGENCE REGIONALE DE SANTE NOUVELLE AQUITAINE | B49: 0 | C49: Matériel pour manifestations | D49: =ISBLANK(B49) -> FALSE | E49: =if(D50=TRUE, CONCATENATE(A49," ",A50),A49) -> AGENCE REGIONALE DE SANTE NOUVELLE AQUITAINE
A50: AGIR POUR UN COMMERE EQUITABLE ET SOLIDAIRE EN AQUITAINE - | B50: 500 | D50: =ISBLANK(B50) -> FALSE | E50: =if(D51=TRUE, CONCATENATE(A50," ",A51),A50) -> AGIR POUR UN COMMERE EQUITABLE ET SOLIDAIRE EN AQUITAINE - ACESA
A51: ACESA | D51: =ISBLANK(B51) -> TRUE | E51: =if(D52=TRUE, CONCATENATE(A51," ",A52),A51) -> ACESA
A52: AGORA DES ARTS | B52: 5000 | C52: Matériel pour manifestations | D52: =ISBLANK(B52) -> FALSE | E52: =if(D53=TRUE, CONCATENATE(A52," ",A53),A52) -> AGORA DES ARTS
A53: AIDE AUX AIDANTS DU PAVILLON | B53: 2000 | D53: =ISBLANK(B53) -> FALSE | E53: =if(D54=TRUE, CONCATENATE(A53," ",A54),A53) -> AIDE AUX AIDANTS DU PAVILLON
A54: AIDES AQUITAINE | B54: 5500 | D54: =ISBLANK(B54) -> FALSE | E54: =if(D55=TRUE, CONCATENATE(A54," ",A55),A54) -> AIDES AQUITAINE
A55: AIGUILLES ET CALAME | B55: 0 | C55: Locaux | D55: =ISBLANK(B55) -> FALSE | E55: =if(D56=TRUE, CONCATENATE(A55," ",A56),A55) -> AIGUILLES ET CALAME
A56: AIKIDO BORDEAUX BASTIDE | B56: 2000 | C56: Equipements sportifs | D56: =ISBLANK(B56) -> FALSE | E56: =if(D57=TRUE, CONCATENATE(A56," ",A57),A56) -> AIKIDO BORDEAUX BASTIDE
A57: AIM ACTIONS INTER MEDIATION | B57: 20060 | D57: =ISBLANK(B57) -> FALSE | E57: =if(D58=TRUE, CONCATENATE(A57," ",A58),A57) -> AIM ACTIONS INTER MEDIATION
A58: AIR ROLLER (ATTENTION INERTIE RENOUVELABLE) | B58: 11000 | C58: Locaux, équipements sportifs | D58: =ISBLANK(B58) -> FALSE | E58: =if(D59=TRUE, CONCATENATE(A58," ",A59),A58) -> AIR ROLLER (ATTENTION INERTIE RENOUVELABLE)
A59: ALAM AMIS DU LIVRE ANCIEN ET MODERNE | B59: 0 | C59: Locaux, matériel pour manifestations | D59: =ISBLANK(B59) -> FALSE | E59: =if(D60=TRUE, CONCATENATE(A59," ",A60),A59) -> ALAM AMIS DU LIVRE ANCIEN ET MODERNE
A60: ALGERIENS DE L'AQUITAINE | B60: 0 | C60: Locaux | D60: =ISBLANK(B60) -> FALSE | E60: =if(D61=TRUE, CONCATENATE(A60," ",A61),A60) -> ALGERIENS DE L'AQUITAINE
A61: ALLIANCE DEPARTEMENT 33, JUSQU'AU BOUT ACCOMPAGNER LA | B61: 4500 | C61: Locaux | D61: =ISBLANK(B61) -> FALSE | E61: =if(D62=TRUE, CONCATENATE(A61," ",A62),A61) -> ALLIANCE DEPARTEMENT 33, JUSQU'AU BOUT ACCOMPAGNER LA VIE...
A62: VIE... | D62: =ISBLANK(B62) -> TRUE | E62: =if(D63=TRUE, CONCATENATE(A62," ",A63),A62) -> VIE...
A63: ALLIANCE FRANCAISE DE BORDEAUX AQUITAINE | B63: 0 | C63: Locaux | D63: =ISBLANK(B63) -> FALSE | E63: =if(D64=TRUE, CONCATENATE(A63," ",A64),A63) -> ALLIANCE FRANCAISE DE BORDEAUX AQUITAINE
A64: ALPTIS | B64: 0 | C64: Locaux | D64: =ISBLANK(B64) -> FALSE | E64: =if(D65=TRUE, CONCATENATE(A64," ",A65),A64) -> ALPTIS
A65: ALTER INSERTION | B65: 0 | C65: Matériel pour manifestations | D65: =ISBLANK(B65) -> FALSE | E65: =if(D66=TRUE, CONCATENATE(A65," ",A66),A65) -> ALTER INSERTION
A66: AMADEUS | B66: 1000 | D66: =ISBLANK(B66) -> FALSE | E66: =if(D67=TRUE, CONCATENATE(A66," ",A67),A66) -> AMADEUS
A67: AMBASSADE REGIONALE DES CONFRERIES DE PRODUITS DE | B67: 500 | D67: =ISBLANK(B67) -> FALSE | E67: =if(D68=TRUE, CONCATENATE(A67," ",A68),A67) -> AMBASSADE REGIONALE DES CONFRERIES DE PRODUITS DE TERROIR ET DU GOUT
A68: TERROIR ET DU GOUT | D68: =ISBLANK(B68) -> TRUE | E68: =if(D69=TRUE, CONCATENATE(A68," ",A69),A68) -> TERROIR ET DU GOUT
A69: AMELIORATION DES CONDITIONS DE VIE DES ENFANTS | B69: 571 | D69: =ISBLANK(B69) -> FALSE | E69: =if(D70=TRUE, CONCATENATE(A69," ",A70),A69) -> AMELIORATION DES CONDITIONS DE VIE DES ENFANTS ADOLESCENTS HOSPITALISES
A70: ADOLESCENTS HOSPITALISES | D70: =ISBLANK(B70) -> TRUE | E70: =if(D71=TRUE, CONCATENATE(A70," ",A71),A70) -> ADOLESCENTS HOSPITALISES
A71: AMEPI | B71: 0 | C71: Locaux | D71: =ISBLANK(B71) -> FALSE | E71: =if(D72=TRUE, CONCATENATE(A71," ",A72),A71) -> AMEPI
A72: AMICALE BORDELAISE TRACTION AVANT CITROEN | B72: 0 | C72: Locaux | D72: =ISBLANK(B72) -> FALSE | E72: =if(D73=TRUE, CONCATENATE(A72," ",A73),A72) -> AMICALE BORDELAISE TRACTION AVANT CITROEN
A73: AMICALE COMORIENNE DE BORDEAUX | B73: 0 | C73: Locaux | D73: =ISBLANK(B73) -> FALSE | E73: =if(D74=TRUE, CONCATENATE(A73," ",A74),A73) -> AMICALE COMORIENNE DE BORDEAUX
A74: AMICALE DE LA RESIDENCE DU LAC | B74: 0 | C74: Locaux | D74: =ISBLANK(B74) -> FALSE | E74: =if(D75=TRUE, CONCATENATE(A74," ",A75),A74) -> AMICALE DE LA RESIDENCE DU LAC
A75: AMICALE DES ANCIENS DE LA LEGION ETRANGERE | B75: 1000 | D75: =ISBLANK(B75) -> FALSE | E75: =if(D76=TRUE, CONCATENATE(A75," ",A76),A75) -> AMICALE DES ANCIENS DE LA LEGION ETRANGERE
A76: AMICALE DES ANCIENS DE MARIE-BRIZARD - AAMB | B76: 0 | C76: Locaux | D76: =ISBLANK(B76) -> FALSE | E76: =if(D77=TRUE, CONCATENATE(A76," ",A77),A76) -> AMICALE DES ANCIENS DE MARIE-BRIZARD - AAMB
A77: AMICALE DES ANCIENS DES NOUVELLES GALERIES DE BORDEAUX | B77: 0 | C77: Locaux | D77: =ISBLANK(B77) -> FALSE | E77: =if(D78=TRUE, CONCATENATE(A77," ",A78),A77) -> AMICALE DES ANCIENS DES NOUVELLES GALERIES DE BORDEAUX
A78: AMICALE DES ANCIENS DES TROUPES DE MARINE DE BORDEAUX ET | B78: 500 | D78: =ISBLANK(B78) -> FALSE | E78: =if(D79=TRUE, CONCATENATE(A78," ",A79),A78) -> AMICALE DES ANCIENS DES TROUPES DE MARINE DE BORDEAUX ET D'AQUITAINE
A79: D'AQUITAINE | D79: =ISBLANK(B79) -> TRUE | E79: =if(D80=TRUE, CONCATENATE(A79," ",A80),A79) -> D'AQUITAINE
A80: AMICALE DES ANCIENS GUERILLEROS ESPAGNOLS EN FRANCE-FFI - | B80: 0 | C80: Locaux | D80: =ISBLANK(B80) -> FALSE | E80: =if(D81=TRUE, CONCATENATE(A80," ",A81),A80) -> AMICALE DES ANCIENS GUERILLEROS ESPAGNOLS EN FRANCE-FFI - SECTION DE LA GIRONDE
A81: SECTION DE LA GIRONDE | D81: =ISBLANK(B81) -> TRUE | E81: =if(D82=TRUE, CONCATENATE(A81," ",A82),A81) -> SECTION DE LA GIRONDE
A82: AMICALE DES AVEYRONNAIS DE BORDEAUX ET GIRONDE | B82: 0 | C82: Locaux | D82: =ISBLANK(B82) -> FALSE | E82: =if(D83=TRUE, CONCATENATE(A82," ",A83),A82) -> AMICALE DES AVEYRONNAIS DE BORDEAUX ET GIRONDE
A83: AMICALE DES ETABLISSEMENTS SCOLAIRES LAIQUES DE BACALAN - | B83: 82238 | C83: Locaux, équipements sportifs, matériel pour | D83: =ISBLANK(B83) -> FALSE | E83: =if(D84=TRUE, CONCATENATE(A83," ",A84),A83) -> AMICALE DES ETABLISSEMENTS SCOLAIRES LAIQUES DE BACALAN - ALB
A84: ALB | C84: manifestations | D84: =ISBLANK(B84) -> TRUE | E84: =if(D85=TRUE, CONCATENATE(A84," ",A85),A84) -> ALB
A85: AMICALE DES LOCATAIRES DU PORT DE LA LUNE | B85: 4000 | D85: =ISBLANK(B85) -> FALSE | E85: =if(D86=TRUE, CONCATENATE(A85," ",A86),A85) -> AMICALE DES LOCATAIRES DU PORT DE LA LUNE
A86: AMICALE DES PARACHUTISTES DU SUD-OUEST | B86: 300 | D86: =ISBLANK(B86) -> FALSE | E86: =if(D87=TRUE, CONCATENATE(A86," ",A87),A86) -> AMICALE DES PARACHUTISTES DU SUD-OUEST
A87: AMICALE DES PARENTS D'ELEVES DE L'ECOLE STEHELIN | B87: 8605 | D87: =ISBLANK(B87) -> FALSE | E87: =if(D88=TRUE, CONCATENATE(A87," ",A88),A87) -> AMICALE DES PARENTS D'ELEVES DE L'ECOLE STEHELIN
A88: AMICALE DES PHILIPPEVILLOIS, CONSTANTINOIS ET LEURS AMIS - | B88: 0 | C88: Locaux | D88: =ISBLANK(B88) -> FALSE | E88: =if(D89=TRUE, CONCATENATE(A88," ",A89),A88) -> AMICALE DES PHILIPPEVILLOIS, CONSTANTINOIS ET LEURS AMIS - APCA
A89: APCA | D89: =ISBLANK(B89) -> TRUE | E89: =if(D90=TRUE, CONCATENATE(A89," ",A90),A89) -> APCA
A90: AMICALE DES RETRAITES U.G.R.R. - I.S.I.C.A. DE BORDEAUX | B90: 0 | C90: Locaux | D90: =ISBLANK(B90) -> FALSE | E90: =if(D91=TRUE, CONCATENATE(A90," ",A91),A90) -> AMICALE DES RETRAITES U.G.R.R. - I.S.I.C.A. DE BORDEAUX
A91: AMICALE DU PATRONAGE LAIQUE ET DU CONSEIL DE PARENTS | B91: 1000 | C91: Matériel pour manifestations | D91: =ISBLANK(B91) -> FALSE | E91: =if(D92=TRUE, CONCATENATE(A91," ",A92),A91) -> AMICALE DU PATRONAGE LAIQUE ET DU CONSEIL DE PARENTS D'ELEVES DU GROUPE SCOLAIRE NUYENS
A92: D'ELEVES DU GROUPE SCOLAIRE NUYENS | D92: =ISBLANK(B92) -> TRUE | E92: =if(D93=TRUE, CONCATENATE(A92," ",A93),A92) -> D'ELEVES DU GROUPE SCOLAIRE NUYENS
A93: AMICALE LAIQUE BORDEAUX CENTRE | B93: 2500 | C93: Locaux, équipements sportifs | D93: =ISBLANK(B93) -> FALSE | E93: =if(D94=TRUE, CONCATENATE(A93," ",A94),A93) -> AMICALE LAIQUE BORDEAUX CENTRE
A94: AMICALE LAIQUE DAVID JOHNSTON LAGRANGE ALBERT BARRAUD | B94: 450195 | C94: Equipements sportifs | D94: =ISBLANK(B94) -> FALSE | E94: =if(D95=TRUE, CONCATENATE(A94," ",A95),A94) -> AMICALE LAIQUE DAVID JOHNSTON LAGRANGE ALBERT BARRAUD NAUJAC
A95: NAUJAC | D95: =ISBLANK(B95) -> TRUE | E95: =if(D96=TRUE, CONCATENATE(A95," ",A96),A95) -> NAUJAC
A96: AMICALE LAIQUE DU GROUPE SCOLAIRE LEONARD-LENOIR - | B96: 0 | C96: Equipements sportifs | D96: =ISBLANK(B96) -> FALSE | E96: =if(D97=TRUE, CONCATENATE(A96," ",A97),A96) -> AMICALE LAIQUE DU GROUPE SCOLAIRE LEONARD-LENOIR - MONTAUD - NUITS
A97: MONTAUD - NUITS | D97: =ISBLANK(B97) -> TRUE | E97: =if(D98=TRUE, CONCATENATE(A97," ",A98),A97) -> MONTAUD - NUITS
A98: AMICALE LAIQUE LEONARD LENOIR | B98: 0 | C98: Locaux | D98: =ISBLANK(B98) -> FALSE | E98: =if(D99=TRUE, CONCATENATE(A98," ",A99),A98) -> AMICALE LAIQUE LEONARD LENOIR
A99: AMICALE NATIONALE DES RETRAITES DE L'AUDIOVISUEL | B99: 0 | C99: Locaux | D99: =ISBLANK(B99) -> FALSE | E99: =if(D100=TRUE, CONCATENATE(A99," ",A100),A99) -> AMICALE NATIONALE DES RETRAITES DE L'AUDIOVISUEL
A100: AMIS D'ARS ET FIDES BORDEAUX | B100: 2000 | C100: Locaux | D100: =ISBLANK(B100) -> FALSE | E100: =if(D101=TRUE, CONCATENATE(A100," ",A101),A100) -> AMIS D'ARS ET FIDES BORDEAUX
...

Sheet etape3
A1: on rajoute les en-têtes et on se prépare à supprimer les lignes qui ont un "TRUE". Elle correspondant à des morceaux de données inutiles, qu'on a déjà recollés par ailleurs. Mais comme ma formule de colonne E s'appuie sur le TRUE, il faut que je copie toute la colonne E et que je fasse edition --> collage spécial --> coller uniquement les valeurs dans la colonne E. Là c'est juste les résultats qui restent, la formule derrière a disparu. Je peux supprimer mes TRUE sans souci
B2: Montant du fonds de concours ou de la subvention (numéraire) | C2: Prestations en nature | D2: isblank | E2: nom des bénéficiaires
A3: "BAMBINO BERTHELOT" ASSOCIATION DE PARENTS D'ELEVES DE | B3: 0 | C3: Locaux | D3: =ISBLANK(B3) -> FALSE | E3: "BAMBINO BERTHELOT" ASSOCIATION DE PARENTS D'ELEVES DE L'ECOLE MATERNELLE BERTHELOT A BORDEAUX
A4: L'ECOLE MATERNELLE BERTHELOT A BORDEAUX | D4: =ISBLANK(B4) -> TRUE | E4: L'ECOLE MATERNELLE BERTHELOT A BORDEAUX
A5: 1001 JEUNES BORDELAIS | B5: 0 | C5: Matériel pour manifestations | D5: =ISBLANK(B5) -> FALSE | E5: 1001 JEUNES BORDELAIS
A6: 2AA | B6: 0 | C6: Locaux | D6: =ISBLANK(B6) -> FALSE | E6: 2AA
A7: 2SI2LA | B7: 0 | C7: Locaux | D7: =ISBLANK(B7) -> FALSE | E7: 2SI2LA
A8: 4 CATS | B8: 0 | C8: Locaux | D8: =ISBLANK(B8) -> FALSE | E8: 4 CATS
A9: 5UN7 | B9: 1000 | D9: =ISBLANK(B9) -> FALSE | E9: 5UN7
A10: 60 000 REBONDS | B10: 1800 | D10: =ISBLANK(B10) -> FALSE | E10: 60 000 REBONDS
A11: 9-33 | B11: 19000 | C11: Communication, locaux | D11: =ISBLANK(B11) -> FALSE | E11: 9-33
A12: A L EAU MUSIC | B12: 500 | D12: =ISBLANK(B12) -> FALSE | E12: A L EAU MUSIC
A13: A PART ENTIERE | B13: 2000 | D13: =ISBLANK(B13) -> FALSE | E13: A PART ENTIERE
A14: A PETIT PAS | B14: 3000 | D14: =ISBLANK(B14) -> FALSE | E14: A PETIT PAS
A15: A TRAVERS CHANT | B15: 0 | C15: Locaux | D15: =ISBLANK(B15) -> FALSE | E15: A TRAVERS CHANT
A16: A2RUNNING | B16: 0 | C16: Locaux | D16: =ISBLANK(B16) -> FALSE | E16: A2RUNNING
A17: ABALONE CHASSE BORDEAUX | B17: 0 | C17: Locaux, équipements sportifs | D17: =ISBLANK(B17) -> FALSE | E17: ABALONE CHASSE BORDEAUX
A18: ABEILLES BORDELAISES | B18: 0 | C18: Locaux | D18: =ISBLANK(B18) -> FALSE | E18: ABEILLES BORDELAISES
A19: ACADEMIE BUSHIKAI KARATE DO | B19: 0 | C19: Equipements sportifs | D19: =ISBLANK(B19) -> FALSE | E19: ACADEMIE BUSHIKAI KARATE DO
A20: ACADEMIE DES SCIENCES, BELLES LETTRES ET ARTS DE | B20: 7600 | C20: Locaux, matériel pour manifestations | D20: =ISBLANK(B20) -> FALSE | E20: ACADEMIE DES SCIENCES, BELLES LETTRES ET ARTS DE BORDEAUX
A21: BORDEAUX | D21: =ISBLANK(B21) -> TRUE | E21: BORDEAUX
A22: ACADEMIE PROSPECTIVE NOUVELLES TECHNOLOGIES | B22: 0 | C22: Locaux | D22: =ISBLANK(B22) -> FALSE | E22: ACADEMIE PROSPECTIVE NOUVELLES TECHNOLOGIES
A23: ACADEMIE YOUNUS | B23: 22000 | C23: Locaux, équipements sportifs, matériel pour | D23: =ISBLANK(B23) -> FALSE | E23: ACADEMIE YOUNUS
C24: manifestations | D24: =ISBLANK(B24) -> TRUE
A25: ACCOMPAGNEMENT ET RECHERCHE PSYCHO-SOCIO EDUCATIFS | B25: 0 | C25: Locaux | D25: =ISBLANK(B25) -> FALSE | E25: ACCOMPAGNEMENT ET RECHERCHE PSYCHO-SOCIO EDUCATIFS POUR LES JEUNES (ARPEJE)
A26: POUR LES JEUNES (ARPEJE) | D26: =ISBLANK(B26) -> TRUE | E26: POUR LES JEUNES (ARPEJE)
A27: ACCOMPAGNEMENT PSYCHOLOGIQUE ET MEDIATION | B27: 5000 | D27: =ISBLANK(B27) -> FALSE | E27: ACCOMPAGNEMENT PSYCHOLOGIQUE ET MEDIATION INTERCULTURELLE - AMI
A28: INTERCULTURELLE - AMI | D28: =ISBLANK(B28) -> TRUE | E28: INTERCULTURELLE - AMI
A29: ACCOMPAGNER CONDUIRE TRANSMETTRE - ACT | B29: 300 | C29: Locaux | D29: =ISBLANK(B29) -> FALSE | E29: ACCOMPAGNER CONDUIRE TRANSMETTRE - ACT
A30: ACCORDERIE BORDEAUX SUD | B30: 4500 | C30: Locaux | D30: =ISBLANK(B30) -> FALSE | E30: ACCORDERIE BORDEAUX SUD
A31: ACHATS GROUPES ASSOCIATIF POUR L'ECONOMIE SOLIDAIRE DE | B31: 0 | C31: Locaux | D31: =ISBLANK(B31) -> FALSE | E31: ACHATS GROUPES ASSOCIATIF POUR L'ECONOMIE SOLIDAIRE DE BORDEAUX - AGAPES
A32: BORDEAUX - AGAPES | D32: =ISBLANK(B32) -> TRUE | E32: BORDEAUX - AGAPES
A33: ACIDD, ASSOCIATION COMMUNICATION ET INFORMATION POUR LE | B33: 10000 | C33: Locaux | D33: =ISBLANK(B33) -> FALSE | E33: ACIDD, ASSOCIATION COMMUNICATION ET INFORMATION POUR LE DEVELOPPEMENT DURABLE
A34: DEVELOPPEMENT DURABLE | D34: =ISBLANK(B34) -> TRUE | E34: DEVELOPPEMENT DURABLE
A35: ACINQBYS_ESPACE 29 A5BIS | B35: 22000 | D35: =ISBLANK(B35) -> FALSE | E35: ACINQBYS_ESPACE 29 A5BIS
A36: ACTA GIRONDE - AGIR CONTRE LA TORTURE DES ANIMAUX | B36: 0 | C36: Locaux | D36: =ISBLANK(B36) -> FALSE | E36: ACTA GIRONDE - AGIR CONTRE LA TORTURE DES ANIMAUX
A37: ACTIFS 33 | B37: 2400 | D37: =ISBLANK(B37) -> FALSE | E37: ACTIFS 33
A38: ACTIMAGE | B38: 6500 | D38: =ISBLANK(B38) -> FALSE | E38: ACTIMAGE
A39: ACTION CONTRE LA FAIM | B39: 0 | C39: Locaux | D39: =ISBLANK(B39) -> FALSE | E39: ACTION CONTRE LA FAIM
A40: ACTION INTERNATIONALE POUR LA PAIX ET LE DEVELOPPEMENT | B40: 0 | C40: Locaux | D40: =ISBLANK(B40) -> FALSE | E40: ACTION INTERNATIONALE POUR LA PAIX ET LE DEVELOPPEMENT
A41: AD LUCEM THEATRE | B41: 0 | C41: Locaux | D41: =ISBLANK(B41) -> FALSE | E41: AD LUCEM THEATRE
A42: ADDAH 33 | B42: 500 | D42: =ISBLANK(B42) -> FALSE | E42: ADDAH 33
A43: ADORA | B43: 5000 | C43: Locaux | D43: =ISBLANK(B43) -> FALSE | E43: ADORA
A44: ADRIA | B44: 1500 | D44: =ISBLANK(B44) -> FALSE | E44: ADRIA
A45: AEP SAINT PROJET | B45: 0 | C45: Matériel pour manifestations | D45: =ISBLANK(B45) -> FALSE | E45: AEP SAINT PROJET
A46: AFRICAFRANCE | B46: 1500 | D46: =ISBLANK(B46) -> FALSE | E46: AFRICAFRANCE
A47: AGENCE D'URBANISME BORDEAUX METROPOLE AQUITAINE | B47: 60000 | D47: =ISBLANK(B47) -> FALSE | E47: AGENCE D'URBANISME BORDEAUX METROPOLE AQUITAINE (A'URBA)
A48: (A'URBA) | D48: =ISBLANK(B48) -> TRUE | E48: (A'URBA)
A49: AGENCE LOCALE DE L'ENERGIE ET DU CLIMAT (ALEC) | B49: 6000 | C49: Locaux | D49: =ISBLANK(B49) -> FALSE | E49: AGENCE LOCALE DE L'ENERGIE ET DU CLIMAT (ALEC)
A50: AGENCE REGIONALE DE SANTE NOUVELLE AQUITAINE | B50: 0 | C50: Matériel pour manifestations | D50: =ISBLANK(B50) -> FALSE | E50: AGENCE REGIONALE DE SANTE NOUVELLE AQUITAINE
A51: AGIR POUR UN COMMERE EQUITABLE ET SOLIDAIRE EN AQUITAINE - | B51: 500 | D51: =ISBLANK(B51) -> FALSE | E51: AGIR POUR UN COMMERE EQUITABLE ET SOLIDAIRE EN AQUITAINE - ACESA
A52: ACESA | D52: =ISBLANK(B52) -> TRUE | E52: ACESA
A53: AGORA DES ARTS | B53: 5000 | C53: Matériel pour manifestations | D53: =ISBLANK(B53) -> FALSE | E53: AGORA DES ARTS
A54: AIDE AUX AIDANTS DU PAVILLON | B54: 2000 | D54: =ISBLANK(B54) -> FALSE | E54: AIDE AUX AIDANTS DU PAVILLON
A55: AIDES AQUITAINE | B55: 5500 | D55: =ISBLANK(B55) -> FALSE | E55: AIDES AQUITAINE
A56: AIGUILLES ET CALAME | B56: 0 | C56: Locaux | D56: =ISBLANK(B56) -> FALSE | E56: AIGUILLES ET CALAME
A57: AIKIDO BORDEAUX BASTIDE | B57: 2000 | C57: Equipements sportifs | D57: =ISBLANK(B57) -> FALSE | E57: AIKIDO BORDEAUX BASTIDE
A58: AIM ACTIONS INTER MEDIATION | B58: 20060 | D58: =ISBLANK(B58) -> FALSE | E58: AIM ACTIONS INTER MEDIATION
A59: AIR ROLLER (ATTENTION INERTIE RENOUVELABLE) | B59: 11000 | C59: Locaux, équipements sportifs | D59: =ISBLANK(B59) -> FALSE | E59: AIR ROLLER (ATTENTION INERTIE RENOUVELABLE)
A60: ALAM AMIS DU LIVRE ANCIEN ET MODERNE | B60: 0 | C60: Locaux, matériel pour manifestations | D60: =ISBLANK(B60) -> FALSE | E60: ALAM AMIS DU LIVRE ANCIEN ET MODERNE
A61: ALGERIENS DE L'AQUITAINE | B61: 0 | C61: Locaux | D61: =ISBLANK(B61) -> FALSE | E61: ALGERIENS DE L'AQUITAINE
A62: ALLIANCE DEPARTEMENT 33, JUSQU'AU BOUT ACCOMPAGNER LA | B62: 4500 | C62: Locaux | D62: =ISBLANK(B62) -> FALSE | E62: ALLIANCE DEPARTEMENT 33, JUSQU'AU BOUT ACCOMPAGNER LA VIE...
A63: VIE... | D63: =ISBLANK(B63) -> TRUE | E63: VIE...
A64: ALLIANCE FRANCAISE DE BORDEAUX AQUITAINE | B64: 0 | C64: Locaux | D64: =ISBLANK(B64) -> FALSE | E64: ALLIANCE FRANCAISE DE BORDEAUX AQUITAINE
A65: ALPTIS | B65: 0 | C65: Locaux | D65: =ISBLANK(B65) -> FALSE | E65: ALPTIS
A66: ALTER INSERTION | B66: 0 | C66: Matériel pour manifestations | D66: =ISBLANK(B66) -> FALSE | E66: ALTER INSERTION
A67: AMADEUS | B67: 1000 | D67: =ISBLANK(B67) -> FALSE | E67: AMADEUS
A68: AMBASSADE REGIONALE DES CONFRERIES DE PRODUITS DE | B68: 500 | D68: =ISBLANK(B68) -> FALSE | E68: AMBASSADE REGIONALE DES CONFRERIES DE PRODUITS DE TERROIR ET DU GOUT
A69: TERROIR ET DU GOUT | D69: =ISBLANK(B69) -> TRUE | E69: TERROIR ET DU GOUT
A70: AMELIORATION DES CONDITIONS DE VIE DES ENFANTS | B70: 571 | D70: =ISBLANK(B70) -> FALSE | E70: AMELIORATION DES CONDITIONS DE VIE DES ENFANTS ADOLESCENTS HOSPITALISES
A71: ADOLESCENTS HOSPITALISES | D71: =ISBLANK(B71) -> TRUE | E71: ADOLESCENTS HOSPITALISES
A72: AMEPI | B72: 0 | C72: Locaux | D72: =ISBLANK(B72) -> FALSE | E72: AMEPI
A73: AMICALE BORDELAISE TRACTION AVANT CITROEN | B73: 0 | C73: Locaux | D73: =ISBLANK(B73) -> FALSE | E73: AMICALE BORDELAISE TRACTION AVANT CITROEN
A74: AMICALE COMORIENNE DE BORDEAUX | B74: 0 | C74: Locaux | D74: =ISBLANK(B74) -> FALSE | E74: AMICALE COMORIENNE DE BORDEAUX
A75: AMICALE DE LA RESIDENCE DU LAC | B75: 0 | C75: Locaux | D75: =ISBLANK(B75) -> FALSE | E75: AMICALE DE LA RESIDENCE DU LAC
A76: AMICALE DES ANCIENS DE LA LEGION ETRANGERE | B76: 1000 | D76: =ISBLANK(B76) -> FALSE | E76: AMICALE DES ANCIENS DE LA LEGION ETRANGERE
A77: AMICALE DES ANCIENS DE MARIE-BRIZARD - AAMB | B77: 0 | C77: Locaux | D77: =ISBLANK(B77) -> FALSE | E77: AMICALE DES ANCIENS DE MARIE-BRIZARD - AAMB
A78: AMICALE DES ANCIENS DES NOUVELLES GALERIES DE BORDEAUX | B78: 0 | C78: Locaux | D78: =ISBLANK(B78) -> FALSE | E78: AMICALE DES ANCIENS DES NOUVELLES GALERIES DE BORDEAUX
A79: AMICALE DES ANCIENS DES TROUPES DE MARINE DE BORDEAUX ET | B79: 500 | D79: =ISBLANK(B79) -> FALSE | E79: AMICALE DES ANCIENS DES TROUPES DE MARINE DE BORDEAUX ET D'AQUITAINE
A80: D'AQUITAINE | D80: =ISBLANK(B80) -> TRUE | E80: D'AQUITAINE
A81: AMICALE DES ANCIENS GUERILLEROS ESPAGNOLS EN FRANCE-FFI - | B81: 0 | C81: Locaux | D81: =ISBLANK(B81) -> FALSE | E81: AMICALE DES ANCIENS GUERILLEROS ESPAGNOLS EN FRANCE-FFI - SECTION DE LA GIRONDE
A82: SECTION DE LA GIRONDE | D82: =ISBLANK(B82) -> TRUE | E82: SECTION DE LA GIRONDE
A83: AMICALE DES AVEYRONNAIS DE BORDEAUX ET GIRONDE | B83: 0 | C83: Locaux | D83: =ISBLANK(B83) -> FALSE | E83: AMICALE DES AVEYRONNAIS DE BORDEAUX ET GIRONDE
A84: AMICALE DES ETABLISSEMENTS SCOLAIRES LAIQUES DE BACALAN - | B84: 82238 | C84: Locaux, équipements sportifs, matériel pour | D84: =ISBLANK(B84) -> FALSE | E84: AMICALE DES ETABLISSEMENTS SCOLAIRES LAIQUES DE BACALAN - ALB
A85: ALB | C85: manifestations | D85: =ISBLANK(B85) -> TRUE | E85: ALB
A86: AMICALE DES LOCATAIRES DU PORT DE LA LUNE | B86: 4000 | D86: =ISBLANK(B86) -> FALSE | E86: AMICALE DES LOCATAIRES DU PORT DE LA LUNE
A87: AMICALE DES PARACHUTISTES DU SUD-OUEST | B87: 300 | D87: =ISBLANK(B87) -> FALSE | E87: AMICALE DES PARACHUTISTES DU SUD-OUEST
A88: AMICALE DES PARENTS D'ELEVES DE L'ECOLE STEHELIN | B88: 8605 | D88: =ISBLANK(B88) -> FALSE | E88: AMICALE DES PARENTS D'ELEVES DE L'ECOLE STEHELIN
A89: AMICALE DES PHILIPPEVILLOIS, CONSTANTINOIS ET LEURS AMIS - | B89: 0 | C89: Locaux | D89: =ISBLANK(B89) -> FALSE | E89: AMICALE DES PHILIPPEVILLOIS, CONSTANTINOIS ET LEURS AMIS - APCA
A90: APCA | D90: =ISBLANK(B90) -> TRUE | E90: APCA
A91: AMICALE DES RETRAITES U.G.R.R. - I.S.I.C.A. DE BORDEAUX | B91: 0 | C91: Locaux | D91: =ISBLANK(B91) -> FALSE | E91: AMICALE DES RETRAITES U.G.R.R. - I.S.I.C.A. DE BORDEAUX
A92: AMICALE DU PATRONAGE LAIQUE ET DU CONSEIL DE PARENTS | B92: 1000 | C92: Matériel pour manifestations | D92: =ISBLANK(B92) -> FALSE | E92: AMICALE DU PATRONAGE LAIQUE ET DU CONSEIL DE PARENTS D'ELEVES DU GROUPE SCOLAIRE NUYENS
A93: D'ELEVES DU GROUPE SCOLAIRE NUYENS | D93: =ISBLANK(B93) -> TRUE | E93: D'ELEVES DU GROUPE SCOLAIRE NUYENS
A94: AMICALE LAIQUE BORDEAUX CENTRE | B94: 2500 | C94: Locaux, équipements sportifs | D94: =ISBLANK(B94) -> FALSE | E94: AMICALE LAIQUE BORDEAUX CENTRE
A95: AMICALE LAIQUE DAVID JOHNSTON LAGRANGE ALBERT BARRAUD | B95: 450195 | C95: Equipements sportifs | D95: =ISBLANK(B95) -> FALSE | E95: AMICALE LAIQUE DAVID JOHNSTON LAGRANGE ALBERT BARRAUD NAUJAC
A96: NAUJAC | D96: =ISBLANK(B96) -> TRUE | E96: NAUJAC
A97: AMICALE LAIQUE DU GROUPE SCOLAIRE LEONARD-LENOIR - | B97: 0 | C97: Equipements sportifs | D97: =ISBLANK(B97) -> FALSE | E97: AMICALE LAIQUE DU GROUPE SCOLAIRE LEONARD-LENOIR - MONTAUD - NUITS
A98: MONTAUD - NUITS | D98: =ISBLANK(B98) -> TRUE | E98: MONTAUD - NUITS
A99: AMICALE LAIQUE LEONARD LENOIR | B99: 0 | C99: Locaux | D99: =ISBLANK(B99) -> FALSE | E99: AMICALE LAIQUE LEONARD LENOIR
A100: AMICALE NATIONALE DES RETRAITES DE L'AUDIOVISUEL | B100: 0 | C100: Locaux | D100: =ISBLANK(B100) -> FALSE | E100: AMICALE NATIONALE DES RETRAITES DE L'AUDIOVISUEL
...

Sheet etape4
A1: Je crée un filtre sur la colonne "isblank" et je filtre seulement les TRUE, afin de les supprimer: magique, il ne reste plus que les FALSE!
B2: Montant du fonds de concours ou de la subvention (numéraire) | C2: Prestations en nature | D2: isblank | E2: nom des bénéficiaires
A3: "BAMBINO BERTHELOT" ASSOCIATION DE PARENTS D'ELEVES DE | B3: 0 | C3: Locaux | D3: =ISBLANK(B3) -> FALSE | E3: "BAMBINO BERTHELOT" ASSOCIATION DE PARENTS D'ELEVES DE L'ECOLE MATERNELLE BERTHELOT A BORDEAUX
A4: 1001 JEUNES BORDELAIS | B4: 0 | C4: Matériel pour manifestations | D4: =ISBLANK(B4) -> FALSE | E4: 1001 JEUNES BORDELAIS
A5: 2AA | B5: 0 | C5: Locaux | D5: =ISBLANK(B5) -> FALSE | E5: 2AA
A6: 2SI2LA | B6: 0 | C6: Locaux | D6: =ISBLANK(B6) -> FALSE | E6: 2SI2LA
A7: 4 CATS | B7: 0 | C7: Locaux | D7: =ISBLANK(B7) -> FALSE | E7: 4 CATS
A8: 5UN7 | B8: 1000 | D8: =ISBLANK(B8) -> FALSE | E8: 5UN7
A9: 60 000 REBONDS | B9: 1800 | D9: =ISBLANK(B9) -> FALSE | E9: 60 000 REBONDS
A10: 9-33 | B10: 19000 | C10: Communication, locaux | D10: =ISBLANK(B10) -> FALSE | E10: 9-33
A11: A L EAU MUSIC | B11: 500 | D11: =ISBLANK(B11) -> FALSE | E11: A L EAU MUSIC
A12: A PART ENTIERE | B12: 2000 | D12: =ISBLANK(B12) -> FALSE | E12: A PART ENTIERE
A13: A PETIT PAS | B13: 3000 | D13: =ISBLANK(B13) -> FALSE | E13: A PETIT PAS
A14: A TRAVERS CHANT | B14: 0 | C14: Locaux | D14: =ISBLANK(B14) -> FALSE | E14: A TRAVERS CHANT
A15: A2RUNNING | B15: 0 | C15: Locaux | D15: =ISBLANK(B15) -> FALSE | E15: A2RUNNING
A16: ABALONE CHASSE BORDEAUX | B16: 0 | C16: Locaux, équipements sportifs | D16: =ISBLANK(B16) -> FALSE | E16: ABALONE CHASSE BORDEAUX
A17: ABEILLES BORDELAISES | B17: 0 | C17: Locaux | D17: =ISBLANK(B17) -> FALSE | E17: ABEILLES BORDELAISES
A18: ACADEMIE BUSHIKAI KARATE DO | B18: 0 | C18: Equipements sportifs | D18: =ISBLANK(B18) -> FALSE | E18: ACADEMIE BUSHIKAI KARATE DO
A19: ACADEMIE DES SCIENCES, BELLES LETTRES ET ARTS DE | B19: 7600 | C19: Locaux, matériel pour manifestations | D19: =ISBLANK(B19) -> FALSE | E19: ACADEMIE DES SCIENCES, BELLES LETTRES ET ARTS DE BORDEAUX
A20: ACADEMIE PROSPECTIVE NOUVELLES TECHNOLOGIES | B20: 0 | C20: Locaux | D20: =ISBLANK(B20) -> FALSE | E20: ACADEMIE PROSPECTIVE NOUVELLES TECHNOLOGIES
A21: ACADEMIE YOUNUS | B21: 22000 | C21: Locaux, équipements sportifs, matériel pour | D21: =ISBLANK(B21) -> FALSE | E21: ACADEMIE YOUNUS
A22: ACCOMPAGNEMENT ET RECHERCHE PSYCHO-SOCIO EDUCATIFS | B22: 0 | C22: Locaux | D22: =ISBLANK(B22) -> FALSE | E22: ACCOMPAGNEMENT ET RECHERCHE PSYCHO-SOCIO EDUCATIFS POUR LES JEUNES (ARPEJE)
A23: ACCOMPAGNEMENT PSYCHOLOGIQUE ET MEDIATION | B23: 5000 | D23: =ISBLANK(B23) -> FALSE | E23: ACCOMPAGNEMENT PSYCHOLOGIQUE ET MEDIATION INTERCULTURELLE - AMI
A24: ACCOMPAGNER CONDUIRE TRANSMETTRE - ACT | B24: 300 | C24: Locaux | D24: =ISBLANK(B24) -> FALSE | E24: ACCOMPAGNER CONDUIRE TRANSMETTRE - ACT
A25: ACCORDERIE BORDEAUX SUD | B25: 4500 | C25: Locaux | D25: =ISBLANK(B25) -> FALSE | E25: ACCORDERIE BORDEAUX SUD
A26: ACHATS GROUPES ASSOCIATIF POUR L'ECONOMIE SOLIDAIRE DE | B26: 0 | C26: Locaux | D26: =ISBLANK(B26) -> FALSE | E26: ACHATS GROUPES ASSOCIATIF POUR L'ECONOMIE SOLIDAIRE DE BORDEAUX - AGAPES
A27: ACIDD, ASSOCIATION COMMUNICATION ET INFORMATION POUR LE | B27: 10000 | C27: Locaux | D27: =ISBLANK(B27) -> FALSE | E27: ACIDD, ASSOCIATION COMMUNICATION ET INFORMATION POUR LE DEVELOPPEMENT DURABLE
A28: ACINQBYS_ESPACE 29 A5BIS | B28: 22000 | D28: =ISBLANK(B28) -> FALSE | E28: ACINQBYS_ESPACE 29 A5BIS
A29: ACTA GIRONDE - AGIR CONTRE LA TORTURE DES ANIMAUX | B29: 0 | C29: Locaux | D29: =ISBLANK(B29) -> FALSE | E29: ACTA GIRONDE - AGIR CONTRE LA TORTURE DES ANIMAUX
A30: ACTIFS 33 | B30: 2400 | D30: =ISBLANK(B30) -> FALSE | E30: ACTIFS 33
A31: ACTIMAGE | B31: 6500 | D31: =ISBLANK(B31) -> FALSE | E31: ACTIMAGE
A32: ACTION CONTRE LA FAIM | B32: 0 | C32: Locaux | D32: =ISBLANK(B32) -> FALSE | E32: ACTION CONTRE LA FAIM
A33: ACTION INTERNATIONALE POUR LA PAIX ET LE DEVELOPPEMENT | B33: 0 | C33: Locaux | D33: =ISBLANK(B33) -> FALSE | E33: ACTION INTERNATIONALE POUR LA PAIX ET LE DEVELOPPEMENT
A34: AD LUCEM THEATRE | B34: 0 | C34: Locaux | D34: =ISBLANK(B34) -> FALSE | E34: AD LUCEM THEATRE
A35: ADDAH 33 | B35: 500 | D35: =ISBLANK(B35) -> FALSE | E35: ADDAH 33
A36: ADORA | B36: 5000 | C36: Locaux | D36: =ISBLANK(B36) -> FALSE | E36: ADORA
A37: ADRIA | B37: 1500 | D37: =ISBLANK(B37) -> FALSE | E37: ADRIA
A38: AEP SAINT PROJET | B38: 0 | C38: Matériel pour manifestations | D38: =ISBLANK(B38) -> FALSE | E38: AEP SAINT PROJET
A39: AFRICAFRANCE | B39: 1500 | D39: =ISBLANK(B39) -> FALSE | E39: AFRICAFRANCE
A40: AGENCE D'URBANISME BORDEAUX METROPOLE AQUITAINE | B40: 60000 | D40: =ISBLANK(B40) -> FALSE | E40: AGENCE D'URBANISME BORDEAUX METROPOLE AQUITAINE (A'URBA)
A41: AGENCE LOCALE DE L'ENERGIE ET DU CLIMAT (ALEC) | B41: 6000 | C41: Locaux | D41: =ISBLANK(B41) -> FALSE | E41: AGENCE LOCALE DE L'ENERGIE ET DU CLIMAT (ALEC)
A42: AGENCE REGIONALE DE SANTE NOUVELLE AQUITAINE | B42: 0 | C42: Matériel pour manifestations | D42: =ISBLANK(B42) -> FALSE | E42: AGENCE REGIONALE DE SANTE NOUVELLE AQUITAINE
A43: AGIR POUR UN COMMERE EQUITABLE ET SOLIDAIRE EN AQUITAINE - | B43: 500 | D43: =ISBLANK(B43) -> FALSE | E43: AGIR POUR UN COMMERE EQUITABLE ET SOLIDAIRE EN AQUITAINE - ACESA
A44: AGORA DES ARTS | B44: 5000 | C44: Matériel pour manifestations | D44: =ISBLANK(B44) -> FALSE | E44: AGORA DES ARTS
A45: AIDE AUX AIDANTS DU PAVILLON | B45: 2000 | D45: =ISBLANK(B45) -> FALSE | E45: AIDE AUX AIDANTS DU PAVILLON
A46: AIDES AQUITAINE | B46: 5500 | D46: =ISBLANK(B46) -> FALSE | E46: AIDES AQUITAINE
A47: AIGUILLES ET CALAME | B47: 0 | C47: Locaux | D47: =ISBLANK(B47) -> FALSE | E47: AIGUILLES ET CALAME
A48: AIKIDO BORDEAUX BASTIDE | B48: 2000 | C48: Equipements sportifs | D48: =ISBLANK(B48) -> FALSE | E48: AIKIDO BORDEAUX BASTIDE
A49: AIM ACTIONS INTER MEDIATION | B49: 20060 | D49: =ISBLANK(B49) -> FALSE | E49: AIM ACTIONS INTER MEDIATION
A50: AIR ROLLER (ATTENTION INERTIE RENOUVELABLE) | B50: 11000 | C50: Locaux, équipements sportifs | D50: =ISBLANK(B50) -> FALSE | E50: AIR ROLLER (ATTENTION INERTIE RENOUVELABLE)
A51: ALAM AMIS DU LIVRE ANCIEN ET MODERNE | B51: 0 | C51: Locaux, matériel pour manifestations | D51: =ISBLANK(B51) -> FALSE | E51: ALAM AMIS DU LIVRE ANCIEN ET MODERNE
A52: ALGERIENS DE L'AQUITAINE | B52: 0 | C52: Locaux | D52: =ISBLANK(B52) -> FALSE | E52: ALGERIENS DE L'AQUITAINE
A53: ALLIANCE DEPARTEMENT 33, JUSQU'AU BOUT ACCOMPAGNER LA | B53: 4500 | C53: Locaux | D53: =ISBLANK(B53) -> FALSE | E53: ALLIANCE DEPARTEMENT 33, JUSQU'AU BOUT ACCOMPAGNER LA VIE...
A54: ALLIANCE FRANCAISE DE BORDEAUX AQUITAINE | B54: 0 | C54: Locaux | D54: =ISBLANK(B54) -> FALSE | E54: ALLIANCE FRANCAISE DE BORDEAUX AQUITAINE
A55: ALPTIS | B55: 0 | C55: Locaux | D55: =ISBLANK(B55) -> FALSE | E55: ALPTIS
A56: ALTER INSERTION | B56: 0 | C56: Matériel pour manifestations | D56: =ISBLANK(B56) -> FALSE | E56: ALTER INSERTION
A57: AMADEUS | B57: 1000 | D57: =ISBLANK(B57) -> FALSE | E57: AMADEUS
A58: AMBASSADE REGIONALE DES CONFRERIES DE PRODUITS DE | B58: 500 | D58: =ISBLANK(B58) -> FALSE | E58: AMBASSADE REGIONALE DES CONFRERIES DE PRODUITS DE TERROIR ET DU GOUT
A59: AMELIORATION DES CONDITIONS DE VIE DES ENFANTS | B59: 571 | D59: =ISBLANK(B59) -> FALSE | E59: AMELIORATION DES CONDITIONS DE VIE DES ENFANTS ADOLESCENTS HOSPITALISES
A60: AMEPI | B60: 0 | C60: Locaux | D60: =ISBLANK(B60) -> FALSE | E60: AMEPI
A61: AMICALE BORDELAISE TRACTION AVANT CITROEN | B61: 0 | C61: Locaux | D61: =ISBLANK(B61) -> FALSE | E61: AMICALE BORDELAISE TRACTION AVANT CITROEN
A62: AMICALE COMORIENNE DE BORDEAUX | B62: 0 | C62: Locaux | D62: =ISBLANK(B62) -> FALSE | E62: AMICALE COMORIENNE DE BORDEAUX
A63: AMICALE DE LA RESIDENCE DU LAC | B63: 0 | C63: Locaux | D63: =ISBLANK(B63) -> FALSE | E63: AMICALE DE LA RESIDENCE DU LAC
A64: AMICALE DES ANCIENS DE LA LEGION ETRANGERE | B64: 1000 | D64: =ISBLANK(B64) -> FALSE | E64: AMICALE DES ANCIENS DE LA LEGION ETRANGERE
A65: AMICALE DES ANCIENS DE MARIE-BRIZARD - AAMB | B65: 0 | C65: Locaux | D65: =ISBLANK(B65) -> FALSE | E65: AMICALE DES ANCIENS DE MARIE-BRIZARD - AAMB
A66: AMICALE DES ANCIENS DES NOUVELLES GALERIES DE BORDEAUX | B66: 0 | C66: Locaux | D66: =ISBLANK(B66) -> FALSE | E66: AMICALE DES ANCIENS DES NOUVELLES GALERIES DE BORDEAUX
A67: AMICALE DES ANCIENS DES TROUPES DE MARINE DE BORDEAUX ET | B67: 500 | D67: =ISBLANK(B67) -> FALSE | E67: AMICALE DES ANCIENS DES TROUPES DE MARINE DE BORDEAUX ET D'AQUITAINE
A68: AMICALE DES ANCIENS GUERILLEROS ESPAGNOLS EN FRANCE-FFI - | B68: 0 | C68: Locaux | D68: =ISBLANK(B68) -> FALSE | E68: AMICALE DES ANCIENS GUERILLEROS ESPAGNOLS EN FRANCE-FFI - SECTION DE LA GIRONDE
A69: AMICALE DES AVEYRONNAIS DE BORDEAUX ET GIRONDE | B69: 0 | C69: Locaux | D69: =ISBLANK(B69) -> FALSE | E69: AMICALE DES AVEYRONNAIS DE BORDEAUX ET GIRONDE
A70: AMICALE DES ETABLISSEMENTS SCOLAIRES LAIQUES DE BACALAN - | B70: 82238 | C70: Locaux, équipements sportifs, matériel pour | D70: =ISBLANK(B70) -> FALSE | E70: AMICALE DES ETABLISSEMENTS SCOLAIRES LAIQUES DE BACALAN - ALB
A71: AMICALE DES LOCATAIRES DU PORT DE LA LUNE | B71: 4000 | D71: =ISBLANK(B71) -> FALSE | E71: AMICALE DES LOCATAIRES DU PORT DE LA LUNE
A72: AMICALE DES PARACHUTISTES DU SUD-OUEST | B72: 300 | D72: =ISBLANK(B72) -> FALSE | E72: AMICALE DES PARACHUTISTES DU SUD-OUEST
A73: AMICALE DES PARENTS D'ELEVES DE L'ECOLE STEHELIN | B73: 8605 | D73: =ISBLANK(B73) -> FALSE | E73: AMICALE DES PARENTS D'ELEVES DE L'ECOLE STEHELIN
A74: AMICALE DES PHILIPPEVILLOIS, CONSTANTINOIS ET LEURS AMIS - | B74: 0 | C74: Locaux | D74: =ISBLANK(B74) -> FALSE | E74: AMICALE DES PHILIPPEVILLOIS, CONSTANTINOIS ET LEURS AMIS - APCA
A75: AMICALE DES RETRAITES U.G.R.R. - I.S.I.C.A. DE BORDEAUX | B75: 0 | C75: Locaux | D75: =ISBLANK(B75) -> FALSE | E75: AMICALE DES RETRAITES U.G.R.R. - I.S.I.C.A. DE BORDEAUX
A76: AMICALE DU PATRONAGE LAIQUE ET DU CONSEIL DE PARENTS | B76: 1000 | C76: Matériel pour manifestations | D76: =ISBLANK(B76) -> FALSE | E76: AMICALE DU PATRONAGE LAIQUE ET DU CONSEIL DE PARENTS D'ELEVES DU GROUPE SCOLAIRE NUYENS
A77: AMICALE LAIQUE BORDEAUX CENTRE | B77: 2500 | C77: Locaux, équipements sportifs | D77: =ISBLANK(B77) -> FALSE | E77: AMICALE LAIQUE BORDEAUX CENTRE
A78: AMICALE LAIQUE DAVID JOHNSTON LAGRANGE ALBERT BARRAUD | B78: 450195 | C78: Equipements sportifs | D78: =ISBLANK(B78) -> FALSE | E78: AMICALE LAIQUE DAVID JOHNSTON LAGRANGE ALBERT BARRAUD NAUJAC
A79: AMICALE LAIQUE DU GROUPE SCOLAIRE LEONARD-LENOIR - | B79: 0 | C79: Equipements sportifs | D79: =ISBLANK(B79) -> FALSE | E79: AMICALE LAIQUE DU GROUPE SCOLAIRE LEONARD-LENOIR - MONTAUD - NUITS
A80: AMICALE LAIQUE LEONARD LENOIR | B80: 0 | C80: Locaux | D80: =ISBLANK(B80) -> FALSE | E80: AMICALE LAIQUE LEONARD LENOIR
A81: AMICALE NATIONALE DES RETRAITES DE L'AUDIOVISUEL | B81: 0 | C81: Locaux | D81: =ISBLANK(B81) -> FALSE | E81: AMICALE NATIONALE DES RETRAITES DE L'AUDIOVISUEL
A82: AMIS D'ARS ET FIDES BORDEAUX | B82: 2000 | C82: Locaux | D82: =ISBLANK(B82) -> FALSE | E82: AMIS D'ARS ET FIDES BORDEAUX
A83: AMIS D'ICI ET D'AILLEURS | B83: 750 | C83: Locaux | D83: =ISBLANK(B83) -> FALSE | E83: AMIS D'ICI ET D'AILLEURS
A84: AMIS DE L'HOTEL DE LALANDE | B84: 3109 | D84: =ISBLANK(B84) -> FALSE | E84: AMIS DE L'HOTEL DE LALANDE
A85: AMIS DE L'ORCHESTRE D'HARMONIE DE BORDEAUX | B85: 11011 | D85: =ISBLANK(B85) -> FALSE | E85: AMIS DE L'ORCHESTRE D'HARMONIE DE BORDEAUX
A86: AMIS DU CAPC MUSEE | B86: 0 | C86: Matériel pour manifestations | D86: =ISBLANK(B86) -> FALSE | E86: AMIS DU CAPC MUSEE
A87: AMITIES FRANCAISES | B87: 0 | C87: Locaux | D87: =ISBLANK(B87) -> FALSE | E87: AMITIES FRANCAISES
A88: AMITIES GENEALOGIQUES BORDELAISES | B88: 0 | C88: Locaux | D88: =ISBLANK(B88) -> FALSE | E88: AMITIES GENEALOGIQUES BORDELAISES
A89: AMNESTY INTERNATIONAL GROUPE 234 DE BORDEAUX CENTRE | B89: 0 | C89: Locaux, matériel pour manifestations | D89: =ISBLANK(B89) -> FALSE | E89: AMNESTY INTERNATIONAL GROUPE 234 DE BORDEAUX CENTRE
A90: AMOR DEL TANGO | B90: 0 | C90: Locaux | D90: =ISBLANK(B90) -> FALSE | E90: AMOR DEL TANGO
A91: AMOS | B91: 15000 | D91: =ISBLANK(B91) -> FALSE | E91: AMOS
A92: ANCIENS BASTIDIENS-CLUB | B92: 0 | C92: Locaux | D92: =ISBLANK(B92) -> FALSE | E92: ANCIENS BASTIDIENS-CLUB
A93: ANIMATIONS VILLAGE SAINT-SEURIN | B93: 0 | C93: Matériel pour manifestations | D93: =ISBLANK(B93) -> FALSE | E93: ANIMATIONS VILLAGE SAINT-SEURIN
A94: ANPAA - ASSOCIATION NATIONALE DE PREVENTION EN | B94: 30000 | C94: Locaux | D94: =ISBLANK(B94) -> FALSE | E94: ANPAA - ASSOCIATION NATIONALE DE PREVENTION EN ALCOOLOGIE ET EN ADDICTOLOGIE
A95: APEC (33PASSAJE ) | B95: 1500 | D95: =ISBLANK(B95) -> FALSE | E95: APEC (33PASSAJE )
A96: APNEE 33 | B96: 0 | C96: Equipements sportifs | D96: =ISBLANK(B96) -> FALSE | E96: APNEE 33
A97: APPEL DES CENT POUR LA PAIX COLLECTIF BORDELAIS | B97: 0 | C97: Locaux, matériel pour manifestations | D97: =ISBLANK(B97) -> FALSE | E97: APPEL DES CENT POUR LA PAIX COLLECTIF BORDELAIS
A98: APPRENDRE AVEC MONTESSORI AUJOURD'HUI | B98: 0 | C98: Locaux | D98: =ISBLANK(B98) -> FALSE | E98: APPRENDRE AVEC MONTESSORI AUJOURD'HUI
A99: APPRENTIS D'AUTEUIL - DELEGATION AQUITAINE | B99: 0 | C99: Matériel pour manifestations | D99: =ISBLANK(B99) -> FALSE | E99: APPRENTIS D'AUTEUIL - DELEGATION AQUITAINE
A100: APPRENTISSA'JEU | B100: 3000 | D100: =ISBLANK(B100) -> FALSE | E100: APPRENTISSA'JEU
...

Sheet etape5
A1: Je peux désormais reconstituter mon jeu de données original, en suppriman la colonne A et en bougeant la colonne E pour qu'elle devienne la nouvelle colonne A. Je supprime aussi la colonne isblank, qui nous aura bien aidé
A2: nom des bénéficiaires | B2: Montant du fonds de concours ou de la subvention (numéraire) | C2: Prestations en nature
A3: "BAMBINO BERTHELOT" ASSOCIATION DE PARENTS D'ELEVES DE L'ECOLE MATERNELLE BERTHELOT A BORDEAUX | B3: 0 | C3: Locaux
A4: 1001 JEUNES BORDELAIS | B4: 0 | C4: Matériel pour manifestations
A5: 2AA | B5: 0 | C5: Locaux
A6: 2SI2LA | B6: 0 | C6: Locaux
A7: 4 CATS | B7: 0 | C7: Locaux
A8: 5UN7 | B8: 1000
A9: 60 000 REBONDS | B9: 1800
A10: 9-33 | B10: 19000 | C10: Communication, locaux
A11: A L EAU MUSIC | B11: 500
A12: A PART ENTIERE | B12: 2000
A13: A PETIT PAS | B13: 3000
A14: A TRAVERS CHANT | B14: 0 | C14: Locaux
A15: A2RUNNING | B15: 0 | C15: Locaux
A16: ABALONE CHASSE BORDEAUX | B16: 0 | C16: Locaux, équipements sportifs
A17: ABEILLES BORDELAISES | B17: 0 | C17: Locaux
A18: ACADEMIE BUSHIKAI KARATE DO | B18: 0 | C18: Equipements sportifs
A19: ACADEMIE DES SCIENCES, BELLES LETTRES ET ARTS DE BORDEAUX | B19: 7600 | C19: Locaux, matériel pour manifestations
A20: ACADEMIE PROSPECTIVE NOUVELLES TECHNOLOGIES | B20: 0 | C20: Locaux
A21: ACADEMIE YOUNUS | B21: 22000 | C21: Locaux, équipements sportifs, matériel pour
A22: ACCOMPAGNEMENT ET RECHERCHE PSYCHO-SOCIO EDUCATIFS POUR LES JEUNES (ARPEJE) | B22: 0 | C22: Locaux
A23: ACCOMPAGNEMENT PSYCHOLOGIQUE ET MEDIATION INTERCULTURELLE - AMI | B23: 5000
A24: ACCOMPAGNER CONDUIRE TRANSMETTRE - ACT | B24: 300 | C24: Locaux
A25: ACCORDERIE BORDEAUX SUD | B25: 4500 | C25: Locaux
A26: ACHATS GROUPES ASSOCIATIF POUR L'ECONOMIE SOLIDAIRE DE BORDEAUX - AGAPES | B26: 0 | C26: Locaux
A27: ACIDD, ASSOCIATION COMMUNICATION ET INFORMATION POUR LE DEVELOPPEMENT DURABLE | B27: 10000 | C27: Locaux
A28: ACINQBYS_ESPACE 29 A5BIS | B28: 22000
A29: ACTA GIRONDE - AGIR CONTRE LA TORTURE DES ANIMAUX | B29: 0 | C29: Locaux
A30: ACTIFS 33 | B30: 2400
A31: ACTIMAGE | B31: 6500
A32: ACTION CONTRE LA FAIM | B32: 0 | C32: Locaux
A33: ACTION INTERNATIONALE POUR LA PAIX ET LE DEVELOPPEMENT | B33: 0 | C33: Locaux
A34: AD LUCEM THEATRE | B34: 0 | C34: Locaux
A35: ADDAH 33 | B35: 500
A36: ADORA | B36: 5000 | C36: Locaux
A37: ADRIA | B37: 1500
A38: AEP SAINT PROJET | B38: 0 | C38: Matériel pour manifestations
A39: AFRICAFRANCE | B39: 1500
A40: AGENCE D'URBANISME BORDEAUX METROPOLE AQUITAINE (A'URBA) | B40: 60000
A41: AGENCE LOCALE DE L'ENERGIE ET DU CLIMAT (ALEC) | B41: 6000 | C41: Locaux
A42: AGENCE REGIONALE DE SANTE NOUVELLE AQUITAINE | B42: 0 | C42: Matériel pour manifestations
A43: AGIR POUR UN COMMERE EQUITABLE ET SOLIDAIRE EN AQUITAINE - ACESA | B43: 500
A44: AGORA DES ARTS | B44: 5000 | C44: Matériel pour manifestations
A45: AIDE AUX AIDANTS DU PAVILLON | B45: 2000
A46: AIDES AQUITAINE | B46: 5500
A47: AIGUILLES ET CALAME | B47: 0 | C47: Locaux
A48: AIKIDO BORDEAUX BASTIDE | B48: 2000 | C48: Equipements sportifs
A49: AIM ACTIONS INTER MEDIATION | B49: 20060
A50: AIR ROLLER (ATTENTION INERTIE RENOUVELABLE) | B50: 11000 | C50: Locaux, équipements sportifs
A51: ALAM AMIS DU LIVRE ANCIEN ET MODERNE | B51: 0 | C51: Locaux, matériel pour manifestations
A52: ALGERIENS DE L'AQUITAINE | B52: 0 | C52: Locaux
A53: ALLIANCE DEPARTEMENT 33, JUSQU'AU BOUT ACCOMPAGNER LA VIE... | B53: 4500 | C53: Locaux
A54: ALLIANCE FRANCAISE DE BORDEAUX AQUITAINE | B54: 0 | C54: Locaux
A55: ALPTIS | B55: 0 | C55: Locaux
A56: ALTER INSERTION | B56: 0 | C56: Matériel pour manifestations
A57: AMADEUS | B57: 1000
A58: AMBASSADE REGIONALE DES CONFRERIES DE PRODUITS DE TERROIR ET DU GOUT | B58: 500
A59: AMELIORATION DES CONDITIONS DE VIE DES ENFANTS ADOLESCENTS HOSPITALISES | B59: 571
A60: AMEPI | B60: 0 | C60: Locaux
A61: AMICALE BORDELAISE TRACTION AVANT CITROEN | B61: 0 | C61: Locaux
A62: AMICALE COMORIENNE DE BORDEAUX | B62: 0 | C62: Locaux
A63: AMICALE DE LA RESIDENCE DU LAC | B63: 0 | C63: Locaux
A64: AMICALE DES ANCIENS DE LA LEGION ETRANGERE | B64: 1000
A65: AMICALE DES ANCIENS DE MARIE-BRIZARD - AAMB | B65: 0 | C65: Locaux
A66: AMICALE DES ANCIENS DES NOUVELLES GALERIES DE BORDEAUX | B66: 0 | C66: Locaux
A67: AMICALE DES ANCIENS DES TROUPES DE MARINE DE BORDEAUX ET D'AQUITAINE | B67: 500
A68: AMICALE DES ANCIENS GUERILLEROS ESPAGNOLS EN FRANCE-FFI - SECTION DE LA GIRONDE | B68: 0 | C68: Locaux
A69: AMICALE DES AVEYRONNAIS DE BORDEAUX ET GIRONDE | B69: 0 | C69: Locaux
A70: AMICALE DES ETABLISSEMENTS SCOLAIRES LAIQUES DE BACALAN - ALB | B70: 82238 | C70: Locaux, équipements sportifs, matériel pour
A71: AMICALE DES LOCATAIRES DU PORT DE LA LUNE | B71: 4000
A72: AMICALE DES PARACHUTISTES DU SUD-OUEST | B72: 300
A73: AMICALE DES PARENTS D'ELEVES DE L'ECOLE STEHELIN | B73: 8605
A74: AMICALE DES PHILIPPEVILLOIS, CONSTANTINOIS ET LEURS AMIS - APCA | B74: 0 | C74: Locaux
A75: AMICALE DES RETRAITES U.G.R.R. - I.S.I.C.A. DE BORDEAUX | B75: 0 | C75: Locaux
A76: AMICALE DU PATRONAGE LAIQUE ET DU CONSEIL DE PARENTS D'ELEVES DU GROUPE SCOLAIRE NUYENS | B76: 1000 | C76: Matériel pour manifestations
A77: AMICALE LAIQUE BORDEAUX CENTRE | B77: 2500 | C77: Locaux, équipements sportifs
A78: AMICALE LAIQUE DAVID JOHNSTON LAGRANGE ALBERT BARRAUD NAUJAC | B78: 450195 | C78: Equipements sportifs
A79: AMICALE LAIQUE DU GROUPE SCOLAIRE LEONARD-LENOIR - MONTAUD - NUITS | B79: 0 | C79: Equipements sportifs
A80: AMICALE LAIQUE LEONARD LENOIR | B80: 0 | C80: Locaux
A81: AMICALE NATIONALE DES RETRAITES DE L'AUDIOVISUEL | B81: 0 | C81: Locaux
A82: AMIS D'ARS ET FIDES BORDEAUX | B82: 2000 | C82: Locaux
A83: AMIS D'ICI ET D'AILLEURS | B83: 750 | C83: Locaux
A84: AMIS DE L'HOTEL DE LALANDE | B84: 3109
A85: AMIS DE L'ORCHESTRE D'HARMONIE DE BORDEAUX | B85: 11011
A86: AMIS DU CAPC MUSEE | B86: 0 | C86: Matériel pour manifestations
A87: AMITIES FRANCAISES | B87: 0 | C87: Locaux
A88: AMITIES GENEALOGIQUES BORDELAISES | B88: 0 | C88: Locaux
A89: AMNESTY INTERNATIONAL GROUPE 234 DE BORDEAUX CENTRE | B89: 0 | C89: Locaux, matériel pour manifestations
A90: AMOR DEL TANGO | B90: 0 | C90: Locaux
A91: AMOS | B91: 15000
A92: ANCIENS BASTIDIENS-CLUB | B92: 0 | C92: Locaux
A93: ANIMATIONS VILLAGE SAINT-SEURIN | B93: 0 | C93: Matériel pour manifestations
A94: ANPAA - ASSOCIATION NATIONALE DE PREVENTION EN ALCOOLOGIE ET EN ADDICTOLOGIE | B94: 30000 | C94: Locaux
A95: APEC (33PASSAJE ) | B95: 1500
A96: APNEE 33 | B96: 0 | C96: Equipements sportifs
A97: APPEL DES CENT POUR LA PAIX COLLECTIF BORDELAIS | B97: 0 | C97: Locaux, matériel pour manifestations
A98: APPRENDRE AVEC MONTESSORI AUJOURD'HUI | B98: 0 | C98: Locaux
A99: APPRENTIS D'AUTEUIL - DELEGATION AQUITAINE | B99: 0 | C99: Matériel pour manifestations
A100: APPRENTISSA'JEU | B100: 3000
...

Sheet clean
A1: nom des bénéficiaires | B1: Montant du fonds de concours ou de la subvention (numéraire) | C1: Prestations en nature
A2: OPERA NATIONAL DE BORDEAUX | B2: 16167670
A3: ASSOCIATION DES CENTRES D'ANIMATION DE QUARTIERS DE BORDEAUX - ACAQB | B3: 8060927.5 | C3: Communication, locaux, équipements sportifs,
A4: CCAS DE BORDEAUX | B4: 7912204
A5: ECOLE D'ENSEIGNEMENT SUPÉRIEUR D'ART DE BORDEAUX - ESAB | B5: 3120000
A6: ASSOCIATION PITCHOUN | B6: 1735000 | C6: Locaux
A7: THEATRE NATIONAL DE BORDEAUX EN AQUITAINE - TNBA | B7: 1646816 | C7: Communication, locaux
A8: ASSOCIATION PETITE ENFANCE ENFANCE ET FAMILLE - APEEF | B8: 1578403 | C8: Locaux, matériel pour manifestations
A9: UNION SAINT-BRUNO | B9: 1537650 | C9: Locaux, équipements sportifs, matériel pour
A10: SPORTING CHANTECLER BORDEAUX NORD LE LAC | B10: 1128560 | C10: Locaux, équipements sportifs, matériel pour
A11: AVANT GARDE ET JEANNE D'ARC DE BORDEAUX CAUDERAN - AGJA BORDEAUX CAUDERAN | B11: 1089439 | C11: Locaux, équipements sportifs, matériel pour
A12: UNION SPORTIVE LES CHARTRONS | B12: 896350 | C12: Locaux, équipements sportifs, matériel pour
A13: LES JEUNES DE SAINT AUGUSTIN - JSA | B13: 892663 | C13: Locaux, équipements sportifs, matériel pour
A14: UNION SAINT JEAN - MAISON DE QUARTIER | B14: 879983 | C14: Locaux, équipements sportifs, matériel pour
A15: STADE BORDELAIS ASPTT | B15: 819458 | C15: Locaux, équipements sportifs, matériel pour
A16: ARC EN REVE | B16: 752250 | C16: Communication, matériel pour manifestations, locaux
A17: MAISON DE L'EMPLOI, DE L'INSERTION ECONOMIQUE ET DE L'ENTREPRISE DE BORDEAUX | B17: 678000
A18: CLUB PYRENEES AQUITAINE, ASSOCIATION SPORTIVE, EDUCATIVE ET CULTURELLE | B18: 634600 | C18: Locaux, équipements sportifs, matériel pour
A19: P'TIT BOUT'CHOU | B19: 567000 | C19: Matériel pour manifestations
A20: ASSOCIATION BRINS D'EVEIL | B20: 532800
A21: ASSOCIATION DE GESTION ET D'ANIMATION DES CRECHES C.S.F. (AGEAC/CSF) | B21: 512833.33
A22: MISSION LOCALE BORDEAUX AVENIR JEUNES | B22: 494000 | C22: Locaux, matériel pour manifestations
A23: GP INTENCITE CENTRE SOCIAL ET CULTUREL DU GRAND PARC | B23: 492222 | C23: Locaux, matériel pour manifestations
A24: INTERLUDE | B24: 478850 | C24: Locaux, matériel pour manifestations
A25: CENTRE SOCIAL ET FAMILIAL BORDEAUX NORD | B25: 461165 | C25: Locaux, équipements sportifs, matériel pour
A26: AMICALE LAIQUE DAVID JOHNSTON LAGRANGE ALBERT BARRAUD NAUJAC | B26: 450195 | C26: Equipements sportifs
A27: SASP UNION BORDEAUX BEGLES | B27: 450000 | C27: Matériel pour manifestations
A28: FOYER FRATERNEL | B28: 426565 | C28: Locaux, matériel pour manifestations
A29: FESTIVAL DES ARTS DE BORDEAUX | B29: 402000 | C29: Communication, locaux
A30: ASSOCIATION DU COMITE DES OEUVRES SOCIALES DES MUNICIPAUX DE BORDEAUX - ACOSMB | B30: 380000 | C30: Matériel pour manifestations
A31: POLE D'ENSEIGNEMENT SUPERIEUR DE LA MUSIQUE ET DE LA DANSE DE BORDEAUX AQUITAINE - PESMD | B31: 357672 | C31: Locaux
A32: AUTEUIL PETITE ENFANCE | B32: 347000
A33: LES COQS ROUGES | B33: 343924 | C33: Equipements sportifs, matériel pour manifestations
A34: BORDEAUX GRANDS EVENEMENTS (BGE) | B34: 339500 | C34: Communication, locaux
A35: GESTION DU CENTRE DE LOISIRS DE LA POSTE ALEMA | B35: 334000
A36: ASSOCIATION PETITS BOUCHONS | B36: 311500
A37: ASSOCIATION POUR L'INNOVATION EN MATIERE D'INTEGRATION | B37: 300000
A38: BOXERS DE BORDEAUX | B38: 283000
A39: SASP JSA BORDEAUX METROPOLE | B39: 280000 | C39: Matériel pour manifestations
A40: CLUB ATHLETIQUE MUNICIPAL DE BORDEAUX - CAM | B40: 243834 | C40: Locaux, équipements sportifs, matériel pour
A41: LES ENFANTS D'OSIRIS | B41: 240000
A42: PARALLELES ATTITUDES DIFFUSION - ROCKSCHOOL | B42: 237000 | C42: Locaux, matériel pour manifestations, matériel
A43: BORDEAUX ETUDIANTS CLUB - BEC | B43: 223734 | C43: Locaux, équipements sportifs, matériel pour
A44: EVEILLEZ LES BEBES | B44: 210000
A45: LES PARENTS DE CAUDERAN | B45: 205000
A46: LUCILANN | B46: 200000
A47: BORDEAUX GIRONDE INVESTISSEMENT | B47: 198775 | C47: Matériel pour manifestations
A48: LA MANUFACTURE ATLANTIQUE | B48: 198000 | C48: Communication, locaux, matériel pour
A49: GROUPEMENT D'INTERET PUBLIC BORDEAUX MEDIATION | B49: 190000
A50: ESCALES LITTERAIRES BORDEAUX AQUITAINE | B50: 185000 | C50: Communication, locaux, matériel pour manifestations
A51: ASSOCIATION LA COCCINELLE | B51: 180000
A52: O'PTIMÔMES LOISIRS | B52: 170592
A53: ASTROLABE | B53: 153407 | C53: Locaux, matériel pour manifestations
A54: GIRONDINS DE BORDEAUX BASTIDE HANDBALL CLUB | B54: 141174 | C54: Locaux, équipements sportifs, matériel pour
A55: LES GIRONDINS DE BORDEAUX | B55: 132000 | C55: Locaux, équipements sportifs, matériel pour
A56: NUAGE BLEU | B56: 130000 | C56: Locaux
A57: OGEC LYCEE BEL ORME | B57: 120000
A58: LA RONDE DES QUARTIERS DE BORDEAUX | B58: 119100 | C58: Communication, locaux, matériel pour manifestations
A59: VILLA PRIMROSE | B59: 119000 | C59: Communication, équipements sportifs, matériel pour
A60: EMULATION NAUTIQUE DE BORDEAUX | B60: 118603 | C60: Locaux, équipements sportifs, matériel pour
A61: CAISSE SOCIALE DE DEVELOPPEMENT LOCAL | B61: 115000
A62: COS VILLA PIA - EHPAD LES DAMES DE LA FOI | B62: 115000 | C62: Matériel pour manifestations
A63: GLOB THEATRE | B63: 115000 | C63: Locaux, matériel pour manifestations
A64: MAISON DES JEUNES ET DE LA CULTURE CENTRE DE LOISIRS DES DEUX VILLES - MJC CL2V | B64: 110350 | C64: Matériel pour manifestations
A65: ECOLE SUPERIEURE DE THEATRE BORDEAUX AQUITAINE - ESTBA | B65: 109834
A66: UNIS CITE | B66: 105000 | C66: Locaux, matériel pour manifestations
A67: FOOTBALL CLUB DES GIRONDINS DE BORDEAUX - FCGB | B67: 100000 | C67: Equipements sportifs
A68: UNION BORDEAUX METROPOLE - UBM | B68: 83680 | C68: Locaux, équipements sportifs
A69: AMICALE DES ETABLISSEMENTS SCOLAIRES LAIQUES DE BACALAN - ALB | B69: 82238 | C69: Locaux, équipements sportifs, matériel pour
A70: CAP SCIENCES | B70: 81568
A71: BORDEAUX MERIGNAC VOLLEY | B71: 80000 | C71: Equipements sportifs
A72: LA HALLE DES DOUVES | B72: 80000 | C72: Locaux
A73: SOLIHA, SOLIDAIRES POUR L'HABITAT, GIRONDE | B73: 73900 | C73: Locaux
A74: SEMER LE DOUTE | B74: 73250 | C74: Communication, locaux, matériel pour
A75: HALTE 33 | B75: 66000
A76: RESEAU PAUL BERT CENTRE SOCIAL ET CULTUREL | B76: 64000
A77: AGENCE D'URBANISME BORDEAUX METROPOLE AQUITAINE (A'URBA) | B77: 60000
A78: CHAHUTS | B78: 57500 | C78: Communication, locaux, matériel pour manifestations
A79: LA CAISSE A OUTILS | B79: 57005
A80: LA MEMOIRE DE BORDEAUX METROPOLE | B80: 56105 | C80: Locaux, matériel informatique
A81: MAISON DE L'EUROPE BORDEAUX-AQUITAINE (MEBA) | B81: 56000 | C81: Locaux
A82: ASSOCIATION LAIQUE LE PRADO | B82: 55000
A83: LES PETITS DEBROUILLARDS AQUITAINE | B83: 54201 | C83: Matériel pour manifestations
A84: FONDATION D'AUTEUIL AQUITAINE | B84: 52500 | C84: Locaux
A85: THEATRE DU PONT TOURNANT | B85: 52250
A86: REGIE DE QUARTIER HABITER BACALAN | B86: 51000 | C86: Locaux
A87: ASSOCIATION DE DEFENSE DES MUSIQUES ALTERNATIVES EN AQUITAINE - ADMAA (ALLEZ LES FILLES) | B87: 50580 | C87: Communication, matériel pour manifestations
A88: ASSOCIATION UNION BORDEAUX BEGLES | B88: 50000 | C88: Matériel pour manifestations
A89: LA CITE DU VIN | B89: 50000
A90: LE SERVICE GAGNANT | B90: 50000
A91: MAIRES RESPONSABLES METROPOLES FRANCOPHONES - AIMF | B91: 50000
A92: CENTRE D'INFORMATION JEUNESSE AQUITAINE - CIJA | B92: 49000 | C92: Locaux, matériel pour manifestations
A93: ECOLE DE CIRQUE DE BORDEAUX, CENTRE CULTUREL DES ARTS DU CIRQUE | B93: 46500 | C93: Locaux
A94: MAISON DE NOLAN | B94: 46000
A95: ASSOCIATION GIRONDINE D'EDUCATION SPECIALISEE ET DE PREVENTION SOCIALE - AGEP | B95: 45400 | C95: Locaux
A96: ATELIER GRAPHITE | B96: 44200 | C96: Locaux
A97: COMPAGNIE DES MARCHES DE L'ETE | B97: 41500 | C97: Communication, locaux, matériel pour manifestations
A98: MUSIQUES DE NUIT - DIFFUSION | B98: 40700 | C98: Communication, matériel pour manifestations
A99: CONGRES ET EXPOSITIONS DE BORDEAUX | B99: 40000 | C99: Communication, matériel pour manifestations
A100: ASSOCIATION PROMOTION INSERTION SPORT EN AQUITAINE - APIS | B100: 37754 | C100: Equipements sportifs, matériel pour manifestations
...

Sheet verif1
A1: Maintenant que j'ai une jeu de données propre, je peux passer à l'étape de vérification statistique: je vais regarder des indicateurs statistiques classiques qui me donneront une idée de si il y a des choses étranges qui se passent dans mon jeu de données. Ici par exemple, le fait que la médiane et la moyenne soient à 0 signifie que la majorité des associations ne reçoivent aucun appui financier. Est-ce que cela fait sens ? C'est là où votre bon sens et votre connaissance du contexte doit vous guider : impossible d'analyser des données sans comprendre leur contexte ! Ici vous pouvez aussi comparer le total obtenu avec le total affiché dans le PDF. Si le chiffre n'est pas le même, préparez-vous à vérifier 2, 3 fois toutes vos étapes d'extraction et de nettoyage de données. Si le décalage reste toujours, l'erreur est peut-être dans le fichier d'origine !
A2: COUNT | B2: =COUNT(B9:B1541) -> 1533
A3: MAXIMUM | B3: =MAX(B9:B1541) -> 16167670
A4: MINIMUM | B4: =MIN(B9:B1541) -> 0
A5: MEDIANE | B5: =MEDIAN(B9:B1541) -> 0
A6: MOYENNE | B6: =AVERAGE(B9:B1541) -> 44559.533
A7: TOTAL | B7: =SUM(B9:B1541) -> 68309764
A8: nom des bénéficiaires | B8: Montant du fonds de concours ou de la subvention (numéraire) | C8: Prestations en nature
A9: "BAMBINO BERTHELOT" ASSOCIATION DE PARENTS D'ELEVES DE L'ECOLE MATERNELLE BERTHELOT A BORDEAUX | B9: 0 | C9: Locaux
A10: 1001 JEUNES BORDELAIS | B10: 0 | C10: Matériel pour manifestations
A11: 2AA | B11: 0 | C11: Locaux
A12: 2SI2LA | B12: 0 | C12: Locaux
A13: 4 CATS | B13: 0 | C13: Locaux
A14: 5UN7 | B14: 1000
A15: 60 000 REBONDS | B15: 1800
A16: 9-33 | B16: 19000 | C16: Communication, locaux
A17: A L EAU MUSIC | B17: 500
A18: A PART ENTIERE | B18: 2000
A19: A PETIT PAS | B19: 3000
A20: A TRAVERS CHANT | B20: 0 | C20: Locaux
A21: A2RUNNING | B21: 0 | C21: Locaux
A22: ABALONE CHASSE BORDEAUX | B22: 0 | C22: Locaux, équipements sportifs
A23: ABEILLES BORDELAISES | B23: 0 | C23: Locaux
A24: ACADEMIE BUSHIKAI KARATE DO | B24: 0 | C24: Equipements sportifs
A25: ACADEMIE DES SCIENCES, BELLES LETTRES ET ARTS DE BORDEAUX | B25: 7600 | C25: Locaux, matériel pour manifestations
A26: ACADEMIE PROSPECTIVE NOUVELLES TECHNOLOGIES | B26: 0 | C26: Locaux
A27: ACADEMIE YOUNUS | B27: 22000 | C27: Locaux, équipements sportifs, matériel pour
A28: ACCOMPAGNEMENT ET RECHERCHE PSYCHO-SOCIO EDUCATIFS POUR LES JEUNES (ARPEJE) | B28: 0 | C28: Locaux
A29: ACCOMPAGNEMENT PSYCHOLOGIQUE ET MEDIATION INTERCULTURELLE - AMI | B29: 5000
A30: ACCOMPAGNER CONDUIRE TRANSMETTRE - ACT | B30: 300 | C30: Locaux
A31: ACCORDERIE BORDEAUX SUD | B31: 4500 | C31: Locaux
A32: ACHATS GROUPES ASSOCIATIF POUR L'ECONOMIE SOLIDAIRE DE BORDEAUX - AGAPES | B32: 0 | C32: Locaux
A33: ACIDD, ASSOCIATION COMMUNICATION ET INFORMATION POUR LE DEVELOPPEMENT DURABLE | B33: 10000 | C33: Locaux
A34: ACINQBYS_ESPACE 29 A5BIS | B34: 22000
A35: ACTA GIRONDE - AGIR CONTRE LA TORTURE DES ANIMAUX | B35: 0 | C35: Locaux
A36: ACTIFS 33 | B36: 2400
A37: ACTIMAGE | B37: 6500
A38: ACTION CONTRE LA FAIM | B38: 0 | C38: Locaux
A39: ACTION INTERNATIONALE POUR LA PAIX ET LE DEVELOPPEMENT | B39: 0 | C39: Locaux
A40: AD LUCEM THEATRE | B40: 0 | C40: Locaux
A41: ADDAH 33 | B41: 500
A42: ADORA | B42: 5000 | C42: Locaux
A43: ADRIA | B43: 1500
A44: AEP SAINT PROJET | B44: 0 | C44: Matériel pour manifestations
A45: AFRICAFRANCE | B45: 1500
A46: AGENCE D'URBANISME BORDEAUX METROPOLE AQUITAINE (A'URBA) | B46: 60000
A47: AGENCE LOCALE DE L'ENERGIE ET DU CLIMAT (ALEC) | B47: 6000 | C47: Locaux
A48: AGENCE REGIONALE DE SANTE NOUVELLE AQUITAINE | B48: 0 | C48: Matériel pour manifestations
A49: AGIR POUR UN COMMERE EQUITABLE ET SOLIDAIRE EN AQUITAINE - ACESA | B49: 500
A50: AGORA DES ARTS | B50: 5000 | C50: Matériel pour manifestations
A51: AIDE AUX AIDANTS DU PAVILLON | B51: 2000
A52: AIDES AQUITAINE | B52: 5500
A53: AIGUILLES ET CALAME | B53: 0 | C53: Locaux
A54: AIKIDO BORDEAUX BASTIDE | B54: 2000 | C54: Equipements sportifs
A55: AIM ACTIONS INTER MEDIATION | B55: 20060
A56: AIR ROLLER (ATTENTION INERTIE RENOUVELABLE) | B56: 11000 | C56: Locaux, équipements sportifs
A57: ALAM AMIS DU LIVRE ANCIEN ET MODERNE | B57: 0 | C57: Locaux, matériel pour manifestations
A58: ALGERIENS DE L'AQUITAINE | B58: 0 | C58: Locaux
A59: ALLIANCE DEPARTEMENT 33, JUSQU'AU BOUT ACCOMPAGNER LA VIE... | B59: 4500 | C59: Locaux
A60: ALLIANCE FRANCAISE DE BORDEAUX AQUITAINE | B60: 0 | C60: Locaux
A61: ALPTIS | B61: 0 | C61: Locaux
A62: ALTER INSERTION | B62: 0 | C62: Matériel pour manifestations
A63: AMADEUS | B63: 1000
A64: AMBASSADE REGIONALE DES CONFRERIES DE PRODUITS DE TERROIR ET DU GOUT | B64: 500
A65: AMELIORATION DES CONDITIONS DE VIE DES ENFANTS ADOLESCENTS HOSPITALISES | B65: 571
A66: AMEPI | B66: 0 | C66: Locaux
A67: AMICALE BORDELAISE TRACTION AVANT CITROEN | B67: 0 | C67: Locaux
A68: AMICALE COMORIENNE DE BORDEAUX | B68: 0 | C68: Locaux
A69: AMICALE DE LA RESIDENCE DU LAC | B69: 0 | C69: Locaux
A70: AMICALE DES ANCIENS DE LA LEGION ETRANGERE | B70: 1000
A71: AMICALE DES ANCIENS DE MARIE-BRIZARD - AAMB | B71: 0 | C71: Locaux
A72: AMICALE DES ANCIENS DES NOUVELLES GALERIES DE BORDEAUX | B72: 0 | C72: Locaux
A73: AMICALE DES ANCIENS DES TROUPES DE MARINE DE BORDEAUX ET D'AQUITAINE | B73: 500
A74: AMICALE DES ANCIENS GUERILLEROS ESPAGNOLS EN FRANCE-FFI - SECTION DE LA GIRONDE | B74: 0 | C74: Locaux
A75: AMICALE DES AVEYRONNAIS DE BORDEAUX ET GIRONDE | B75: 0 | C75: Locaux
A76: AMICALE DES ETABLISSEMENTS SCOLAIRES LAIQUES DE BACALAN - ALB | B76: 82238 | C76: Locaux, équipements sportifs, matériel pour
A77: AMICALE DES LOCATAIRES DU PORT DE LA LUNE | B77: 4000
A78: AMICALE DES PARACHUTISTES DU SUD-OUEST | B78: 300
A79: AMICALE DES PARENTS D'ELEVES DE L'ECOLE STEHELIN | B79: 8605
A80: AMICALE DES PHILIPPEVILLOIS, CONSTANTINOIS ET LEURS AMIS - APCA | B80: 0 | C80: Locaux
A81: AMICALE DES RETRAITES U.G.R.R. - I.S.I.C.A. DE BORDEAUX | B81: 0 | C81: Locaux
A82: AMICALE DU PATRONAGE LAIQUE ET DU CONSEIL DE PARENTS D'ELEVES DU GROUPE SCOLAIRE NUYENS | B82: 1000 | C82: Matériel pour manifestations
A83: AMICALE LAIQUE BORDEAUX CENTRE | B83: 2500 | C83: Locaux, équipements sportifs
A84: AMICALE LAIQUE DAVID JOHNSTON LAGRANGE ALBERT BARRAUD NAUJAC | B84: 450195 | C84: Equipements sportifs
A85: AMICALE LAIQUE DU GROUPE SCOLAIRE LEONARD-LENOIR - MONTAUD - NUITS | B85: 0 | C85: Equipements sportifs
A86: AMICALE LAIQUE LEONARD LENOIR | B86: 0 | C86: Locaux
A87: AMICALE NATIONALE DES RETRAITES DE L'AUDIOVISUEL | B87: 0 | C87: Locaux
A88: AMIS D'ARS ET FIDES BORDEAUX | B88: 2000 | C88: Locaux
A89: AMIS D'ICI ET D'AILLEURS | B89: 750 | C89: Locaux
A90: AMIS DE L'HOTEL DE LALANDE | B90: 3109
A91: AMIS DE L'ORCHESTRE D'HARMONIE DE BORDEAUX | B91: 11011
A92: AMIS DU CAPC MUSEE | B92: 0 | C92: Matériel pour manifestations
A93: AMITIES FRANCAISES | B93: 0 | C93: Locaux
A94: AMITIES GENEALOGIQUES BORDELAISES | B94: 0 | C94: Locaux
A95: AMNESTY INTERNATIONAL GROUPE 234 DE BORDEAUX CENTRE | B95: 0 | C95: Locaux, matériel pour manifestations
A96: AMOR DEL TANGO | B96: 0 | C96: Locaux
A97: AMOS | B97: 15000
A98: ANCIENS BASTIDIENS-CLUB | B98: 0 | C98: Locaux
A99: ANIMATIONS VILLAGE SAINT-SEURIN | B99: 0 | C99: Matériel pour manifestations
A100: ANPAA - ASSOCIATION NATIONALE DE PREVENTION EN ALCOOLOGIE ET EN ADDICTOLOGIE | B100: 30000 | C100: Locaux
...

Sheet analyse1
A1: nom des bénéficiaires | B1: Montant du fonds de concours ou de la subvention (numéraire) | C1: Prestations en nature | D1: avec/sans
A2: OPERA NATIONAL DE BORDEAUX | B2: 16167670 | D2: =IF(B2=0,"SANS","AVEC") -> AVEC
A3: ASSOCIATION DES CENTRES D'ANIMATION DE QUARTIERS DE BORDEAUX - ACAQB | B3: 8060927.5 | C3: Communication, locaux, équipements sportifs, | D3: =IF(B3=0,"SANS","AVEC") -> AVEC
A4: CCAS DE BORDEAUX | B4: 7912204 | D4: =IF(B4=0,"SANS","AVEC") -> AVEC
A5: ECOLE D'ENSEIGNEMENT SUPÉRIEUR D'ART DE BORDEAUX - ESAB | B5: 3120000 | D5: =IF(B5=0,"SANS","AVEC") -> AVEC
A6: ASSOCIATION PITCHOUN | B6: 1735000 | C6: Locaux | D6: =IF(B6=0,"SANS","AVEC") -> AVEC
A7: THEATRE NATIONAL DE BORDEAUX EN AQUITAINE - TNBA | B7: 1646816 | C7: Communication, locaux | D7: =IF(B7=0,"SANS","AVEC") -> AVEC
A8: ASSOCIATION PETITE ENFANCE ENFANCE ET FAMILLE - APEEF | B8: 1578403 | C8: Locaux, matériel pour manifestations | D8: =IF(B8=0,"SANS","AVEC") -> AVEC
A9: UNION SAINT-BRUNO | B9: 1537650 | C9: Locaux, équipements sportifs, matériel pour | D9: =IF(B9=0,"SANS","AVEC") -> AVEC
A10: SPORTING CHANTECLER BORDEAUX NORD LE LAC | B10: 1128560 | C10: Locaux, équipements sportifs, matériel pour | D10: =IF(B10=0,"SANS","AVEC") -> AVEC
A11: AVANT GARDE ET JEANNE D'ARC DE BORDEAUX CAUDERAN - AGJA BORDEAUX CAUDERAN | B11: 1089439 | C11: Locaux, équipements sportifs, matériel pour | D11: =IF(B11=0,"SANS","AVEC") -> AVEC
A12: UNION SPORTIVE LES CHARTRONS | B12: 896350 | C12: Locaux, équipements sportifs, matériel pour | D12: =IF(B12=0,"SANS","AVEC") -> AVEC
A13: LES JEUNES DE SAINT AUGUSTIN - JSA | B13: 892663 | C13: Locaux, équipements sportifs, matériel pour | D13: =IF(B13=0,"SANS","AVEC") -> AVEC
A14: UNION SAINT JEAN - MAISON DE QUARTIER | B14: 879983 | C14: Locaux, équipements sportifs, matériel pour | D14: =IF(B14=0,"SANS","AVEC") -> AVEC
A15: STADE BORDELAIS ASPTT | B15: 819458 | C15: Locaux, équipements sportifs, matériel pour | D15: =IF(B15=0,"SANS","AVEC") -> AVEC
A16: ARC EN REVE | B16: 752250 | C16: Communication, matériel pour manifestations, locaux | D16: =IF(B16=0,"SANS","AVEC") -> AVEC
A17: MAISON DE L'EMPLOI, DE L'INSERTION ECONOMIQUE ET DE L'ENTREPRISE DE BORDEAUX | B17: 678000 | D17: =IF(B17=0,"SANS","AVEC") -> AVEC
A18: CLUB PYRENEES AQUITAINE, ASSOCIATION SPORTIVE, EDUCATIVE ET CULTURELLE | B18: 634600 | C18: Locaux, équipements sportifs, matériel pour | D18: =IF(B18=0,"SANS","AVEC") -> AVEC
A19: P'TIT BOUT'CHOU | B19: 567000 | C19: Matériel pour manifestations | D19: =IF(B19=0,"SANS","AVEC") -> AVEC
A20: ASSOCIATION BRINS D'EVEIL | B20: 532800 | D20: =IF(B20=0,"SANS","AVEC") -> AVEC
A21: ASSOCIATION DE GESTION ET D'ANIMATION DES CRECHES C.S.F. (AGEAC/CSF) | B21: 512833.33 | D21: =IF(B21=0,"SANS","AVEC") -> AVEC
A22: MISSION LOCALE BORDEAUX AVENIR JEUNES | B22: 494000 | C22: Locaux, matériel pour manifestations | D22: =IF(B22=0,"SANS","AVEC") -> AVEC
A23: GP INTENCITE CENTRE SOCIAL ET CULTUREL DU GRAND PARC | B23: 492222 | C23: Locaux, matériel pour manifestations | D23: =IF(B23=0,"SANS","AVEC") -> AVEC
A24: INTERLUDE | B24: 478850 | C24: Locaux, matériel pour manifestations | D24: =IF(B24=0,"SANS","AVEC") -> AVEC
A25: CENTRE SOCIAL ET FAMILIAL BORDEAUX NORD | B25: 461165 | C25: Locaux, équipements sportifs, matériel pour | D25: =IF(B25=0,"SANS","AVEC") -> AVEC
A26: AMICALE LAIQUE DAVID JOHNSTON LAGRANGE ALBERT BARRAUD NAUJAC | B26: 450195 | C26: Equipements sportifs | D26: =IF(B26=0,"SANS","AVEC") -> AVEC
A27: SASP UNION BORDEAUX BEGLES | B27: 450000 | C27: Matériel pour manifestations | D27: =IF(B27=0,"SANS","AVEC") -> AVEC
A28: FOYER FRATERNEL | B28: 426565 | C28: Locaux, matériel pour manifestations | D28: =IF(B28=0,"SANS","AVEC") -> AVEC
A29: FESTIVAL DES ARTS DE BORDEAUX | B29: 402000 | C29: Communication, locaux | D29: =IF(B29=0,"SANS","AVEC") -> AVEC
A30: ASSOCIATION DU COMITE DES OEUVRES SOCIALES DES MUNICIPAUX DE BORDEAUX - ACOSMB | B30: 380000 | C30: Matériel pour manifestations | D30: =IF(B30=0,"SANS","AVEC") -> AVEC
A31: POLE D'ENSEIGNEMENT SUPERIEUR DE LA MUSIQUE ET DE LA DANSE DE BORDEAUX AQUITAINE - PESMD | B31: 357672 | C31: Locaux | D31: =IF(B31=0,"SANS","AVEC") -> AVEC
A32: AUTEUIL PETITE ENFANCE | B32: 347000 | D32: =IF(B32=0,"SANS","AVEC") -> AVEC
A33: LES COQS ROUGES | B33: 343924 | C33: Equipements sportifs, matériel pour manifestations | D33: =IF(B33=0,"SANS","AVEC") -> AVEC
A34: BORDEAUX GRANDS EVENEMENTS (BGE) | B34: 339500 | C34: Communication, locaux | D34: =IF(B34=0,"SANS","AVEC") -> AVEC
A35: GESTION DU CENTRE DE LOISIRS DE LA POSTE ALEMA | B35: 334000 | D35: =IF(B35=0,"SANS","AVEC") -> AVEC
A36: ASSOCIATION PETITS BOUCHONS | B36: 311500 | D36: =IF(B36=0,"SANS","AVEC") -> AVEC
A37: ASSOCIATION POUR L'INNOVATION EN MATIERE D'INTEGRATION | B37: 300000 | D37: =IF(B37=0,"SANS","AVEC") -> AVEC
A38: BOXERS DE BORDEAUX | B38: 283000 | D38: =IF(B38=0,"SANS","AVEC") -> AVEC
A39: SASP JSA BORDEAUX METROPOLE | B39: 280000 | C39: Matériel pour manifestations | D39: =IF(B39=0,"SANS","AVEC") -> AVEC
A40: CLUB ATHLETIQUE MUNICIPAL DE BORDEAUX - CAM | B40: 243834 | C40: Locaux, équipements sportifs, matériel pour | D40: =IF(B40=0,"SANS","AVEC") -> AVEC
A41: LES ENFANTS D'OSIRIS | B41: 240000 | D41: =IF(B41=0,"SANS","AVEC") -> AVEC
A42: PARALLELES ATTITUDES DIFFUSION - ROCKSCHOOL | B42: 237000 | C42: Locaux, matériel pour manifestations, matériel | D42: =IF(B42=0,"SANS","AVEC") -> AVEC
A43: BORDEAUX ETUDIANTS CLUB - BEC | B43: 223734 | C43: Locaux, équipements sportifs, matériel pour | D43: =IF(B43=0,"SANS","AVEC") -> AVEC
A44: EVEILLEZ LES BEBES | B44: 210000 | D44: =IF(B44=0,"SANS","AVEC") -> AVEC
A45: LES PARENTS DE CAUDERAN | B45: 205000 | D45: =IF(B45=0,"SANS","AVEC") -> AVEC
A46: LUCILANN | B46: 200000 | D46: =IF(B46=0,"SANS","AVEC") -> AVEC
A47: BORDEAUX GIRONDE INVESTISSEMENT | B47: 198775 | C47: Matériel pour manifestations | D47: =IF(B47=0,"SANS","AVEC") -> AVEC
A48: LA MANUFACTURE ATLANTIQUE | B48: 198000 | C48: Communication, locaux, matériel pour | D48: =IF(B48=0,"SANS","AVEC") -> AVEC
A49: GROUPEMENT D'INTERET PUBLIC BORDEAUX MEDIATION | B49: 190000 | D49: =IF(B49=0,"SANS","AVEC") -> AVEC
A50: ESCALES LITTERAIRES BORDEAUX AQUITAINE | B50: 185000 | C50: Communication, locaux, matériel pour manifestations | D50: =IF(B50=0,"SANS","AVEC") -> AVEC
A51: ASSOCIATION LA COCCINELLE | B51: 180000 | D51: =IF(B51=0,"SANS","AVEC") -> AVEC
A52: O'PTIMÔMES LOISIRS | B52: 170592 | D52: =IF(B52=0,"SANS","AVEC") -> AVEC
A53: ASTROLABE | B53: 153407 | C53: Locaux, matériel pour manifestations | D53: =IF(B53=0,"SANS","AVEC") -> AVEC
A54: GIRONDINS DE BORDEAUX BASTIDE HANDBALL CLUB | B54: 141174 | C54: Locaux, équipements sportifs, matériel pour | D54: =IF(B54=0,"SANS","AVEC") -> AVEC
A55: LES GIRONDINS DE BORDEAUX | B55: 132000 | C55: Locaux, équipements sportifs, matériel pour | D55: =IF(B55=0,"SANS","AVEC") -> AVEC
A56: NUAGE BLEU | B56: 130000 | C56: Locaux | D56: =IF(B56=0,"SANS","AVEC") -> AVEC
A57: OGEC LYCEE BEL ORME | B57: 120000 | D57: =IF(B57=0,"SANS","AVEC") -> AVEC
A58: LA RONDE DES QUARTIERS DE BORDEAUX | B58: 119100 | C58: Communication, locaux, matériel pour manifestations | D58: =IF(B58=0,"SANS","AVEC") -> AVEC
A59: VILLA PRIMROSE | B59: 119000 | C59: Communication, équipements sportifs, matériel pour | D59: =IF(B59=0,"SANS","AVEC") -> AVEC
A60: EMULATION NAUTIQUE DE BORDEAUX | B60: 118603 | C60: Locaux, équipements sportifs, matériel pour | D60: =IF(B60=0,"SANS","AVEC") -> AVEC
A61: CAISSE SOCIALE DE DEVELOPPEMENT LOCAL | B61: 115000 | D61: =IF(B61=0,"SANS","AVEC") -> AVEC
A62: COS VILLA PIA - EHPAD LES DAMES DE LA FOI | B62: 115000 | C62: Matériel pour manifestations | D62: =IF(B62=0,"SANS","AVEC") -> AVEC
A63: GLOB THEATRE | B63: 115000 | C63: Locaux, matériel pour manifestations | D63: =IF(B63=0,"SANS","AVEC") -> AVEC
A64: MAISON DES JEUNES ET DE LA CULTURE CENTRE DE LOISIRS DES DEUX VILLES - MJC CL2V | B64: 110350 | C64: Matériel pour manifestations | D64: =IF(B64=0,"SANS","AVEC") -> AVEC
A65: ECOLE SUPERIEURE DE THEATRE BORDEAUX AQUITAINE - ESTBA | B65: 109834 | D65: =IF(B65=0,"SANS","AVEC") -> AVEC
A66: UNIS CITE | B66: 105000 | C66: Locaux, matériel pour manifestations | D66: =IF(B66=0,"SANS","AVEC") -> AVEC
A67: FOOTBALL CLUB DES GIRONDINS DE BORDEAUX - FCGB | B67: 100000 | C67: Equipements sportifs | D67: =IF(B67=0,"SANS","AVEC") -> AVEC
A68: UNION BORDEAUX METROPOLE - UBM | B68: 83680 | C68: Locaux, équipements sportifs | D68: =IF(B68=0,"SANS","AVEC") -> AVEC
A69: AMICALE DES ETABLISSEMENTS SCOLAIRES LAIQUES DE BACALAN - ALB | B69: 82238 | C69: Locaux, équipements sportifs, matériel pour | D69: =IF(B69=0,"SANS","AVEC") -> AVEC
A70: CAP SCIENCES | B70: 81568 | D70: =IF(B70=0,"SANS","AVEC") -> AVEC
A71: BORDEAUX MERIGNAC VOLLEY | B71: 80000 | C71: Equipements sportifs | D71: =IF(B71=0,"SANS","AVEC") -> AVEC
A72: LA HALLE DES DOUVES | B72: 80000 | C72: Locaux | D72: =IF(B72=0,"SANS","AVEC") -> AVEC
A73: SOLIHA, SOLIDAIRES POUR L'HABITAT, GIRONDE | B73: 73900 | C73: Locaux | D73: =IF(B73=0,"SANS","AVEC") -> AVEC
A74: SEMER LE DOUTE | B74: 73250 | C74: Communication, locaux, matériel pour | D74: =IF(B74=0,"SANS","AVEC") -> AVEC
A75: HALTE 33 | B75: 66000 | D75: =IF(B75=0,"SANS","AVEC") -> AVEC
A76: RESEAU PAUL BERT CENTRE SOCIAL ET CULTUREL | B76: 64000 | D76: =IF(B76=0,"SANS","AVEC") -> AVEC
A77: AGENCE D'URBANISME BORDEAUX METROPOLE AQUITAINE (A'URBA) | B77: 60000 | D77: =IF(B77=0,"SANS","AVEC") -> AVEC
A78: CHAHUTS | B78: 57500 | C78: Communication, locaux, matériel pour manifestations | D78: =IF(B78=0,"SANS","AVEC") -> AVEC
A79: LA CAISSE A OUTILS | B79: 57005 | D79: =IF(B79=0,"SANS","AVEC") -> AVEC
A80: LA MEMOIRE DE BORDEAUX METROPOLE | B80: 56105 | C80: Locaux, matériel informatique | D80: =IF(B80=0,"SANS","AVEC") -> AVEC
A81: MAISON DE L'EUROPE BORDEAUX-AQUITAINE (MEBA) | B81: 56000 | C81: Locaux | D81: =IF(B81=0,"SANS","AVEC") -> AVEC
A82: ASSOCIATION LAIQUE LE PRADO | B82: 55000 | D82: =IF(B82=0,"SANS","AVEC") -> AVEC
A83: LES PETITS DEBROUILLARDS AQUITAINE | B83: 54201 | C83: Matériel pour manifestations | D83: =IF(B83=0,"SANS","AVEC") -> AVEC
A84: FONDATION D'AUTEUIL AQUITAINE | B84: 52500 | C84: Locaux | D84: =IF(B84=0,"SANS","AVEC") -> AVEC
A85: THEATRE DU PONT TOURNANT | B85: 52250 | D85: =IF(B85=0,"SANS","AVEC") -> AVEC
A86: REGIE DE QUARTIER HABITER BACALAN | B86: 51000 | C86: Locaux | D86: =IF(B86=0,"SANS","AVEC") -> AVEC
A87: ASSOCIATION DE DEFENSE DES MUSIQUES ALTERNATIVES EN AQUITAINE - ADMAA (ALLEZ LES FILLES) | B87: 50580 | C87: Communication, matériel pour manifestations | D87: =IF(B87=0,"SANS","AVEC") -> AVEC
A88: ASSOCIATION UNION BORDEAUX BEGLES | B88: 50000 | C88: Matériel pour manifestations | D88: =IF(B88=0,"SANS","AVEC") -> AVEC
A89: LA CITE DU VIN | B89: 50000 | D89: =IF(B89=0,"SANS","AVEC") -> AVEC
A90: LE SERVICE GAGNANT | B90: 50000 | D90: =IF(B90=0,"SANS","AVEC") -> AVEC
A91: MAIRES RESPONSABLES METROPOLES FRANCOPHONES - AIMF | B91: 50000 | D91: =IF(B91=0,"SANS","AVEC") -> AVEC
A92: CENTRE D'INFORMATION JEUNESSE AQUITAINE - CIJA | B92: 49000 | C92: Locaux, matériel pour manifestations | D92: =IF(B92=0,"SANS","AVEC") -> AVEC
A93: ECOLE DE CIRQUE DE BORDEAUX, CENTRE CULTUREL DES ARTS DU CIRQUE | B93: 46500 | C93: Locaux | D93: =IF(B93=0,"SANS","AVEC") -> AVEC
A94: MAISON DE NOLAN | B94: 46000 | D94: =IF(B94=0,"SANS","AVEC") -> AVEC
A95: ASSOCIATION GIRONDINE D'EDUCATION SPECIALISEE ET DE PREVENTION SOCIALE - AGEP | B95: 45400 | C95: Locaux | D95: =IF(B95=0,"SANS","AVEC") -> AVEC
A96: ATELIER GRAPHITE | B96: 44200 | C96: Locaux | D96: =IF(B96=0,"SANS","AVEC") -> AVEC
A97: COMPAGNIE DES MARCHES DE L'ETE | B97: 41500 | C97: Communication, locaux, matériel pour manifestations | D97: =IF(B97=0,"SANS","AVEC") -> AVEC
A98: MUSIQUES DE NUIT - DIFFUSION | B98: 40700 | C98: Communication, matériel pour manifestations | D98: =IF(B98=0,"SANS","AVEC") -> AVEC
A99: CONGRES ET EXPOSITIONS DE BORDEAUX | B99: 40000 | C99: Communication, matériel pour manifestations | D99: =IF(B99=0,"SANS","AVEC") -> AVEC
A100: ASSOCIATION PROMOTION INSERTION SPORT EN AQUITAINE - APIS | B100: 37754 | C100: Equipements sportifs, matériel pour manifestations | D100: =IF(B100=0,"SANS","AVEC") -> AVEC
...

Sheet analyse2
E2: %AVEC | F2: %SANS
E3: =B3/$B$23 -> 0.51486486 | F3: =C3/$C$23 -> 0
E4: =B4/$B$23 -> 0.0027027027 | F4: =C4/$C$23 -> 0.0050441362
E5: =B5/$B$23 -> 0.0013513514 | F5: =C5/$C$23 -> 0
E6: =B6/$B$23 -> 0.010810811 | F6: =C6/$C$23 -> 0.001261034
E7: =B7/$B$23 -> 0.0013513514 | F7: =C7/$C$23 -> 0
E8: =B8/$B$23 -> 0.0027027027 | F8: =C8/$C$23 -> 0
E9: =B9/$B$23 -> 0.012162162 | F9: =C9/$C$23 -> 0
E10: =B10/$B$23 -> 0.0013513514 | F10: =C10/$C$23 -> 0
E11: =B11/$B$23 -> 0.0040540541 | F11: =C11/$C$23 -> 0.001261034
E12: =B12/$B$23 -> 0.0027027027 | F12: =C12/$C$23 -> 0
E13: =B13/$B$23 -> 0.028378378 | F13: =C13/$C$23 -> 0.095838588
E14: =B14/$B$23 -> 0.013513514 | F14: =C14/$C$23 -> 0.011349306
... E22: =B22/$B$23 -> 0.097297297 | F22: =C22/$C$23 -> 0.16519546
E23: =SUM(E3:E22) -> 1 | F23: =SUM(F3:F22) -> 1

Sheet consolidvert1
A1: nom des bénéficiaires | B1: Montant du fonds de concours ou de la subvention (numéraire) | C1: Prestations en nature
A2: 100 PROPOS SANS REPONSE | B2: 760
A3: 1001 JEUNES BORDELAIS | B3: 0 | C3: Matériel pour manifestations
A4: 2A - ATELIERS ARTISTIQUES | B4: 0 | C4: Locaux
A5: 2MOIZAILES | B5: 500
A6: 5UN7 | B6: 2000
A7: 60 000 REBONDS | B7: 1800
A8: 9EME TEMPS | B8: 1600
A9: A FOND TU PEUX ! | B9: 0 | C9: Matériel pour manifestations
A10: A PART CA TOUT VA BIEN | B10: 0 | C10: Locaux
A11: A PART ENTIERE | B11: 700 | C11: Matériel pour manifestations
A12: A TRAVERS CHANT | B12: 0 | C12: Locaux
A13: A.A.O (AM ANGEGEBENEM ORT) | B13: 2000
A14: A2RUNNING | B14: 0 | C14: Locaux
A15: ABALONE CHASSE BORDEAUX - ACB | B15: 0 | C15: Equipements sportifs, locaux
A16: ABEILLES BORDELAISES | B16: 0 | C16: Locaux
A17: ABICE | B17: 0 | C17: Matériel pour manifestations
A18: ACADEMIE BUSHIKAI KARATE DO | B18: 0 | C18: Equipements sportifs
A19: ACADEMIE DES SCIENCES, BELLES LETTRES ET ARTS DE BORDEAUX | B19: 7600 | C19: Locaux
A20: ACADEMIE YOUNUS | B20: 22016 | C20: Matériel pour manifestations, équipements sportifs,
A21: ACARBO | B21: 0 | C21: Equipements sportifs
A22: ACCOMPAGNEMENT ET RECHERCHE PSYCHO-SOCIO EDUCATIFS POUR LES JEUNES (ARPEJE) | B22: 0 | C22: Locaux
A23: ACCOMPAGNEMENT PSYCHOLOGIQUE ET MEDIATION INTERCULTURELLE - AMI | B23: 7000 | C23: Locaux
A24: ACCOMPAGNEMENT RECHERCHE PSYCHO EDUCATIFS POUR LES JEUNES | B24: 1500
A25: ACCOMPAGNER CONDUIRE TRANSMETTRE - ACT | B25: 300 | C25: Locaux
A26: ACCORDERIE BORDEAUX | B26: 6180 | C26: Locaux
A27: ACEPP 33/47 - ASSOCIATION DES COLLECTIFS ENFANTS PARENTS PROFESSIONNELS 33/47 | B27: 0 | C27: Matériel pour manifestations
A28: ACIDD, ASSOCIATION COMMUNICATION ET INFORMATION POUR LE DEVELOPPEMENT DURABLE | B28: 10000 | C28: Locaux
A29: ACINQBYS_ESPACE 29 A5BIS | B29: 20000
A30: ACTA GIRONDE - AGIR CONTRE LA TORTURE DES ANIMAUX | B30: 0 | C30: Locaux
A31: ACTIFS 33 | B31: 2400
A32: ACTIMAGE | B32: 29000 | C32: Locaux
A33: ACTION INTERNATIONALE POUR LA PAIX ET LE DEVELOPPEMENT (AIPD) | B33: 0 | C33: Locaux
A34: ACTION JAZZ | B34: 10738 | C34: Matériel pour manifestations, locaux
A35: ACTIV'ACTION | B35: 0 | C35: Locaux
A36: AD HOC : ASSOCIATION DES DOCTORANTS EN DROIT DE L'UNIVERSITE DE BORDEAUX | B36: 0 | C36: Locaux
A37: ADDAH 33 | B37: 500
A38: ADORA - ASS. DEVELOPPEMENT ET ACCOMPAGNEMENT AQUITAINE ORIENTATION PERS. ET PROF. TOUT AU LONG VIE | B38: 8000 | C38: Locaux
A39: AEP SAINT GABRIEL | B39: 800
A40: AES | B40: 0 | C40: Locaux
A41: AFRICAFRANCE | B41: 1500
A42: AGENCE D'URBANISME BORDEAUX METROPOLE AQUITAINE (A'URBA) | B42: 60000
A43: AGENCE LOCALE DE L'ENERGIE ET DU CLIMAT - ALEC | B43: 0 | C43: Locaux
A44: AGIR POUR UN COMMERCE EQUITABLE ET SOLIDAIRE EN AQUITAINE - ACESA | B44: 500
A45: AGORA DES ARTS | B45: 1500 | C45: Matériel pour manifestations, locaux
A46: AIDE AUX AIDANTS DU PAVILLON | B46: 2000
A47: AIDE AUX MINEURS DEFAVORISES - AAMD | B47: 0 | C47: Locaux
A48: AIDE AUX PARENTS D'ENFANTS SOUFFRANT DU SYNDROME DE L'ANTI-CONVULSIVANT (APESAC) | B48: 0 | C48: Locaux
A49: AIDES AQUITAINE | B49: 2000
A50: AIDOMI | B50: 0 | C50: Locaux
A51: AIGUILLES ET CALAME | B51: 0 | C51: Locaux
A52: AIKIDO BORDEAUX BASTIDE | B52: 0 | C52: Equipements sportifs
A53: AIM ACTIONS INTER MEDIATION | B53: 25000
A54: AIR 3 (AIR CUBE) | B54: 0 | C54: Locaux
A55: AIR ROLLER (ATTENTION INERTIE RENOUVELABLE) | B55: 9000 | C55: Equipements sportifs, locaux
A56: AKELIO ACCOMPAGNEMENT (RESEAU JEUNESSE OUTRE MER) | B56: 0 | C56: Locaux
A57: ALCHIMYSTIK EVENTS | B57: 550
A58: ALGERIENS DE L'AQUITAINE | B58: 0 | C58: Locaux
A59: ALLIANCE DEPARTEMENT 33, JUSQU'AU BOUT ACCOMPAGNER LA VIE... | B59: 5000 | C59: Matériel pour manifestations, locaux
A60: ALLO AMIANTE | B60: 0 | C60: Matériel pour manifestations
A61: ALPHONSE | B61: 0 | C61: Matériel pour manifestations
A62: ALTAIR (ASSOCIATION LES TERRITOIRES DE L'ART DE L'INDIVIDU DE LA RELATION) | B62: 1000
A63: ALTERNATIVE URBAINE DE BORDEAUX | B63: 2000
A64: AMADEUS | B64: 1000
A65: AMICALE BORDELAISE TRACTION AVANT CITROEN | B65: 0 | C65: Locaux
A66: AMICALE DE MADAGASCAR (AM) | B66: 0 | C66: Locaux
A67: AMICALE DES ANCIENS DE LA LEGION ETRANGERE | B67: 1000
A68: AMICALE DES ANCIENS DE MARIE-BRIZARD - AAMB | B68: 0 | C68: Locaux
A69: AMICALE DES ANCIENS DES TROUPES DE MARINE DE BORDEAUX ET D'AQUITAINE | B69: 500
A70: AMICALE DES ANCIENS GUERILLEROS ESPAGNOLS EN FRANCE-FFI - SECTION DE LA GIRONDE | B70: 0 | C70: Locaux
A71: AMICALE DES AVEYRONNAIS DE BORDEAUX ET GIRONDE | B71: 0 | C71: Locaux
A72: AMICALE DES ETABLISSEMENTS SCOLAIRES LAIQUES DE BACALAN - ALB | B72: 88869 | C72: Matériel pour manifestations, équipements sportifs,
A73: AMICALE DES IVOIRIENS VIVANT EN GIRONDE AKWABA | B73: 0 | C73: Locaux
A74: AMICALE DES LOCATAIRES DU PORT DE LA LUNE | B74: 6500
A75: AMICALE DES PARACHUTISTES DU SUD-OUEST | B75: 300
A76: AMICALE DES PARENTS D'ELEVES DE L'ECOLE STEHELIN | B76: 8605
A77: AMICALE DES RETRAITES U.G.R.R. - I.S.I.C.A. DE BORDEAUX | B77: 0 | C77: Locaux
A78: AMICALE DES SAPEURS POMPIERS DU SECTEUR D'INTERVENTION DE BORDEAUX METROPOLE | B78: 0 | C78: Matériel pour manifestations
A79: AMICALE DU PATRONAGE LAIQUE ET DU CONSEIL DE PARENTS D'ELEVES DU GROUPE SCOLAIRE NUYENS | B79: 0 | C79: Matériel pour manifestations
A80: AMICALE LAIQUE BORDEAUX BENAUGE | B80: 1759
A81: AMICALE LAIQUE BORDEAUX CENTRE | B81: 2500 | C81: Equipements sportifs, locaux
A82: AMICALE LAIQUE DAVID JOHNSTON LAGRANGE ALBERT BARRAUD NAUJAC | B82: 389346
A83: AMICALE LAIQUE DU GROUPE SCOLAIRE LEONARD-LENOIR - MONTAUD - NUITS | B83: 0 | C83: Equipements sportifs
A84: AMIS D'ARS ET FIDES BORDEAUX | B84: 2000 | C84: Matériel pour manifestations, locaux
A85: AMIS DE L'HOTEL DE LALANDE | B85: 2434.58
A86: AMIS DE L'ORCHESTRE D'HARMONIE DE BORDEAUX | B86: 4000
A87: AMIS DU CAPC MUSEE | B87: 0 | C87: Matériel pour manifestations
A88: AMIS DU SCOUTISME EUROPEEN DE GIRONDE | B88: 2250
A89: AMITIE MULTICULTURELLE INTEGRATION SOCIO-ECONOMIQUE, PROMOTION, ANIMATION, DEVELOPPEMENT (AMISPAD) | B89: 0 | C89: Locaux
A90: AMITIES FRANCAISES | B90: 0 | C90: Locaux
A91: AMITIES GENEALOGIQUES BORDELAISES | B91: 0 | C91: Locaux
A92: AMNESTY INTERNATIONAL GROUPE 234 DE BORDEAUX CENTRE | B92: 0 | C92: Locaux
A93: AMOS | B93: 15000
A94: ANCIENS BASTIDIENS-CLUB | B94: 0 | C94: Locaux
A95: ANIMATIONS VILLAGE SAINT-SEURIN | B95: 0 | C95: Matériel pour manifestations, locaux
A96: ANPAA - ASSOCIATION NATIONALE DE PREVENTION EN ALCOOLOGIE ET EN ADDICTOLOGIE | B96: 10000 | C96: Locaux
A97: ANTROPOLOGIA | B97: 0 | C97: Locaux
A98: APA SANTE NUTRITION | B98: 1512
A99: APEL ASSOMPTION SAINTE CLOTIDE | B99: 700
A100: APNEE 33 | B100: 0 | C100: Equipements sportifs
...

Sheet consolidvert2
A1: Année | B1: nom des bénéficiaires | C1: Montant du fonds de concours ou de la subvention (numéraire) | D1: Prestations en nature
A2: 2016 | B2: OPERA NATIONAL DE BORDEAUX | C2: 16167670
A3: 2016 | B3: ASSOCIATION DES CENTRES D'ANIMATION DE QUARTIERS DE BORDEAUX - ACAQB | C3: 8060927.5 | D3: Communication, locaux, équipements sportifs,
A4: 2016 | B4: CCAS DE BORDEAUX | C4: 7912204
A5: 2016 | B5: ECOLE D'ENSEIGNEMENT SUPÉRIEUR D'ART DE BORDEAUX - ESAB | C5: 3120000
A6: 2016 | B6: ASSOCIATION PITCHOUN | C6: 1735000 | D6: Locaux
A7: 2016 | B7: THEATRE NATIONAL DE BORDEAUX EN AQUITAINE - TNBA | C7: 1646816 | D7: Communication, locaux
A8: 2016 | B8: ASSOCIATION PETITE ENFANCE ENFANCE ET FAMILLE - APEEF | C8: 1578403 | D8: Locaux, matériel pour manifestations
A9: 2016 | B9: UNION SAINT-BRUNO | C9: 1537650 | D9: Locaux, équipements sportifs, matériel pour
A10: 2016 | B10: SPORTING CHANTECLER BORDEAUX NORD LE LAC | C10: 1128560 | D10: Locaux, équipements sportifs, matériel pour
A11: 2016 | B11: AVANT GARDE ET JEANNE D'ARC DE BORDEAUX CAUDERAN - AGJA BORDEAUX CAUDERAN | C11: 1089439 | D11: Locaux, équipements sportifs, matériel pour
A12: 2016 | B12: UNION SPORTIVE LES CHARTRONS | C12: 896350 | D12: Locaux, équipements sportifs, matériel pour
A13: 2016 | B13: LES JEUNES DE SAINT AUGUSTIN - JSA | C13: 892663 | D13: Locaux, équipements sportifs, matériel pour
A14: 2016 | B14: UNION SAINT JEAN - MAISON DE QUARTIER | C14: 879983 | D14: Locaux, équipements sportifs, matériel pour
A15: 2016 | B15: STADE BORDELAIS ASPTT | C15: 819458 | D15: Locaux, équipements sportifs, matériel pour
A16: 2016 | B16: ARC EN REVE | C16: 752250 | D16: Communication, matériel pour manifestations, locaux
A17: 2016 | B17: MAISON DE L'EMPLOI, DE L'INSERTION ECONOMIQUE ET DE L'ENTREPRISE DE BORDEAUX | C17: 678000
A18: 2016 | B18: CLUB PYRENEES AQUITAINE, ASSOCIATION SPORTIVE, EDUCATIVE ET CULTURELLE | C18: 634600 | D18: Locaux, équipements sportifs, matériel pour
A19: 2016 | B19: P'TIT BOUT'CHOU | C19: 567000 | D19: Matériel pour manifestations
A20: 2016 | B20: ASSOCIATION BRINS D'EVEIL | C20: 532800
A21: 2016 | B21: ASSOCIATION DE GESTION ET D'ANIMATION DES CRECHES C.S.F. (AGEAC/CSF) | C21: 512833.33
A22: 2016 | B22: MISSION LOCALE BORDEAUX AVENIR JEUNES | C22: 494000 | D22: Locaux, matériel pour manifestations
A23: 2016 | B23: GP INTENCITE CENTRE SOCIAL ET CULTUREL DU GRAND PARC | C23: 492222 | D23: Locaux, matériel pour manifestations
A24: 2016 | B24: INTERLUDE | C24: 478850 | D24: Locaux, matériel pour manifestations
A25: 2016 | B25: CENTRE SOCIAL ET FAMILIAL BORDEAUX NORD | C25: 461165 | D25: Locaux, équipements sportifs, matériel pour
A26: 2016 | B26: AMICALE LAIQUE DAVID JOHNSTON LAGRANGE ALBERT BARRAUD NAUJAC | C26: 450195 | D26: Equipements sportifs
A27: 2016 | B27: SASP UNION BORDEAUX BEGLES | C27: 450000 | D27: Matériel pour manifestations
A28: 2016 | B28: FOYER FRATERNEL | C28: 426565 | D28: Locaux, matériel pour manifestations
A29: 2016 | B29: FESTIVAL DES ARTS DE BORDEAUX | C29: 402000 | D29: Communication, locaux
A30: 2016 | B30: ASSOCIATION DU COMITE DES OEUVRES SOCIALES DES MUNICIPAUX DE BORDEAUX - ACOSMB | C30: 380000 | D30: Matériel pour manifestations
A31: 2016 | B31: POLE D'ENSEIGNEMENT SUPERIEUR DE LA MUSIQUE ET DE LA DANSE DE BORDEAUX AQUITAINE - PESMD | C31: 357672 | D31: Locaux
A32: 2016 | B32: AUTEUIL PETITE ENFANCE | C32: 347000
A33: 2016 | B33: LES COQS ROUGES | C33: 343924 | D33: Equipements sportifs, matériel pour manifestations
A34: 2016 | B34: BORDEAUX GRANDS EVENEMENTS (BGE) | C34: 339500 | D34: Communication, locaux
A35: 2016 | B35: GESTION DU CENTRE DE LOISIRS DE LA POSTE ALEMA | C35: 334000
A36: 2016 | B36: ASSOCIATION PETITS BOUCHONS | C36: 311500
A37: 2016 | B37: ASSOCIATION POUR L'INNOVATION EN MATIERE D'INTEGRATION | C37: 300000
A38: 2016 | B38: BOXERS DE BORDEAUX | C38: 283000
A39: 2016 | B39: SASP JSA BORDEAUX METROPOLE | C39: 280000 | D39: Matériel pour manifestations
A40: 2016 | B40: CLUB ATHLETIQUE MUNICIPAL DE BORDEAUX - CAM | C40: 243834 | D40: Locaux, équipements sportifs, matériel pour
A41: 2016 | B41: LES ENFANTS D'OSIRIS | C41: 240000
A42: 2016 | B42: PARALLELES ATTITUDES DIFFUSION - ROCKSCHOOL | C42: 237000 | D42: Locaux, matériel pour manifestations, matériel
A43: 2016 | B43: BORDEAUX ETUDIANTS CLUB - BEC | C43: 223734 | D43: Locaux, équipements sportifs, matériel pour
A44: 2016 | B44: EVEILLEZ LES BEBES | C44: 210000
A45: 2016 | B45: LES PARENTS DE CAUDERAN | C45: 205000
A46: 2016 | B46: LUCILANN | C46: 200000
A47: 2016 | B47: BORDEAUX GIRONDE INVESTISSEMENT | C47: 198775 | D47: Matériel pour manifestations
A48: 2016 | B48: LA MANUFACTURE ATLANTIQUE | C48: 198000 | D48: Communication, locaux, matériel pour
A49: 2016 | B49: GROUPEMENT D'INTERET PUBLIC BORDEAUX MEDIATION | C49: 190000
A50: 2016 | B50: ESCALES LITTERAIRES BORDEAUX AQUITAINE | C50: 185000 | D50: Communication, locaux, matériel pour manifestations
A51: 2016 | B51: ASSOCIATION LA COCCINELLE | C51: 180000
A52: 2016 | B52: O'PTIMÔMES LOISIRS | C52: 170592
A53: 2016 | B53: ASTROLABE | C53: 153407 | D53: Locaux, matériel pour manifestations
A54: 2016 | B54: GIRONDINS DE BORDEAUX BASTIDE HANDBALL CLUB | C54: 141174 | D54: Locaux, équipements sportifs, matériel pour
A55: 2016 | B55: LES GIRONDINS DE BORDEAUX | C55: 132000 | D55: Locaux, équipements sportifs, matériel pour
A56: 2016 | B56: NUAGE BLEU | C56: 130000 | D56: Locaux
A57: 2016 | B57: OGEC LYCEE BEL ORME | C57: 120000
A58: 2016 | B58: LA RONDE DES QUARTIERS DE BORDEAUX | C58: 119100 | D58: Communication, locaux, matériel pour manifestations
A59: 2016 | B59: VILLA PRIMROSE | C59: 119000 | D59: Communication, équipements sportifs, matériel pour
A60: 2016 | B60: EMULATION NAUTIQUE DE BORDEAUX | C60: 118603 | D60: Locaux, équipements sportifs, matériel pour
A61: 2016 | B61: CAISSE SOCIALE DE DEVELOPPEMENT LOCAL | C61: 115000
A62: 2016 | B62: COS VILLA PIA - EHPAD LES DAMES DE LA FOI | C62: 115000 | D62: Matériel pour manifestations
A63: 2016 | B63: GLOB THEATRE | C63: 115000 | D63: Locaux, matériel pour manifestations
A64: 2016 | B64: MAISON DES JEUNES ET DE LA CULTURE CENTRE DE LOISIRS DES DEUX VILLES - MJC CL2V | C64: 110350 | D64: Matériel pour manifestations
A65: 2016 | B65: ECOLE SUPERIEURE DE THEATRE BORDEAUX AQUITAINE - ESTBA | C65: 109834
A66: 2016 | B66: UNIS CITE | C66: 105000 | D66: Locaux, matériel pour manifestations
A67: 2016 | B67: FOOTBALL CLUB DES GIRONDINS DE BORDEAUX - FCGB | C67: 100000 | D67: Equipements sportifs
A68: 2016 | B68: UNION BORDEAUX METROPOLE - UBM | C68: 83680 | D68: Locaux, équipements sportifs
A69: 2016 | B69: AMICALE DES ETABLISSEMENTS SCOLAIRES LAIQUES DE BACALAN - ALB | C69: 82238 | D69: Locaux, équipements sportifs, matériel pour
A70: 2016 | B70: CAP SCIENCES | C70: 81568
A71: 2016 | B71: BORDEAUX MERIGNAC VOLLEY | C71: 80000 | D71: Equipements sportifs
A72: 2016 | B72: LA HALLE DES DOUVES | C72: 80000 | D72: Locaux
A73: 2016 | B73: SOLIHA, SOLIDAIRES POUR L'HABITAT, GIRONDE | C73: 73900 | D73: Locaux
A74: 2016 | B74: SEMER LE DOUTE | C74: 73250 | D74: Communication, locaux, matériel pour
A75: 2016 | B75: HALTE 33 | C75: 66000
A76: 2016 | B76: RESEAU PAUL BERT CENTRE SOCIAL ET CULTUREL | C76: 64000
A77: 2016 | B77: AGENCE D'URBANISME BORDEAUX METROPOLE AQUITAINE (A'URBA) | C77: 60000
A78: 2016 | B78: CHAHUTS | C78: 57500 | D78: Communication, locaux, matériel pour manifestations
A79: 2016 | B79: LA CAISSE A OUTILS | C79: 57005
A80: 2016 | B80: LA MEMOIRE DE BORDEAUX METROPOLE | C80: 56105 | D80: Locaux, matériel informatique
A81: 2016 | B81: MAISON DE L'EUROPE BORDEAUX-AQUITAINE (MEBA) | C81: 56000 | D81: Locaux
A82: 2016 | B82: ASSOCIATION LAIQUE LE PRADO | C82: 55000
A83: 2016 | B83: LES PETITS DEBROUILLARDS AQUITAINE | C83: 54201 | D83: Matériel pour manifestations
A84: 2016 | B84: FONDATION D'AUTEUIL AQUITAINE | C84: 52500 | D84: Locaux
A85: 2016 | B85: THEATRE DU PONT TOURNANT | C85: 52250
A86: 2016 | B86: REGIE DE QUARTIER HABITER BACALAN | C86: 51000 | D86: Locaux
A87: 2016 | B87: ASSOCIATION DE DEFENSE DES MUSIQUES ALTERNATIVES EN AQUITAINE - ADMAA (ALLEZ LES FILLES) | C87: 50580 | D87: Communication, matériel pour manifestations
A88: 2016 | B88: ASSOCIATION UNION BORDEAUX BEGLES | C88: 50000 | D88: Matériel pour manifestations
A89: 2016 | B89: LA CITE DU VIN | C89: 50000
A90: 2016 | B90: LE SERVICE GAGNANT | C90: 50000
A91: 2016 | B91: MAIRES RESPONSABLES METROPOLES FRANCOPHONES - AIMF | C91: 50000
A92: 2016 | B92: CENTRE D'INFORMATION JEUNESSE AQUITAINE - CIJA | C92: 49000 | D92: Locaux, matériel pour manifestations
A93: 2016 | B93: ECOLE DE CIRQUE DE BORDEAUX, CENTRE CULTUREL DES ARTS DU CIRQUE | C93: 46500 | D93: Locaux
A94: 2016 | B94: MAISON DE NOLAN | C94: 46000
A95: 2016 | B95: ASSOCIATION GIRONDINE D'EDUCATION SPECIALISEE ET DE PREVENTION SOCIALE - AGEP | C95: 45400 | D95: Locaux
A96: 2016 | B96: ATELIER GRAPHITE | C96: 44200 | D96: Locaux
A97: 2016 | B97: COMPAGNIE DES MARCHES DE L'ETE | C97: 41500 | D97: Communication, locaux, matériel pour manifestations
A98: 2016 | B98: MUSIQUES DE NUIT - DIFFUSION | C98: 40700 | D98: Communication, matériel pour manifestations
A99: 2016 | B99: CONGRES ET EXPOSITIONS DE BORDEAUX | C99: 40000 | D99: Communication, matériel pour manifestations
A100: 2016 | B100: ASSOCIATION PROMOTION INSERTION SPORT EN AQUITAINE - APIS | C100: 37754 | D100: Equipements sportifs, matériel pour manifestations
...

Sheet clean2
A1: Année | B1: nom des bénéficiaires | C1: Montant du fonds de concours ou de la subvention (numéraire) | D1: Prestations en nature
A2: 2016 | B2: OPERA NATIONAL DE BORDEAUX | C2: 16167670
A3: 2016 | B3: ASSOCIATION DES CENTRES D'ANIMATION DE QUARTIERS DE BORDEAUX - ACAQB | C3: 8060927.5 | D3: Communication, locaux, équipements sportifs,
A4: 2016 | B4: CCAS DE BORDEAUX | C4: 7912204
A5: 2016 | B5: ECOLE D'ENSEIGNEMENT SUPERIEUR D'ART DE BORDEAUX - ESAB | C5: 3120000
A6: 2016 | B6: ASSOCIATION PITCHOUN | C6: 1735000 | D6: Locaux
A7: 2016 | B7: THEATRE NATIONAL DE BORDEAUX EN AQUITAINE - TNBA | C7: 1646816 | D7: Communication, locaux
A8: 2016 | B8: ASSOCIATION PETITE ENFANCE ENFANCE ET FAMILLE - APEEF | C8: 1578403 | D8: Locaux, matériel pour manifestations
A9: 2016 | B9: UNION SAINT-BRUNO | C9: 1537650 | D9: Locaux, équipements sportifs, matériel pour
A10: 2016 | B10: SPORTING CHANTECLER BORDEAUX NORD LE LAC | C10: 1128560 | D10: Locaux, équipements sportifs, matériel pour
A11: 2016 | B11: AVANT GARDE ET JEANNE D'ARC DE BORDEAUX CAUDERAN - AGJA BORDEAUX CAUDERAN | C11: 1089439 | D11: Locaux, équipements sportifs, matériel pour
A12: 2016 | B12: UNION SPORTIVE LES CHARTRONS | C12: 896350 | D12: Locaux, équipements sportifs, matériel pour
A13: 2016 | B13: LES JEUNES DE SAINT AUGUSTIN - JSA | C13: 892663 | D13: Locaux, équipements sportifs, matériel pour
A14: 2016 | B14: UNION SAINT JEAN - MAISON DE QUARTIER | C14: 879983 | D14: Locaux, équipements sportifs, matériel pour
A15: 2016 | B15: STADE BORDELAIS ASPTT | C15: 819458 | D15: Locaux, équipements sportifs, matériel pour
A16: 2016 | B16: ARC EN REVE | C16: 752250 | D16: Communication, matériel pour manifestations, locaux
A17: 2016 | B17: MAISON DE L'EMPLOI, DE L'INSERTION ECONOMIQUE ET DE L'ENTREPRISE DE BORDEAUX | C17: 678000
A18: 2016 | B18: CLUB PYRENEES AQUITAINE, ASSOCIATION SPORTIVE, EDUCATIVE ET CULTURELLE | C18: 634600 | D18: Locaux, équipements sportifs, matériel pour
A19: 2016 | B19: P'TIT BOUT'CHOU | C19: 567000 | D19: Matériel pour manifestations
A20: 2016 | B20: ASSOCIATION BRINS D'EVEIL | C20: 532800
A21: 2016 | B21: ASSOCIATION DE GESTION ET D'ANIMATION DES CRECHES C.S.F. (AGEAC/CSF) | C21: 512833.33
A22: 2016 | B22: MISSION LOCALE BORDEAUX AVENIR JEUNES | C22: 494000 | D22: Locaux, matériel pour manifestations
A23: 2016 | B23: GP INTENCITE CENTRE SOCIAL ET CULTUREL DU GRAND PARC | C23: 492222 | D23: Locaux, matériel pour manifestations
A24: 2016 | B24: INTERLUDE | C24: 478850 | D24: Locaux, matériel pour manifestations
A25: 2016 | B25: CENTRE SOCIAL ET FAMILIAL BORDEAUX NORD | C25: 461165 | D25: Locaux, équipements sportifs, matériel pour
A26: 2016 | B26: AMICALE LAIQUE DAVID JOHNSTON LAGRANGE ALBERT BARRAUD NAUJAC | C26: 450195 | D26: Equipements sportifs
A27: 2016 | B27: SASP UNION BORDEAUX BEGLES | C27: 450000 | D27: Matériel pour manifestations
A28: 2016 | B28: FOYER FRATERNEL | C28: 426565 | D28: Locaux, matériel pour manifestations
A29: 2016 | B29: FESTIVAL DES ARTS DE BORDEAUX | C29: 402000 | D29: Communication, locaux
A30: 2016 | B30: ASSOCIATION DU COMITE DES OEUVRES SOCIALES DES MUNICIPAUX DE BORDEAUX - ACOSMB | C30: 380000 | D30: Matériel pour manifestations
A31: 2016 | B31: POLE D'ENSEIGNEMENT SUPERIEUR DE LA MUSIQUE ET DE LA DANSE DE BORDEAUX AQUITAINE - PESMD | C31: 357672 | D31: Locaux
A32: 2016 | B32: AUTEUIL PETITE ENFANCE | C32: 347000
A33: 2016 | B33: LES COQS ROUGES | C33: 343924 | D33: Equipements sportifs, matériel pour manifestations
A34: 2016 | B34: BORDEAUX GRANDS EVENEMENTS (BGE) | C34: 339500 | D34: Communication, locaux
A35: 2016 | B35: GESTION DU CENTRE DE LOISIRS DE LA POSTE ALEMA | C35: 334000
A36: 2016 | B36: ASSOCIATION PETITS BOUCHONS | C36: 311500
A37: 2016 | B37: ASSOCIATION POUR L'INNOVATION EN MATIERE D'INTEGRATION | C37: 300000
A38: 2016 | B38: BOXERS DE BORDEAUX | C38: 283000
A39: 2016 | B39: SASP JSA BORDEAUX METROPOLE | C39: 280000 | D39: Matériel pour manifestations
A40: 2016 | B40: CLUB ATHLETIQUE MUNICIPAL DE BORDEAUX - CAM | C40: 243834 | D40: Locaux, équipements sportifs, matériel pour
A41: 2016 | B41: LES ENFANTS D'OSIRIS | C41: 240000
A42: 2016 | B42: PARALLELES ATTITUDES DIFFUSION - ROCKSCHOOL | C42: 237000 | D42: Locaux, matériel pour manifestations, matériel
A43: 2016 | B43: BORDEAUX ETUDIANTS CLUB - BEC | C43: 223734 | D43: Locaux, équipements sportifs, matériel pour
A44: 2016 | B44: EVEILLEZ LES BEBES | C44: 210000
A45: 2016 | B45: LES PARENTS DE CAUDERAN | C45: 205000
A46: 2016 | B46: LUCILANN | C46: 200000
A47: 2016 | B47: BORDEAUX GIRONDE INVESTISSEMENT | C47: 198775 | D47: Matériel pour manifestations
A48: 2016 | B48: LA MANUFACTURE ATLANTIQUE | C48: 198000 | D48: Communication, locaux, matériel pour
A49: 2016 | B49: GROUPEMENT D'INTERET PUBLIC BORDEAUX MEDIATION | C49: 190000
A50: 2016 | B50: ESCALES LITTERAIRES BORDEAUX AQUITAINE | C50: 185000 | D50: Communication, locaux, matériel pour manifestations
A51: 2016 | B51: ASSOCIATION LA COCCINELLE | C51: 180000
A52: 2016 | B52: O'PTIMÔMES LOISIRS | C52: 170592
A53: 2016 | B53: ASTROLABE | C53: 153407 | D53: Locaux, matériel pour manifestations
A54: 2016 | B54: GIRONDINS DE BORDEAUX BASTIDE HANDBALL CLUB | C54: 141174 | D54: Locaux, équipements sportifs, matériel pour
A55: 2016 | B55: LES GIRONDINS DE BORDEAUX | C55: 132000 | D55: Locaux, équipements sportifs, matériel pour
A56: 2016 | B56: NUAGE BLEU | C56: 130000 | D56: Locaux
A57: 2016 | B57: OGEC LYCEE BEL ORME | C57: 120000
A58: 2016 | B58: LA RONDE DES QUARTIERS DE BORDEAUX | C58: 119100 | D58: Communication, locaux, matériel pour manifestations
A59: 2016 | B59: VILLA PRIMROSE | C59: 119000 | D59: Communication, équipements sportifs, matériel pour
A60: 2016 | B60: EMULATION NAUTIQUE DE BORDEAUX | C60: 118603 | D60: Locaux, équipements sportifs, matériel pour
A61: 2016 | B61: CAISSE SOCIALE DE DEVELOPPEMENT LOCAL | C61: 115000
A62: 2016 | B62: COS VILLA PIA - EHPAD LES DAMES DE LA FOI | C62: 115000 | D62: Matériel pour manifestations
A63: 2016 | B63: GLOB THEATRE | C63: 115000 | D63: Locaux, matériel pour manifestations
A64: 2016 | B64: MAISON DES JEUNES ET DE LA CULTURE CENTRE DE LOISIRS DES DEUX VILLES - MJC CL2V | C64: 110350 | D64: Matériel pour manifestations
A65: 2016 | B65: ECOLE SUPERIEURE DE THEATRE BORDEAUX AQUITAINE - ESTBA | C65: 109834
A66: 2016 | B66: UNIS CITE | C66: 105000 | D66: Locaux, matériel pour manifestations
A67: 2016 | B67: FOOTBALL CLUB DES GIRONDINS DE BORDEAUX - FCGB | C67: 100000 | D67: Equipements sportifs
A68: 2016 | B68: UNION BORDEAUX METROPOLE - UBM | C68: 83680 | D68: Locaux, équipements sportifs
A69: 2016 | B69: AMICALE DES ETABLISSEMENTS SCOLAIRES LAIQUES DE BACALAN - ALB | C69: 82238 | D69: Locaux, équipements sportifs, matériel pour
A70: 2016 | B70: CAP SCIENCES | C70: 81568
A71: 2016 | B71: BORDEAUX MERIGNAC VOLLEY | C71: 80000 | D71: Equipements sportifs
A72: 2016 | B72: LA HALLE DES DOUVES | C72: 80000 | D72: Locaux
A73: 2016 | B73: SOLIHA, SOLIDAIRES POUR L'HABITAT, GIRONDE | C73: 73900 | D73: Locaux
A74: 2016 | B74: SEMER LE DOUTE | C74: 73250 | D74: Communication, locaux, matériel pour
A75: 2016 | B75: HALTE 33 | C75: 66000
A76: 2016 | B76: RESEAU PAUL BERT CENTRE SOCIAL ET CULTUREL | C76: 64000
A77: 2016 | B77: AGENCE D'URBANISME BORDEAUX METROPOLE AQUITAINE (A'URBA) | C77: 60000
A78: 2016 | B78: CHAHUTS | C78: 57500 | D78: Communication, locaux, matériel pour manifestations
A79: 2016 | B79: LA CAISSE A OUTILS | C79: 57005
A80: 2016 | B80: LA MEMOIRE DE BORDEAUX METROPOLE | C80: 56105 | D80: Locaux, matériel informatique
A81: 2016 | B81: MAISON DE L'EUROPE BORDEAUX-AQUITAINE (MEBA) | C81: 56000 | D81: Locaux
A82: 2016 | B82: ASSOCIATION LAIQUE LE PRADO | C82: 55000
A83: 2016 | B83: LES PETITS DEBROUILLARDS AQUITAINE | C83: 54201 | D83: Matériel pour manifestations
A84: 2016 | B84: FONDATION D'AUTEUIL AQUITAINE | C84: 52500 | D84: Locaux
A85: 2016 | B85: THEATRE DU PONT TOURNANT | C85: 52250
A86: 2016 | B86: REGIE DE QUARTIER HABITER BACALAN | C86: 51000 | D86: Locaux
A87: 2016 | B87: ASSOCIATION DE DEFENSE DES MUSIQUES ALTERNATIVES EN AQUITAINE - ADMAA (ALLEZ LES FILLES) | C87: 50580 | D87: Communication, matériel pour manifestations
A88: 2016 | B88: ASSOCIATION UNION BORDEAUX BEGLES | C88: 50000 | D88: Matériel pour manifestations
A89: 2016 | B89: LA CITE DU VIN | C89: 50000
A90: 2016 | B90: LE SERVICE GAGNANT | C90: 50000
A91: 2016 | B91: MAIRES RESPONSABLES METROPOLES FRANCOPHONES - AIMF | C91: 50000
A92: 2016 | B92: CENTRE D'INFORMATION JEUNESSE AQUITAINE - CIJA | C92: 49000 | D92: Locaux, matériel pour manifestations
A93: 2016 | B93: ECOLE DE CIRQUE DE BORDEAUX, CENTRE CULTUREL DES ARTS DU CIRQUE | C93: 46500 | D93: Locaux
A94: 2016 | B94: MAISON DE NOLAN | C94: 46000
A95: 2016 | B95: ASSOCIATION GIRONDINE D'EDUCATION SPECIALISEE ET DE PREVENTION SOCIALE - AGEP | C95: 45400 | D95: Locaux
A96: 2016 | B96: ATELIER GRAPHITE | C96: 44200 | D96: Locaux
A97: 2016 | B97: COMPAGNIE DES MARCHES DE L'ETE | C97: 41500 | D97: Communication, locaux, matériel pour manifestations
A98: 2016 | B98: MUSIQUES DE NUIT - DIFFUSION | C98: 40700 | D98: Communication, matériel pour manifestations
A99: 2016 | B99: CONGRES ET EXPOSITIONS DE BORDEAUX | C99: 40000 | D99: Communication, matériel pour manifestations
A100: 2016 | B100: ASSOCIATION PROMOTION INSERTION SPORT EN AQUITAINE - APIS | C100: 37754 | D100: Equipements sportifs, matériel pour manifestations
...

Sheet verif2
D2: 2016 + 2017 | E2: =countif(B2:B2203,">1") -> 936
D3: 2016 ou 2017 | E3: =countif(B3:B2204,"=1") -> 1266

Sheet analyse3.
G2: 2016 + 2017 | H2: =countif(B2:B2203,">1") -> 981
G3: 2016 ou 2017 | H3: =countif(B3:B2204,"=1") -> 0

Sheet consolid1
A1: web-scraper-start-url | B1: nom | C1: description | D1: adresse | E1: code postal | F1: telephone | G1: president | H1: site web | I1: categorie
A2: https://assos.bordeaux.fr/association/detail/1857 | B2: PERCAL TANGO | C2: Promouvoir la culture argentine à travers la musique, la danse, le théâtre. Création et vente des spectacles vivants. | D2: 86 Cours Victor Hugo | E2: 33000 | F2: 05 40 05 22 45 | G2: null | H2: null | I2: null
A3: https://assos.bordeaux.fr/association/detail/634 | B3: ARTISANS DU MONDE BORDEAUX - ADM | C3: Promouvoir le commerce équitable afin de permettre aux producteurs de pays ou régions défavorisés de vivre dignement de leur travail et être acteur de leur développement. Permettre aux consommateurs d'être informés sur les dysfonctionnements du commerce international. Contribuer à changer les mécanismes du commerce international | D3: 30 rue du Parlement Saint Pierre | E3: 33000 | F3: 05 56 44 23 33 | G3: null | H3: admbordeaux.org | I3: Entraide, solidarité, humanitaire
A4: https://assos.bordeaux.fr/association/detail/955 | B4: CERCLE PHILATÉLIQUE BORDEAUX AQUITAINE - CPBA | C4: Association philatélique (collection de timbres) et marcophile (marques postales) atteignant une dizaine d'années d'existence forte de 160 membres actifs. Cette association est ouverte à tous les philatélistes débutants ou confirmés, de tous les âges. Ses adhérents ont la possibilité de se réunir pour échanger et chercher des pièces manquantes à leurs collections, 4 samedis par mois. | D4: 8 Rue de Blois Chez M. Langella | E4: 33600 | F4: 05 56 07 24 64 | G4: Gérard Langella | H4: null | I4: Loisirs
A5: https://assos.bordeaux.fr/association/detail/588 | B5: ALLO AMIANTE | C5: Défense des victimes de l'amiante et des victimes de maladies professionnelles faisant suite à une exposition aux autres agents cancérigènes ; prévention chez les particuliers et éradication de l'amiante | D5: 5 place, Amédée St Germain | E5: 33800 | F5: 05 56 91 60 69 | G5: Georges ARNAUDEAU | H5: null | I5: Santé, bien-être
A6: https://assos.bordeaux.fr/association/detail/680 | B6: CENTRE ACCUEIL CONSULTATION INFORMATION SEXUALITÉ - CACIS | C6: Dans une démarche d’éducation populaire, le CACIS se donne pour finalité de permettre à toute personne, jeune ou adulte, de trouver les moyens de vivre sa sexualité dans notre société et d’agir contre toute forme d’exclusion liée à la santé, à la sexualité et au genre. | D6: Place de l'Europe BP 44 | E6: 33030 | F6: 05 56 39 11 69 | G6: Brigitte Tandonnet | H6: cacis-pro.fr | I6: Santé, bien-être
A7: https://assos.bordeaux.fr/association/detail/1132 | B7: HANDI CAP NOUVELLE AQUITAINE - HCNA | C7: Handi CAP Nouvelle Aquitaine est une association loi 1901 qui a pour objet d'informer les personnes touchées et concernées par le handicap ou la perte d'autonomie sur les loisirs accessibles des secteurs du tourisme, de la culture, du sport présents en Nouvelle Aquitaine. Elle fait coopérer les partenaires de ces secteurs pour collecter et organiser la diffusion de ces informations. | D7: 436 av de Verdun | E7: 33700 | F7: 05 56 12 39 39 | G7: Patrick TREINS | H7: null | I7: null
A8: https://assos.bordeaux.fr/association/detail/1394 | B8: ASSOCIATION DES SAHRAOUIS À BORDEAUX - ASB | C8: Notre association a pour but de faire connaitre et reconnaître le peuple du Sahara Occidental, son histoire, sa culture, sa vie, son territoire et ses ressources auprès de l'opinion française et internationale. Mais aussi de soutenir les sahraouis dans les difficultés matérielles quotidiennes et dans la lutte pacifique vers la résolution du problème de décolonisation de leur pays. | D8: 9 bis cours Edouard Vaillant | E8: 33300 | F8: 06 05 90 55 41 | G8: Mohamed Salem Mohamed Brahim | H8: null | I8: Culture
A9: https://assos.bordeaux.fr/association/detail/1820 | B9: LES CRAYONNEUSES | C9: Action de médiation artistique, culturelle, bien-être. Création d'ouvrages et objets papiers. | D9: 3 chemin du Grand Port | E9: 33880 | F9: 06 87 19 99 02 | G9: null | H9: lescrayonneuses.com | I9: Santé, bien-être
A10: https://assos.bordeaux.fr/association/detail/515 | B10: OPÉRA BASTIDE - OB | C10: la compagnie Opéra Bastide représentait initialement un espace de création où l'apprentissage du métier se fait immédiatement par la scène, au contact du public, en dehors du cadre institutionnel. | D10: BP 24 BP 24 | E10: 33034 | F10: 06 58 52 19 58 | G10: null | H10: null | I10: Culture
A11: https://assos.bordeaux.fr/association/detail/713 | B11: ASSOCIATION DES AMIS D’ELIANE LAVAIL - AMIDEL | D11: pas d'adresse | G11: null | H11: null | I11: null
A12: https://assos.bordeaux.fr/association/detail/615 | B12: MAM'AN LES TI'BATEAUX | C12: L’objet de l’association de maison d’assistant(e)s maternel(le)s est le suivant : Création, ouverture et gestion d'une maison d'assistant(e)s maternel(le)s (M.A.M.) avec un projet de mixité dans l'accueil d'enfants non porteurs de handicaps âgés de deux mois et demi à quatre ans et d'enfants porteurs de handicaps ou atteints d'une maladie chronique âgés de deux mois et demi à six ans. | D12: 06 Place Philippe Lebon | E12: 33300 | F12: 06 79 08 95 93 | G12: Christine MOUNIER | I12: Education - Enfance - Jeunesse - Vie étudiante
A13: https://assos.bordeaux.fr/association/detail/1405 | B13: WINE WILD WEST | C13: L'association Wine Wild West a pour objet : l’organisation et la promotion d’un rassemblement annuel de danseurs de west coast swing en région bordelaise dénommé Wine Wild West. Ce rassemblement est un festival qui comprend des cours de danse et soirées de west coast swing. De plus le festival propose des découvertes œnologiques et de spécialités Bordelaises. | D13: 10 impasse Manes Chez Mme Dubernet | E13: 33110 | F13: 06 52 06 18 13 | G13: null | H13: www.winewildwest-bordeaux.fr | I13: Culture
A14: https://assos.bordeaux.fr/association/detail/1194 | B14: UNION SAINT-BRUNO - USB | C14: Favoriser la pratique du sport sous toutes ses formes au titre du loisir et/ou de la compétition. | D14: 49 rue Brizard | E14: 33000 | F14: 05 56 96 33 53 | G14: null | H14: www.saint-bruno.org | I14: Sport
A15: https://assos.bordeaux.fr/association/detail/1053 | B15: BXA - ESPRIT VOILE - BXA EV | C15: Proposer la découverte et le perfectionnement à la voile au départ de Bordeaux sur l'estuaire de la Gironde avec le voilier habitable de l’association (7,5 m ESTE 24). Développer, promouvoir et favoriser des activités à caractère culturel et sportif dans le domaine du nautisme avec comme champ d’action les bassins à flot de Bordeaux, la ville de Bordeaux et au delà. | D15: Bld Alfred DANEY Quai ouest Bassin à flot n° 2 | E15: 33300 | F15: 07 69 17 50 70 | G15: null | H15: www.bxaespritvoile.fr | I15: Sport
A16: https://assos.bordeaux.fr/association/detail/567 | B16: ASSOCIATION PARLECOUTER | C16: Enseigner l'apprentissage d'outils de communication bienveillante et respectueuse, basés sur l'écoute active, profonde et sans jugement, sur le développement de l'empathie, pour une meilleure compréhension de l'autre et de soi. L'association vise à créer des conditions favorables à l'éducation et l'accompagnement des enfants / adolescents, à instaurer des relations plus sereines en famille et en société. | D16: 11 rue du Palais Gallien, Appt A314 | E16: 33000 | F16: 06 78 66 97 33 | G16: null | H16: parlecouter.wixsite.com/bordeaux | I16: Education - Enfance - Jeunesse - Vie étudiante
A17: https://assos.bordeaux.fr/association/detail/1441 | B17: AIDOMI | C17: AIDOMI est une association d'aide et de soins à domicile organisée en Service Polyvalent d'Aide et de Soins à Domicile (SPASAD). Nos services accompagnent 24h /24h les personnes vulnérables et les proches aidants dans le maintien à domicile à travers des missions d'aide à domicile (entretien du domicile, préparation des repas, accompagnement à la vie sociale) et des soins infirmiers et d'hygiène. | D17: 22 rue professeur lannelongue | E17: 33300 | F17: 05 56 01 91 91 | G17: null | H17: aidomi.fr | I17: Santé, bien-être
A18: https://assos.bordeaux.fr/association/detail/796 | B18: ASSOCIATION FRANCO-JAPONAISE D'ÉCHANGES CULTURELS RIVAGES - RIVAGES | C18: L'association à pour but de développer les relations culturelles franco-japonaises pour un enrichissement mutuel par des actions de diffusion de la culture, du savoir faire et de l'art japonais (exposition, conférences, cours, pratiques artistiques et de bien être). | D18: 47 rue Jean Soula | E18: 33000 | F18: 05 47 29 56 30 | G18: null | H18: www.association-rivages.org | I18: Santé, bien-être
A19: https://assos.bordeaux.fr/association/detail/1317 | B19: PROMOFEMMES | C19: Insertion sociale, professionnelle, culturelle et citoyenne des femmes d’origine étrangère et de leur famille | D19: 10 rue Carpenteyre | E19: 33800 | F19: 05 56 94 64 07 | G19: null | H19: www.promofemmes.org | I19: Entraide, solidarité, humanitaire
A20: https://assos.bordeaux.fr/association/detail/1258 | B20: LE FESTIN | C20: Depuis près de trente ans, la revue le festin permet à un large public de découvrir les richesses artistiques du Sud-Ouest. Elle est aujourd’hui reconnue comme la première publication culturelle et touristique de la région. Du local à l’universel, des monuments historiques à la création la plus contemporaine, la revue trimestrielle défend en effet une vision dynamique et originale de la culture. | D20: 176 rue Achard Zone d'activités Achard - Bât F1 | E20: 33300 | F20: 05 56 69 72 46 | G20: null | H20: null | I20: Culture
A21: https://assos.bordeaux.fr/association/detail/1227 | B21: LES DETRITIVORES - DTTV | D21: pas d'adresse | G21: null | H21: null | I21: null
A22: https://assos.bordeaux.fr/association/detail/711 | B22: FRÈRES DES HOMMES - FDH | C22: La Pépinière de la solidarité internationale (créée par Frères des Hommes) est un dispositif d’accueil et d’accompagnement ouvert à tous ceux qui veulent mener un projet de solidarité internationale. Il s’adresse également à ceux qui souhaitent accompagner un ou plusieurs porteurs de projet dans leur démarche en devenant tuteur bénévole. | D22: 2 rue de Savoie 75006 Paris | E22: 33 | F22: 01 55 42 62 62 | G22: null | H22: www.fdh.org | I22: Entraide, solidarité, humanitaire
A23: https://assos.bordeaux.fr/association/detail/974 | B23: PHILOSPHÈRES | C23: Ouvrir un espace de réflexion philosophique aux enfants, adolescents, adultes : la proposition s’adresse à tous et s’inscrit dans une démarche culturelle durable et solidaire. Ateliers à visée philosophique pour enfants, pour adultes, événements sur la place publique, projet éditorial sur la mémoire, cinéphilo, écriture & poésie... La philosophie est un « terreau » qui favorise une existence harmonieuse pour tous. | D23: 6 rue Gaspard philippe | E23: 33800 | F23: 06 77 60 53 90 | G23: null | H23: www.philospheres.org | I23: Vivre ensemble, vie quotidienne
A24: https://assos.bordeaux.fr/association/detail/1199 | B24: UNION BORDEAUX MÉTROPOLE - UBM | C24: La présente association, sans but lucratif, a pour objet la pratique et l'organisation de toutes activités sportives, éducatives, culturelles, de loisirs, bien-être, gastronomiques. L’association est ouverte aux agents de la Mairie de Bordeaux, de la Métropole de Bordeaux (EPCI), et des communes membres de la Métropole, actifs et retraités ainsi qu’à leurs ayants droit et extérieurs (article 5). | D24: Hôtel de Bordeaux métropole Esplanade Charles de Gaulle | E24: 33045 | F24: 05 57 20 70 56 | G24: MARC JOKIEL | H24: null | I24: Loisirs
A25: https://assos.bordeaux.fr/association/detail/862 | B25: LES BALADES ALTERNATIVES | C25: L'Alternative Urbaine Bordeaux propose des balades pédestres alternatives à impact positif pour le territoire. D'une part, elles sortent des sentiers touristiques habituels en mettant en valeur des quartiers dits "populaires" ; D'autre part parce que ces balades sont animées par des "éclaireurs urbains" en insertion professionnelle que nous formons et rémunérons dans le cadre d'une activité tremplin vers l'emploi. | D25: 40 rue Laffiteau Chez Astrolabe | E25: 33800 | F25: 07 67 65 24 84 | G25: null | H25: bordeaux.alternative-urbaine.com | I25: Culture
A26: https://assos.bordeaux.fr/association/detail/1503 | B26: TEST 1809 | C26: Association test | D26: Rue Claude Bonnier | E26: 33000 | F26: 05 10 10 34 64 | G26: null | H26: null | I26: Vivre ensemble, vie quotidienne
A27: https://assos.bordeaux.fr/association/detail/598 | B27: ASSOCIATION ODYSSÉE | C27: Contribuer à l'engagement et à la participation de tous, pour renforcer la citoyenneté européenne et l'émergence de « citoyens du monde » Donner des clés de lecture pour appréhender la diversité et la complexité du monde actuel et développer l'apprentissage interculturel en promouvant et en mettant en œuvre des échanges européens et internationaux Faciliter le vivre ensemble et le travailler ensemble | D27: 5 rue Marengo | E27: 33000 | F27: 06 09 46 33 14 | G27: Elisabeth SILVA | H27: www.associationodyssee.fr | I27: Education - Enfance - Jeunesse - Vie étudiante
A28: https://assos.bordeaux.fr/association/detail/782 | B28: LA CLÉ DES ONDES | C28: Ouverte à toutes et tous, la Clé des Ondes est la radio qui se mouille pour qu'il fasse beau. Elle se fait l'écho du mouvement culturel, social, associatif, environnemental. D'ici et d'ailleurs, de toutes les couleurs, de toutes les nationalités, de toutes les musiques, de tout ce qui bouge, elle ouvre ses micros aux sans-voix. Elle s'écoute sur le 90.10 en FM et sur lacdo.org. | D28: 71 cours Edouard Vaillant | E28: 33300 | F28: 05 56 39 87 57 | G28: Gilbert Hanna | H28: www.lacdo.org | I28: Vivre ensemble, vie quotidienne
A29: https://assos.bordeaux.fr/association/detail/1042 | B29: OPTIMOMES LOISIRS | C29: Favoriser l'esprit de découverte chez les jeunes en leur proposant des programmes d'activités variées (Culture, sport, nature et science) ; promouvoir la pratique des activités sportives, artistiques, scientifiques et de nature en proposant la création de structures accueils ( écoles élémentaires/maternelles,CE) ; promouvoir grâce à des pratiques ludiques, la découverte de l'environnement auprès des enfants. | D29: 10 rue de la Moulinatte | E29: 33130 | F29: 05 56 85 53 14 | G29: null | H29: optimomesloisirs.com | I29: Education - Enfance - Jeunesse - Vie étudiante
A30: https://assos.bordeaux.fr/association/detail/1275 | B30: ATELIER D'ÉCO SOLIDAIRE - ADS | C30: La Recyclerie créative de Bordeaux est depuis 2010 un des leviers de l’innovation sociale territoriale dans la réutilisation de matières, objets et mobilier dont les usagers, les entreprises et les collectivités veulent se débarrasser. Par le travail croisé de salariés, de bénévoles de tous âges et de stagiaires de tous horizons, elle alimente une expérimentation concrète et et prône un retour au « bon sens ». | D30: 7 rue la Motte Picquet | E30: 33300 | F30: 05 56 10 46 19 | G30: null | H30: null | I30: Cadre de vie environnement
A31: https://assos.bordeaux.fr/association/detail/626 | B31: HÉLIOS EVENEMENTS - O S G | C31: Cette association a pour but de promouvoir et de développer les pratiques musicales : par la production de spectacles vivants les "Mini concerts'' comprenant la participation de l’orchestre symphonique de Gironde et de son activité de diffusion d’artistes ; par l’édition de supports informatifs et pédagogiques ; par l’organisation d’actions de formation musicale en favorisant les pratiques amateurs | D31: 2 rue Frédéric Bastiat | E31: 33100 | F31: 06 11 10 03 77 | G31: null | H31: orchestresymphoniquedegironde.fr | I31: Culture
A32: https://assos.bordeaux.fr/association/detail/1410 | B32: RIRE EN-JE - CLUB DE RIRE BX | C32: Amélioration du mieux être et des relations humaines notamment en faisant connaitre la méthode du Rire sans raison du Dr Kataria afin d'apporter de la joie de vivre, de la bonne humeur, et du bien être ; en connectant les personnes à travers le rire ; en trouvant du bonheur à rendre les gens heureux et en apportant de l'amour inconditionnel. | D32: 36 allée Haussmann | E32: 33300 | F32: 06 12 29 51 96 | G32: Pascale Senon | I32: Santé, bien-être
A33: https://assos.bordeaux.fr/association/detail/1576 | B33: ASSOCIATION FRANÇAISE DE RUGBY SUBAQUATIQUE - AFRS | C33: Développer la pratique du rugby subaquatique en France et favoriser la participation à des compétitions nationales et internationales. | D33: Rue Kléber | E33: 33800 | F33: 06 24 40 80 30 | G33: Anaïs De Chaumont | H33: null | I33: Sport
A34: https://assos.bordeaux.fr/association/detail/1734 | B34: LA CASSETTE | C34: La Cassette promeut I'art & la culture, crée des échanges sociaux & culturels, organise du spectacle vivant, des expositions, aide & conseille à la production musicale et le spectacle, conseille les lieux de diffusion à la programmation, résidence artistiques, accompagnement à l'enregistrement audio, accompagnement à la réalisation de vidéos, développement de projets artistiques... | D34: 55 rue Galin | E34: 33100 | F34: 06 84 31 45 04 | G34: milos ares asian teran | H34: null | I34: Culture
A35: https://assos.bordeaux.fr/association/detail/555 | B35: PRATIKABLE - PTK | C35: L'association Pratikable a pour but de valoriser et promouvoir le handicap à travers les sports de glisse et les sports à sensation. | D35: 13 Rue Charles Perrault | E35: 33370 | F35: 06 45 86 91 69 | G35: Wilfried Panatier | H35: www.pratikable.com | I35: Sport
A36: https://assos.bordeaux.fr/association/detail/1182 | B36: CULTIVER L'ÉQUILIBRE | C36: Accompagner, transmettre et promouvoir auprès de tout public différentes pratiques et techniques ayant pour objectif d’améliorer la santé (état de bien-être total physique, mental et social) et de permettre le développement personnel des personnes. Créer une dynamique de partage, d’échange et de mise en réseau de différents professionnels proposant ces pratiques. | D36: 147 avenue de Labarde | E36: 33300 | F36: 06 62 44 90 99 | G36: null | I36: Santé, bien-être
A37: https://assos.bordeaux.fr/association/detail/949 | B37: MOUVEMENT LE CRI | C37: Le Cri a pour objet de lutter contre toute forme de violences en particulier celles liées au système prostitutionnel. Elle se fixe une triple mission de prévention, d’information et de médiation. | D37: 58, rue Schoelcher | E37: 33300 | F37: 05 56 39 05 96 | G37: null | H37: null | I37: null
A38: https://assos.bordeaux.fr/association/detail/668 | B38: FÉDÉRATION DES RADIOS ASSOCIATIVES DE LA GIRONDE - FEDERA 33 | C38: Établir des échanges entre les radios, par des rencontres avec thème (échange de programmes, nouvelles technologies et numérique, gestion administrative, fonction employeur, droits d’auteur…) et en créer les outils de mise en œuvre. Aider les radios à la constitution des nombreux dossiers administratifs. Intervenir auprès de radios en difficulté par le conseil auprès de leurs instances dirigeantes. | D38: 153 rue David Johnston | E38: 33000 | F38: 06 52 84 62 80 | G38: Nicole Teyssier | H38: www.federa33.org/la-federa33 | I38: Culture
A39: https://assos.bordeaux.fr/association/detail/511 | B39: CALIXTE COEUR DE BASTIDE | C39: l association a pour but de créer et développer des animations et événements ,mener des réflexions,pour dynamiser la place CALIXTE CAMELLE et son quartier,en renforçant le lien social.De part son objet, l association peut être emmenée à exercer des activités économiques. | D39: le pti salon 60 rue bonnefin | E39: 33100 | F39: 06 61 18 87 34 | G39: null | H39: Facebook Facebook | I39: Vivre ensemble, vie quotidienne
A40: https://assos.bordeaux.fr/association/detail/982 | B40: LES PINSONS | C40: L'association Les Pinsons gère l'Institut Pinsons (première structure passerelle d'accueil des 2/6 ans inspirée de l'approche éducative et pédagogique de Reggio Emilia et du modèle scandinave de la petite enfance) et les ateliers Let's (le meilleur des pédagogies actives - Montessori, Reggio, Fröbel - associés à nos ateliers ludo-éducatifs : Code et robotique, cuisine, jardinage, jeux de société, arts plastiques...) | D40: 6 rue Jean Bedouret | E40: 33100 | F40: 06 95 48 28 48 | G40: Adeline Charneau | H40: www.institutpinsons.com | I40: Education - Enfance - Jeunesse - Vie étudiante
A41: https://assos.bordeaux.fr/association/detail/1307 | B41: DYNAMIC KARATE BORDEAUX - DKB | C41: L'association Dynamic Karate Bordeaux a pour objet de développer le karate do shotokan et les valeurs intrinsèques liées au Dojo Kun | D41: 21 bis avenue de brivazac | E41: 33600 | F41: 06 17 64 85 32 | G41: null | I41: Sport
A42: https://assos.bordeaux.fr/association/detail/1166 | B42: ASSOCIATION EXPRESSIONS | C42: L’association Expression est un lieu de pratiques culturelles et artistiques. Elle propose des ateliers hebdomadaires et mensuels. Elle regroupe sur un même lieu la danse, le yoga, la peinture, la sophrologie, le tissage à partir de matériaux de recyclage et le travail corporel. Elle offre un espace propice à la création dans un cadre apaisant et atypique au cœur de Bordeaux, dans le quartier Fondaudège. | D42: 23 impasse Sully | E42: 33000 | F42: 05 56 01 12 41 | G42: null | H42: www.associationexpression.com | I42: Culture
A43: https://assos.bordeaux.fr/association/detail/1669 | B43: ALLIANCE 33 - ALLIANCE 33 | C43: accompagnement bénévole des personnes gravement malades ou en fin de vie et de leurs proches, dans le cadre de la loi du 9 juin 1999 sur les soins palliatifs, en vue de soulager les souffrances physiques, morales, psychologiques et spirituelles , en institution ou à domicile, ou à l'antenne pour les soutiens et suivis de deuils. | D43: 380 cours de la Somme | E43: 33800 | F43: 05 56 43 07 07 | G43: null | H43: www.alliance.asso.fr | I43: Entraide, solidarité, humanitaire
A44: https://assos.bordeaux.fr/association/detail/593 | B44: LE LABO DES HISTOIRES NOUVELLE-AQUITAINE | D44: pas d'adresse | G44: null | H44: null | I44: null
A45: https://assos.bordeaux.fr/association/detail/1072 | B45: ACTE | C45: Association d'aide au retour à l'emploi destinée principalement aux cadres sans emploi ou en reconversion professionnelle. Il s'agit d'un accompagnement individualisé et personnalisé jusqu'au retour à l'emploi. | D45: 6 rue de Ségur | E45: 33000 | F45: 05 56 81 77 59 | G45: null | H45: htpp:/www.acte-asso.fr | I45: null
A46: https://assos.bordeaux.fr/association/detail/1706 | B46: FEARLESS CULTURE | C46: Notre objectif est de venir en aide aux demandeurs d’asile et aux réfugiés grâce à l’organisation d’événements culturels dont les bénéfices sont reversés à des associations ou centres d’accueil de réfugiés. | D46: 14 rue Saint Nicolas | E46: 33800 | F46: 06 25 91 24 64 | G46: Marylou Hallaf | I46: Entraide, solidarité, humanitaire
A47: https://assos.bordeaux.fr/association/detail/678 | B47: TANGO NOMADE - TANGO NOMADE | C47: Promouvoir la connaissance de la danse et de permettre des échanges culturels par ce biais. Cette association a une finalité sportive culturelle et artistique et souhaite par ce biais lutter contre toutes formes de discriminations. Mettre en place des spectacles et à animer tous types de manifestations sportives culturelles et artistiques. | D47: 17 allée Eugène Delacroix Apt 18 | E47: 33800 | F47: 06 83 79 62 63 | G47: Perrine NIVET | H47: tangonomade.com | I47: Culture
A48: https://assos.bordeaux.fr/association/detail/1090 | B48: GRAINES DE SOLIDARITÉ | C48: Association humanitaire dont l'objectif est d'apporter une aide alimentaire aux personnes et aux familles en grande difficulté. Cette aide prend la forme de distribution de colis alimentaires hebdomadaires destinés à des personnes isolées et à des familles, de couscous en période hivernale et de maraudes dans les rues de Bordeaux. Elle aide à l'insertion par le biais d'ateliers de langue et de cuisine du monde. | D48: 48, rue Kléber | E48: 33800 | F48: 06 50 52 40 52 | G48: Hanifa MZIZOUA | H48: grainesdesolidarite.e-monsite.com | I48: Entraide, solidarité, humanitaire
A49: https://assos.bordeaux.fr/association/detail/1128 | B49: ASSOCIATION SPORT EMPLOI - AES | C49: L'Association a pour but de faciliter l'accueil, l'information, l'orientation, la formaion, l'insertion et l'emploi de tout public par le biais de la pratique sportive | D49: pas d'adresse | G49: null | H49: null | I49: null
A50: https://assos.bordeaux.fr/association/detail/1025 | B50: SO COOPÉRATION | C50: SO Coopération est le Réseau Régional Multi-Acteurs (RRMA) pour la coopération et la solidarité internationales. ​ Sous l'acronyme ce qu'il faut retenir ; c'est l'espace qui est offert aux acteurs de la Nouvelle-Aquitaine, qu'ils soient associatifs, collectivités, universités, entreprises, établissement publics ou autres, pour s'informer, échanger, entreprendre des projets de coopération et de solidarité | D50: 10 Esplanade des Antilles, Maison des Sciences de l'Homme | E50: 33607 | F50: 05 56 84 45 68 | G50: null | H50: www.socooperation.org | I50: Entraide, solidarité, humanitaire
A51: https://assos.bordeaux.fr/association/detail/1163 | B51: ASSOCIATION DE SOUTIEN AUX INVENTIONS LIBRES / BANZAÏ LAB | D51: pas d'adresse | G51: null | H51: null | I51: null
A52: https://assos.bordeaux.fr/association/detail/1172 | B52: CRÉASSEMBLE - BXGOSPELACADEMY | C52: créer, développer et soutenir des événements et des projets alternatifs, culturels, artistiques, récréatifs et ou éducatifs comme moyens d’action pour l’épanouissement de l’individu, des groupes et des sociétés dans le respect de son environnement. | D52: 26, rue Marius Olivier | E52: 33130 | F52: 06 03 30 12 02 | G52: null | H52: bordeaux-gospel-academy.com | I52: Culture
A53: https://assos.bordeaux.fr/association/detail/1479 | B53: FRENCH TECH BORDEAUX | C53: L’association French Tech Bordeaux a pour but de développer la croissance des écosystèmes de startups et d’entreprises innovantes bordelaises et néo-aquitaines, avec 3 grandes ambitions : Fédérer et animer l’écosystème au service de la croissance ; Promouvoir et représenter les startups de Bordeaux et sa région ; Porter l’excellence française du label French Tech dans le territoire et à l’international. | D53: 20 Quai Lawton CS50100 | E53: 33300 | F53: 06 35 54 25 55 | G53: Jérôme LELEU | H53: www.frenchtechbordeaux.com | I53: Economie
A54: https://assos.bordeaux.fr/association/detail/892 | B54: ASSOCIATION PRENDRE SOIN DU LIEN - APSL | C54: L'association APSL s'adresse à un public de seniors. Elle propose "Le Lien'Aînés", de l'animation à domicile en groupe. Les sorties et rencontres proposées incluent le transport, pour des personnes vivant à domicile qui ne peuvent plus sortir seules de chez elles et qui sont en recherche de nouveaux contacts pour éviter la solitude. APSL organise aussi la "Mobil'Aînés", une marche en rolateurs, intergénérationnelle. | D54: 40 Allées d'Orléans Immeuble Le Splendide | E54: 33000 | F54: 06 75 01 40 81 | G54: null | I54: Vivre ensemble, vie quotidienne
A55: https://assos.bordeaux.fr/association/detail/1171 | B55: LE CHŒUR VOYAGEUR | C55: L’association a pour but de constituer une chorale et des ensembles instrumentaux afin de se produire en France et à l'étranger, dans le cadre de simples concerts, d'interventions culturelles mais aussi d'échanges avec d'autres chorales. | D55: 148 boulevard du Président Franklin Roosevelt | E55: 33800 | F55: 06 84 84 76 80 | G55: null | H55: lechoeurvoyageur.fr | I55: Culture
A56: https://assos.bordeaux.fr/association/detail/979 | B56: UNION SPORTIVE JEUNES DE SAINT-AUGUSTIN-CLUB PYRÉNÉES AQUITAINE - US-JSA-CPA | D56: pas d'adresse | G56: null | H56: null | I56: null
A57: https://assos.bordeaux.fr/association/detail/893 | B57: ASSOCIATION NATIONALE DES ASSISTANT(E)S MATERNEL(LE)S AGREE(E)S REUNI(E)S INTER-DEPARTEMENTALE - AMARID | C57: L’Association Nationale AMARID : Défense des Intérêts de l'enfant, Information aux parents concernant la profession de l'Assistant(e) Maternel(le) Droits et Devoirs des Assistant(e) Maternel(le),Droits et Devoirs des Parents, Faire EVOLUER la Profession d'Assistant(e) Maternel(le) | D57: 8 RUE DU CHASSELAS | E57: 33370 | F57: 05 56 32 58 24 | G57: null | H57: www.amarid.fr | I57: null
A58: https://assos.bordeaux.fr/association/detail/1365 | B58: SOLID'EARTH - SE | C58: Solid’Earth est l’association de développement durable et de solidarité internationale de l’école de commerce KEDGE Business School Campus de Bordeaux. L’association compte 85 membres et est ainsi la plus grande association du campus. Elle défend des valeurs fortes telles que le respect de l’environnement et de l’être humain, la solidarité et la diversité, ou encore la consommation responsable. | D58: 680 Cours de la libération KEDGE Business School | E58: 33405 | F58: 06 80 03 24 32 | G58: null | H58: www.solidearth.fr | I58: Entraide, solidarité, humanitaire
A59: https://assos.bordeaux.fr/association/detail/1754 | B59: LA BELLA BORDEAUX | C59: Promouvoir le patrimoine ainsi que la vie artistique et culturelle de la ville de Bordeaux par le biais d'expositions, rencontres, séminaires, ateliers et d'autres animations. Créer des actions de médiation culturelle et favoriser l'émergence de nouveaux talents. Organiser des événements artistiques et des sorties culturelles collectives pour ses membres. Encourager et soutenir la diversité culturelle. | D59: 169, rue Palais Gallien | E59: 33000 | F59: 06 89 69 68 38 | G59: Luciana M. Morgera | H59: null | I59: Culture
A60: https://assos.bordeaux.fr/association/detail/1250 | B60: CHORALE CHŒUR DES ECLUSES | C60: Nous sommes une chorale dynamique aimant chanter dans la bonne humeur. Notre répertoire est la variété française. Nous recrutons toutes voix. Il n' y a pas besoin de connaitre le solfège. Nous travaillons sur support d'enregistrement. Si vous aimez chanter et partager des moments conviviaux, n’hésitez pas à venir nous rejoindre tous les lundis soirs de 20h30 à 22h30 salle Simone Noailles au Grand Parc. | D60: 8 rue Maryse Bastié apt 14 | E60: 33300 | F60: 06 60 95 25 66 | G60: Sandra BOIRON | H60: null | I60: Culture
A61: https://assos.bordeaux.fr/association/detail/1381 | B61: KLAUS COMPAGNIE | C61: Association travaillant dans la culture inclusive (valides-handicapés). Création d’œuvres chorégraphiques (ballets). Organisation du Festival Mixamum (festival pluridisciplinaire mêlant des artistes valides et handicapés). Ateliers de danse contemporaine adaptée (valides et handicapés). Ateliers ponctuels de sensibilisation de la danse adaptée (valides et handicapés) | D61: 11 rue Erik Satie | E61: 33200 | F61: 06 09 44 46 70 | G61: null | H61: www.klauscompagnie.fr | I61: Culture
A62: https://assos.bordeaux.fr/association/detail/1630 | B62: ASSOCIATION MALINE | C62: Développer des projets artistiques, quels qu'ils soient, favoriser l’émergence de nouveaux talents par le soutien de la pratique amateur,défendre la diversité culturelle en soutenant des artistes de tout horizon,favoriser dans un cadre convivial la rencontre entre les populations, les professionnels et les amateurs,permettre l’accès au plus grand nombre en pratiquant le principe de la participation libre et adaptée. | D62: 8 Rue de Barsac | E62: 33800 | F62: 06 61 98 24 24 | G62: null | H62: associationmaline.wordpress.com | I62: Culture
A63: https://assos.bordeaux.fr/association/detail/1830 | B63: PHOENIX.UNIVERSEL - PHUN | D63: pas d'adresse | G63: null | H63: null | I63: null
A64: https://assos.bordeaux.fr/association/detail/676 | B64: LE CRAYON PAPOTE | C64: L'association le Crayon Papote à pour but de partager et faire découvrir le milieu de la création artistique et de sensibiliser à l'éco-responsabilité et au développement durable. | D64: 184 rue fondaudège | E64: 33000 | F64: 06 51 03 98 24 | G64: null | H64: www.lecrayonpapote.com | I64: Loisirs
A65: https://assos.bordeaux.fr/association/detail/739 | B65: ASSOCIATION POUR LA RECHERCHE EN PRÉVENTION PSYCHIQUE PRÉCOCE EN PÉRINATALITÉ - ARPPPP | D65: pas d'adresse | G65: null | H65: null | I65: null
A66: https://assos.bordeaux.fr/association/detail/675 | B66: LA LECHE LEAGUE GROUPE DE BORDEAUX - LLL FRANCE | C66: Aider les mères dans leur chemin d'allaitement, quel que soit leur projet, pour un jour ou plus. Leur apporter soutien, entraide, information récente et pertinente, ainsi que différents outils pour vivre sereinement leur allaitement, et remettre entre les mains des parents l'accompagnement de leur enfant. | D66: Impasse du grand Barrail | E66: 33710 | F66: 07 83 00 14 06 | G66: null | H66: www.lllfrance.org | I66: Santé, bien-être
A67: https://assos.bordeaux.fr/association/detail/961 | B67: CERCLE OENOPHILE AQUITAIN - COA | C67: L'association a pour objet principal de parfaire les connaissances oenologiques des adhérents | D67: 18 rue Auguste Merillon | E67: 33000 | F67: 05 56 96 51 98 | G67: Georges Laborde | H67: null | I67: Culture
A68: https://assos.bordeaux.fr/association/detail/614 | B68: DRÔLE DE SCÈNE | C68: notre café-théâtre est un lieu simple et chaleureux grâce à nos bénévoles. Notre programmation propose soit : des soirées comédie-club, soit des one man show, ou bien des spectacles pour le jeune public.Notre but est de promouvoir le spectacle vivant et de proposer aux spectateurs même les plus jeunes une programmation qualitative, dans un petit espace où la convivialité est naturelle. | D68: 164 rue Stéhélin | E68: 33200 | F68: 06 80 28 02 40 | G68: null | I68: Culture
A69: https://assos.bordeaux.fr/association/detail/1821 | B69: DEUX BOUTS | C69: Création de réseaux d'entraide où les aidés s'engagent à devenir aidants. Notre premier réseau, EDDIE s'adresse aux SDF. Nous inscrivons notre action dans le Plan Logement d'Abord en utilisant l'intermédiation locative, l'accompagnement pluridisciplinaire et la pair-aidance pour créer un processus de réinsertion accélérée. | D69: . | E69: 33000 | F69: 07 81 50 71 09 | G69: null | H69: deuxbouts.org | I69: Entraide, solidarité, humanitaire
A70: https://assos.bordeaux.fr/association/detail/1818 | B70: CENTRE DE VOILE DE BORDEAUX-LAC - CVBL | C70: Promotion et développement de la pratique de la voile, l’initiation, le perfectionnement à la pratique de la voile. Organisation de manifestations nautiques contribuant à l’animation du Lac de Bordeaux. | D70: Boulevard Jacques Chaban-Delmas | E70: 33520 | F70: 06 86 96 13 43 | G70: null | H70: voilebordeauxlac.fr | I70: Sport
A71: https://assos.bordeaux.fr/association/detail/1442 | B71: W568925635 | D71: pas d'adresse | G71: null | H71: null | I71: null
A72: https://assos.bordeaux.fr/association/detail/531 | B72: COLLECTIF 05/15 | C72: Proposer à tous les publics des randonnées, des courts séjours à vocation pédestre, mais également des visites, dans la région. L'association propose également des ateliers confort et bien-être (sophrologie), ainsi que des ateliers cuisine vietnamienne ! | D72: 31 rue Lachassaigne chez Mme DAO DUC Sylvie | E72: 33000 | F72: 06 45 04 57 24 | G72: null | I72: Sport
A73: https://assos.bordeaux.fr/association/detail/625 | B73: ASSOCIATION DES ANGOLAIS DE BORDEAUX - AAB | C73: Créer une synergie autor des problèmes sociaux ,culturels et économiques par l'accueil;Diffuser la langue Portugaise et les langues natives de l'Angola Umbundu,Kimbundu....; Favoriser une meilleure connaissance mutuelle entre l'Angola et la France ; Cours de danse traditionnelles Angolaises ; Organisation de manifestations culturelles , théâtre ,spectacles, récitals,expositions conférences. | D73: 12 Avenue des 40 Journaux appt 162 | E73: 33300 | F73: 06 05 83 19 95 | G73: null | H73: null | I73: Sport
A74: https://assos.bordeaux.fr/association/detail/838 | B74: ASSOCIATION POUR LE DON DE SANG BENEVOLE DE BORDEAUX ET ENVIRONS | C74: Promouvoir le don de sang bénévole Accueillir et informer les donneur de sang | D74: Residence de la mairie Bat 14 apt 9 | E74: 33130 | F74: 06 88 36 66 94 | G74: Sandrine DUPLACEAU | H74: null | I74: Santé, bien-être
A75: https://assos.bordeaux.fr/association/detail/820 | B75: CLUB LOISIRS AQUITAINE CULTURE - CLAC | C75: L'association œuvre pour la découverte de notre environnement proche et pour la culture. Elle favorise les liens nature/culture en proposant des ateliers, stages, balades à destination de tous les publics. Elle s'appuie sur des approches pédagogiques créatives et innovantes, notamment celles venant des pays scandinaves. | D75: 3 rue de Tauzia | E75: 33800 | F75: 06 87 38 99 08 | G75: null | I75: Culture
A76: https://assos.bordeaux.fr/association/detail/778 | B76: SALSA WITH S - SWS | C76: L’association a pour objet l’éveil et l’expression corporelle dans les danses latines et tropicales. | D76: 62bis rue paul antin | E76: 33800 | F76: 06 87 46 12 72 | G76: carole Couture | I76: Sport
A77: https://assos.bordeaux.fr/association/detail/805 | B77: COMPAGNIE LEITMOTIV | C77: La Compagnie Leitmotiv à Bordeaux a pour vocation d'être la compagnie de toutes et de tous, permettant à tout le monde de pratiquer une activité théâtrale. Théâtre Humour ou théâtre plus traditionnel, nos cours vous sont ouverts... En scène ! | D77: 84 rue Amédée St Germain La Laiterie | E77: 33800 | F77: 06 26 39 30 40 | G77: null | H77: www.compagnie-leitmotiv.com | I77: Culture
A78: https://assos.bordeaux.fr/association/detail/1588 | B78: DÉFENSE DES RÉSIDENTS DES QUARTIERS BORDEAUX MÉTROPOLE - ADDR.DQBM | D78: pas d'adresse | G78: null | H78: null | I78: null
A79: https://assos.bordeaux.fr/association/detail/1255 | B79: WEJOB | C79: WeJOB propose des services d'insertion et de RH innovants, aux demandeurs d'emploi et aux entreprises. WeJOB associe des démarches collaboratives à de l'expertise et de l'accompagnement spécialisé. L'offre de WeJOB s'adresse aux personnes en recherche d'emploi et aux entreprises avec des programmes collectifs et individuels, des services de formation, de recrutement et de conseil. | D79: http://www.we-job.com/ | E79: 33000 | F79: 06 58 72 27 89 | G79: null | H79: www.we-job.com | I79: Emploi, insertion professionnelle, formation
A80: https://assos.bordeaux.fr/association/detail/673 | B80: ACADÉMIE KARATÉ YOGA BORDEAUX BASTIDE | C80: Association ayant pour but de promouvoir l'enseignement du karaté-do, du handi-karaté et du hatha-yoga pour tous mais aussi pour les futures mamans et les enfants, par le biais de l'activité physique sportive et du bien-être. | D80: 17 rue Calvimont Coté Cour | E80: 33100 | F80: 06 22 60 34 58 | G80: null | H80: www.hathayogasimplifie-bordeaux.fr | I80: Sport
A81: https://assos.bordeaux.fr/association/detail/1689 | B81: ENSEMBLE2GENERATIONS - E2G | C81: FAVORISER LES RELATIONS INTERGENERATIONNELLES AU TRAVERS DU LOGEMENT ET DE PARTAGES D'ACTIVITES | D81: 85 rue Camille GODARD | E81: 33000 | F81: 07 86 62 26 07 | G81: Ariane MOREAU | H81: null | I81: null
A82: https://assos.bordeaux.fr/association/detail/1149 | B82: ASTROLABE | C82: L 'association Astrolabe (Espace de Vie Sociale) propose de l'accompagnement à la scolarité, des loisirs, des activités familiales, des séjours pour tous. Elle fédère et participe à l'animation de la vie du quartier. Ses projets, activités et animations sont réalisées avec les habitants dans un esprit d'éducation populaire, d'innovation et de solidarité. | D82: 40 rue Laffiteau | E82: 33800 | F82: 05 56 85 74 59 | G82: Joël DUCOS | I82: Education - Enfance - Jeunesse - Vie étudiante
A83: https://assos.bordeaux.fr/association/detail/1827 | B83: LABO - ATELIERS & LIVRES POUR ENFANTS | D83: pas d'adresse | G83: null | H83: null | I83: null
A84: https://assos.bordeaux.fr/association/detail/1785 | B84: STUDIO CANOPÉE - SC | C84: Le Studio Canopée se donne pour mission de proposer des activités physiques douces centrées sur le thème du bien-être. Notre credo ? Proposer des cours collectifs de Pilates, Yoga et Marche Nordique en petits groupes afin de garantir un suivi et un accompagnement personnalisé pour chacun de nos adhérents. Envie d’en savoir plus ? N’hésitez pas à nous rencontrer ! | D84: 28 avenue André Reinson, Résidence Canopée, Bat F Appt 617, 4è étage | E84: 33300 | F84: 07 89 63 06 34 | G84: Matthieu Robert | H84: null | I84: Sport
A85: https://assos.bordeaux.fr/association/detail/965 | B85: ASSOCIATION DANZA EVOLUCION | C85: Danza Evolucion est une association loi 1901 qui a pour but de promouvoir la danse dans toute sa diversité sur le Bassin d'Arcachon à Biganos. Ori Tahiti (danse polynésienne) avec sa troupe Manava Ori Tahiti , Boogie-woogie, Sévillanes, Bachata Reggaeton et Ukulélé ! | D85: 106 Rue Joseph cruchon | E85: 33380 | F85: 06 44 18 51 92 | G85: Marie Christine Legrand | H85: www.danzaevolucion.fr/m | I85: Culture
A86: https://assos.bordeaux.fr/association/detail/1323 | B86: ASSOCIATION NATIONALE DES MEMBRES DE L’ORDRE NATIONAL DU MÉRITE - ANMONM | C86: Buts de l'association : assurer le rayonnement et le prestige de l’Ordre en tous lieux ; maintenir et développer les valeurs morales et civiques liées à la qualité de compagnon ; renforcer les liens de solidarité entre les membres de l’Ordre et pratiquer l’entraide ; participer au devoir national de mémoire ; développer l'esprit de la citoyenneté et du civisme. | D86: 185 Cours Balguerie Stuttenberg Appartement 124 | E86: 33300 | F86: 06 22 53 93 15 | G86: Bernard Miot | H86: null | I86: Vivre ensemble, vie quotidienne
A87: https://assos.bordeaux.fr/association/detail/1243 | B87: HANDI'CHIENS | C87: HANDI’CHIENS est une association régie, créée en 1989 et reconnue d’utilité publique en 2012. HANDI’CHIENS a pour mission d’éduquer et de remettre GRATUITEMENT des Chiens d’Assistance à des personnes en situation de handicap. Grâce à la complicité qui l’unit à l’homme et aux 50 commandes qu'il maitrise, un “handi’chien” offre à son bénéficiaire une meilleure autonomie, plus de liberté, et favorise le lien social. | D87: 13 rue l'abbé Groult 75015 PARIS | E87: 33 | F87: 01 45 86 58 88 | G87: null | H87: www.handichiens.org | I87: null
A88: https://assos.bordeaux.fr/association/detail/1161 | B88: MAISON DES SOURDS DE LA GIRONDE - MS33 | C88: Diffuser et promouvoir la culture sourd à Bordeaux et en Gironde. Aide à la personne, conférences et ateliers, cours de Langue des Signes Française. | D88: 406 boulevard du président Wilson | E88: 33000 | F88: 06 59 41 90 23 | G88: Nathalie Verny | I88: Entraide, solidarité, humanitaire
A89: https://assos.bordeaux.fr/association/detail/956 | B89: LA VIE A DOMICILE -MAISON DE LA SANTÉ ET DES AIDANTS | C89: L'association se définit comme une plateforme de services à domicile qui permet l'orientation dans une filière de soin et d'aide, intégrée et complémentaire. Elle propose une réponse graduée aux besoins des personnes fragilisées par l'âge, la dépendance, le handicap ou la maladie Elle accompagne et soutient les aidants en offrant des services innovants et de répit | D89: 412 avenue de verdun | E89: 33700 | F89: 05 56 55 04 38 | G89: null | H89: www.viesantemerignac.fr | I89: Santé, bien-être
A90: https://assos.bordeaux.fr/association/detail/613 | B90: BORDEAUX BASTIDE BASKET | C90: Pratique du Basket-ball | D90: 96, rue de la Benauge | E90: 33100 | F90: 06 61 48 03 85 | G90: null | H90: null | I90: Sport
A91: https://assos.bordeaux.fr/association/detail/618 | B91: ORCHESTRE PAPAGENO | C91: L'Orchestre Papageno a été crée en 2007 et regroupe des musiciens amateurs (cordes, bois et cuivres) de tous les âges. Le groupe est dirigé par un chef professionnel, Nicolas Piquet, et propose un répertoire varié, essentiellement de musique classique et musique de films. L'Orchestre Papageno se produit lors de 10 concerts par an environ, et collabore avec d'autres orchestres et des écoles de musique. | D91: 19 place des Basques Addeo-Orchestre Papageno | E91: 33000 | F91: 06 20 79 07 11 | G91: Richard Albiach | H91: www.orchestrepapageno.com | I91: Culture
A92: https://assos.bordeaux.fr/association/detail/996 | B92: SECOURS POPULAIRE FÉDÉRATION DE GIRONDE - SPF | C92: Le secours populaire vient en aide aux personnes en difficultés en France et dans le monde: victime de la pauvreté et de la précarité, de l'exclusion. Généraliste de la solidarité: intervention sur l'urgence alimentaire, vestimentaire, action d'accompagnement des personnes, accès aux loisirs, vacances et différentes actions mises en oeuvre par des bénévoles. | D92: fédération du secours populaire 95 quai de paludate// 6 rue Belcier | E92: 33800 | F92: 05 56 92 79 92 | G92: null | H92: www.secourspopulaire.fr/33 | I92: Entraide, solidarité, humanitaire
A93: https://assos.bordeaux.fr/association/detail/1778 | B93: LES SOURCES | C93: Cours de yoga de l'énergie | D93: 1 avenue Brémontier | E93: 33950 | F93: 06 98 99 68 71 | G93: null | H93: energieyoga.com | I93: Sport
A94: https://assos.bordeaux.fr/association/detail/1044 | B94: LES FEES PAPILLONS | C94: CENTRE BEAUTE, BIEN-ETRE, ET ESTIME DE SOI, SOLIDAIRE La finalité de l'association LES FEES PAPILLONS est d'aider des Femmes en difficulté à (re)trouver la dignité, l'estime de soi, la confiance en soi et l'énergie indispensables pour leur bien-être, et leur insertion sociale et professionnelle. Les FEES sont des professionnelles bénévoles qui offrent ces soins et ateliers aux bénéficiaires: les PAPILLONS. | D94: Résidence du Lac, Apt 289, Entrée R, Avenue Laroque | E94: 33300 | F94: 05 56 29 56 34 | G94: Patricia CHAUFFOURIER | H94: www.lesfeespapillons.fr | I94: Santé, bien-être
A95: https://assos.bordeaux.fr/association/detail/1002 | B95: GIRONDINS DE BORDEAUX BASTIDE HANDBALL CLUB - GBBHBC | C95: Le développement et la promotion du handball par la pratique de ce sport à tous niveaux, la gestion et l'animation d’activités sportives donnant lieu à l'organisation de manifestations gratuites ou payantes et versement de rémunération, l'association peut également mener toutes les actions en relation avec son objet notamment de formation au profit de sportifs, ou sociales (sur Bordeaux Bastide et/ou métropole). | D95: 96 rue de la Benauge BP 14 | E95: 33100 | F95: 05 56 67 81 06 | G95: Christian Malichecq | H95: girondins-handball.clubeo.com | I95: Sport
A96: https://assos.bordeaux.fr/association/detail/1744 | B96: ASSOCIATION IMPRIMERIE DU LOUP - TYPOGRAPHIE | D96: pas d'adresse | G96: null | H96: null | I96: null
A97: https://assos.bordeaux.fr/association/detail/1065 | B97: ASSOCIATION GÉNÉRATION DUPATY - A.G. DUPATY | C97: Favoriser l'apprentissage , accompagner les adhérents et usagers dans l'accessibilité, découvrir et animer diverses actions éducatives, culturelles, artistiques, physiques et sportives, éduquer à l'environnement, à la citoyenneté, lutter contre les discriminations et favoriser les rencontres intergénérationnelles.Organiser à côté de l'ECOLE des actions sur les temps périscolaires et postscolaires | D97: 74 rue Joséphine Ecole Dupaty | E97: 33300 | F97: 07 71 80 07 22 | G97: null | H97: null | I97: Vivre ensemble, vie quotidienne
A98: https://assos.bordeaux.fr/association/detail/685 | B98: ACT'IMAGE | C98: L’association Act'Image a pour objectif de promouvoir la création photographique, de développer des actions culturelles liées à la photographie et de favoriser sa diffusion. Les actions mises en places permettent d’alimenter le dispositif culturel du territoire afin de le valoriser et de permettre aux citoyens de trouver un épanouissement culturel au travers de la photographie. | D98: 72, rue Emile Fourcand | E98: 33000 | F98: 06 09 73 05 80 | G98: null | H98: www.act-image.fr | I98: Culture
A99: https://assos.bordeaux.fr/association/detail/1520 | B99: ASSOCIATION L'IRRÉGULIÈRE | C99: L’IRRÉGULIÈRE conçoit et organise des événements culturels qui visent à favoriser la mixité des domaines artistiques, soutenir et promouvoir des artistes et collectifs bordelais et d’origines diverses. Elle propose régulièrement des actions de médiation culturelle pour sensibiliser le public à la création (manifestations portées par l'asso, commandes ou partenariats avec différentes structures publiques ou privées). | D99: 15 place Renaudel | E99: 33800 | F99: 06 42 40 96 65 | G99: null | H99: null | I99: Culture
A100: https://assos.bordeaux.fr/association/detail/1378 | B100: COMPAGNIE ARTISTIQUE YAKKA - CIE YAKKA | C100: La compagnie artistique « Yakka » a été créée pour permettre aux artistes de la Francophonie de travailler ensemble autour de projets de création artistique mêlant différents corps de métiers existants dans l’art . La dynamique de la compagnie se base sur le désir de trouver, travailler et faire partager aux publics, des œuvres d’ auteurs issus du paysage littéraire francophone. | D100: 60 cours Aristide Briand | E100: 33000 | F100: 07 81 73 45 84 | G100: null | H100: cieyakka.com | I100: Culture
...

Sheet consolid2
A1: nom des bénéficiaires | B1: Montant du fonds de concours ou de la subvention (numéraire) | C1: Prestations en nature | D1: avec/sans | E1: categorie | F1: president
A2: OPERA NATIONAL DE BORDEAUX | B2: 16167670 | D2: =IF(B2=0,"SANS","AVEC") -> AVEC | E2: {=INDEX(consolid1!$I$2:$I$904,MATCH(A2,consolid1!$B$2:$B$904,0))} -> #N/A | F2: {=INDEX(consolid1!$G$2:$G1534,MATCH(A2,consolid1!$B$2:$B1534,0))} -> #N/A
A3: ASSOCIATION DES CENTRES D'ANIMATION DE QUARTIERS DE BORDEAUX - ACAQB | B3: 8060927.5 | C3: Communication, locaux, équipements sportifs, | D3: =IF(B3=0,"SANS","AVEC") -> AVEC | E3: {=INDEX(consolid1!$I$2:$I$904,MATCH(A3,consolid1!$B$2:$B$904,0))} -> #N/A | F3: {=INDEX(consolid1!$G$2:$G1534,MATCH(A3,consolid1!$B$2:$B1534,0))} -> #N/A
A4: CCAS DE BORDEAUX | B4: 7912204 | D4: =IF(B4=0,"SANS","AVEC") -> AVEC | E4: {=INDEX(consolid1!$I$2:$I$904,MATCH(A4,consolid1!$B$2:$B$904,0))} -> #N/A | F4: {=INDEX(consolid1!$G$2:$G1534,MATCH(A4,consolid1!$B$2:$B1534,0))} -> #N/A
A5: ECOLE D'ENSEIGNEMENT SUPÉRIEUR D'ART DE BORDEAUX - ESAB | B5: 3120000 | D5: =IF(B5=0,"SANS","AVEC") -> AVEC | E5: {=INDEX(consolid1!$I$2:$I$904,MATCH(A5,consolid1!$B$2:$B$904,0))} -> #N/A | F5: {=INDEX(consolid1!$G$2:$G1534,MATCH(A5,consolid1!$B$2:$B1534,0))} -> #N/A
A6: ASSOCIATION PITCHOUN | B6: 1735000 | C6: Locaux | D6: =IF(B6=0,"SANS","AVEC") -> AVEC | E6: {=INDEX(consolid1!$I$2:$I$904,MATCH(A6,consolid1!$B$2:$B$904,0))} -> #N/A | F6: {=INDEX(consolid1!$G$2:$G1534,MATCH(A6,consolid1!$B$2:$B1534,0))} -> #N/A
A7: THEATRE NATIONAL DE BORDEAUX EN AQUITAINE - TNBA | B7: 1646816 | C7: Communication, locaux | D7: =IF(B7=0,"SANS","AVEC") -> AVEC | E7: {=INDEX(consolid1!$I$2:$I$904,MATCH(A7,consolid1!$B$2:$B$904,0))} -> #N/A | F7: {=INDEX(consolid1!$G$2:$G1534,MATCH(A7,consolid1!$B$2:$B1534,0))} -> #N/A
A8: ASSOCIATION PETITE ENFANCE ENFANCE ET FAMILLE - APEEF | B8: 1578403 | C8: Locaux, matériel pour manifestations | D8: =IF(B8=0,"SANS","AVEC") -> AVEC | E8: {=INDEX(consolid1!$I$2:$I$904,MATCH(A8,consolid1!$B$2:$B$904,0))} -> #N/A | F8: {=INDEX(consolid1!$G$2:$G1534,MATCH(A8,consolid1!$B$2:$B1534,0))} -> #N/A
A9: UNION SAINT-BRUNO | B9: 1537650 | C9: Locaux, équipements sportifs, matériel pour | D9: =IF(B9=0,"SANS","AVEC") -> AVEC | E9: {=INDEX(consolid1!$I$2:$I$904,MATCH(A9,consolid1!$B$2:$B$904,0))} -> #N/A | F9: {=INDEX(consolid1!$G$2:$G1534,MATCH(A9,consolid1!$B$2:$B1534,0))} -> #N/A
A10: SPORTING CHANTECLER BORDEAUX NORD LE LAC | B10: 1128560 | C10: Locaux, équipements sportifs, matériel pour | D10: =IF(B10=0,"SANS","AVEC") -> AVEC | E10: {=INDEX(consolid1!$I$2:$I$904,MATCH(A10,consolid1!$B$2:$B$904,0))} -> #N/A | F10: {=INDEX(consolid1!$G$2:$G1534,MATCH(A10,consolid1!$B$2:$B1534,0))} -> #N/A
A11: AVANT GARDE ET JEANNE D'ARC DE BORDEAUX CAUDERAN - AGJA BORDEAUX CAUDERAN | B11: 1089439 | C11: Locaux, équipements sportifs, matériel pour | D11: =IF(B11=0,"SANS","AVEC") -> AVEC | E11: {=INDEX(consolid1!$I$2:$I$904,MATCH(A11,consolid1!$B$2:$B$904,0))} -> #N/A | F11: {=INDEX(consolid1!$G$2:$G1534,MATCH(A11,consolid1!$B$2:$B1534,0))} -> #N/A
A12: UNION SPORTIVE LES CHARTRONS | B12: 896350 | C12: Locaux, équipements sportifs, matériel pour | D12: =IF(B12=0,"SANS","AVEC") -> AVEC | E12: {=INDEX(consolid1!$I$2:$I$904,MATCH(A12,consolid1!$B$2:$B$904,0))} -> #N/A | F12: {=INDEX(consolid1!$G$2:$G1534,MATCH(A12,consolid1!$B$2:$B1534,0))} -> #N/A
A13: LES JEUNES DE SAINT AUGUSTIN - JSA | B13: 892663 | C13: Locaux, équipements sportifs, matériel pour | D13: =IF(B13=0,"SANS","AVEC") -> AVEC | E13: {=INDEX(consolid1!$I$2:$I$904,MATCH(A13,consolid1!$B$2:$B$904,0))} -> #N/A | F13: {=INDEX(consolid1!$G$2:$G1534,MATCH(A13,consolid1!$B$2:$B1534,0))} -> #N/A
A14: UNION SAINT JEAN - MAISON DE QUARTIER | B14: 879983 | C14: Locaux, équipements sportifs, matériel pour | D14: =IF(B14=0,"SANS","AVEC") -> AVEC | E14: {=INDEX(consolid1!$I$2:$I$904,MATCH(A14,consolid1!$B$2:$B$904,0))} -> #N/A | F14: {=INDEX(consolid1!$G$2:$G1534,MATCH(A14,consolid1!$B$2:$B1534,0))} -> #N/A
A15: STADE BORDELAIS ASPTT | B15: 819458 | C15: Locaux, équipements sportifs, matériel pour | D15: =IF(B15=0,"SANS","AVEC") -> AVEC | E15: {=INDEX(consolid1!$I$2:$I$904,MATCH(A15,consolid1!$B$2:$B$904,0))} -> #N/A | F15: {=INDEX(consolid1!$G$2:$G1534,MATCH(A15,consolid1!$B$2:$B1534,0))} -> #N/A
A16: ARC EN REVE | B16: 752250 | C16: Communication, matériel pour manifestations, locaux | D16: =IF(B16=0,"SANS","AVEC") -> AVEC | E16: {=INDEX(consolid1!$I$2:$I$904,MATCH(A16,consolid1!$B$2:$B$904,0))} -> #N/A | F16: {=INDEX(consolid1!$G$2:$G1534,MATCH(A16,consolid1!$B$2:$B1534,0))} -> #N/A
A17: MAISON DE L'EMPLOI, DE L'INSERTION ECONOMIQUE ET DE L'ENTREPRISE DE BORDEAUX | B17: 678000 | D17: =IF(B17=0,"SANS","AVEC") -> AVEC | E17: {=INDEX(consolid1!$I$2:$I$904,MATCH(A17,consolid1!$B$2:$B$904,0))} -> #N/A | F17: {=INDEX(consolid1!$G$2:$G1534,MATCH(A17,consolid1!$B$2:$B1534,0))} -> #N/A
A18: CLUB PYRENEES AQUITAINE, ASSOCIATION SPORTIVE, EDUCATIVE ET CULTURELLE | B18: 634600 | C18: Locaux, équipements sportifs, matériel pour | D18: =IF(B18=0,"SANS","AVEC") -> AVEC | E18: {=INDEX(consolid1!$I$2:$I$904,MATCH(A18,consolid1!$B$2:$B$904,0))} -> #N/A | F18: {=INDEX(consolid1!$G$2:$G1534,MATCH(A18,consolid1!$B$2:$B1534,0))} -> #N/A
A19: P'TIT BOUT'CHOU | B19: 567000 | C19: Matériel pour manifestations | D19: =IF(B19=0,"SANS","AVEC") -> AVEC | E19: {=INDEX(consolid1!$I$2:$I$904,MATCH(A19,consolid1!$B$2:$B$904,0))} -> #N/A | F19: {=INDEX(consolid1!$G$2:$G1534,MATCH(A19,consolid1!$B$2:$B1534,0))} -> #N/A
A20: ASSOCIATION BRINS D'EVEIL | B20: 532800 | D20: =IF(B20=0,"SANS","AVEC") -> AVEC | E20: {=INDEX(consolid1!$I$2:$I$904,MATCH(A20,consolid1!$B$2:$B$904,0))} -> #N/A | F20: {=INDEX(consolid1!$G$2:$G1534,MATCH(A20,consolid1!$B$2:$B1534,0))} -> #N/A
A21: ASSOCIATION DE GESTION ET D'ANIMATION DES CRECHES C.S.F. (AGEAC/CSF) | B21: 512833.33 | D21: =IF(B21=0,"SANS","AVEC") -> AVEC | E21: {=INDEX(consolid1!$I$2:$I$904,MATCH(A21,consolid1!$B$2:$B$904,0))} -> #N/A | F21: {=INDEX(consolid1!$G$2:$G1534,MATCH(A21,consolid1!$B$2:$B1534,0))} -> #N/A
A22: MISSION LOCALE BORDEAUX AVENIR JEUNES | B22: 494000 | C22: Locaux, matériel pour manifestations | D22: =IF(B22=0,"SANS","AVEC") -> AVEC | E22: {=INDEX(consolid1!$I$2:$I$904,MATCH(A22,consolid1!$B$2:$B$904,0))} -> #N/A | F22: {=INDEX(consolid1!$G$2:$G1534,MATCH(A22,consolid1!$B$2:$B1534,0))} -> #N/A
A23: GP INTENCITE CENTRE SOCIAL ET CULTUREL DU GRAND PARC | B23: 492222 | C23: Locaux, matériel pour manifestations | D23: =IF(B23=0,"SANS","AVEC") -> AVEC | E23: {=INDEX(consolid1!$I$2:$I$904,MATCH(A23,consolid1!$B$2:$B$904,0))} -> #N/A | F23: {=INDEX(consolid1!$G$2:$G1534,MATCH(A23,consolid1!$B$2:$B1534,0))} -> #N/A
A24: INTERLUDE | B24: 478850 | C24: Locaux, matériel pour manifestations | D24: =IF(B24=0,"SANS","AVEC") -> AVEC | E24: {=INDEX(consolid1!$I$2:$I$904,MATCH(A24,consolid1!$B$2:$B$904,0))} -> #N/A | F24: {=INDEX(consolid1!$G$2:$G1534,MATCH(A24,consolid1!$B$2:$B1534,0))} -> #N/A
A25: CENTRE SOCIAL ET FAMILIAL BORDEAUX NORD | B25: 461165 | C25: Locaux, équipements sportifs, matériel pour | D25: =IF(B25=0,"SANS","AVEC") -> AVEC | E25: {=INDEX(consolid1!$I$2:$I$904,MATCH(A25,consolid1!$B$2:$B$904,0))} -> #N/A | F25: {=INDEX(consolid1!$G$2:$G1534,MATCH(A25,consolid1!$B$2:$B1534,0))} -> #N/A
A26: AMICALE LAIQUE DAVID JOHNSTON LAGRANGE ALBERT BARRAUD NAUJAC | B26: 450195 | C26: Equipements sportifs | D26: =IF(B26=0,"SANS","AVEC") -> AVEC | E26: {=INDEX(consolid1!$I$2:$I$904,MATCH(A26,consolid1!$B$2:$B$904,0))} -> #N/A | F26: {=INDEX(consolid1!$G$2:$G1534,MATCH(A26,consolid1!$B$2:$B1534,0))} -> #N/A
A27: SASP UNION BORDEAUX BEGLES | B27: 450000 | C27: Matériel pour manifestations | D27: =IF(B27=0,"SANS","AVEC") -> AVEC | E27: {=INDEX(consolid1!$I$2:$I$904,MATCH(A27,consolid1!$B$2:$B$904,0))} -> #N/A | F27: {=INDEX(consolid1!$G$2:$G1534,MATCH(A27,consolid1!$B$2:$B1534,0))} -> #N/A
A28: FOYER FRATERNEL | B28: 426565 | C28: Locaux, matériel pour manifestations | D28: =IF(B28=0,"SANS","AVEC") -> AVEC | E28: {=INDEX(consolid1!$I$2:$I$904,MATCH(A28,consolid1!$B$2:$B$904,0))} -> #N/A | F28: {=INDEX(consolid1!$G$2:$G1534,MATCH(A28,consolid1!$B$2:$B1534,0))} -> #N/A
A29: FESTIVAL DES ARTS DE BORDEAUX | B29: 402000 | C29: Communication, locaux | D29: =IF(B29=0,"SANS","AVEC") -> AVEC | E29: {=INDEX(consolid1!$I$2:$I$904,MATCH(A29,consolid1!$B$2:$B$904,0))} -> #N/A | F29: {=INDEX(consolid1!$G$2:$G1534,MATCH(A29,consolid1!$B$2:$B1534,0))} -> #N/A
A30: ASSOCIATION DU COMITE DES OEUVRES SOCIALES DES MUNICIPAUX DE BORDEAUX - ACOSMB | B30: 380000 | C30: Matériel pour manifestations | D30: =IF(B30=0,"SANS","AVEC") -> AVEC | E30: {=INDEX(consolid1!$I$2:$I$904,MATCH(A30,consolid1!$B$2:$B$904,0))} -> #N/A | F30: {=INDEX(consolid1!$G$2:$G1534,MATCH(A30,consolid1!$B$2:$B1534,0))} -> #N/A
A31: POLE D'ENSEIGNEMENT SUPERIEUR DE LA MUSIQUE ET DE LA DANSE DE BORDEAUX AQUITAINE - PESMD | B31: 357672 | C31: Locaux | D31: =IF(B31=0,"SANS","AVEC") -> AVEC | E31: {=INDEX(consolid1!$I$2:$I$904,MATCH(A31,consolid1!$B$2:$B$904,0))} -> #N/A | F31: {=INDEX(consolid1!$G$2:$G1534,MATCH(A31,consolid1!$B$2:$B1534,0))} -> #N/A
A32: AUTEUIL PETITE ENFANCE | B32: 347000 | D32: =IF(B32=0,"SANS","AVEC") -> AVEC | E32: {=INDEX(consolid1!$I$2:$I$904,MATCH(A32,consolid1!$B$2:$B$904,0))} -> #N/A | F32: {=INDEX(consolid1!$G$2:$G1534,MATCH(A32,consolid1!$B$2:$B1534,0))} -> #N/A
A33: LES COQS ROUGES | B33: 343924 | C33: Equipements sportifs, matériel pour manifestations | D33: =IF(B33=0,"SANS","AVEC") -> AVEC | E33: {=INDEX(consolid1!$I$2:$I$904,MATCH(A33,consolid1!$B$2:$B$904,0))} -> #N/A | F33: {=INDEX(consolid1!$G$2:$G1534,MATCH(A33,consolid1!$B$2:$B1534,0))} -> #N/A
A34: BORDEAUX GRANDS EVENEMENTS (BGE) | B34: 339500 | C34: Communication, locaux | D34: =IF(B34=0,"SANS","AVEC") -> AVEC | E34: {=INDEX(consolid1!$I$2:$I$904,MATCH(A34,consolid1!$B$2:$B$904,0))} -> #N/A | F34: {=INDEX(consolid1!$G$2:$G1534,MATCH(A34,consolid1!$B$2:$B1534,0))} -> #N/A
A35: GESTION DU CENTRE DE LOISIRS DE LA POSTE ALEMA | B35: 334000 | D35: =IF(B35=0,"SANS","AVEC") -> AVEC | E35: {=INDEX(consolid1!$I$2:$I$904,MATCH(A35,consolid1!$B$2:$B$904,0))} -> #N/A | F35: {=INDEX(consolid1!$G$2:$G1534,MATCH(A35,consolid1!$B$2:$B1534,0))} -> #N/A
A36: ASSOCIATION PETITS BOUCHONS | B36: 311500 | D36: =IF(B36=0,"SANS","AVEC") -> AVEC | E36: {=INDEX(consolid1!$I$2:$I$904,MATCH(A36,consolid1!$B$2:$B$904,0))} -> #N/A | F36: {=INDEX(consolid1!$G$2:$G1534,MATCH(A36,consolid1!$B$2:$B1534,0))} -> #N/A
A37: ASSOCIATION POUR L'INNOVATION EN MATIERE D'INTEGRATION | B37: 300000 | D37: =IF(B37=0,"SANS","AVEC") -> AVEC | E37: {=INDEX(consolid1!$I$2:$I$904,MATCH(A37,consolid1!$B$2:$B$904,0))} -> #N/A | F37: {=INDEX(consolid1!$G$2:$G1534,MATCH(A37,consolid1!$B$2:$B1534,0))} -> #N/A
A38: BOXERS DE BORDEAUX | B38: 283000 | D38: =IF(B38=0,"SANS","AVEC") -> AVEC | E38: {=INDEX(consolid1!$I$2:$I$904,MATCH(A38,consolid1!$B$2:$B$904,0))} -> #N/A | F38: {=INDEX(consolid1!$G$2:$G1534,MATCH(A38,consolid1!$B$2:$B1534,0))} -> #N/A
A39: SASP JSA BORDEAUX METROPOLE | B39: 280000 | C39: Matériel pour manifestations | D39: =IF(B39=0,"SANS","AVEC") -> AVEC | E39: {=INDEX(consolid1!$I$2:$I$904,MATCH(A39,consolid1!$B$2:$B$904,0))} -> #N/A | F39: {=INDEX(consolid1!$G$2:$G1534,MATCH(A39,consolid1!$B$2:$B1534,0))} -> #N/A
A40: CLUB ATHLETIQUE MUNICIPAL DE BORDEAUX - CAM | B40: 243834 | C40: Locaux, équipements sportifs, matériel pour | D40: =IF(B40=0,"SANS","AVEC") -> AVEC | E40: {=INDEX(consolid1!$I$2:$I$904,MATCH(A40,consolid1!$B$2:$B$904,0))} -> #N/A | F40: {=INDEX(consolid1!$G$2:$G1534,MATCH(A40,consolid1!$B$2:$B1534,0))} -> #N/A
A41: LES ENFANTS D'OSIRIS | B41: 240000 | D41: =IF(B41=0,"SANS","AVEC") -> AVEC | E41: {=INDEX(consolid1!$I$2:$I$904,MATCH(A41,consolid1!$B$2:$B$904,0))} -> #N/A | F41: {=INDEX(consolid1!$G$2:$G1534,MATCH(A41,consolid1!$B$2:$B1534,0))} -> #N/A
A42: PARALLELES ATTITUDES DIFFUSION - ROCKSCHOOL | B42: 237000 | C42: Locaux, matériel pour manifestations, matériel | D42: =IF(B42=0,"SANS","AVEC") -> AVEC | E42: {=INDEX(consolid1!$I$2:$I$904,MATCH(A42,consolid1!$B$2:$B$904,0))} -> #N/A | F42: {=INDEX(consolid1!$G$2:$G1534,MATCH(A42,consolid1!$B$2:$B1534,0))} -> #N/A
A43: BORDEAUX ETUDIANTS CLUB - BEC | B43: 223734 | C43: Locaux, équipements sportifs, matériel pour | D43: =IF(B43=0,"SANS","AVEC") -> AVEC | E43: {=INDEX(consolid1!$I$2:$I$904,MATCH(A43,consolid1!$B$2:$B$904,0))} -> #N/A | F43: {=INDEX(consolid1!$G$2:$G1534,MATCH(A43,consolid1!$B$2:$B1534,0))} -> #N/A
A44: EVEILLEZ LES BEBES | B44: 210000 | D44: =IF(B44=0,"SANS","AVEC") -> AVEC | E44: {=INDEX(consolid1!$I$2:$I$904,MATCH(A44,consolid1!$B$2:$B$904,0))} -> #N/A | F44: {=INDEX(consolid1!$G$2:$G1534,MATCH(A44,consolid1!$B$2:$B1534,0))} -> #N/A
A45: LES PARENTS DE CAUDERAN | B45: 205000 | D45: =IF(B45=0,"SANS","AVEC") -> AVEC | E45: {=INDEX(consolid1!$I$2:$I$904,MATCH(A45,consolid1!$B$2:$B$904,0))} -> #N/A | F45: {=INDEX(consolid1!$G$2:$G1534,MATCH(A45,consolid1!$B$2:$B1534,0))} -> #N/A
A46: LUCILANN | B46: 200000 | D46: =IF(B46=0,"SANS","AVEC") -> AVEC | E46: {=INDEX(consolid1!$I$2:$I$904,MATCH(A46,consolid1!$B$2:$B$904,0))} -> #N/A | F46: {=INDEX(consolid1!$G$2:$G1534,MATCH(A46,consolid1!$B$2:$B1534,0))} -> #N/A
A47: BORDEAUX GIRONDE INVESTISSEMENT | B47: 198775 | C47: Matériel pour manifestations | D47: =IF(B47=0,"SANS","AVEC") -> AVEC | E47: {=INDEX(consolid1!$I$2:$I$904,MATCH(A47,consolid1!$B$2:$B$904,0))} -> #N/A | F47: {=INDEX(consolid1!$G$2:$G1534,MATCH(A47,consolid1!$B$2:$B1534,0))} -> #N/A
A48: LA MANUFACTURE ATLANTIQUE | B48: 198000 | C48: Communication, locaux, matériel pour | D48: =IF(B48=0,"SANS","AVEC") -> AVEC | E48: {=INDEX(consolid1!$I$2:$I$904,MATCH(A48,consolid1!$B$2:$B$904,0))} -> #N/A | F48: {=INDEX(consolid1!$G$2:$G1534,MATCH(A48,consolid1!$B$2:$B1534,0))} -> #N/A
A49: GROUPEMENT D'INTERET PUBLIC BORDEAUX MEDIATION | B49: 190000 | D49: =IF(B49=0,"SANS","AVEC") -> AVEC | E49: {=INDEX(consolid1!$I$2:$I$904,MATCH(A49,consolid1!$B$2:$B$904,0))} -> #N/A | F49: {=INDEX(consolid1!$G$2:$G1534,MATCH(A49,consolid1!$B$2:$B1534,0))} -> #N/A
A50: ESCALES LITTERAIRES BORDEAUX AQUITAINE | B50: 185000 | C50: Communication, locaux, matériel pour manifestations | D50: =IF(B50=0,"SANS","AVEC") -> AVEC | E50: {=INDEX(consolid1!$I$2:$I$904,MATCH(A50,consolid1!$B$2:$B$904,0))} -> #N/A | F50: {=INDEX(consolid1!$G$2:$G1534,MATCH(A50,consolid1!$B$2:$B1534,0))} -> #N/A
A51: ASSOCIATION LA COCCINELLE | B51: 180000 | D51: =IF(B51=0,"SANS","AVEC") -> AVEC | E51: {=INDEX(consolid1!$I$2:$I$904,MATCH(A51,consolid1!$B$2:$B$904,0))} -> #N/A | F51: {=INDEX(consolid1!$G$2:$G1534,MATCH(A51,consolid1!$B$2:$B1534,0))} -> #N/A
A52: O'PTIMÔMES LOISIRS | B52: 170592 | D52: =IF(B52=0,"SANS","AVEC") -> AVEC | E52: {=INDEX(consolid1!$I$2:$I$904,MATCH(A52,consolid1!$B$2:$B$904,0))} -> #N/A | F52: {=INDEX(consolid1!$G$2:$G1534,MATCH(A52,consolid1!$B$2:$B1534,0))} -> #N/A
A53: ASTROLABE | B53: 153407 | C53: Locaux, matériel pour manifestations | D53: =IF(B53=0,"SANS","AVEC") -> AVEC | E53: {=INDEX(consolid1!$I$2:$I$904,MATCH(A53,consolid1!$B$2:$B$904,0))} -> Education - Enfance - Jeunesse - Vie étudiante | F53: {=INDEX(consolid1!$G$2:$G1534,MATCH(A53,consolid1!$B$2:$B1534,0))} -> Joël DUCOS
A54: GIRONDINS DE BORDEAUX BASTIDE HANDBALL CLUB | B54: 141174 | C54: Locaux, équipements sportifs, matériel pour | D54: =IF(B54=0,"SANS","AVEC") -> AVEC | E54: {=INDEX(consolid1!$I$2:$I$904,MATCH(A54,consolid1!$B$2:$B$904,0))} -> #N/A | F54: {=INDEX(consolid1!$G$2:$G1534,MATCH(A54,consolid1!$B$2:$B1534,0))} -> #N/A
A55: LES GIRONDINS DE BORDEAUX | B55: 132000 | C55: Locaux, équipements sportifs, matériel pour | D55: =IF(B55=0,"SANS","AVEC") -> AVEC | E55: {=INDEX(consolid1!$I$2:$I$904,MATCH(A55,consolid1!$B$2:$B$904,0))} -> #N/A | F55: {=INDEX(consolid1!$G$2:$G1534,MATCH(A55,consolid1!$B$2:$B1534,0))} -> #N/A
A56: NUAGE BLEU | B56: 130000 | C56: Locaux | D56: =IF(B56=0,"SANS","AVEC") -> AVEC | E56: {=INDEX(consolid1!$I$2:$I$904,MATCH(A56,consolid1!$B$2:$B$904,0))} -> #N/A | F56: {=INDEX(consolid1!$G$2:$G1534,MATCH(A56,consolid1!$B$2:$B1534,0))} -> #N/A
A57: OGEC LYCEE BEL ORME | B57: 120000 | D57: =IF(B57=0,"SANS","AVEC") -> AVEC | E57: {=INDEX(consolid1!$I$2:$I$904,MATCH(A57,consolid1!$B$2:$B$904,0))} -> #N/A | F57: {=INDEX(consolid1!$G$2:$G1534,MATCH(A57,consolid1!$B$2:$B1534,0))} -> #N/A
A58: LA RONDE DES QUARTIERS DE BORDEAUX | B58: 119100 | C58: Communication, locaux, matériel pour manifestations | D58: =IF(B58=0,"SANS","AVEC") -> AVEC | E58: {=INDEX(consolid1!$I$2:$I$904,MATCH(A58,consolid1!$B$2:$B$904,0))} -> Economie | F58: {=INDEX(consolid1!$G$2:$G1534,MATCH(A58,consolid1!$B$2:$B1534,0))} -> null
A59: VILLA PRIMROSE | B59: 119000 | C59: Communication, équipements sportifs, matériel pour | D59: =IF(B59=0,"SANS","AVEC") -> AVEC | E59: {=INDEX(consolid1!$I$2:$I$904,MATCH(A59,consolid1!$B$2:$B$904,0))} -> #N/A | F59: {=INDEX(consolid1!$G$2:$G1534,MATCH(A59,consolid1!$B$2:$B1534,0))} -> #N/A
A60: EMULATION NAUTIQUE DE BORDEAUX | B60: 118603 | C60: Locaux, équipements sportifs, matériel pour | D60: =IF(B60=0,"SANS","AVEC") -> AVEC | E60: {=INDEX(consolid1!$I$2:$I$904,MATCH(A60,consolid1!$B$2:$B$904,0))} -> #N/A | F60: {=INDEX(consolid1!$G$2:$G1534,MATCH(A60,consolid1!$B$2:$B1534,0))} -> #N/A
A61: CAISSE SOCIALE DE DEVELOPPEMENT LOCAL | B61: 115000 | D61: =IF(B61=0,"SANS","AVEC") -> AVEC | E61: {=INDEX(consolid1!$I$2:$I$904,MATCH(A61,consolid1!$B$2:$B$904,0))} -> #N/A | F61: {=INDEX(consolid1!$G$2:$G1534,MATCH(A61,consolid1!$B$2:$B1534,0))} -> #N/A
A62: COS VILLA PIA - EHPAD LES DAMES DE LA FOI | B62: 115000 | C62: Matériel pour manifestations | D62: =IF(B62=0,"SANS","AVEC") -> AVEC | E62: {=INDEX(consolid1!$I$2:$I$904,MATCH(A62,consolid1!$B$2:$B$904,0))} -> #N/A | F62: {=INDEX(consolid1!$G$2:$G1534,MATCH(A62,consolid1!$B$2:$B1534,0))} -> #N/A
A63: GLOB THEATRE | B63: 115000 | C63: Locaux, matériel pour manifestations | D63: =IF(B63=0,"SANS","AVEC") -> AVEC | E63: {=INDEX(consolid1!$I$2:$I$904,MATCH(A63,consolid1!$B$2:$B$904,0))} -> #N/A | F63: {=INDEX(consolid1!$G$2:$G1534,MATCH(A63,consolid1!$B$2:$B1534,0))} -> #N/A
A64: MAISON DES JEUNES ET DE LA CULTURE CENTRE DE LOISIRS DES DEUX VILLES - MJC CL2V | B64: 110350 | C64: Matériel pour manifestations | D64: =IF(B64=0,"SANS","AVEC") -> AVEC | E64: {=INDEX(consolid1!$I$2:$I$904,MATCH(A64,consolid1!$B$2:$B$904,0))} -> #N/A | F64: {=INDEX(consolid1!$G$2:$G1534,MATCH(A64,consolid1!$B$2:$B1534,0))} -> #N/A
A65: ECOLE SUPERIEURE DE THEATRE BORDEAUX AQUITAINE - ESTBA | B65: 109834 | D65: =IF(B65=0,"SANS","AVEC") -> AVEC | E65: {=INDEX(consolid1!$I$2:$I$904,MATCH(A65,consolid1!$B$2:$B$904,0))} -> #N/A | F65: {=INDEX(consolid1!$G$2:$G1534,MATCH(A65,consolid1!$B$2:$B1534,0))} -> #N/A
A66: UNIS CITE | B66: 105000 | C66: Locaux, matériel pour manifestations | D66: =IF(B66=0,"SANS","AVEC") -> AVEC | E66: {=INDEX(consolid1!$I$2:$I$904,MATCH(A66,consolid1!$B$2:$B$904,0))} -> #N/A | F66: {=INDEX(consolid1!$G$2:$G1534,MATCH(A66,consolid1!$B$2:$B1534,0))} -> #N/A
A67: FOOTBALL CLUB DES GIRONDINS DE BORDEAUX - FCGB | B67: 100000 | C67: Equipements sportifs | D67: =IF(B67=0,"SANS","AVEC") -> AVEC | E67: {=INDEX(consolid1!$I$2:$I$904,MATCH(A67,consolid1!$B$2:$B$904,0))} -> #N/A | F67: {=INDEX(consolid1!$G$2:$G1534,MATCH(A67,consolid1!$B$2:$B1534,0))} -> #N/A
A68: UNION BORDEAUX METROPOLE - UBM | B68: 83680 | C68: Locaux, équipements sportifs | D68: =IF(B68=0,"SANS","AVEC") -> AVEC | E68: {=INDEX(consolid1!$I$2:$I$904,MATCH(A68,consolid1!$B$2:$B$904,0))} -> #N/A | F68: {=INDEX(consolid1!$G$2:$G1534,MATCH(A68,consolid1!$B$2:$B1534,0))} -> #N/A
A69: AMICALE DES ETABLISSEMENTS SCOLAIRES LAIQUES DE BACALAN - ALB | B69: 82238 | C69: Locaux, équipements sportifs, matériel pour | D69: =IF(B69=0,"SANS","AVEC") -> AVEC | E69: {=INDEX(consolid1!$I$2:$I$904,MATCH(A69,consolid1!$B$2:$B$904,0))} -> #N/A | F69: {=INDEX(consolid1!$G$2:$G1534,MATCH(A69,consolid1!$B$2:$B1534,0))} -> #N/A
A70: CAP SCIENCES | B70: 81568 | D70: =IF(B70=0,"SANS","AVEC") -> AVEC | E70: {=INDEX(consolid1!$I$2:$I$904,MATCH(A70,consolid1!$B$2:$B$904,0))} -> Sciences | F70: {=INDEX(consolid1!$G$2:$G1534,MATCH(A70,consolid1!$B$2:$B1534,0))} -> Didier POURQUERY
A71: BORDEAUX MERIGNAC VOLLEY | B71: 80000 | C71: Equipements sportifs | D71: =IF(B71=0,"SANS","AVEC") -> AVEC | E71: {=INDEX(consolid1!$I$2:$I$904,MATCH(A71,consolid1!$B$2:$B$904,0))} -> #N/A | F71: {=INDEX(consolid1!$G$2:$G1534,MATCH(A71,consolid1!$B$2:$B1534,0))} -> #N/A
A72: LA HALLE DES DOUVES | B72: 80000 | C72: Locaux | D72: =IF(B72=0,"SANS","AVEC") -> AVEC | E72: {=INDEX(consolid1!$I$2:$I$904,MATCH(A72,consolid1!$B$2:$B$904,0))} -> #N/A | F72: {=INDEX(consolid1!$G$2:$G1534,MATCH(A72,consolid1!$B$2:$B1534,0))} -> #N/A
A73: SOLIHA, SOLIDAIRES POUR L'HABITAT, GIRONDE | B73: 73900 | C73: Locaux | D73: =IF(B73=0,"SANS","AVEC") -> AVEC | E73: {=INDEX(consolid1!$I$2:$I$904,MATCH(A73,consolid1!$B$2:$B$904,0))} -> #N/A | F73: {=INDEX(consolid1!$G$2:$G1534,MATCH(A73,consolid1!$B$2:$B1534,0))} -> #N/A
A74: SEMER LE DOUTE | B74: 73250 | C74: Communication, locaux, matériel pour | D74: =IF(B74=0,"SANS","AVEC") -> AVEC | E74: {=INDEX(consolid1!$I$2:$I$904,MATCH(A74,consolid1!$B$2:$B$904,0))} -> #N/A | F74: {=INDEX(consolid1!$G$2:$G1534,MATCH(A74,consolid1!$B$2:$B1534,0))} -> #N/A
A75: HALTE 33 | B75: 66000 | D75: =IF(B75=0,"SANS","AVEC") -> AVEC | E75: {=INDEX(consolid1!$I$2:$I$904,MATCH(A75,consolid1!$B$2:$B$904,0))} -> #N/A | F75: {=INDEX(consolid1!$G$2:$G1534,MATCH(A75,consolid1!$B$2:$B1534,0))} -> #N/A
A76: RESEAU PAUL BERT CENTRE SOCIAL ET CULTUREL | B76: 64000 | D76: =IF(B76=0,"SANS","AVEC") -> AVEC | E76: {=INDEX(consolid1!$I$2:$I$904,MATCH(A76,consolid1!$B$2:$B$904,0))} -> #N/A | F76: {=INDEX(consolid1!$G$2:$G1534,MATCH(A76,consolid1!$B$2:$B1534,0))} -> #N/A
A77: AGENCE D'URBANISME BORDEAUX METROPOLE AQUITAINE (A'URBA) | B77: 60000 | D77: =IF(B77=0,"SANS","AVEC") -> AVEC | E77: {=INDEX(consolid1!$I$2:$I$904,MATCH(A77,consolid1!$B$2:$B$904,0))} -> #N/A | F77: {=INDEX(consolid1!$G$2:$G1534,MATCH(A77,consolid1!$B$2:$B1534,0))} -> #N/A
A78: CHAHUTS | B78: 57500 | C78: Communication, locaux, matériel pour manifestations | D78: =IF(B78=0,"SANS","AVEC") -> AVEC | E78: {=INDEX(consolid1!$I$2:$I$904,MATCH(A78,consolid1!$B$2:$B$904,0))} -> Culture | F78: {=INDEX(consolid1!$G$2:$G1534,MATCH(A78,consolid1!$B$2:$B1534,0))} -> François Pouthier
A79: LA CAISSE A OUTILS | B79: 57005 | D79: =IF(B79=0,"SANS","AVEC") -> AVEC | E79: {=INDEX(consolid1!$I$2:$I$904,MATCH(A79,consolid1!$B$2:$B$904,0))} -> #N/A | F79: {=INDEX(consolid1!$G$2:$G1534,MATCH(A79,consolid1!$B$2:$B1534,0))} -> #N/A
A80: LA MEMOIRE DE BORDEAUX METROPOLE | B80: 56105 | C80: Locaux, matériel informatique | D80: =IF(B80=0,"SANS","AVEC") -> AVEC | E80: {=INDEX(consolid1!$I$2:$I$904,MATCH(A80,consolid1!$B$2:$B$904,0))} -> #N/A | F80: {=INDEX(consolid1!$G$2:$G1534,MATCH(A80,consolid1!$B$2:$B1534,0))} -> #N/A
A81: MAISON DE L'EUROPE BORDEAUX-AQUITAINE (MEBA) | B81: 56000 | C81: Locaux | D81: =IF(B81=0,"SANS","AVEC") -> AVEC | E81: {=INDEX(consolid1!$I$2:$I$904,MATCH(A81,consolid1!$B$2:$B$904,0))} -> #N/A | F81: {=INDEX(consolid1!$G$2:$G1534,MATCH(A81,consolid1!$B$2:$B1534,0))} -> #N/A
A82: ASSOCIATION LAIQUE LE PRADO | B82: 55000 | D82: =IF(B82=0,"SANS","AVEC") -> AVEC | E82: {=INDEX(consolid1!$I$2:$I$904,MATCH(A82,consolid1!$B$2:$B$904,0))} -> #N/A | F82: {=INDEX(consolid1!$G$2:$G1534,MATCH(A82,consolid1!$B$2:$B1534,0))} -> #N/A
A83: LES PETITS DEBROUILLARDS AQUITAINE | B83: 54201 | C83: Matériel pour manifestations | D83: =IF(B83=0,"SANS","AVEC") -> AVEC | E83: {=INDEX(consolid1!$I$2:$I$904,MATCH(A83,consolid1!$B$2:$B$904,0))} -> #N/A | F83: {=INDEX(consolid1!$G$2:$G1534,MATCH(A83,consolid1!$B$2:$B1534,0))} -> #N/A
A84: FONDATION D'AUTEUIL AQUITAINE | B84: 52500 | C84: Locaux | D84: =IF(B84=0,"SANS","AVEC") -> AVEC | E84: {=INDEX(consolid1!$I$2:$I$904,MATCH(A84,consolid1!$B$2:$B$904,0))} -> #N/A | F84: {=INDEX(consolid1!$G$2:$G1534,MATCH(A84,consolid1!$B$2:$B1534,0))} -> #N/A
A85: THEATRE DU PONT TOURNANT | B85: 52250 | D85: =IF(B85=0,"SANS","AVEC") -> AVEC | E85: {=INDEX(consolid1!$I$2:$I$904,MATCH(A85,consolid1!$B$2:$B$904,0))} -> #N/A | F85: {=INDEX(consolid1!$G$2:$G1534,MATCH(A85,consolid1!$B$2:$B1534,0))} -> #N/A
A86: REGIE DE QUARTIER HABITER BACALAN | B86: 51000 | C86: Locaux | D86: =IF(B86=0,"SANS","AVEC") -> AVEC | E86: {=INDEX(consolid1!$I$2:$I$904,MATCH(A86,consolid1!$B$2:$B$904,0))} -> #N/A | F86: {=INDEX(consolid1!$G$2:$G1534,MATCH(A86,consolid1!$B$2:$B1534,0))} -> #N/A
A87: ASSOCIATION DE DEFENSE DES MUSIQUES ALTERNATIVES EN AQUITAINE - ADMAA (ALLEZ LES FILLES) | B87: 50580 | C87: Communication, matériel pour manifestations | D87: =IF(B87=0,"SANS","AVEC") -> AVEC | E87: {=INDEX(consolid1!$I$2:$I$904,MATCH(A87,consolid1!$B$2:$B$904,0))} -> #N/A | F87: {=INDEX(consolid1!$G$2:$G1534,MATCH(A87,consolid1!$B$2:$B1534,0))} -> #N/A
A88: ASSOCIATION UNION BORDEAUX BEGLES | B88: 50000 | C88: Matériel pour manifestations | D88: =IF(B88=0,"SANS","AVEC") -> AVEC | E88: {=INDEX(consolid1!$I$2:$I$904,MATCH(A88,consolid1!$B$2:$B$904,0))} -> #N/A | F88: {=INDEX(consolid1!$G$2:$G1534,MATCH(A88,consolid1!$B$2:$B1534,0))} -> #N/A
A89: LA CITE DU VIN | B89: 50000 | D89: =IF(B89=0,"SANS","AVEC") -> AVEC | E89: {=INDEX(consolid1!$I$2:$I$904,MATCH(A89,consolid1!$B$2:$B$904,0))} -> #N/A | F89: {=INDEX(consolid1!$G$2:$G1534,MATCH(A89,consolid1!$B$2:$B1534,0))} -> #N/A
A90: LE SERVICE GAGNANT | B90: 50000 | D90: =IF(B90=0,"SANS","AVEC") -> AVEC | E90: {=INDEX(consolid1!$I$2:$I$904,MATCH(A90,consolid1!$B$2:$B$904,0))} -> #N/A | F90: {=INDEX(consolid1!$G$2:$G1534,MATCH(A90,consolid1!$B$2:$B1534,0))} -> #N/A
A91: MAIRES RESPONSABLES METROPOLES FRANCOPHONES - AIMF | B91: 50000 | D91: =IF(B91=0,"SANS","AVEC") -> AVEC | E91: {=INDEX(consolid1!$I$2:$I$904,MATCH(A91,consolid1!$B$2:$B$904,0))} -> #N/A | F91: {=INDEX(consolid1!$G$2:$G1534,MATCH(A91,consolid1!$B$2:$B1534,0))} -> #N/A
A92: CENTRE D'INFORMATION JEUNESSE AQUITAINE - CIJA | B92: 49000 | C92: Locaux, matériel pour manifestations | D92: =IF(B92=0,"SANS","AVEC") -> AVEC | E92: {=INDEX(consolid1!$I$2:$I$904,MATCH(A92,consolid1!$B$2:$B$904,0))} -> #N/A | F92: {=INDEX(consolid1!$G$2:$G1534,MATCH(A92,consolid1!$B$2:$B1534,0))} -> #N/A
A93: ECOLE DE CIRQUE DE BORDEAUX, CENTRE CULTUREL DES ARTS DU CIRQUE | B93: 46500 | C93: Locaux | D93: =IF(B93=0,"SANS","AVEC") -> AVEC | E93: {=INDEX(consolid1!$I$2:$I$904,MATCH(A93,consolid1!$B$2:$B$904,0))} -> #N/A | F93: {=INDEX(consolid1!$G$2:$G1534,MATCH(A93,consolid1!$B$2:$B1534,0))} -> #N/A
A94: MAISON DE NOLAN | B94: 46000 | D94: =IF(B94=0,"SANS","AVEC") -> AVEC | E94: {=INDEX(consolid1!$I$2:$I$904,MATCH(A94,consolid1!$B$2:$B$904,0))} -> #N/A | F94: {=INDEX(consolid1!$G$2:$G1534,MATCH(A94,consolid1!$B$2:$B1534,0))} -> #N/A
A95: ASSOCIATION GIRONDINE D'EDUCATION SPECIALISEE ET DE PREVENTION SOCIALE - AGEP | B95: 45400 | C95: Locaux | D95: =IF(B95=0,"SANS","AVEC") -> AVEC | E95: {=INDEX(consolid1!$I$2:$I$904,MATCH(A95,consolid1!$B$2:$B$904,0))} -> #N/A | F95: {=INDEX(consolid1!$G$2:$G1534,MATCH(A95,consolid1!$B$2:$B1534,0))} -> #N/A
A96: ATELIER GRAPHITE | B96: 44200 | C96: Locaux | D96: =IF(B96=0,"SANS","AVEC") -> AVEC | E96: {=INDEX(consolid1!$I$2:$I$904,MATCH(A96,consolid1!$B$2:$B$904,0))} -> #N/A | F96: {=INDEX(consolid1!$G$2:$G1534,MATCH(A96,consolid1!$B$2:$B1534,0))} -> #N/A
A97: COMPAGNIE DES MARCHES DE L'ETE | B97: 41500 | C97: Communication, locaux, matériel pour manifestations | D97: =IF(B97=0,"SANS","AVEC") -> AVEC | E97: {=INDEX(consolid1!$I$2:$I$904,MATCH(A97,consolid1!$B$2:$B$904,0))} -> #N/A | F97: {=INDEX(consolid1!$G$2:$G1534,MATCH(A97,consolid1!$B$2:$B1534,0))} -> #N/A
A98: MUSIQUES DE NUIT - DIFFUSION | B98: 40700 | C98: Communication, matériel pour manifestations | D98: =IF(B98=0,"SANS","AVEC") -> AVEC | E98: {=INDEX(consolid1!$I$2:$I$904,MATCH(A98,consolid1!$B$2:$B$904,0))} -> #N/A | F98: {=INDEX(consolid1!$G$2:$G1534,MATCH(A98,consolid1!$B$2:$B1534,0))} -> #N/A
A99: CONGRES ET EXPOSITIONS DE BORDEAUX | B99: 40000 | C99: Communication, matériel pour manifestations | D99: =IF(B99=0,"SANS","AVEC") -> AVEC | E99: {=INDEX(consolid1!$I$2:$I$904,MATCH(A99,consolid1!$B$2:$B$904,0))} -> #N/A | F99: {=INDEX(consolid1!$G$2:$G1534,MATCH(A99,consolid1!$B$2:$B1534,0))} -> #N/A
A100: ASSOCIATION PROMOTION INSERTION SPORT EN AQUITAINE - APIS | B100: 37754 | C100: Equipements sportifs, matériel pour manifestations | D100: =IF(B100=0,"SANS","AVEC") -> AVEC | E100: {=INDEX(consolid1!$I$2:$I$904,MATCH(A100,consolid1!$B$2:$B$904,0))} -> #N/A | F100: {=INDEX(consolid1!$G$2:$G1534,MATCH(A100,consolid1!$B$2:$B1534,0))} -> #N/A
...

Sheet analyse3

Sheet analyse4`

Sheet analyse5
