Workbook

Sheet nosdeputes.fr_deputes2018-05-31
A1: id | B1: nom | C1: nom_de_famille | D1: prenom | E1: sexe | F1: date_naissance | G1: lieu_naissance | H1: num_deptmt | I1: nom_circo | J1: num_circo | K1: mandat_debut | L1: mandat_fin | M1: ancien_depute | N1: groupe_sigle | O1: parti_ratt_financier | P1: sites_web | Q1: anciens_mandats | R1: profession | S1: place_en_hemicycle | T1: url_an | U1: id_an | V1: slug | W1: url_nosdeputes | X1: url_nosdeputes_api | Y1: nb_mandats | Z1: twitter
A2: 1 | B2: Alain Ballay | C2: Lamour | D2: Jean-François | E2: H | F2: 20487 | G2: Paris (Paris) | H2: 75 | I2: Paris | J2: 13 | K2: 41080 | L2: 42906 | M2: 1 | N2: LR | O2: Les Républicains | P2: http://www.jflamour.fr|https://twitter.com/JF_Lamour| | Q2: 20/06/2007 / 19/06/2012 / fin de législature|20/06/2012 / / | | R2: Kinésithérapeute | S2: 80 | T2: http://www2.assemblee-nationale.fr/deputes/fiche/OMC_PA230329 | U2: 230329 | V2: jean-francois-lamour | W2: https://2012-2017.nosdeputes.fr/jean-francois-lamour | X2: https://2012-2017.nosdeputes.fr/jean-francois-lamour/csv | Y2: 2 | Z2: JF_Lamour
A3: 2 | B3: Alain Bocquet | C3: Clément | D3: Jean-Michel | E3: H | F3: 20028 | G3: Mauprevoir (Vienne) | H3: 86 | I3: Vienne | J3: 3 | K3: 41080 | L3: 42906 | M3: 1 | N3: SER | O3: Parti socialiste | P3: https://twitter.com/jmclement86|http://www.jeanmichelclement.com| | Q3: 20/06/2007 / 19/06/2012 / fin de législature|20/06/2012 / / | | R3: Avocat | S3: 263 | T3: http://www2.assemblee-nationale.fr/deputes/fiche/OMC_PA336439 | U3: 336439 | V3: jean-michel-clement | W3: https://2012-2017.nosdeputes.fr/jean-michel-clement | X3: https://2012-2017.nosdeputes.fr/jean-michel-clement/csv | Y3: 2 | Z3: jmclement86
A4: 3 | B4: Alain Calmette | C4: Reynès | D4: Bernard | E4: H | F4: 19650 | G4: Meknès (Maroc) | H4: 13 | I4: Bouches-du-Rhône | J4: 15 | K4: 41080 | L4: 42906 | M4: 1 | N4: LR | O4: Les Républicains | P4: http://www.bernard-reynes.com|https://twitter.com/bernardreynes| | Q4: 20/06/2007 / 19/06/2012 / fin de législature|20/06/2012 / / | | R4: Chirurgien-Dentiste | S4: 190 | T4: http://www2.assemblee-nationale.fr/deputes/fiche/OMC_PA330788 | U4: 330788 | V4: bernard-reynes | W4: https://2012-2017.nosdeputes.fr/bernard-reynes | X4: https://2012-2017.nosdeputes.fr/bernard-reynes/csv | Y4: 2 | Z4: bernardreynes
A5: 4 | B5: Alain Chrétien | C5: Hurel | D5: Sandrine | E5: F | F5: 25057 | G5: Lisieux (Calvados) | H5: 76 | I5: Seine-Maritime | J5: 6 | K5: 41080 | L5: 42243 | M5: 1 | O5: Parti socialiste | P5: http://www.sandrine-hurel.info|https://twitter.com/sandrinehurel|http://www.sandrine-hurel.info/index.php| | Q5: 20/06/2007 / 19/06/2012 / fin de législature|20/06/2012 / 27/08/2015 / prolongation de mission temporaire| | R5: Secrétaire de direction | S5: 460 | T5: http://www2.assemblee-nationale.fr/deputes/fiche/OMC_PA304016 | U5: 304016 | V5: sandrine-hurel | W5: https://2012-2017.nosdeputes.fr/sandrine-hurel | X5: https://2012-2017.nosdeputes.fr/sandrine-hurel/csv | Y5: 2 | Z5: sandrinehurel
A6: 5 | B6: Alain Claeys | C6: Laffineur | D6: Marc | E6: H | F6: 16659 | G6: Maubeuge (Nord) | H6: 49 | I6: Maine-et-Loire | J6: 7 | K6: 41080 | L6: 42906 | M6: 1 | N6: LR | O6: Les Républicains | P6: http://www.marclaffineur.fr|https://twitter.com/Marclaffineur| | Q6: 20/06/2012 / / |01/06/1997 / 18/06/2002 / fin de législature|02/04/1993 / 21/04/1997 / fin de législature|19/06/2002 / 19/06/2007 / fin de législature|17/06/2012 / 19/06/2012 / fin de législature|20/06/2007 / 29/07/2011 / nomination comme membre du gouvernement|13/06/1988 / 01/04/1993 / fin de législature| | R6: Médecin anesthésiste-réanimateur | S6: 183 | T6: http://www2.assemblee-nationale.fr/deputes/fiche/OMC_PA1790 | U6: 1790 | V6: marc-laffineur | W6: https://2012-2017.nosdeputes.fr/marc-laffineur | X6: https://2012-2017.nosdeputes.fr/marc-laffineur/csv | Y6: 2 | Z6: Marclaffineur
A7: 6 | B7: Alain Fauré | C7: Courson (de) | D7: Charles | E7: H | F7: 19086 | G7: Paris (Paris) | H7: 51 | I7: Marne | J7: 5 | K7: 41080 | L7: 42906 | M7: 1 | N7: UDI | O7: Association PSLE - Nouveau centre | P7: https://twitter.com/C_deCourson| | Q7: 20/06/2007 / 19/06/2012 / fin de législature|20/06/2012 / / |01/06/1997 / 18/06/2002 / fin de législature|02/04/1993 / 21/04/1997 / fin de législature|19/06/2002 / 19/06/2007 / fin de législature| | R7: Magistrat à la Cour des comptes (conseiller référendaire de première classe) | S7: 295 | T7: http://www2.assemblee-nationale.fr/deputes/fiche/OMC_PA942 | U7: 942 | V7: charles-de-courson | W7: https://2012-2017.nosdeputes.fr/charles-de-courson | X7: https://2012-2017.nosdeputes.fr/charles-de-courson/csv | Y7: 3 | Z7: C_deCourson
A8: 7 | B8: Alain Gest | C8: Paul | D8: Christian | E8: H | F8: 21998 | G8: Clermont-Ferrand (Puy-de-Dôme) | H8: 58 | I8: Nièvre | J8: 2 | K8: 41080 | L8: 42906 | M8: 1 | N8: SER | O8: Parti socialiste | P8: http://www.christianpaul.fr|https://twitter.com/christianpaul58| | Q8: 20/06/2007 / 19/06/2012 / fin de législature|20/06/2012 / / |19/06/2002 / 19/06/2007 / fin de législature|01/06/1997 / 30/09/2000 / nomination comme membre du gouvernement| | R8: Administrateur civil | S8: 336 | T8: http://www2.assemblee-nationale.fr/deputes/fiche/OMC_PA2338 | U8: 2338 | V8: christian-paul | W8: https://2012-2017.nosdeputes.fr/christian-paul | X8: https://2012-2017.nosdeputes.fr/christian-paul/csv | Y8: 2 | Z8: christianpaul58
A9: 8 | B9: Alain Leboeuf | C9: Dufau | D9: Jean-Pierre | E9: H | F9: 15892 | G9: Capbreton (Landes) | H9: 40 | I9: Landes | J9: 2 | K9: 41080 | L9: 42906 | M9: 1 | N9: SER | O9: Parti socialiste | P9: http://www.jeanpierredufau.org| | Q9: 20/06/2007 / 19/06/2012 / fin de législature|20/06/2012 / / |01/06/1997 / 18/06/2002 / fin de législature|19/06/2002 / 19/06/2007 / fin de législature| | R9: Enseignant retraité | S9: 500 | T9: http://www2.assemblee-nationale.fr/deputes/fiche/OMC_PA1182 | U9: 1182 | V9: jean-pierre-dufau | W9: https://2012-2017.nosdeputes.fr/jean-pierre-dufau | X9: https://2012-2017.nosdeputes.fr/jean-pierre-dufau/csv | Y9: 2
A10: 9 | B10: Alain Marc | C10: Féron | D10: Hervé | E10: H | F10: 20670 | G10: Luxeuil-les-Bains (Haute-Saône) | H10: 54 | I10: Meurthe-et-Moselle | J10: 2 | K10: 41080 | L10: 42906 | M10: 1 | N10: SER | O10: Parti socialiste | P10: http://herveferon.fr| | Q10: 20/06/2007 / 19/06/2012 / fin de législature|20/06/2012 / / | | R10: Homme de lettres et artiste | S10: 524 | T10: http://www2.assemblee-nationale.fr/deputes/fiche/OMC_PA333335 | U10: 333335 | V10: herve-feron | W10: https://2012-2017.nosdeputes.fr/herve-feron | X10: https://2012-2017.nosdeputes.fr/herve-feron/csv | Y10: 2
A11: 10 | B11: Alain Marleix | C11: Touraine | D11: Jean-Louis | E11: H | F11: 16718 | G11: Lyon (3ème arrondissement) (Rhône) | H11: 69 | I11: Rhône | J11: 3 | K11: 41080 | L11: 42906 | M11: 1 | N11: SER | O11: Parti socialiste | P11: http://www.jeanlouistouraine.fr| | Q11: 20/06/2007 / 19/06/2012 / fin de législature|20/06/2012 / / | | R11: Professeur de médecine | S11: 518 | T11: http://www2.assemblee-nationale.fr/deputes/fiche/OMC_PA334768 | U11: 334768 | V11: jean-louis-touraine | W11: https://2012-2017.nosdeputes.fr/jean-louis-touraine | X11: https://2012-2017.nosdeputes.fr/jean-louis-touraine/csv | Y11: 3
A12: 11 | B12: Alain Marsaud | C12: Giacobbi | D12: Paul | E12: H | F12: 20975 | G12: Courbevoie (Hauts-de-Seine) | H12: 2B | I12: Haute-Corse | J12: 2 | K12: 41080 | L12: 42906 | M12: 1 | N12: RRDP | O12: Parti radical de gauche | P12: https://twitter.com/pgiacobbi|http://blog.paul-giacobbi.org| | Q12: 20/06/2007 / 19/06/2012 / fin de législature|20/06/2012 / / |19/06/2002 / 19/06/2007 / fin de législature| | R12: Administrateur civil au ministère de l'équipement | S12: 269 | T12: http://www2.assemblee-nationale.fr/deputes/fiche/OMC_PA267407 | U12: 267407 | V12: paul-giacobbi | W12: https://2012-2017.nosdeputes.fr/paul-giacobbi | X12: https://2012-2017.nosdeputes.fr/paul-giacobbi/csv | Y12: 3 | Z12: pgiacobbi
A13: 12 | B13: Alain Marty | C13: Le Fur | D13: Marc | E13: H | F13: 20787 | G13: Dakar (Sénégal) | H13: 22 | I13: Côtes-d'Armor | J13: 3 | K13: 41080 | L13: 42906 | M13: 1 | N13: LR | O13: Les Républicains | P13: http://www.marclefur.bzh|http://www.marclefur.com|https://twitter.com/marclefur| | Q13: 20/06/2007 / 19/06/2012 / fin de législature|20/06/2012 / / |02/04/1993 / 21/04/1997 / fin de législature|19/06/2002 / 19/06/2007 / fin de législature| | R13: Sous-préfet | S13: 96 | T13: http://www2.assemblee-nationale.fr/deputes/fiche/OMC_PA1874 | U13: 1874 | V13: marc-le-fur | W13: https://2012-2017.nosdeputes.fr/marc-le-fur | X13: https://2012-2017.nosdeputes.fr/marc-le-fur/csv | Y13: 2 | Z13: marclefur
A14: 13 | B14: Alain Moyne-Bressand | C14: Marsac | D14: Jean-René | E14: H | F14: 19835 | G14: Béganne (Morbihan) | H14: 35 | I14: Ille-et-Vilaine | J14: 4 | K14: 41080 | L14: 42906 | M14: 1 | N14: SER | O14: Parti socialiste | P14: http://www.jrmarsac-leblog.typepad.fr| | Q14: 20/06/2007 / 19/06/2012 / fin de législature|20/06/2012 / / | | R14: Cadre | S14: 527 | T14: http://www2.assemblee-nationale.fr/deputes/fiche/OMC_PA332206 | U14: 332206 | V14: jean-rene-marsac | W14: https://2012-2017.nosdeputes.fr/jean-rene-marsac | X14: https://2012-2017.nosdeputes.fr/jean-rene-marsac/csv | Y14: 1
A15: 14 | B15: Alain Rodet | C15: Leonetti | D15: Jean | E15: H | F15: 17723 | G15: Marseille (Bouches-du-Rhône) | H15: 6 | I15: Alpes-Maritimes | J15: 7 | K15: 41080 | L15: 42906 | M15: 1 | N15: LR | O15: Les Républicains | P15: http://jeanleonetti.com|http://www.jeanleonetti.fr|https://twitter.com/JeanLeonetti| | Q15: 20/06/2012 / / |01/06/1997 / 18/06/2002 / fin de législature|19/06/2002 / 19/06/2007 / fin de législature|17/06/2012 / 19/06/2012 / fin de législature|20/06/2007 / 29/07/2011 / nomination comme membre du gouvernement| | R15: Praticien hospitalier | S15: 81 | T15: http://www2.assemblee-nationale.fr/deputes/fiche/OMC_PA1946 | U15: 1946 | V15: jean-leonetti | W15: https://2012-2017.nosdeputes.fr/jean-leonetti | X15: https://2012-2017.nosdeputes.fr/jean-leonetti/csv | Y15: 2 | Z15: JeanLeonetti
A16: 15 | B16: Alain Rousset | C16: Fourneyron | D16: Valérie | E16: F | F16: 21827 | G16: Petit Quevilly (Seine-Maritime) | H16: 76 | I16: Seine-Maritime | J16: 1 | K16: 41824 | L16: 42906 | M16: 1 | N16: SER | O16: Parti socialiste | P16: http://www.valerie-fourneyron.fr| | Q16: 20/06/2012 / 21/07/2012 / nomination comme membre du gouvernement|04/07/2014 / / |20/06/2007 / 16/06/2012 / nomination comme membre du gouvernement| | R16: Médecin | S16: 335 | T16: http://www2.assemblee-nationale.fr/deputes/fiche/OMC_PA335543 | U16: 335543 | V16: valerie-fourneyron | W16: https://2012-2017.nosdeputes.fr/valerie-fourneyron | X16: https://2012-2017.nosdeputes.fr/valerie-fourneyron/csv | Y16: 2
A17: 16 | B17: Alain Suguenot | C17: Rugy (de) | D17: François | E17: H | F17: 27004 | G17: Nantes (Loire-Atlantique) | H17: 44 | I17: Loire-Atlantique | J17: 1 | K17: 41080 | L17: 42906 | M17: 1 | N17: SER | O17: Parti socialiste | P17: http://www.francoisderugy.fr|http://www.derugy2017.fr|https://twitter.com/FdeRugy| | Q17: 20/06/2007 / 19/06/2012 / fin de législature|20/06/2012 / / | | R17: Assistant parlementaire | S17: 274 | T17: http://www2.assemblee-nationale.fr/deputes/fiche/OMC_PA332747 | U17: 332747 | V17: francois-de-rugy | W17: https://2012-2017.nosdeputes.fr/francois-de-rugy | X17: https://2012-2017.nosdeputes.fr/francois-de-rugy/csv | Y17: 3 | Z17: FdeRugy
A18: 17 | B18: Alain Tourret | C18: Chartier | D18: Jérôme | E18: H | F18: 24425 | G18: Paris (Paris) | H18: 95 | I18: Val-d'Oise | J18: 7 | K18: 41080 | L18: 42906 | M18: 1 | N18: LR | O18: Les Républicains | P18: http://www.jeromechartier.fr|https://twitter.com/jechartier| | Q18: 20/06/2007 / 19/06/2012 / fin de législature|20/06/2012 / / |19/06/2002 / 19/06/2007 / fin de législature| | R18: Ancien associé gérant | S18: 85 | T18: http://www2.assemblee-nationale.fr/deputes/fiche/OMC_PA267895 | U18: 267895 | V18: jerome-chartier | W18: https://2012-2017.nosdeputes.fr/jerome-chartier | X18: https://2012-2017.nosdeputes.fr/jerome-chartier/csv | Y18: 3 | Z18: jechartier
A19: 18 | B19: Alain Vidalies | C19: Jung | D19: Armand | E19: H | F19: 18610 | G19: Theding (Moselle) | H19: 67 | I19: Bas-Rhin | J19: 1 | K19: 41080 | L19: 42432 | M19: 1 | O19: Parti socialiste | P19: http://www.armandjung-depute.fr| | Q19: 20/06/2007 / 19/06/2012 / fin de législature|20/06/2012 / 03/03/2016 / démission|19/06/2002 / 19/06/2007 / fin de législature|05/07/1997 / 18/06/2002 / fin de législature| | R19: Fonctionnaire territorial | S19: 383 | T19: http://www2.assemblee-nationale.fr/deputes/fiche/OMC_PA1748 | U19: 1748 | V19: armand-jung | W19: https://2012-2017.nosdeputes.fr/armand-jung | X19: https://2012-2017.nosdeputes.fr/armand-jung/csv | Y19: 1
A20: 633 | B20: Alexis Bachelay | C20: Gauquelin | D20: Renaud | E20: H | F20: 20035 | G20: Paris (Paris) | H20: 69 | I20: Rhône | J20: 7 | K20: 42441 | L20: 42906 | M20: 1 | N20: SER | O20: Parti socialiste | Q20: 12/03/2016 / / | | R20: Médecin généraliste | S20: 541 | T20: http://www2.assemblee-nationale.fr/deputes/fiche/OMC_PA643165 | U20: 643165 | V20: renaud-gauquelin | W20: https://2012-2017.nosdeputes.fr/renaud-gauquelin | X20: https://2012-2017.nosdeputes.fr/renaud-gauquelin/csv | Y20: 2
A21: 19 | B21: Alfred Marie-Jeanne | C21: Hillmeyer | D21: Francis | E21: H | F21: 17054 | G21: Mulhouse (Haut-Rhin) | H21: 68 | I21: Haut-Rhin | J21: 6 | K21: 41080 | L21: 42906 | M21: 1 | N21: UDI | O21: Association PSLE - Nouveau centre | Q21: 20/06/2007 / 19/06/2012 / fin de législature|20/06/2012 / / |26/06/2000 / 18/06/2002 / fin de législature|19/06/2002 / 19/06/2007 / fin de législature| | R21: Journaliste reporter-photographe | S21: 234 | T21: http://www2.assemblee-nationale.fr/deputes/fiche/OMC_PA216574 | U21: 216574 | V21: francis-hillmeyer | W21: https://2012-2017.nosdeputes.fr/francis-hillmeyer | X21: https://2012-2017.nosdeputes.fr/francis-hillmeyer/csv | Y21: 2
A22: 20 | B22: André Chassaigne | C22: Lemasle | D22: Patrick | E22: H | F22: 19132 | G22: Saint-Hilaire-du-Harcouët (Manche) | H22: 31 | I22: Haute-Garonne | J22: 7 | K22: 41080 | L22: 42906 | M22: 1 | N22: SER | O22: Parti socialiste | Q22: 20/06/2007 / 19/06/2012 / fin de législature|20/06/2012 / / |19/06/2002 / 19/06/2007 / fin de législature|03/07/1997 / 18/06/2002 / fin de législature| | R22: Exploitant agricole | S22: 540 | T22: http://www2.assemblee-nationale.fr/deputes/fiche/OMC_PA1936 | U22: 1936 | V22: patrick-lemasle | W22: https://2012-2017.nosdeputes.fr/patrick-lemasle | X22: https://2012-2017.nosdeputes.fr/patrick-lemasle/csv | Y22: 2
A23: 21 | B23: André Santini | C23: Lambert | D23: Jérôme | E23: H | F23: 20978 | G23: Vincennes (Val-de-Marne) | H23: 16 | I23: Charente | J23: 3 | K23: 41080 | L23: 42906 | M23: 1 | N23: RRDP | O23: Parti socialiste | Q23: 20/06/2007 / 19/06/2012 / fin de législature|20/06/2012 / / |01/06/1997 / 18/06/2002 / fin de législature|19/06/2002 / 19/06/2007 / fin de législature|02/04/1986 / 14/05/1988 / fin de législature|13/06/1988 / 01/04/1993 / fin de législature| | R23: Cadre de l'industrie | S23: 300 | T23: http://www2.assemblee-nationale.fr/deputes/fiche/OMC_PA1809 | U23: 1809 | V23: jerome-lambert | W23: https://2012-2017.nosdeputes.fr/jerome-lambert | X23: https://2012-2017.nosdeputes.fr/jerome-lambert/csv | Y23: 1
A24: 22 | B24: André Schneider | C24: Verchère | D24: Patrice | E24: H | F24: 27027 | G24: Coteau (Loire) | H24: 69 | I24: Rhône | J24: 8 | K24: 41080 | L24: 42906 | M24: 1 | N24: LR | O24: Les Républicains | P24: http://www.patriceverchere.fr| | Q24: 20/06/2007 / 19/06/2012 / fin de législature|20/06/2012 / / | | R24: Assistant parlementaire | S24: 143 | T24: http://www2.assemblee-nationale.fr/deputes/fiche/OMC_PA334843 | U24: 334843 | V24: patrice-verchere | W24: https://2012-2017.nosdeputes.fr/patrice-verchere | X24: https://2012-2017.nosdeputes.fr/patrice-verchere/csv | Y24: 2
A25: 23 | B25: Anne Grommerch | C25: Gaymard | D25: Hervé | E25: H | F25: 22067 | G25: Bourg-Saint-Maurice (Savoie) | H25: 73 | I25: Savoie | J25: 2 | K25: 41080 | L25: 42906 | M25: 1 | N25: LR | O25: Les Républicains | P25: http://www.herve-gaymard.fr|https://twitter.com/HGaymard|http://www.herve-gaymard.com| | Q25: 20/06/2007 / 19/06/2012 / fin de législature|20/06/2012 / / |01/06/1997 / 07/06/2002 / nomination comme membre du gouvernement|17/07/1995 / 16/08/1995 / nomination comme membre du gouvernement|02/05/1993 / 06/06/1995 / démission|19/06/2002 / 18/07/2002 / nomination comme membre du gouvernement| | R25: Administrateur civil | S25: 170 | T25: http://www2.assemblee-nationale.fr/deputes/fiche/OMC_PA1445 | U25: 1445 | V25: herve-gaymard | W25: https://2012-2017.nosdeputes.fr/herve-gaymard | X25: https://2012-2017.nosdeputes.fr/herve-gaymard/csv | Y25: 2 | Z25: HGaymard
A26: 24 | B26: Anne-Christine Lang | C26: Salen | D26: Paul | E26: H | F26: 18066 | G26: Veauche (Loire) | H26: 42 | I26: Loire | J26: 6 | K26: 41080 | L26: 42906 | M26: 1 | N26: LR | O26: Les Républicains | P26: http://www.paulsalendepute.fr| | Q26: 20/06/2012 / / |06/05/2011 / 19/06/2012 / fin de législature| | R26: Retraité | S26: 241 | T26: http://www2.assemblee-nationale.fr/deputes/fiche/OMC_PA2664 | U26: 2664 | V26: paul-salen | W26: https://2012-2017.nosdeputes.fr/paul-salen | X26: https://2012-2017.nosdeputes.fr/paul-salen/csv | Y26: 1
A27: 25 | B27: Anne-Lise Dufour-Tonini | C27: Lazaro | D27: Thierry | E27: H | F27: 22186 | G27: Lille (Nord) | H27: 59 | I27: Nord | J27: 6 | K27: 41080 | L27: 42906 | M27: 1 | N27: LR | O27: Les Républicains | P27: http://thierrylazaro.fr| | Q27: 20/06/2007 / 19/06/2012 / fin de législature|20/06/2012 / / |01/06/1997 / 18/06/2002 / fin de législature|02/04/1993 / 21/04/1997 / fin de législature|19/06/2002 / 19/06/2007 / fin de législature| | R27: Chargé de communication | S27: 89 | T27: http://www2.assemblee-nationale.fr/deputes/fiche/OMC_PA1857 | U27: 1857 | V27: thierry-lazaro | W27: https://2012-2017.nosdeputes.fr/thierry-lazaro | X27: https://2012-2017.nosdeputes.fr/thierry-lazaro/csv | Y27: 2
A28: 26 | B28: Anne-Yvonne Le Dain | C28: Got | D28: Pascale | E28: F | F28: 22372 | G28: Royan (Charente-Maritime) | H28: 33 | I28: Gironde | J28: 5 | K28: 41080 | L28: 42906 | M28: 1 | N28: SER | O28: Parti socialiste | Q28: 20/06/2007 / 19/06/2012 / fin de législature|20/06/2012 / / | | R28: Journaliste | S28: 523 | T28: http://www2.assemblee-nationale.fr/deputes/fiche/OMC_PA331973 | U28: 331973 | V28: pascale-got | W28: https://2012-2017.nosdeputes.fr/pascale-got | X28: https://2012-2017.nosdeputes.fr/pascale-got/csv | Y28: 2
A29: 27 | B29: Annick Girardin | C29: Guégot | D29: Françoise | E29: F | F29: 22869 | G29: Oullins (Rhône) | H29: 76 | I29: Seine-Maritime | J29: 2 | K29: 41080 | L29: 42906 | M29: 1 | N29: LR | O29: Les Républicains | P29: https://twitter.com/fguegot|http://www.francoiseguegot.fr| | Q29: 20/06/2007 / 19/06/2012 / fin de législature|20/06/2012 / / | | R29: Maître de conférences associée | S29: 91 | T29: http://www2.assemblee-nationale.fr/deputes/fiche/OMC_PA335567 | U29: 335567 | V29: francoise-guegot | W29: https://2012-2017.nosdeputes.fr/francoise-guegot | X29: https://2012-2017.nosdeputes.fr/francoise-guegot/csv | Y29: 2 | Z29: fguegot
A30: 28 | B30: Annick Le Loch | C30: Perez | D30: Jean-Claude | E30: H | F30: 23467 | G30: Carcassonne (Aude) | H30: 11 | I30: Aude | J30: 1 | K30: 41080 | L30: 42906 | M30: 1 | N30: SER | O30: Parti socialiste | P30: http://www.jeanclaudeperez.net| | Q30: 20/06/2007 / 19/06/2012 / fin de législature|20/06/2012 / / |01/06/1997 / 18/06/2002 / fin de législature|19/06/2002 / 19/06/2007 / fin de législature| | R30: Secrétaire de mairie | S30: 412 | T30: http://www2.assemblee-nationale.fr/deputes/fiche/OMC_PA2365 | U30: 2365 | V30: jean-claude-perez | W30: https://2012-2017.nosdeputes.fr/jean-claude-perez | X30: https://2012-2017.nosdeputes.fr/jean-claude-perez/csv | Y30: 2
A31: 29 | B31: Annick Lepetit | C31: Mariani | D31: Thierry | E31: H | F31: 21405 | G31: Orange (Vaucluse) | H31: 999 | I31: Français établis hors de France | J31: 11 | K31: 41080 | L31: 42906 | M31: 1 | N31: LR | O31: Les Républicains | P31: http://www.thierrymariani.com|https://twitter.com/ThierryMARIANI| | Q31: 20/06/2012 / / |20/06/2007 / 15/12/2010 / nomination comme membre du gouvernement|01/06/1997 / 18/06/2002 / fin de législature|02/04/1993 / 21/04/1997 / fin de législature|19/06/2002 / 19/06/2007 / fin de législature|17/06/2012 / 19/06/2012 / fin de législature| | R31: Cadre | S31: 7 | T31: http://www2.assemblee-nationale.fr/deputes/fiche/OMC_PA2073 | U31: 2073 | V31: thierry-mariani | W31: https://2012-2017.nosdeputes.fr/thierry-mariani | X31: https://2012-2017.nosdeputes.fr/thierry-mariani/csv | Y31: 2 | Z31: ThierryMARIANI
A32: 30 | B32: Annie Genevard | C32: Reynier | D32: Franck | E32: H | F32: 24035 | G32: Montélimar (Drôme) | H32: 26 | I32: Drôme | J32: 2 | K32: 41080 | L32: 42906 | M32: 1 | N32: UDI | O32: Union des Radicaux, Centristes, Indépendants et Démocrates | P32: http://www.franckreynier.fr|http://www.franck-reynier.fr|https://twitter.com/FranckReynier| | Q32: 20/06/2007 / 19/06/2012 / fin de législature|20/06/2012 / / | | R32: Informaticien | S32: 211 | T32: http://www2.assemblee-nationale.fr/deputes/fiche/OMC_PA331442 | U32: 331442 | V32: franck-reynier | W32: https://2012-2017.nosdeputes.fr/franck-reynier | X32: https://2012-2017.nosdeputes.fr/franck-reynier/csv | Y32: 2 | Z32: FranckReynier
A33: 31 | B33: Annie Le Houerou | C33: Lepetit | D33: Annick | E33: F | F33: 21275 | G33: Boulogne-Billancourt (Hauts-de-Seine) | H33: 75 | I33: Paris | J33: 3 | K33: 41080 | L33: 42906 | M33: 1 | N33: SER | O33: Parti socialiste | P33: http://www.annicklepetit.fr|https://twitter.com/annick_lepetit| | Q33: 20/06/2007 / 19/06/2012 / fin de législature|20/06/2012 / / |19/06/2002 / 21/11/2002 / annulation de l'élection sur décision du conseil constitutionnel|03/02/2003 / 19/06/2007 / fin de législature| | R33: Cadre | S33: 372 | T33: http://www2.assemblee-nationale.fr/deputes/fiche/OMC_PA267965 | U33: 267965 | V33: annick-lepetit | W33: https://2012-2017.nosdeputes.fr/annick-lepetit | X33: https://2012-2017.nosdeputes.fr/annick-lepetit/csv | Y33: 2 | Z33: annick_lepetit
A34: 32 | B34: Antoine Herth | C34: Mamère | D34: Noël | E34: H | F34: 17892 | G34: Libourne (Gironde) | H34: 33 | I34: Gironde | J34: 3 | K34: 41080 | L34: 42906 | M34: 1 | N34: NI | O34: Europe Écologie Les Verts | P34: https://twitter.com/noelmamere| | Q34: 20/06/2007 / 19/06/2012 / fin de législature|20/06/2012 / / |01/06/1997 / 18/06/2002 / fin de législature|19/06/2002 / 19/06/2007 / fin de législature| | R34: Journaliste | S34: 303 | T34: http://www2.assemblee-nationale.fr/deputes/fiche/OMC_PA2045 | U34: 2045 | V34: noel-mamere | W34: https://2012-2017.nosdeputes.fr/noel-mamere | X34: https://2012-2017.nosdeputes.fr/noel-mamere/csv | Y34: 2 | Z34: noelmamere
A35: 33 | B35: Arlette Grosskost | C35: Scellier | D35: François | E35: H | F35: 13277 | G35: Amiens (Somme) | H35: 95 | I35: Val-d'Oise | J35: 6 | K35: 41080 | L35: 42906 | M35: 1 | N35: LR | O35: Union des Radicaux, Centristes, Indépendants et Démocrates | P35: http://www.scellier.net| | Q35: 20/06/2007 / 19/06/2012 / fin de législature|20/06/2012 / / |19/06/2002 / 19/06/2007 / fin de législature| | R35: Directeur divisionnaire des impôts honoraire | S35: 6 | T35: http://www2.assemblee-nationale.fr/deputes/fiche/OMC_PA2700 | U35: 2700 | V35: francois-scellier | W35: https://2012-2017.nosdeputes.fr/francois-scellier | X35: https://2012-2017.nosdeputes.fr/francois-scellier/csv | Y35: 2
A36: 34 | B36: Armand Jung | C36: Cherpion | D36: Gérard | E36: H | F36: 17607 | G36: Dombasle-sur-Meurthe (Meurthe-et-Moselle) | H36: 88 | I36: Vosges | J36: 2 | K36: 41080 | L36: 42906 | M36: 1 | N36: LR | O36: Les Républicains | P36: http://www.gerard-cherpion.fr|https://twitter.com/GerardCherpion| | Q36: 20/06/2007 / 19/06/2012 / fin de législature|20/06/2012 / / |02/04/1993 / 21/04/1997 / fin de législature|19/06/2002 / 19/06/2007 / fin de législature| | R36: Pharmacien | S36: 114 | T36: http://www2.assemblee-nationale.fr/deputes/fiche/OMC_PA856 | U36: 856 | V36: gerard-cherpion | W36: https://2012-2017.nosdeputes.fr/gerard-cherpion | X36: https://2012-2017.nosdeputes.fr/gerard-cherpion/csv | Y36: 2 | Z36: GerardCherpion
A37: 35 | B37: Arnaud Leroy | C37: Fraysse | D37: Jacqueline | E37: F | F37: 17223 | G37: Paris (Paris) | H37: 92 | I37: Hauts-de-Seine | J37: 4 | K37: 41080 | L37: 42906 | M37: 1 | N37: GDR | O37: Forces de gauche | Q37: 20/06/2007 / 19/06/2012 / fin de législature|20/06/2012 / / |02/07/1981 / 01/04/1986 / fin de législature|03/04/1978 / 22/05/1981 / fin de législature|01/06/1997 / 18/06/2002 / fin de législature|19/06/2002 / 19/06/2007 / fin de législature| | R37: Médecin cardiologue | S37: 590 | T37: http://www2.assemblee-nationale.fr/deputes/fiche/OMC_PA1364 | U37: 1364 | V37: jacqueline-fraysse | W37: https://2012-2017.nosdeputes.fr/jacqueline-fraysse | X37: https://2012-2017.nosdeputes.fr/jacqueline-fraysse/csv | Y37: 2
A38: 36 | B38: Arnaud Richard | C38: Leroy | D38: Maurice | E38: H | F38: 21583 | G38: Paris (Paris) | H38: 41 | I38: Loir-et-Cher | J38: 3 | K38: 41080 | L38: 42906 | M38: 1 | N38: UDI | O38: Association PSLE - Nouveau centre | P38: https://twitter.com/MauriceLeroy|http://www.mauriceleroymedia.com|http://www.facebook.com/maurice.leroy.politique| | Q38: 20/06/2012 / / |20/06/2007 / 15/12/2010 / nomination comme membre du gouvernement|01/06/1997 / 18/06/2002 / fin de législature|19/06/2002 / 19/06/2007 / fin de législature|17/06/2012 / 19/06/2012 / fin de législature| | R38: Économiste | S38: 200 | T38: http://www2.assemblee-nationale.fr/deputes/fiche/OMC_PA1960 | U38: 1960 | V38: maurice-leroy | W38: https://2012-2017.nosdeputes.fr/maurice-leroy | X38: https://2012-2017.nosdeputes.fr/maurice-leroy/csv | Y38: 2 | Z38: MauriceLeroy
A39: 37 | B39: Arnaud Robinet | C39: Vercamer | D39: Francis | E39: H | F39: 21315 | G39: Lille (Nord) | H39: 59 | I39: Nord | J39: 7 | K39: 41080 | L39: 42906 | M39: 1 | N39: UDI | O39: Association PSLE - Nouveau centre | P39: http://www.vercamer.fr| | Q39: 20/06/2007 / 19/06/2012 / fin de législature|20/06/2012 / / |19/06/2002 / 19/06/2007 / fin de législature| | R39: Ingénieur | S39: 191 | T39: http://www2.assemblee-nationale.fr/deputes/fiche/OMC_PA267585 | U39: 267585 | V39: francis-vercamer | W39: https://2012-2017.nosdeputes.fr/francis-vercamer | X39: https://2012-2017.nosdeputes.fr/francis-vercamer/csv | Y39: 2
A40: 38 | B40: Arnaud Viala | C40: Cornut-Gentille | D40: François | E40: H | F40: 21327 | G40: Saint-Mandé (Val-de-Marne) | H40: 52 | I40: Haute-Marne | J40: 2 | K40: 41080 | L40: 42906 | M40: 1 | N40: LR | O40: Les Républicains | P40: http://www.francois.cornut-gentille.fr| | Q40: 20/06/2007 / 19/06/2012 / fin de législature|20/06/2012 / / |01/06/1997 / 18/06/2002 / fin de législature|02/04/1993 / 21/04/1997 / fin de législature|19/06/2002 / 19/06/2007 / fin de législature| | R40: Cadre d'entreprise | S40: 94 | T40: http://www2.assemblee-nationale.fr/deputes/fiche/OMC_PA923 | U40: 923 | V40: francois-cornut-gentille | W40: https://2012-2017.nosdeputes.fr/francois-cornut-gentille | X40: https://2012-2017.nosdeputes.fr/francois-cornut-gentille/csv | Y40: 2
A41: 39 | B41: Ary Chalus | C41: Jacquat | D41: Denis | E41: H | F41: 16221 | G41: Thiaucourt (Meurthe-et-Moselle) | H41: 57 | I41: Moselle | J41: 2 | K41: 41080 | L41: 42906 | M41: 1 | N41: LR | O41: Les Républicains | P41: http://www.denisjacquat.fr| | Q41: 20/06/2007 / 19/06/2012 / fin de législature|20/06/2012 / / |01/06/1997 / 18/06/2002 / fin de législature|02/04/1993 / 21/04/1997 / fin de législature|19/06/2002 / 19/06/2007 / fin de législature|02/04/1986 / 14/05/1988 / fin de législature|13/06/1988 / 01/04/1993 / fin de législature| | R41: Médecin O.R.L. retraité | S41: 135 | T41: http://www2.assemblee-nationale.fr/deputes/fiche/OMC_PA1699 | U41: 1699 | V41: denis-jacquat | W41: https://2012-2017.nosdeputes.fr/denis-jacquat | X41: https://2012-2017.nosdeputes.fr/denis-jacquat/csv | Y41: 2
A42: 40 | B42: Audrey Linkenheld | C42: Dosière | D42: René | E42: H | F42: 15191 | G42: Origny-Sainte-Benoîte (Aisne) | H42: 2 | I42: Aisne | J42: 1 | K42: 41080 | L42: 42906 | M42: 1 | N42: SER | O42: Parti socialiste | Q42: 20/06/2007 / 19/06/2012 / fin de législature|20/06/2012 / / |01/06/1997 / 18/06/2002 / fin de législature|19/06/2002 / 19/06/2007 / fin de législature|13/06/1988 / 01/04/1993 / fin de législature| | R42: Consultant international | S42: 461 | T42: http://www2.assemblee-nationale.fr/deputes/fiche/OMC_PA1155 | U42: 1155 | V42: rene-dosiere | W42: https://2012-2017.nosdeputes.fr/rene-dosiere | X42: https://2012-2017.nosdeputes.fr/rene-dosiere/csv | Y42: 1
A43: 41 | B43: Aurélie Filippetti | C43: Carrillon-Couvreur | D43: Martine | E43: F | F43: 17613 | G43: Lyon 6ème (Rhône) | H43: 58 | I43: Nièvre | J43: 1 | K43: 41080 | L43: 42906 | M43: 1 | N43: SER | O43: Parti socialiste | Q43: 20/06/2007 / 19/06/2012 / fin de législature|20/06/2012 / / |19/06/2002 / 19/06/2007 / fin de législature| | R43: Directrice d'un institut médico-éducatif | S43: 415 | T43: http://www2.assemblee-nationale.fr/deputes/fiche/OMC_PA267188 | U43: 267188 | V43: martine-carrillon-couvreur | W43: https://2012-2017.nosdeputes.fr/martine-carrillon-couvreur | X43: https://2012-2017.nosdeputes.fr/martine-carrillon-couvreur/csv | Y43: 2
A44: 42 | B44: Avi Assouly | C44: Pons | D44: Josette | E44: F | F44: 17513 | G44: Saint-Cyr-sur-Mer (Var) | H44: 83 | I44: Var | J44: 6 | K44: 41080 | L44: 42906 | M44: 1 | N44: LR | O44: Les Républicains | Q44: 20/06/2007 / 19/06/2012 / fin de législature|20/06/2012 / / |19/06/2002 / 19/06/2007 / fin de législature| | R44: Sans profession declaree | S44: 109 | T44: http://www2.assemblee-nationale.fr/deputes/fiche/OMC_PA267598 | U44: 267598 | V44: josette-pons | W44: https://2012-2017.nosdeputes.fr/josette-pons | X44: https://2012-2017.nosdeputes.fr/josette-pons/csv | Y44: 2
A45: 43 | B45: Axel Poniatowski | C45: Voisin | D45: Michel | E45: H | F45: 16351 | G45: Replonges (Ain) | H45: 1 | I45: Ain | J45: 4 | K45: 41080 | L45: 42906 | M45: 1 | N45: LR | O45: Les Républicains | Q45: 20/06/2007 / 19/06/2012 / fin de législature|20/06/2012 / / |01/06/1997 / 18/06/2002 / fin de législature|02/04/1993 / 21/04/1997 / fin de législature|19/06/2002 / 19/06/2007 / fin de législature|13/06/1988 / 01/04/1993 / fin de législature| | R45: Expert-comptable, commissaire aux comptes et expert judiciaire | S45: 28 | T45: http://www2.assemblee-nationale.fr/deputes/fiche/OMC_PA2936 | U45: 2936 | V45: michel-voisin | W45: https://2012-2017.nosdeputes.fr/michel-voisin | X45: https://2012-2017.nosdeputes.fr/michel-voisin/csv | Y45: 2
A46: 44 | B46: Axelle Lemaire | C46: Terrasse | D46: Pascal | E46: H | F46: 23676 | G46: Bagnols-sur-Cèze (Gard) | H46: 7 | I46: Ardèche | J46: 1 | K46: 41080 | L46: 42817 | M46: 1 | N46: SER | O46: Parti socialiste | P46: http://www.pascalterrasse.fr|https://twitter.com/pterrasse| | Q46: 20/06/2007 / 19/06/2012 / fin de législature|01/06/1997 / 18/06/2002 / fin de législature|19/06/2002 / 19/06/2007 / fin de législature|20/06/2012 / 23/03/2017 / démission| | R46: Directeur de maison de retraite | S46: 333 | T46: http://www2.assemblee-nationale.fr/deputes/fiche/OMC_PA2799 | U46: 2799 | V46: pascal-terrasse | W46: https://2012-2017.nosdeputes.fr/pascal-terrasse | X46: https://2012-2017.nosdeputes.fr/pascal-terrasse/csv | Y46: 2 | Z46: pterrasse
A47: 45 | B47: Barbara Pompili | C47: Le Roux | D47: Bruno | E47: H | F47: 23864 | G47: Gennevilliers (Hauts-de-Seine) | H47: 93 | I47: Seine-Saint-Denis | J47: 1 | K47: 42847 | L47: 42906 | M47: 1 | N47: SER | O47: Parti socialiste | P47: http://www.brunoleroux.org|http://www.interieur.gouv.fr|https://twitter.com/BrunoLeRoux| | Q47: 20/06/2007 / 19/06/2012 / fin de législature|01/06/1997 / 18/06/2002 / fin de législature|19/06/2002 / 19/06/2007 / fin de législature|20/06/2012 / 06/01/2017 / nomination comme membre du gouvernement|22/04/2017 / / | | R47: Consultant en gestion et management | S47: 454 | T47: http://www2.assemblee-nationale.fr/deputes/fiche/OMC_PA1886 | U47: 1886 | V47: bruno-le-roux | W47: https://2012-2017.nosdeputes.fr/bruno-le-roux | X47: https://2012-2017.nosdeputes.fr/bruno-le-roux/csv | Y47: 1 | Z47: BrunoLeRoux
A48: 46 | B48: Barbara Romagnan | C48: Le Guen | D48: Jean-Marie | E48: H | F48: 19362 | G48: Paris (Paris) | H48: 75 | I48: Paris | J48: 9 | K48: 41080 | L48: 41768 | M48: 1 | O48: Parti socialiste | P48: http://www.jmlg.fr|http://blog.jmlg.fr|https://twitter.com/jm_leguen| | Q48: 20/06/2007 / 19/06/2012 / fin de législature|01/06/1997 / 18/06/2002 / fin de législature|19/06/2002 / 19/06/2007 / fin de législature|29/07/1988 / 16/12/1992 / démission|20/06/2012 / 09/05/2014 / nomination comme membre du gouvernement| | R48: Médecin | S48: 256 | T48: http://www2.assemblee-nationale.fr/deputes/fiche/OMC_PA1880 | U48: 1880 | V48: jean-marie-le-guen | W48: https://2012-2017.nosdeputes.fr/jean-marie-le-guen | X48: https://2012-2017.nosdeputes.fr/jean-marie-le-guen/csv | Y48: 4 | Z48: jm_leguen
A49: 47 | B49: Béatrice Santais | C49: Mignon | D49: Jean-Claude | E49: H | F49: 18296 | G49: Corbeil-Essonnes (Essonne) | H49: 77 | I49: Seine-et-Marne | J49: 1 | K49: 41080 | L49: 42906 | M49: 1 | N49: LR | O49: Les Républicains | P49: https://twitter.com/JC_Mignon77|http://www.jean-claude-mignon.net| | Q49: 20/06/2007 / 19/06/2012 / fin de législature|20/06/2012 / / |01/06/1997 / 18/06/2002 / fin de législature|02/04/1993 / 21/04/1997 / fin de législature|19/06/2002 / 19/06/2007 / fin de législature|13/06/1988 / 01/04/1993 / fin de législature| | R49: Ancien chef d'entreprise | S49: 27 | T49: http://www2.assemblee-nationale.fr/deputes/fiche/OMC_PA2191 | U49: 2191 | V49: jean-claude-mignon | W49: https://2012-2017.nosdeputes.fr/jean-claude-mignon | X49: https://2012-2017.nosdeputes.fr/jean-claude-mignon/csv | Y49: 2 | Z49: JC_Mignon77
A50: 48 | B50: Benoist Apparu | C50: Rousset | D50: Alain | E50: H | F50: 18675 | G50: Chazelles-sur-Lyon (Loire) | H50: 33 | I50: Gironde | J50: 7 | K50: 41080 | L50: 42906 | M50: 1 | N50: SER | O50: Parti socialiste | P50: http://www.alainrousset.net|http://www.laregion-alpc.fr|https://twitter.com/al_rousset|http://www.nouvelle-aquitaine.fr| | Q50: 20/06/2007 / 19/06/2012 / fin de législature|20/06/2012 / / | | R50: Cadre supérieur du secteur privé | S50: 339 | T50: http://www2.assemblee-nationale.fr/deputes/fiche/OMC_PA331990 | U50: 331990 | V50: alain-rousset | W50: https://2012-2017.nosdeputes.fr/alain-rousset | X50: https://2012-2017.nosdeputes.fr/alain-rousset/csv | Y50: 2 | Z50: al_rousset
A51: 49 | B51: Benoît Hamon | C51: Daubresse | D51: Marc-Philippe | E51: H | F51: 19572 | G51: Lille (Nord) | H51: 59 | I51: Nord | J51: 4 | K51: 41080 | L51: 42906 | M51: 1 | N51: LR | O51: Les Républicains | P51: http://www.mpdaubresse.com|https://twitter.com/DAUBRESSE_MP| | Q51: 20/06/2012 / / |01/06/1997 / 18/06/2002 / fin de législature|02/04/1993 / 21/04/1997 / fin de législature|19/09/2005 / 19/06/2007 / fin de législature|14/12/2010 / 19/06/2012 / fin de législature|03/02/1992 / 01/04/1993 / fin de législature|20/06/2007 / 23/04/2010 / nomination comme membre du gouvernement|19/06/2002 / 30/04/2004 / nomination comme membre du gouvernement| | R51: Ancien directeur d'une société de recrutement | S51: 26 | T51: http://www2.assemblee-nationale.fr/deputes/fiche/OMC_PA1001 | U51: 1001 | V51: marc-philippe-daubresse | W51: https://2012-2017.nosdeputes.fr/marc-philippe-daubresse | X51: https://2012-2017.nosdeputes.fr/marc-philippe-daubresse/csv | Y51: 2 | Z51: DAUBRESSE_MP
A52: 50 | B52: Bérengère Poletti | C52: Ciotti | D52: Éric | E52: H | F52: 24013 | G52: Nice (Alpes-Maritimes) | H52: 6 | I52: Alpes-Maritimes | J52: 1 | K52: 41080 | L52: 42906 | M52: 1 | N52: LR | O52: Les Républicains | P52: http://www.eric-ciotti.fr|http://www.eric-ciotti.com|https://twitter.com/ECiotti| | Q52: 20/06/2007 / 19/06/2012 / fin de législature|20/06/2012 / / | | R52: Sans profession declaree | S52: 196 | T52: http://www2.assemblee-nationale.fr/deputes/fiche/OMC_PA330240 | U52: 330240 | V52: eric-ciotti | W52: https://2012-2017.nosdeputes.fr/eric-ciotti | X52: https://2012-2017.nosdeputes.fr/eric-ciotti/csv | Y52: 2 | Z52: ECiotti
A53: 51 | B53: Bernadette Laclais | C53: Lurel | D53: Victorin | E53: H | F53: 18860 | G53: Vieux-Habitants (Guadeloupe) | H53: 971 | I53: Guadeloupe | J53: 4 | K53: 41762 | L53: 42906 | M53: 1 | N53: SER | O53: Parti socialiste | P53: https://twitter.com/VictorinLurel|http://www.lurel.parti-socialiste.fr| | Q53: 20/06/2012 / 21/07/2012 / nomination comme membre du gouvernement|19/06/2002 / 19/06/2007 / fin de législature|20/06/2007 / 16/06/2012 / nomination comme membre du gouvernement|03/05/2014 / / | | R53: Fonctionnaire retraité | S53: 256 | T53: http://www2.assemblee-nationale.fr/deputes/fiche/OMC_PA268048 | U53: 268048 | V53: victorin-lurel | W53: https://2012-2017.nosdeputes.fr/victorin-lurel | X53: https://2012-2017.nosdeputes.fr/victorin-lurel/csv | Y53: 2 | Z53: VictorinLurel
A54: 52 | B54: Bernard Accoyer | C54: Bataille | D54: Christian | E54: H | F54: 16935 | G54: Rieux-en-Cambrésis (Nord) | H54: 59 | I54: Nord | J54: 12 | K54: 41080 | L54: 42906 | M54: 1 | N54: SER | O54: Parti socialiste | P54: http://christianbataille.typepad.fr| | Q54: 20/06/2007 / 19/06/2012 / fin de législature|20/06/2012 / / |01/06/1997 / 18/06/2002 / fin de législature|02/04/1993 / 21/04/1997 / fin de législature|19/06/2002 / 19/06/2007 / fin de législature|13/06/1988 / 01/04/1993 / fin de législature| | R54: Professeur de lettres | S54: 354 | T54: http://www2.assemblee-nationale.fr/deputes/fiche/OMC_PA394 | U54: 394 | V54: christian-bataille | W54: https://2012-2017.nosdeputes.fr/christian-bataille | X54: https://2012-2017.nosdeputes.fr/christian-bataille/csv | Y54: 2
A55: 53 | B55: Bernard Brochand | C55: Urvoas | D55: Jean-Jacques | E55: H | F55: 21812 | G55: Brest (Finistère) | H55: 29 | I55: Finistère | J55: 1 | K55: 41080 | L55: 42427 | M55: 1 | O55: Parti socialiste | P55: http://www.urvoas.bzh|http://www.justice.gouv.fr|https://twitter.com/JJUrvoas| | Q55: 20/06/2012 / 27/02/2016 / nomination comme membre du gouvernement|20/06/2007 / 19/06/2012 / fin de législature| | R55: Maître de conférences | S55: 440 | T55: http://www2.assemblee-nationale.fr/deputes/fiche/OMC_PA331594 | U55: 331594 | V55: jean-jacques-urvoas | W55: https://2012-2017.nosdeputes.fr/jean-jacques-urvoas | X55: https://2012-2017.nosdeputes.fr/jean-jacques-urvoas/csv | Y55: 1 | Z55: JJUrvoas
A56: 54 | B56: Bernard Cazeneuve | C56: Rogemont | D56: Marcel | E56: H | F56: 17535 | G56: Coye La Foret (Oise) | H56: 35 | I56: Ille-et-Vilaine | J56: 8 | K56: 41080 | L56: 42906 | M56: 1 | N56: SER | O56: Parti socialiste | P56: http://marcelrogemont.net|https://twitter.com/marcelrogemont| | Q56: 20/06/2007 / 19/06/2012 / fin de législature|20/06/2012 / / |01/06/1997 / 18/06/2002 / fin de législature| | R56: Cadre | S56: 528 | T56: http://www2.assemblee-nationale.fr/deputes/fiche/OMC_PA2603 | U56: 2603 | V56: marcel-rogemont | W56: https://2012-2017.nosdeputes.fr/marcel-rogemont | X56: https://2012-2017.nosdeputes.fr/marcel-rogemont/csv | Y56: 2 | Z56: marcelrogemont
A57: 55 | B57: Bernard Debré | C57: Imbert | D57: Françoise | E57: F | F57: 17426 | G57: Verdun-sur-Garonne (Tarn-et-Garonne) | H57: 31 | I57: Haute-Garonne | J57: 5 | K57: 41080 | L57: 42906 | M57: 1 | N57: SER | O57: Parti socialiste | P57: http://www.francoise-imbert.fr| | Q57: 20/06/2007 / 19/06/2012 / fin de législature|20/06/2012 / / |01/06/1997 / 18/06/2002 / fin de législature|19/06/2002 / 19/06/2007 / fin de législature| | R57: Ancienne chef de cabinet du maire de Colomiers | S57: 532 | T57: http://www2.assemblee-nationale.fr/deputes/fiche/OMC_PA1689 | U57: 1689 | V57: francoise-imbert | W57: https://2012-2017.nosdeputes.fr/francoise-imbert | X57: https://2012-2017.nosdeputes.fr/francoise-imbert/csv | Y57: 1
A58: 56 | B58: Bernard Deflesselles | C58: Fabius | D58: Laurent | E58: H | F58: 17034 | G58: Paris (Paris) | H58: 76 | I58: Seine-Maritime | J58: 4 | K58: 41080 | L58: 41111 | M58: 1 | P58: http://www.laurent-fabius.net| | Q58: 20/06/2012 / 21/07/2012 / nomination comme membre du gouvernement|02/07/1981 / 23/07/1981 / nomination comme membre du gouvernement|01/06/1997 / 27/04/2000 / nomination comme membre du gouvernement|19/06/2002 / 19/06/2007 / fin de législature|06/06/1988 / 01/04/1993 / fin de législature|20/06/2007 / 04/06/2012 / démission|03/04/1978 / 22/05/1981 / fin de législature|02/04/1993 / 21/04/1997 / fin de législature|02/04/1986 / 14/05/1988 / fin de législature| | R58: Ancien Maître des requêtes au Conseil d'Etat | T58: http://www2.assemblee-nationale.fr/deputes/fiche/OMC_PA1268 | U58: 1268 | V58: laurent-fabius | W58: https://2012-2017.nosdeputes.fr/laurent-fabius | X58: https://2012-2017.nosdeputes.fr/laurent-fabius/csv | Y58: 2
A59: 57 | B59: Bernard Gérard | C59: Iborra | D59: Monique | E59: F | F59: 16504 | G59: Maison Carrée (Algérie) | H59: 31 | I59: Haute-Garonne | J59: 6 | K59: 41080 | L59: 42906 | M59: 1 | N59: SER | O59: Non rattaché | P59: http://www.moniqueiborra.net|https://twitter.com/MoniqueIborra| | Q59: 20/06/2007 / 19/06/2012 / fin de législature|20/06/2012 / / | | R59: Retraitée de la Fonction publique | S59: 370 | T59: http://www2.assemblee-nationale.fr/deputes/fiche/OMC_PA331835 | U59: 331835 | V59: monique-iborra | W59: https://2012-2017.nosdeputes.fr/monique-iborra | X59: https://2012-2017.nosdeputes.fr/monique-iborra/csv | Y59: 2 | Z59: MoniqueIborra
A60: 58 | B60: Bernard Lesterlin | C60: Goasguen | D60: Claude | E60: H | F60: 16508 | G60: Toulon (Var) | H60: 75 | I60: Paris | J60: 14 | K60: 41080 | L60: 42906 | M60: 1 | N60: LR | O60: Les Républicains | P60: http://www.claudegoasguen.fr|https://twitter.com/ClaudeGoasguen| | Q60: 20/06/2007 / 19/06/2012 / fin de législature|20/06/2012 / / |01/06/1997 / 18/06/2002 / fin de législature|19/06/2002 / 19/06/2007 / fin de législature|02/05/1993 / 18/06/1995 / nomination comme membre du gouvernement| | R60: Avocat à la Cour d'appel de Paris | S60: 172 | T60: http://www2.assemblee-nationale.fr/deputes/fiche/OMC_PA1498 | U60: 1498 | V60: claude-goasguen | W60: https://2012-2017.nosdeputes.fr/claude-goasguen | X60: https://2012-2017.nosdeputes.fr/claude-goasguen/csv | Y60: 3 | Z60: ClaudeGoasguen
A61: 59 | B61: Bernard Perrut | C61: Fasquelle | D61: Daniel | E61: H | F61: 23027 | G61: Saint-Omer (Pas-de-Calais) | H61: 62 | I61: Pas-de-Calais | J61: 4 | K61: 41080 | L61: 42906 | M61: 1 | N61: LR | O61: Les Républicains | P61: https://twitter.com/DFasquelle|http://www.danielfasquelle.blogspot.com| | Q61: 20/06/2007 / 19/06/2012 / fin de législature|20/06/2012 / / | | R61: Professeur des Universités | S61: 62 | T61: http://www2.assemblee-nationale.fr/deputes/fiche/OMC_PA334149 | U61: 334149 | V61: daniel-fasquelle | W61: https://2012-2017.nosdeputes.fr/daniel-fasquelle | X61: https://2012-2017.nosdeputes.fr/daniel-fasquelle/csv | Y61: 2 | Z61: DFasquelle
A62: 60 | B62: Bernard Reynès | C62: Fort | D62: Marie-Louise | E62: F | F62: 18600 | G62: Villeneuve-La-Guyard (Yonne) | H62: 89 | I62: Yonne | J62: 3 | K62: 41080 | L62: 42906 | M62: 1 | N62: LR | O62: Les Républicains | P62: http://www.marielouisefort.fr| | Q62: 20/06/2007 / 19/06/2012 / fin de législature|20/06/2012 / / | | R62: Sans profession declaree | S62: 87 | T62: http://www2.assemblee-nationale.fr/deputes/fiche/OMC_PA336576 | U62: 336576 | V62: marie-louise-fort | W62: https://2012-2017.nosdeputes.fr/marie-louise-fort | X62: https://2012-2017.nosdeputes.fr/marie-louise-fort/csv | Y62: 2
A63: 61 | B63: Bernard Roman | C63: Fillon | D63: François | E63: H | F63: 19787 | G63: Mans (Sarthe) | H63: 75 | I63: Paris | J63: 2 | K63: 41080 | L63: 42906 | M63: 1 | N63: LR | O63: Les Républicains | P63: http://www.fillon2017.fr|http://www.blog-fillon.com|https://twitter.com/FrancoisFillon| | Q63: 20/06/2012 / / |02/07/1981 / 01/04/1986 / fin de législature|19/06/2002 / 19/07/2002 / nomination comme membre du gouvernement|06/06/1988 / 01/04/1993 / fin de législature|02/04/1993 / 01/05/1993 / nomination comme membre du gouvernement|01/06/1997 / 07/06/2002 / nomination comme membre du gouvernement|20/06/2007 / 19/07/2007 / nomination comme membre du gouvernement|02/04/1986 / 14/05/1988 / fin de législature| | R63: Sans profession declaree | S63: 168 | T63: http://www2.assemblee-nationale.fr/deputes/fiche/OMC_PA1310 | U63: 1310 | V63: francois-fillon | W63: https://2012-2017.nosdeputes.fr/francois-fillon | X63: https://2012-2017.nosdeputes.fr/francois-fillon/csv | Y63: 2 | Z63: FrancoisFillon
A64: 62 | B64: Bertrand Pancher | C64: Benoit | D64: Thierry | E64: H | F64: 24363 | G64: Fougères (Ille-et-Vilaine) | H64: 35 | I64: Ille-et-Vilaine | J64: 6 | K64: 41080 | L64: 42906 | M64: 1 | N64: UDI | O64: Union des Radicaux, Centristes, Indépendants et Démocrates | P64: http://www.thierry-benoit.fr| | Q64: 20/06/2007 / 19/06/2012 / fin de législature|20/06/2012 / / | | R64: Représentant de commerce | S64: 245 | T64: http://www2.assemblee-nationale.fr/deputes/fiche/OMC_PA332228 | U64: 332228 | V64: thierry-benoit | W64: https://2012-2017.nosdeputes.fr/thierry-benoit | X64: https://2012-2017.nosdeputes.fr/thierry-benoit/csv | Y64: 2
A65: 63 | B65: Boinali Said | C65: Dolez | D65: Marc | E65: H | F65: 19288 | G65: Douai (Nord) | H65: 59 | I65: Nord | J65: 17 | K65: 41080 | L65: 42906 | M65: 1 | N65: GDR | O65: Parti communiste Français | P65: http://www.marc-dolez.net| | Q65: 20/06/2007 / 19/06/2012 / fin de législature|20/06/2012 / / |01/06/1997 / 18/06/2002 / fin de législature|19/06/2002 / 19/06/2007 / fin de législature|13/06/1988 / 01/04/1993 / fin de législature| | R65: Maître de conférences | S65: 583 | T65: http://www2.assemblee-nationale.fr/deputes/fiche/OMC_PA1141 | U65: 1141 | V65: marc-dolez | W65: https://2012-2017.nosdeputes.fr/marc-dolez | X65: https://2012-2017.nosdeputes.fr/marc-dolez/csv | Y65: 1
A66: 64 | B66: Brigitte Allain | C66: Vigier | D66: Philippe | E66: H | F66: 21219 | G66: Valence (Drôme) | H66: 28 | I66: Eure-et-Loir | J66: 4 | K66: 41080 | L66: 42906 | M66: 1 | N66: UDI | O66: Association PSLE - Nouveau centre | P66: http://www.philippevigier.com|https://twitter.com/VigierPhilippe| | Q66: 20/06/2007 / 19/06/2012 / fin de législature|20/06/2012 / / | | R66: Biologiste A.I.H.P. | S66: 294 | T66: http://www2.assemblee-nationale.fr/deputes/fiche/OMC_PA331582 | U66: 331582 | V66: philippe-vigier | W66: https://2012-2017.nosdeputes.fr/philippe-vigier | X66: https://2012-2017.nosdeputes.fr/philippe-vigier/csv | Y66: 3 | Z66: VigierPhilippe
A67: 65 | B67: Brigitte Bourguignon | C67: Vidalies | D67: Alain | E67: H | F67: 18704 | G67: Grenade-sur-l'Adour (Landes) | H67: 40 | I67: Landes | J67: 1 | K67: 41760 | L67: 41908 | M67: 1 | Q67: 20/06/2012 / 21/07/2012 / nomination comme membre du gouvernement|01/05/2014 / 26/09/2014 / nomination comme membre du gouvernement|01/06/1997 / 18/06/2002 / fin de législature|19/06/2002 / 19/06/2007 / fin de législature|20/06/2007 / 16/06/2012 / nomination comme membre du gouvernement|13/06/1988 / 01/04/1993 / fin de législature| | R67: Avocat | S67: 335 | T67: http://www2.assemblee-nationale.fr/deputes/fiche/OMC_PA2912 | U67: 2912 | V67: alain-vidalies | W67: https://2012-2017.nosdeputes.fr/alain-vidalies | X67: https://2012-2017.nosdeputes.fr/alain-vidalies/csv | Y67: 1
A68: 66 | B68: Bruno Le Maire | C68: Bouchet | D68: Jean-Claude | E68: H | F68: 20942 | G68: Cavaillon (Vaucluse) | H68: 84 | I68: Vaucluse | J68: 2 | K68: 41080 | L68: 42906 | M68: 1 | N68: LR | O68: Les Républicains | P68: https://twitter.com/JCBOUCHET|http://www.jeanclaudebouchet.fr| | Q68: 20/06/2007 / 19/06/2012 / fin de législature|20/06/2012 / / | | R68: Gérant de société | S68: 24 | T68: http://www2.assemblee-nationale.fr/deputes/fiche/OMC_PA336316 | U68: 336316 | V68: jean-claude-bouchet | W68: https://2012-2017.nosdeputes.fr/jean-claude-bouchet | X68: https://2012-2017.nosdeputes.fr/jean-claude-bouchet/csv | Y68: 2 | Z68: JCBOUCHET
A69: 67 | B69: Bruno Le Roux | C69: Bouillé | D69: Marie-Odile | E69: F | F69: 18549 | G69: Nantes (Loire-Atlantique) | H69: 44 | I69: Loire-Atlantique | J69: 8 | K69: 41080 | L69: 42906 | M69: 1 | N69: SER | O69: Parti socialiste | Q69: 20/06/2007 / 19/06/2012 / fin de législature|20/06/2012 / / | | R69: Sage-femme | S69: 332 | T69: http://www2.assemblee-nationale.fr/deputes/fiche/OMC_PA332843 | U69: 332843 | V69: marie-odile-bouille | W69: https://2012-2017.nosdeputes.fr/marie-odile-bouille | X69: https://2012-2017.nosdeputes.fr/marie-odile-bouille/csv | Y69: 3
A70: 68 | B70: Bruno Nestor Azerot | C70: Gorges | D70: Jean-Pierre | E70: H | F70: 19574 | G70: Gonesse (Val-d'Oise) | H70: 28 | I70: Eure-et-Loir | J70: 1 | K70: 41080 | L70: 42906 | M70: 1 | N70: LR | O70: Non rattaché | P70: http://www.jpgorges.com| | Q70: 20/06/2012 / / |19/06/2002 / 19/06/2007 / fin de législature|20/06/2007 / 29/11/2007 / annulation de l'élection sur décision du conseil constitutionnel|15/09/2008 / 19/06/2012 / fin de législature| | R70: Directeur informatique | S70: 204 | T70: http://www2.assemblee-nationale.fr/deputes/fiche/OMC_PA267151 | U70: 267151 | V70: jean-pierre-gorges | W70: https://2012-2017.nosdeputes.fr/jean-pierre-gorges | X70: https://2012-2017.nosdeputes.fr/jean-pierre-gorges/csv | Y70: 2
A71: 69 | B71: Camille de Rocca Serra | C71: Dussopt | D71: Olivier | E71: H | F71: 28718 | G71: Annonay (Ardèche) | H71: 7 | I71: Ardèche | J71: 2 | K71: 41080 | L71: 42906 | M71: 1 | N71: SER | O71: Parti socialiste | P71: http://www.olivierdussopt.fr|https://twitter.com/olivierdussopt| | Q71: 20/06/2007 / 19/06/2012 / fin de législature|20/06/2012 / / | | R71: Assistant parlementaire | S71: 267 | T71: http://www2.assemblee-nationale.fr/deputes/fiche/OMC_PA330357 | U71: 330357 | V71: olivier-dussopt | W71: https://2012-2017.nosdeputes.fr/olivier-dussopt | X71: https://2012-2017.nosdeputes.fr/olivier-dussopt/csv | Y71: 2 | Z71: olivierdussopt
A72: 70 | B72: Carlos Da Silva | C72: Bonnot | D72: Marcel | E72: H | F72: 16946 | G72: Remondans (Doubs) | H72: 25 | I72: Doubs | J72: 3 | K72: 41080 | L72: 42906 | M72: 1 | N72: LR | O72: Les Républicains | Q72: 20/06/2007 / 19/06/2012 / fin de législature|20/06/2012 / / |19/06/2002 / 19/06/2007 / fin de législature| | R72: Avocat, ancien bâtonnier de l'Ordre | S72: 18 | T72: http://www2.assemblee-nationale.fr/deputes/fiche/OMC_PA267576 | U72: 267576 | V72: marcel-bonnot | W72: https://2012-2017.nosdeputes.fr/marcel-bonnot | X72: https://2012-2017.nosdeputes.fr/marcel-bonnot/csv | Y72: 2
A73: 71 | B73: Carole Delga | C73: Asensi | D73: François | E73: H | F73: 16589 | G73: Santander (Espagne) | H73: 93 | I73: Seine-Saint-Denis | J73: 11 | K73: 41080 | L73: 42906 | M73: 1 | N73: GDR | O73: Forces de gauche | P73: http://www.francoisasensi.com| | Q73: 20/06/2012 / / |02/07/1981 / 01/04/1986 / fin de législature|01/06/1997 / 18/06/2002 / fin de législature|19/06/2002 / 19/06/2007 / fin de législature|01/02/1989 / 01/04/1993 / fin de législature|13/06/1988 / 26/11/1988 / annulation de l'élection sur décision du conseil constitutionnel|20/06/2007 / 19/06/2012 / fin de législature|02/04/1993 / 21/04/1997 / fin de législature|02/04/1986 / 14/05/1988 / fin de législature|27/01/1981 / 22/05/1981 / fin de législature| | R73: Dessinateur industriel | S73: 588 | T73: http://www2.assemblee-nationale.fr/deputes/fiche/OMC_PA295 | U73: 295 | V73: francois-asensi | W73: https://2012-2017.nosdeputes.fr/francois-asensi | X73: https://2012-2017.nosdeputes.fr/francois-asensi/csv | Y73: 2
A74: 72 | B74: Catherine Beaubatie | C74: Santini | D74: André | E74: H | F74: 14904 | G74: Paris (Paris) | H74: 92 | I74: Hauts-de-Seine | J74: 10 | K74: 41080 | L74: 42906 | M74: 1 | N74: UDI | O74: Union des Radicaux, Centristes, Indépendants et Démocrates | P74: http://andresantini.fr|https://twitter.com/ASantini_UDI| | Q74: 20/06/2012 / / |20/06/2007 / 19/07/2007 / nomination comme membre du gouvernement|02/04/1993 / 21/04/1997 / fin de législature|19/06/2002 / 19/06/2007 / fin de législature|01/06/1997 / 05/04/2001 / démission|24/07/2009 / 19/06/2012 / fin de législature|13/06/1988 / 01/04/1993 / fin de législature| | R74: Maître de conférences à l'Université | S74: 220 | T74: http://www2.assemblee-nationale.fr/deputes/fiche/OMC_PA2675 | U74: 2675 | V74: andre-santini | W74: https://2012-2017.nosdeputes.fr/andre-santini | X74: https://2012-2017.nosdeputes.fr/andre-santini/csv | Y74: 2 | Z74: ASantini_UDI
A75: 73 | B75: Catherine Coutelle | C75: Lellouche | D75: Pierre | E75: H | F75: 18751 | G75: Tunis (Tunisie) | H75: 75 | I75: Paris | J75: 1 | K75: 41080 | L75: 42906 | M75: 1 | N75: LR | O75: Les Républicains | P75: http://www.pierre-lellouche.fr|https://twitter.com/LellouchePierre| | Q75: 20/06/2007 / 23/07/2009 / nomination comme membre du gouvernement|20/06/2012 / / |01/06/1997 / 18/06/2002 / fin de législature|02/04/1993 / 21/04/1997 / fin de législature|19/06/2002 / 19/06/2007 / fin de législature|17/06/2012 / 19/06/2012 / fin de législature| | R75: Avocat et universitaire | S75: 21 | T75: http://www2.assemblee-nationale.fr/deputes/fiche/OMC_PA1931 | U75: 1931 | V75: pierre-lellouche | W75: https://2012-2017.nosdeputes.fr/pierre-lellouche | X75: https://2012-2017.nosdeputes.fr/pierre-lellouche/csv | Y75: 2 | Z75: LellouchePierre
A76: 74 | B76: Catherine Lemorton | C76: Morin | D76: Hervé | E76: H | F76: 22510 | G76: Pont-Audemer (Eure) | H76: 27 | I76: Eure | J76: 3 | K76: 41080 | L76: 42571 | M76: 1 | N76: UDI | O76: Association PSLE - Nouveau Centre | P76: http://www.normandie.fr|http://www.hervemorin.fr|http://www.hervemorinudi2014.fr|https://twitter.com/Herve_Morin|http://www.lanormandieconquerante.fr| | Q76: 20/06/2007 / 19/07/2007 / nomination comme membre du gouvernement|19/06/2002 / 19/06/2007 / fin de législature|14/12/2010 / 19/06/2012 / fin de législature|20/06/2012 / 20/07/2016 / démission|30/11/1998 / 18/06/2002 / fin de législature| | R76: Administrateur à l'Assemblée nationale | S76: 304 | T76: http://www2.assemblee-nationale.fr/deputes/fiche/OMC_PA2236 | U76: 2236 | V76: herve-morin | W76: https://2012-2017.nosdeputes.fr/herve-morin | X76: https://2012-2017.nosdeputes.fr/herve-morin/csv | Y76: 4 | Z76: Herve_Morin
A77: 75 | B77: Catherine Pen | C77: Couve | D77: Jean-Michel | E77: H | F77: 14613 | G77: Muy (Var) | H77: 83 | I77: Var | J77: 4 | K77: 41080 | L77: 42906 | M77: 1 | N77: LR | O77: Les Républicains | P77: https://twitter.com/jmcouve|http://www.jean-michel-couve.fr| | Q77: 20/06/2007 / 19/06/2012 / fin de législature|20/06/2012 / / |01/06/1997 / 18/06/2002 / fin de législature|02/04/1993 / 21/04/1997 / fin de législature|19/06/2002 / 19/06/2007 / fin de législature|02/04/1986 / 14/05/1988 / fin de législature|13/06/1988 / 01/04/1993 / fin de législature| | R77: Cardiologue | S77: 171 | T77: http://www2.assemblee-nationale.fr/deputes/fiche/OMC_PA951 | U77: 951 | V77: jean-michel-couve | W77: https://2012-2017.nosdeputes.fr/jean-michel-couve | X77: https://2012-2017.nosdeputes.fr/jean-michel-couve/csv | Y77: 2 | Z77: jmcouve
A78: 76 | B78: Catherine Quéré | C78: Christ | D78: Jean-Louis | E78: H | F78: 18652 | G78: Ribeauvillé (Haut-Rhin) | H78: 68 | I78: Haut-Rhin | J78: 2 | K78: 41080 | L78: 42906 | M78: 1 | N78: LR | O78: Les Républicains | P78: http://www.jlchrist-depute.fr| | Q78: 20/06/2007 / 19/06/2012 / fin de législature|20/06/2012 / / |19/06/2002 / 19/06/2007 / fin de législature| | R78: Chef d'entreprise | S78: 138 | T78: http://www2.assemblee-nationale.fr/deputes/fiche/OMC_PA267358 | U78: 267358 | V78: jean-louis-christ | W78: https://2012-2017.nosdeputes.fr/jean-louis-christ | X78: https://2012-2017.nosdeputes.fr/jean-louis-christ/csv | Y78: 2
A79: 77 | B79: Catherine Troallic | C79: Chanteguet | D79: Jean-Paul | E79: H | F79: 18241 | G79: Blanc (Indre) | H79: 36 | I79: Indre | J79: 1 | K79: 41080 | L79: 42906 | M79: 1 | N79: SER | O79: Parti socialiste | Q79: 20/06/2007 / 19/06/2012 / fin de législature|20/06/2012 / / |01/06/1997 / 18/06/2002 / fin de législature|19/06/2002 / 19/06/2007 / fin de législature|13/06/1988 / 01/04/1993 / fin de législature| | R79: Conseiller économique | S79: 418 | T79: http://www2.assemblee-nationale.fr/deputes/fiche/OMC_PA810 | U79: 810 | V79: jean-paul-chanteguet | W79: https://2012-2017.nosdeputes.fr/jean-paul-chanteguet | X79: https://2012-2017.nosdeputes.fr/jean-paul-chanteguet/csv | Y79: 2
A80: 78 | B80: Catherine Vautrin | C80: Pinville | D80: Martine | E80: F | F80: 21481 | G80: Angoulême (Charente) | H80: 16 | I80: Charente | J80: 1 | K80: 41080 | L80: 42202 | M80: 1 | O80: Parti socialiste | P80: http://www.martine-pinville.fr|https://twitter.com/deputepinville| | Q80: 20/06/2007 / 19/06/2012 / fin de législature|20/06/2012 / 17/07/2015 / nomination comme membre du gouvernement| | R80: Retraitée de la fonction publique | S80: 250 | T80: http://www2.assemblee-nationale.fr/deputes/fiche/OMC_PA330981 | U80: 330981 | V80: martine-pinville | W80: https://2012-2017.nosdeputes.fr/martine-pinville | X80: https://2012-2017.nosdeputes.fr/martine-pinville/csv | Y80: 3 | Z80: deputepinville
A81: 79 | B81: Cécile Duflot | C81: Moyne-Bressand | D81: Alain | E81: H | F81: 16648 | G81: Jallieu (Isère) | H81: 38 | I81: Isère | J81: 6 | K81: 41080 | L81: 42906 | M81: 1 | N81: LR | O81: Les Républicains | P81: http://www.moynebressand.fr|https://twitter.com/moyne_bressand| | Q81: 20/06/2007 / 19/06/2012 / fin de législature|20/06/2012 / / |01/06/1997 / 18/06/2002 / fin de législature|02/04/1993 / 21/04/1997 / fin de législature|19/06/2002 / 19/06/2007 / fin de législature|02/04/1986 / 14/05/1988 / fin de législature|13/06/1988 / 01/04/1993 / fin de législature| | R81: Chef d'entreprise | S81: 173 | T81: http://www2.assemblee-nationale.fr/deputes/fiche/OMC_PA2250 | U81: 2250 | V81: alain-moyne-bressand | W81: https://2012-2017.nosdeputes.fr/alain-moyne-bressand | X81: https://2012-2017.nosdeputes.fr/alain-moyne-bressand/csv | Y81: 2 | Z81: moyne_bressand
A82: 80 | B82: Cécile Untermaier | C82: Maquet | D82: Jacqueline | E82: F | F82: 18031 | G82: Estrée Blanche (Pas-de-Calais) | H82: 62 | I82: Pas-de-Calais | J82: 2 | K82: 41080 | L82: 42906 | M82: 1 | N82: SER | O82: Parti socialiste | P82: http://jacquelinemaquet2012.fr| | Q82: 20/06/2007 / 19/06/2012 / fin de législature|20/06/2012 / / | | R82: Directrice de mission | S82: 511 | T82: http://www2.assemblee-nationale.fr/deputes/fiche/OMC_PA334116 | U82: 334116 | V82: jacqueline-maquet | W82: https://2012-2017.nosdeputes.fr/jacqueline-maquet | X82: https://2012-2017.nosdeputes.fr/jacqueline-maquet/csv | Y82: 2
A83: 81 | B83: Céleste Lett | C83: Zumkeller | D83: Michel | E83: H | F83: 24128 | G83: Belfort (Territoire de Belfort) | H83: 90 | I83: Territoire de Belfort | J83: 2 | K83: 41080 | L83: 42906 | M83: 1 | N83: UDI | O83: Union des Radicaux, Centristes, Indépendants et Démocrates | P83: http://www.michelzumkeller.fr|https://twitter.com/MichelZumkeller| | Q83: 20/06/2007 / 19/06/2012 / fin de législature|20/06/2012 / / |19/06/2002 / 19/06/2007 / fin de législature| | R83: Comptable | S83: 243 | T83: http://www2.assemblee-nationale.fr/deputes/fiche/OMC_PA267330 | U83: 267330 | V83: michel-zumkeller | W83: https://2012-2017.nosdeputes.fr/michel-zumkeller | X83: https://2012-2017.nosdeputes.fr/michel-zumkeller/csv | Y83: 2 | Z83: MichelZumkeller
A84: 82 | B84: Chantal Berthelot | C84: Reynaud | D84: Marie-Line | E84: F | F84: 19922 | G84: Barbezieux (Charente) | H84: 16 | I84: Charente | J84: 2 | K84: 41080 | L84: 42906 | M84: 1 | N84: SER | O84: Parti socialiste | P84: http://www.marie-line-reynaud.com|https://twitter.com/MLReynaud16| | Q84: 20/06/2007 / 19/06/2012 / fin de législature|20/06/2012 / / |01/06/1997 / 18/06/2002 / fin de législature| | R84: Conseillère technique au centre d'information des droits de la femme | S84: 537 | T84: http://www2.assemblee-nationale.fr/deputes/fiche/OMC_PA2549 | U84: 2549 | V84: marie-line-reynaud | W84: https://2012-2017.nosdeputes.fr/marie-line-reynaud | X84: https://2012-2017.nosdeputes.fr/marie-line-reynaud/csv | Y84: 1 | Z84: MLReynaud16
A85: 83 | B85: Chantal Guittet | C85: Martin | D85: Philippe | E85: H | F85: 19685 | G85: La Garenne-Colombes (Hauts-de-Seine) | H85: 32 | I85: Gers | J85: 1 | K85: 41762 | L85: 42906 | M85: 1 | N85: SER | O85: Parti socialiste | Q85: 20/06/2007 / 19/06/2012 / fin de législature|19/06/2002 / 19/06/2007 / fin de législature|03/05/2014 / / |20/06/2012 / 02/08/2013 / nomination comme membre du gouvernement| | R85: Préfet | S85: 503 | T85: http://www2.assemblee-nationale.fr/deputes/fiche/OMC_PA267278 | U85: 267278 | V85: philippe-martin | W85: https://2012-2017.nosdeputes.fr/philippe-martin | X85: https://2012-2017.nosdeputes.fr/philippe-martin/csv | Y85: 2
A86: 84 | B86: Charles de Courson | C86: Lequiller | D86: Pierre | E86: H | F86: 18236 | G86: Londres (Grande Bretagne) | H86: 78 | I86: Yvelines | J86: 4 | K86: 41080 | L86: 42906 | M86: 1 | N86: LR | O86: Les Républicains | Q86: 20/06/2007 / 19/06/2012 / fin de législature|20/06/2012 / / |01/06/1997 / 18/06/2002 / fin de législature|02/04/1993 / 21/04/1997 / fin de législature|19/06/2002 / 19/06/2007 / fin de législature|13/06/1988 / 01/04/1993 / fin de législature| | R86: Cadre de banque | S86: 186 | T86: http://www2.assemblee-nationale.fr/deputes/fiche/OMC_PA1954 | U86: 1954 | V86: pierre-lequiller | W86: https://2012-2017.nosdeputes.fr/pierre-lequiller | X86: https://2012-2017.nosdeputes.fr/pierre-lequiller/csv | Y86: 2
A87: 85 | B87: Charles de La Verpillière | C87: Dord | D87: Dominique | E87: H | F87: 21794 | G87: Chambéry (Savoie) | H87: 73 | I87: Savoie | J87: 1 | K87: 41080 | L87: 42906 | M87: 1 | N87: LR | O87: Les Républicains | P87: http://www.dominique-dord.eu|https://twitter.com/DominiqueDord| | Q87: 20/06/2007 / 19/06/2012 / fin de législature|20/06/2012 / / |01/06/1997 / 18/06/2002 / fin de législature|19/06/2002 / 19/06/2007 / fin de législature| | R87: Sans profession declaree | S87: 188 | T87: http://www2.assemblee-nationale.fr/deputes/fiche/OMC_PA1152 | U87: 1152 | V87: dominique-dord | W87: https://2012-2017.nosdeputes.fr/dominique-dord | X87: https://2012-2017.nosdeputes.fr/dominique-dord/csv | Y87: 2 | Z87: DominiqueDord
A88: 86 | B88: Charles-Ange Ginesy | C88: Le Bris | D88: Gilbert | E88: H | F88: 17960 | G88: Concarneau (Finistère) | H88: 29 | I88: Finistère | J88: 8 | K88: 41080 | L88: 42906 | M88: 1 | N88: SER | O88: Parti socialiste | P88: http://www.gilbertlebris.net|https://twitter.com/gilbertlebris| | Q88: 20/06/2007 / 19/06/2012 / fin de législature|20/06/2012 / / |25/07/1981 / 03/04/1983 / démission|19/06/2002 / 19/06/2007 / fin de législature|29/07/1988 / 01/04/1993 / fin de législature|05/07/1997 / 18/06/2002 / fin de législature| | R88: Commerçant | S88: 510 | T88: http://www2.assemblee-nationale.fr/deputes/fiche/OMC_PA1866 | U88: 1866 | V88: gilbert-le-bris | W88: https://2012-2017.nosdeputes.fr/gilbert-le-bris | X88: https://2012-2017.nosdeputes.fr/gilbert-le-bris/csv | Y88: 1 | Z88: gilbertlebris
A89: 87 | B89: Chaynesse Khirouni | C89: Gérard | D89: Bernard | E89: H | F89: 19600 | G89: Valenciennes (Nord) | H89: 59 | I89: Nord | J89: 9 | K89: 41080 | L89: 42906 | M89: 1 | N89: LR | O89: Les Républicains | P89: https://twitter.com/bgerard59| | Q89: 20/06/2007 / 19/06/2012 / fin de législature|20/06/2012 / / | | R89: Avocat honoraire | S89: 53 | T89: http://www2.assemblee-nationale.fr/deputes/fiche/OMC_PA1459 | U89: 1459 | V89: bernard-gerard | W89: https://2012-2017.nosdeputes.fr/bernard-gerard | X89: https://2012-2017.nosdeputes.fr/bernard-gerard/csv | Y89: 2 | Z89: bgerard59
A90: 88 | B90: Christian Assaf | C90: Pupponi | D90: François | E90: H | F90: 22858 | G90: Nantua (Ain) | H90: 95 | I90: Val-d'Oise | J90: 8 | K90: 41080 | L90: 42906 | M90: 1 | N90: SER | O90: Parti socialiste | P90: https://twitter.com/fpupponi|http://www.francoispupponi.fr| | Q90: 20/06/2012 / / |16/12/2007 / 19/06/2012 / fin de législature| | R90: Administrateur des Finances publiques adjoint | S90: 444 | T90: http://www2.assemblee-nationale.fr/deputes/fiche/OMC_PA405480 | U90: 405480 | V90: francois-pupponi | W90: https://2012-2017.nosdeputes.fr/francois-pupponi | X90: https://2012-2017.nosdeputes.fr/francois-pupponi/csv | Y90: 2 | Z90: fpupponi
A91: 89 | B91: Christian Bataille | C91: Reitzer | D91: Jean-Luc | E91: H | F91: 18991 | G91: Altkirch (Haut-Rhin) | H91: 68 | I91: Haut-Rhin | J91: 3 | K91: 41080 | L91: 42906 | M91: 1 | N91: LR | O91: Les Républicains | Q91: 20/06/2007 / 19/06/2012 / fin de législature|20/06/2012 / / |01/06/1997 / 18/06/2002 / fin de législature|02/04/1993 / 21/04/1997 / fin de législature|19/06/2002 / 19/06/2007 / fin de législature|06/06/1988 / 01/04/1993 / fin de législature| | R91: Cadre d'entreprise chargé des relations sociales | S91: 162 | T91: http://www2.assemblee-nationale.fr/deputes/fiche/OMC_PA2529 | U91: 2529 | V91: jean-luc-reitzer | W91: https://2012-2017.nosdeputes.fr/jean-luc-reitzer | X91: https://2012-2017.nosdeputes.fr/jean-luc-reitzer/csv | Y91: 2
A92: 90 | B92: Christian Eckert | C92: Herbillon | D92: Michel | E92: H | F92: 18693 | G92: Saint-Mandé (Val-de-Marne) | H92: 94 | I92: Val-de-Marne | J92: 8 | K92: 41080 | L92: 42906 | M92: 1 | N92: LR | O92: Les Républicains | P92: http://www.maisons-alfort.fr| | Q92: 20/06/2007 / 19/06/2012 / fin de législature|20/06/2012 / / |01/06/1997 / 18/06/2002 / fin de législature|19/06/2002 / 19/06/2007 / fin de législature| | R92: Cadre supérieur | S92: 185 | T92: http://www2.assemblee-nationale.fr/deputes/fiche/OMC_PA1630 | U92: 1630 | V92: michel-herbillon | W92: https://2012-2017.nosdeputes.fr/michel-herbillon | X92: https://2012-2017.nosdeputes.fr/michel-herbillon/csv | Y92: 2
A93: 91 | B93: Christian Estrosi | C93: Houillon | D93: Philippe | E93: H | F93: 18977 | G93: Bagnolet (Seine-Saint-Denis) | H93: 95 | I93: Val-d'Oise | J93: 1 | K93: 41080 | L93: 42906 | M93: 1 | N93: LR | O93: Les Républicains | P93: https://twitter.com/PHouillon| | Q93: 20/06/2007 / 19/06/2012 / fin de législature|20/06/2012 / / |01/06/1997 / 18/06/2002 / fin de législature|02/04/1993 / 21/04/1997 / fin de législature|19/06/2002 / 19/06/2007 / fin de législature| | R93: Avocat, ancien Bâtonnier de l'Ordre | S93: 184 | T93: http://www2.assemblee-nationale.fr/deputes/fiche/OMC_PA1661 | U93: 1661 | V93: philippe-houillon | W93: https://2012-2017.nosdeputes.fr/philippe-houillon | X93: https://2012-2017.nosdeputes.fr/philippe-houillon/csv | Y93: 2 | Z93: PHouillon
A94: 92 | B94: Christian Franqueville | C94: Claeys | D94: Alain | E94: H | F94: 17770 | G94: Poitiers (Vienne) | H94: 86 | I94: Vienne | J94: 1 | K94: 41080 | L94: 42906 | M94: 1 | N94: SER | O94: Parti socialiste | Q94: 20/06/2007 / 19/06/2012 / fin de législature|20/06/2012 / / |01/06/1997 / 18/06/2002 / fin de législature|19/06/2002 / 19/06/2007 / fin de législature| | R94: Enseignant | S94: 346 | T94: http://www2.assemblee-nationale.fr/deputes/fiche/OMC_PA872 | U94: 872 | V94: alain-claeys | W94: https://2012-2017.nosdeputes.fr/alain-claeys | X94: https://2012-2017.nosdeputes.fr/alain-claeys/csv | Y94: 2
A95: 93 | B95: Christian Hutin | C95: Rochebloine | D95: François | E95: H | F95: 16741 | G95: Saint-Chamond (Loire) | H95: 42 | I95: Loire | J95: 3 | K95: 41080 | L95: 42906 | M95: 1 | N95: UDI | O95: Union des Radicaux, Centristes, Indépendants et Démocrates | P95: http://www.francois-rochebloine.com| | Q95: 20/06/2007 / 19/06/2012 / fin de législature|20/06/2012 / / |01/06/1997 / 18/06/2002 / fin de législature|02/04/1993 / 21/04/1997 / fin de législature|19/06/2002 / 19/06/2007 / fin de législature|13/06/1988 / 01/04/1993 / fin de législature| | R95: Directeur commercial | S95: 201 | T95: http://www2.assemblee-nationale.fr/deputes/fiche/OMC_PA2597 | U95: 2597 | V95: francois-rochebloine | W95: https://2012-2017.nosdeputes.fr/francois-rochebloine | X95: https://2012-2017.nosdeputes.fr/francois-rochebloine/csv | Y95: 1
A96: 94 | B96: Christian Jacob | C96: Dumont | D96: Jean-Louis | E96: H | F96: 16168 | G96: Jonville (Meuse) | H96: 55 | I96: Meuse | J96: 2 | K96: 41080 | L96: 42906 | M96: 1 | N96: SER | O96: Parti socialiste | P96: http://www.jeanlouisdumont.com| | Q96: 20/06/2007 / 19/06/2012 / fin de législature|20/06/2012 / / |02/07/1981 / 01/04/1986 / fin de législature|01/06/1997 / 18/06/2002 / fin de législature|19/06/2002 / 19/06/2007 / fin de législature|02/04/1986 / 14/05/1988 / fin de législature|13/06/1988 / 01/04/1993 / fin de législature| | R96: Enseignant | S96: 506 | T96: http://www2.assemblee-nationale.fr/deputes/fiche/OMC_PA1199 | U96: 1199 | V96: jean-louis-dumont | W96: https://2012-2017.nosdeputes.fr/jean-louis-dumont | X96: https://2012-2017.nosdeputes.fr/jean-louis-dumont/csv | Y96: 2
A97: 95 | B97: Christian Kert | C97: Martin-Lalande | D97: Patrice | E97: H | F97: 17503 | G97: Grenoble (Isère) | H97: 41 | I97: Loir-et-Cher | J97: 2 | K97: 41080 | L97: 42906 | M97: 1 | N97: LR | O97: Les Républicains | P97: https://twitter.com/deputepml|http://patricemartinlalande.net| | Q97: 20/06/2007 / 19/06/2012 / fin de législature|20/06/2012 / / |01/06/1997 / 18/06/2002 / fin de législature|02/04/1993 / 21/04/1997 / fin de législature|19/06/2002 / 19/06/2007 / fin de législature| | R97: Cadre administratif | S97: 125 | T97: http://www2.assemblee-nationale.fr/deputes/fiche/OMC_PA2099 | U97: 2099 | V97: patrice-martin-lalande | W97: https://2012-2017.nosdeputes.fr/patrice-martin-lalande | X97: https://2012-2017.nosdeputes.fr/patrice-martin-lalande/csv | Y97: 2 | Z97: deputepml
A98: 96 | B98: Christian Paul | C98: Perrut | D98: Bernard | E98: H | F98: 20844 | G98: Villefranche-sur-Saône (Rhône) | H98: 69 | I98: Rhône | J98: 9 | K98: 41080 | L98: 42906 | M98: 1 | N98: LR | O98: Les Républicains | P98: http://www.bperrut.fr|http://www.bernardperrut.com|https://twitter.com/B_Perrut| | Q98: 20/06/2007 / 19/06/2012 / fin de législature|20/06/2012 / / |01/06/1997 / 18/06/2002 / fin de législature|19/06/2002 / 19/06/2007 / fin de législature| | R98: Avocat | S98: 203 | T98: http://www2.assemblee-nationale.fr/deputes/fiche/OMC_PA2377 | U98: 2377 | V98: bernard-perrut | W98: https://2012-2017.nosdeputes.fr/bernard-perrut | X98: https://2012-2017.nosdeputes.fr/bernard-perrut/csv | Y98: 2 | Z98: B_Perrut
A99: 97 | B99: Christine Pires Beaune | C99: Courtial | D99: Édouard | E99: H | F99: 26843 | G99: Neuilly-sur-Seine (Hauts-de-Seine) | H99: 60 | I99: Oise | J99: 7 | K99: 41080 | L99: 42906 | M99: 1 | N99: LR | O99: Les Républicains | P99: http://www.edouard-courtial.fr|https://twitter.com/EdouardCourtial|http://www.facebook.com/edouardcourtialdepute| | Q99: 20/06/2012 / / |19/06/2002 / 19/06/2007 / fin de législature|17/06/2012 / 19/06/2012 / fin de législature|20/06/2007 / 28/10/2011 / nomination comme membre du gouvernement| | R99: Consultant | S99: 41 | T99: http://www2.assemblee-nationale.fr/deputes/fiche/OMC_PA267743 | U99: 267743 | V99: edouard-courtial | W99: https://2012-2017.nosdeputes.fr/edouard-courtial | X99: https://2012-2017.nosdeputes.fr/edouard-courtial/csv | Y99: 2 | Z99: EdouardCourtial
A100: 98 | B100: Christophe Borgel | C100: Fenech | D100: Georges | E100: H | F100: 20023 | G100: Sousse (Tunisie) | H100: 69 | I100: Rhône | J100: 11 | K100: 41080 | L100: 42906 | M100: 1 | N100: LR | O100: Les Républicains | P100: http://www.georgesfenech.fr|http://www.georgesfenech2017.com|https://twitter.com/GeorgesFENECH| | Q100: 20/06/2012 / / |19/06/2002 / 19/06/2007 / fin de législature|20/06/2007 / 27/03/2008 / démission d'office sur décision du conseil constitutionnel| | R100: Magistrat | S100: 141 | T100: http://www2.assemblee-nationale.fr/deputes/fiche/OMC_PA267591 | U100: 267591 | V100: georges-fenech | W100: https://2012-2017.nosdeputes.fr/georges-fenech | X100: https://2012-2017.nosdeputes.fr/georges-fenech/csv | Y100: 3 | Z100: GeorgesFENECH
...

Sheet donnees_L14_PS_1an_amendements_
A1: legislature | B1: id_loi | C1: etape_discussion | D1: id_amendement | E1: date_amendement | H1: tri_date | I1: etape_texte | J1: action_amendement | K1: resume_amendement | L1: url_pdf | M1: statut_amendement | N1: auteur | O1: groupe_politique | P1: statut_auteur | Q1: co-signataires
A2: 14 | B2: PRJLANR5L14B0071 | C2: 1ère lecture (1ère assemblée saisie) | D2: AMANR5L14SEA644420B0071P0D1N407 | E2: 2012-07-12T00:00:00Z | F2: =LEFT(E2,4) -> 2012 | G2: =RIGHT(LEFT(E2,7),2) -> 07 | H2: =F2&G2 -> 201207 | I2: Article 27 | J2: Après le mot : « est », la fin de la première phrase du neuvième alinéa du V de l'article 43 de la loi n° 99‑1172 du 30 décembre 1999 de finances pour 2000 est ainsi rédigée : « , pour le laboratoire de Bure en Meuse, réparti en deux parts entre les départements de la Meuse et de la Haute‑Marne, à raison de 60 % pour la Meuse et 40 % pour la Haute‑Marne, et ce, à compter du 1er janvier 2013 ». | K2: L’objectif du présent amendement est de proposer une nouvelle répartition entre les départements de la Meuse et de la Haute-Marne. Le laboratoire de Bure est situé sur le département de la Meuse et une infime partie dans un rayon de 10 km déborde en Haute-Marne. Aussi, la Meuse accueille l’ensemble des installations dédiées au laboratoire et devra recevoir le site de stockage réversible en couches géologiques profondes des déchets nucléaires (Centre industriel de stockage géologique pour les déchets Haute Activité et Moyenne Activité à Vie Longue- CIGEO). Si le projet d’une zone interdépartementale d’activité économique est prévue, mais toujours pas réalisée, par les deux Conseils généraux, il est donc indispensable d’appliquer dès maintenant la répartition des ressources fiscales liées au laboratoire et au futur centre de stockage à partir de l’accord acté par le Comité de Haut Niveau, soit 60 % pour la Meuse et 40 % pour la Haute-Marne, et ce, en tenant compte du calendrier CIGEO. Aujourd’hui les deux départements reçoivent chacun 30 millions d’euros, sur les 60 millions annuels versés pour les années 2010, 2011 et 2012. | L2: /14/amendements/0071/AN/407.pdf | M2: Discuté | N2: Jean-Louis Dumont | O2: SER | P2: Depute | Q2: Jean-Louis Dumont
A3: 14 | B3: PRJLANR5L14B0071 | C3: 1ère lecture (1ère assemblée saisie) | D3: AMANR5L14SEA644420B0071P0D1N405 | E3: 2012-07-12T00:00:00Z | F3: =LEFT(E3,4) -> 2012 | G3: =RIGHT(LEFT(E3,7),2) -> 07 | H3: =F3&G3 -> 201207 | I3: Article 27 | J3: Le V de l’article 43 de la loi n° 99‑1172 du 30 décembre 1999 de finances pour 2000 est ainsi modifié : 1° Le début du cinquième alinéa est ainsi rédigé : « À compter du 1er janvier 2014 et pour la durée d’exploitation de l’installation, les valeurs...(le reste sans changement) » ; 2° Le tableau du sixième alinéa est ainsi modifié : a) À la troisième ligne de la deuxième colonne, le nombre : « 5,27 » est remplacé par le nombre : « 6,5 » ; b) À la troisième ligne de la troisième colonne, le nombre : « 1,73 » est remplacé par le nombre : « 2 » ; c) À la troisième ligne de la quatrième colonne, le nombre : « 0,87 » est remplacé par le nombre : « 1 » ; d) À la quatrième ligne de la deuxième colonne, le nombre : « 6,08 » est remplacé par le nombre : « 6,5 » ; e) À la cinquième ligne de la deuxième colonne, le nombre : « 6,08 » est remplacé par le nombre : « 6,5 » ; f) À la sixième ligne de la deuxième colonne, le nombre : « 5,32 » est remplacé par le nombre : « 6,5 » ; g) À la sixième ligne de la troisième colonne, le nombre : « 1,75 » est remplacé par le nombre : « 2 » ; h) À la sixième ligne de la quatrième colonne, le nombre : « 0,88 » est remplacé par le nombre : « 1 ». | K3: L’objectif du présent amendement est d’augmenter le montant des taxes additionnelles alimentant la redevance liée au laboratoire de Bure en Meuse et d’augmenter à due concurrence le versement, actuellement de 30 millions d’euros. | L3: /14/amendements/0071/AN/405.pdf | M3: Discuté | N3: Jean-Louis Dumont | O3: SER | P3: Depute | Q3: Jean-Louis Dumont
A4: 14 | B4: PRJLANR5L14B0071 | C4: 1ère lecture (1ère assemblée saisie) | D4: AMANR5L14SEA644420B0071P0D1N413 | E4: 2012-07-12T00:00:00Z | F4: =LEFT(E4,4) -> 2012 | G4: =RIGHT(LEFT(E4,7),2) -> 07 | H4: =F4&G4 -> 201207 | I4: Article 27 | J4: Le début du cinquième alinéa du V de l'article 43 de la loi n° 99–1172 du 30 décembre 1999 de finances pour 2000 est ainsi rédigé : « À compter du 1er janvier 2013, les valeurs...(le reste sans changement) ». | K4: L’objectif du présent amendement est de prolonger la redevance ANDRA liée au versement des taxes additionnelles dues par l’exploitant des installations du laboratoire de Bure en Meuse pour l’année 2013 et suivantes, autant d’années que le laboratoire sera en exploitation. | L4: /14/amendements/0071/AN/413.pdf | M4: Discuté | N4: Jean-Louis Dumont | O4: SER | P4: Depute | Q4: Jean-Louis Dumont
A5: 14 | B5: PRJLANR5L14B0071 | C5: 1ère lecture (1ère assemblée saisie) | D5: AMANR5L14SEA644420B0071P0D1N179 | E5: 2012-07-12T00:00:00Z | F5: =LEFT(E5,4) -> 2012 | G5: =RIGHT(LEFT(E5,7),2) -> 07 | H5: =F5&G5 -> 201207 | I5: Article 4 | J5: Après la référence : « 784, », rédiger ainsi la fin de l'alinéa 7 « les mots : « de celles passées depuis plus de dix ans » sont remplacés par les mots : « d’une seule donation antérieure et, le cas échéant, d’une donation de l’immeuble constituant au jour de la donation la résidence principale du donateur ». ». | K5: Les ménages ayant la possibilité de léguer à leurs enfants plus d'une fois dans la vie 100 000 euros sont extrêmement peu nombreux. En effet le patrimoine médian en France se situe à 150 200 euros. Les 10 % les mieux dotés ont au moins 552 300 euros de patrimoine brut et détiennent près de la moitié de la masse totale de celui-ci. Enfin, les 1 % des ménages les plus riches en termes de patrimoine détiennent chacun plus de 1,9 million d'euros d'avoirs. Cet abattement fiscal concerne donc une infime minorité de ménages déjà privilégiés. Les dispositions actuellement contenues dans le code général des impôts et modifiées par la loi de finances rectificative permettront de verser, tous les 15 ans, 100 000 euros par personne et par enfant exonéré d'impôts, ce qui permet par exemple à des parents avec deux enfants de verser 400 000 euros tous les 15 ans. Cette somme est particulièrement importante au regard de l'imposition à laquelle sont soumis les revenus. Cet amendement vise à rompre avec la République des héritiers, en privilégiant les revenus dégagés par les innovateurs et les créateurs d'emploi par rapport au patrimoine qui aboutit a une reproduction et un renforcement des inégalités entre les citoyens, encore plus rapide ces dernières années. Les inégalités de patrimoine ont en effet augmenté de 30 % entre 2004 et 2010 et sont 50 fois plus fortes que les inégalités de revenu. La fonction redistributive de l'impôt doit donc pleinement jouer son rôle qui a été négligé ces 20 dernières années. | L5: /14/amendements/0071/AN/179.pdf | M5: Irrecevable | N5: Razzy Hammadi | O5: SER | P5: Depute | Q5: Razzy Hammadi
A6: 14 | B6: PRJLANR5L14B0071 | C6: 1ère lecture (1ère assemblée saisie) | D6: AMANR5L14SEA644420B0071P0D1N395 | E6: 2012-07-12T00:00:00Z | F6: =LEFT(E6,4) -> 2012 | G6: =RIGHT(LEFT(E6,7),2) -> 07 | H6: =F6&G6 -> 201207 | I6: Article 6 | J6: Après l'alinéa 1, insérer l'alinéa suivant : « 1° A À la première phrase du premier alinéa du I, les mots : « un milliard » sont remplacés par les mots : « cent-cinquante millions ». | K6: Amendement d'élargissement du seuil de capitalisation boursière à partir duquel les entreprises sont soumises à la taxe sur les transactions financières. | L6: /14/amendements/0071/AN/395.pdf | M6: Discuté | N6: Laurent Grandguillaume | O6: SER | P6: Depute | Q6: Laurent Grandguillaume
A7: 14 | B7: PRJLANR5L14B0071 | C7: 1ère lecture (1ère assemblée saisie) | D7: AMANR5L14SEA644420B0071P0D1N410 | E7: 2012-07-12T00:00:00Z | F7: =LEFT(E7,4) -> 2012 | G7: =RIGHT(LEFT(E7,7),2) -> 07 | H7: =F7&G7 -> 201207 | I7: de finances rectificative pour 2012 | J7: I-Après l’article 43, alinéa 4 du V, LoiLoi n°99-1172 du 30 décembre 1999, modifié par la Loi n° 2011-1977 du 28 décembre 2011-art.46 (V), est ainsi rédigé « A compter du 1er janvier 2014 et pour la durée d’exploitation de l’installation, les valeurs des coefficients s’appliquant aux catégories d’installations visées dans le tableau précédent sont fixées comme suit : » II- A la 3ème ligne de la 2ème colonne du tableau du paragraphe 4, substituer au nombre : « 5,27 » le nombre : « 6,5 ». A la 3ème ligne de la 3ème colonne du tableau du paragraphe 4, substituer au nombre : « 1,73 » le nombre : « 2 ». A la 3ème ligne de la 4ème colonne du tableau du paragraphe 4, substituer au nombre : « 0,87 » le nombre : « 1 ». A la 4ème ligne de la 2ème colonne du tableau du paragraphe 4, substituer au nombre : « 6,08 » le nombre : « 6,5 ». A la 5ème ligne de la 2ème colonne du tableau du paragraphe 4, substituer au nombre : « 6,08 » le nombre : « 6,5 ». A la 6ème ligne de la 2ème colonne du tableau du paragraphe 4, substituer au nombre : « 5,32 » le nombre : « 6,5 ». A la 6ème ligne de la 3ème colonne du tableau du paragraphe 4, substituer au nombre : « 1,75 » le nombre : « 2 ». A la 6ème ligne de la 4ème colonne du tableau du paragraphe 4, substituer au nombre : « 0,88 » le nombre : « 1 ». | K7: L’objectif du présent amendement est d’augmenter le montant des taxes additionnelles alimentant la redevance liée au laboratoire de Bure en Meuse et d’augmenter à due concurrence le versement, actuellement de 30 millions d’euros. | L7: /14/amendements/0071/AN/410.pdf | M7: Retiré | N7: Jean-Louis Dumont | O7: SER | P7: Depute | Q7: Jean-Louis Dumont
A8: 14 | B8: PRJLANR5L14B0235 | C8: 1ère lecture (1ère assemblée saisie) | D8: AMANR5L14SEA644420B0235P2D1N521 | E8: 2012-11-09T00:00:00Z | F8: =LEFT(E8,4) -> 2012 | G8: =RIGHT(LEFT(E8,7),2) -> 11 | H8: =F8&G8 -> 201211 | I8: Article 68 | J8: Après l’alinéa 2, insérer l’alinéa suivant : « 1° bis Au 5° et à la première phrase de l'avant‑dernier alinéa du I, après la référence : « 3° », est insérée la référence : « du I » ; ». | K8: Amendement de coordination. | L8: /14/amendements/0235C/AN/521.pdf | M8: Discuté | N8: Pascal Terrasse | O8: SER | P8: Depute | Q8: Pascal Terrasse
A9: 14 | B9: PRJLANR5L14B0235 | C9: 1ère lecture (1ère assemblée saisie) | D9: AMANR5L14SEA644420B0235P2D1N519 | E9: 2012-11-09T00:00:00Z | F9: =LEFT(E9,4) -> 2012 | G9: =RIGHT(LEFT(E9,7),2) -> 11 | H9: =F9&G9 -> 201211 | I9: Article 67 | J9: Après l’alinéa 80, insérer les trois alinéas suivants : « 20° Aux a) et b) du 2° du I. de l’article L. 5217‑13, après la référence : « 3° », est insérée, par deux fois, la référence : « du I ». « I bis. – 1° À l’article L. 133‑11 du code du tourisme, la référence : « huitième alinéa du 4° » est remplacée par la référence : « deuxième alinéa du II » ; « 2° Le II de l’article 20 de la loi n° 2006‑436 du 14 avril 2006 relative aux parcs nationaux, aux parcs naturels marins et aux parcs naturels régionaux est abrogé ; ». | K9: Amendement de coordination. | L9: /14/amendements/0235C/AN/519.pdf | M9: Discuté | N9: Pascal Terrasse | O9: SER | P9: Depute | Q9: Pascal Terrasse
A10: 14 | B10: PRJLANR5L14B0235 | C10: 1ère lecture (1ère assemblée saisie) | D10: AMANR5L14SEA644420B0235P2D1N705 | E10: 2012-11-12T00:00:00Z | F10: =LEFT(E10,4) -> 2012 | G10: =RIGHT(LEFT(E10,7),2) -> 11 | H10: =F10&G10 -> 201211 | I10: Article 59 | J10: Le a bis de l’article L. 135 B du livre des procédures fiscales, est complété par une phrase ainsi rédigée : « Pour un produit local intégrant le risque de caisse, ces montants sont ventilés par date et type d’encaissement ; » | K10: L’article 100 de la loi de finances pour 2012 a sécurisé l’accès des collectivités locales au détail des données sur la CVAE, basées sur les déclarations des contribuables. Contrairement aux produits CVAE versés en 2011 aux collectivités locales qui correspondaient aux montants déclarés pour un millésime de valeur ajoutée, les produits 2012 correspondent aux montants versés l’année précédente. Les collectivités locales sont ainsi exposées aux risques de caisse. Cet amendement vise ainsi à compléter les informations restituées sur la CVAE pour permettre d’identifier cet écart avec les montants déclarés. Il importe en effet de pouvoir distinguer dans cet écart ce qui relève des ajustements effectués par l’entreprise elle-même (ajustement légal lors du versement des acomptes, en fonction de ses anticipations de réalisation de chiffre d’affaires et valeur ajoutée à clôture de l’exercice, rattrapage sur millésime antérieur et pénalités), de ce qui relève des activités de redressements. | L10: /14/amendements/0235C/AN/705.pdf | M10: Discuté | N10: Alain Rousset | O10: SER | P10: Depute | Q10: Alain Rousset
A11: 14 | B11: PRJLANR5L14B0235 | C11: 1ère lecture (1ère assemblée saisie) | D11: AMANR5L14SEA644420B0235P2D1N411 | E11: 2012-11-08T00:00:00Z | F11: =LEFT(E11,4) -> 2012 | G11: =RIGHT(LEFT(E11,7),2) -> 11 | H11: =F11&G11 -> 201211 | I11: Article 66 | J11: À l’alinéa 4, substituer aux mots : « 3 CIF », les mots : « la Caisse Centrale du Crédit Immobilier de France ». | K11: Amendement de précision. | L11: /14/amendements/0235C/AN/411.pdf | M11: Discuté | N11: Dominique Lefebvre | O11: SER | P11: Depute | Q11: Dominique Lefebvre
A12: 14 | B12: PRJLANR5L14B0235 | C12: 1ère lecture (1ère assemblée saisie) | D12: AMANR5L14SEA644420B0235P2D1N687 | E12: 2012-11-12T00:00:00Z | F12: =LEFT(E12,4) -> 2012 | G12: =RIGHT(LEFT(E12,7),2) -> 11 | H12: =F12&G12 -> 201211 | I12: Article 59 | J12: Les articles L. 2332‑2, L. 3332‑1‑1 et L. 4331‑2‑1 du code général des collectivités territoriales sont ainsi modifiés : 1° Au début du premier alinéa, est insérée la référence : « I » ; 2° Après l’avant-dernier alinéa, il est inséré un alinéa ainsi rédigé : « II. – Pour les impôts non recouvrés par voie de rôle et encaissés par l’État l’année précédente, l’attribution s’effectue en début d’année, avant le 31 janvier suivant le produit notifié provisoire et avant le 31 mars pour l’ajustement correspondant au produit notifié définitif. » ; 3° Au début du dernier alinéa, est insérée la référence : « III ». | K12: Le présent amendement vise à ajuster le versement du produit de CVAE aux collectivités locales, en tenant compte de la réalité d’encaissement par l’État auprès des entreprises. Le versement aux collectivités locales a été calé sur le système des douzièmes qui prévaut en fiscalité directe locale. Or, taxe d’habitation et taxes foncières sont des impôts sur rôle recouvrés en fin d’année par l’État, le versement par douzièmes aux collectivités correspond donc pour partie à des avances. La CVAE est un impôt auto-liquidé, le produit versé aux collectivités locales correspond aux encaissements perçus par l’État l’année précédente (début mai, 15 juin et 15 septembre). Par conséquent, le produit CVAE doit être versé sans délai, en début d’année ; sur la part du produit payé par les entreprises (3/4 du produit CVAE local), l’État bénéficie en effet de la trésorerie l’année précédente, lui permettant de verser la part du produit correspondant aux dégrèvements (1/4 du produit CVAE local) également dès le début d’année suivante. | L12: /14/amendements/0235C/AN/687.pdf | M12: Discuté | N12: Alain Rousset | O12: SER | P12: Depute | Q12: Alain Rousset
A13: 14 | B13: PRJLANR5L14B0235 | C13: 1ère lecture (1ère assemblée saisie) | D13: AMANR5L14SEA644420B0235P2D1N673 | E13: 2012-11-12T00:00:00Z | F13: =LEFT(E13,4) -> 2012 | G13: =RIGHT(LEFT(E13,7),2) -> 11 | H13: =F13&G13 -> 201211 | I13: Article 64 | J13: Après le mot : « communes », rédiger ainsi la fin de l'alinéa 7 : « faisant l’objet d’un arrêté de carence mentionné au L. 302-9-1 du code de la construction et de l’habitation, la taxe est instaurée de plein droit, ce pour la durée de l’arrêté de carence. » | K13: Afin de diminuer la tension locative sur le parc de logements privés, l’objet de cet amendement est de permettre une meilleure mobilisation des logements vacants, en renforçant le dispositif de majoration de la taxe d’habitation qui leur est applicable : les logements visés sont les logements vacants depuis deux ans au moins, soit une diminution de 3 ans de la durée de latence. Cette taxe est constituée comme une taxe d’habitation sur les logements vacants et donc avec les taux de la taxe d’habitation, limitant les questions d’optimisation fiscale, il est préférable que le taux reste celui de la taxe d’habitation. | L13: /14/amendements/0235C/AN/673.pdf | M13: Discuté | N13: Daniel Goldberg | O13: SER | P13: Depute | Q13: Daniel Goldberg
... A21: 14 | B21: PRJLANR5L14B0235 | C21: 1ère lecture (1ère assemblée saisie) | D21: AMANR5L14SEA644420B0235P2D1N177 | E21: 2012-10-31T00:00:00Z | F21: =LEFT(E21,4) -> 2012 | G21: =RIGHT(LEFT(E21,7),2) -> 10 | H21: =F21&G21 -> 201210 | I21: Article 62 | J21: Le Gouvernement remet au Parlement, au plus tard le 1er juin 2013, un rapport sur la situation des conjoints survivants des plus grands invalides de guerre, dont l’indice de pension était supérieur ou égal à 2 000 points. Le rapport précise les pistes envisagées pour augmenter le niveau des pensions des conjoints survivants en proportion des pensions versées aux plus grands invalides de guerre, y compris au moyen d’un prélèvement sur ces pensions. | K21: Les conjoints survivants de très grands invalides se trouvent fréquemment démunis lors du décès de l’ouvrant-droit, alors que le conjoint doit faire face seul aux frais du ménage et aux difficultés causées par le décès de l’invalide. Il existe en effet une disproportion considérable entre la pension que percevait l’invalide et celle qui est versée au conjoint survivant, 500 points au taux normal pour un soldat en application de l’article L. 50 du code des pensions militaires d’invalidité et des victimes de la guerre, majorée forfaitairement de 15 points depuis 2004. Cette disproportion est d’autant plus choquante que, dans presque tous les cas, le conjoint survivant a apporté ses soins à l’invalide, permettant souvent d’éviter une hospitalisation qui aurait été onéreuse pour la collectivité. Les lois de finances pour 2011 et 2011 avaient corrigé à la marge ce système en octroyant un complément de pension de 360 points aux veuves d’invalides bénéficiant de pensions de plus de 11 000 points. Il est temps d’aller plus loin et de mettre en place un dispositif complet, qui prenne en considération le montant des pensions versées aux plus grands invalides pour la fixation du montant des pensions des veuves et éviter ainsi une trop grande disproportion entre les deux. Le rapport du Gouvernement devra permettre d’informer pleinement le Parlement sur ce sujet pour lui permettre d’effectuer des choix en recensant précisément le nombre de veuves, en France et à l’étranger, leur âge et le montant de leurs pensions. Le rapport étudiera aussi la faisabilité de la mise en place d’une taxation des pensions des plus grands invalides pour financer un dispositif qui assure aux veuves une pension décente. | L21: /14/amendements/0235C/AN/177.pdf | M21: Discuté | N21: Daniel Boisserie | O21: SER | P21: Depute | Q21: Daniel Boisserie
A22: 14 | B22: PRJLANR5L14B0235 | C22: 1ère lecture (1ère assemblée saisie) | D22: AMANR5L14SEA644420B0235P2D1N629 | E22: 2012-11-09T00:00:00Z | F22: =LEFT(E22,4) -> 2012 | G22: =RIGHT(LEFT(E22,7),2) -> 11 | H22: =F22&G22 -> 201211 | I22: ÉTAT B | K22: Un amendement n° 446 du Gouvernement a été déposé et adopté le 9 novembre dernier afin de transférer les crédits de la DGME (qui vient d’être rebaptisée Direction interministérielle de modernisation de l’action publique, ou DIMAP), relevant de l’action 4 du programme Stratégie des finances publiques de la présente mission, au programme Coordination du travail gouvernemental de la mission Direction de l’action du Gouvernement, à laquelle la DGME serait désormais rattachée. Parallèlement, l’amendement n° 447 du Gouvernement, déposé sur cette mission, supprime les crédits de l’action 4 du programme Stratégie des finances publiques. La Rapporteure spéciale se félicite que le Gouvernement appuie ainsi les propositions qu’elle a formulées dans son rapport spécial en faveur d’un renforcement du pilotage interministériel de la réforme de l’État, par le rattachement de la DGME aux services du Premier ministre. Par le présent amendement, elle propose d’aller au bout de cette logique, en rattachant à la mission Direction de l’action du Gouvernement, outre la DGME, les programmes informatiques Chorus et ONP, qui relèvent respectivement des actions 05 Information financière de l’État et 06 Systèmes d’information et production de la paye. De tels projets informatiques transversaux sont de réels leviers de modernisation de l’action publique. Or, à l’issue de ses travaux, la Rapporteure spéciale a constaté que leur mise en œuvre pâtissait d’un manque de gouvernance interministérielle, et elle juge que leur rattachement à Bercy n’est pas optimal. Dans cette perspective, le présent amendement supprime le programme Stratégie des finances publiques et modernisation de l’État et reventile ses six actions, ce qui conduit à modifier l’architecture budgétaire de la mission. La DGME ou DIMAP peut donc être rattachée à la mission Direction de l’action du Gouvernement, du fait de l’adoption de l’amendement n° 446 précité, et la Rapporteure spéciale propose en conséquence de supprimer ses crédits (47,64 millions d’euros) au sein du programme Stratégie des finances publiques. Parallèlement, la Rapporteure spéciale propose de réunir les crédits des actions Information financière de l’État (85,3 et 81,6 millions d’euros en AE et CP) et Systèmes d’information et production de la paye (63,1 et 68,3 millions d’euros en AE et CP) du programme Stratégie des finances publiques, au sein d’un nouveau programme intitulé Systèmes d’information transversaux, et de rattacher ce dernier à la mission Direction de l’action du Gouvernement. Néanmoins, le droit existant ne lui permet pas, contrairement au Gouvernement, de créer un programme dans une autre mission ; de ce fait, dans un premier temps, le programme qu’elle crée est maintenu dans la mission Gestion des finances publiques et des ressources humaines. Les trois actions restantes du programme supprimé sont reventilées entre les différents autres programmes de la mission, à dotation constante : – l’action Politique des finances publiques et analyse de la performance des politiques publiques, qui correspond aux moyens de la direction du budget, soit 36,95 millions d’euros, est rattachée au programme Conduite et pilotage des politiques économique et financière ; – l’action Politique de la fonction publique et modernisation de la gestion des ressources humaines, qui regroupe la masse salariale des agents de la Direction générale de l’administration et de la fonction publique (DGAFP) pour 12,9 millions d’euros, est logiquement rattachée au programme Fonction publique, alors que ce programme porte d’ores et déjà les moyens dont dispose la DGAFP pour la formation des fonctionnaires. Ce changement de nomenclature permet de donner davantage de cohérence au programme Fonction publique, en remédiant à l’éclatement des crédits de la DGAFP ; – l’action Régulation des jeux correspond aux crédits de l’Autorité de régulation des jeux en ligne (ARJEL) pour respectivement 9,8 et 10,5 millions d’euros en AE et en CP en 2013 ; son rattachement au programme Stratégie des finances publiques apparaissait dès l’origine quelque peu incongru, comme l’avait souligné le précédent rapporteur spécial. Il semblerait plus pertinent de la placer au sein du programme Développement des entreprises et du tourisme, qui relève de la mission Économie, et qui porte notamment les moyens de la direction générale de la concurrence, de la consommation et de la répression des fraudes (DGCCRF). Néanmoins, encore une fois, le droit en vigueur ne permet pas de procéder par voie d’amendement parlementaire à des transferts de moyens entre deux missions différentes. À défaut, l’action Régulation des jeux est rattachée au programme Facilitation et sécurisation des échanges, pour rejoindre les activités de la direction générale des douanes et des droits indirects, laquelle participe, d’une certaine façon, à la protection des citoyens et des consommateurs, de même que l’ARJEL. | L22: /14/amendements/0235C/AN/629.pdf | M22: Discuté | N22: Karine Berger | O22: SER | P22: Depute | Q22: Karine Berger
A23: 14 | B23: PRJLANR5L14B0235 | C23: 1ère lecture (1ère assemblée saisie) | D23: AMANR5L14SEA644420B0235P2D1N689 | E23: 2012-11-12T00:00:00Z | F23: =LEFT(E23,4) -> 2012 | G23: =RIGHT(LEFT(E23,7),2) -> 11 | H23: =F23&G23 -> 201211 | I23: Article 59 | J23: L’article 1599 quater B du code général des impôts est ainsi modifié : 1° Au a) du I et à la première phrase du a) du III, après le mot : « cuivre », sont insérés les mots : « ou fibre optique » ; 2° Le IV devient le V ; 3° Après le tableau du b) du III, il est inséré un IV ainsi rédigé: « IV. – Les lignes fibre optique, activées pour la première fois au 1er janvier de l’année d’imposition donnent lieu à abattement sur les autres éléments d’assiette de l’opérateur, à due concurrence. Cet abattement ne vaut qu’une fois par ligne fibre optique, tout opérateur confondu. » | K23: Cet amendement a pour but de refonder, pour partie, l’imposition forfaitaire sur les entreprises de réseau (IFER) concernant les opérateurs de téléphonie. Instaurée par la loi de finances initiale 2010 et modifiée par celle de 2011, cette taxe revenant aux Régions est assise sur des éléments de la boucle locale cuivre. Du fait de la mutation technologique en cours vers la fibre optique, ces éléments sont appelés à être progressivement remplacés (effet substitutif total à terme). Afin de pérenniser l’assiette, l’amendement intègre les éléments du réseau fibre optique. Afin d’encourager la substitution de la fibre au cuivre, il prévoit une mesure d’abattement, lors de la 1ère activation de ligne abonné en fibre (IV). | L23: /14/amendements/0235C/AN/689.pdf | M23: Discuté | N23: Alain Rousset | O23: SER | P23: Depute | Q23: Alain Rousset
A24: 14 | B24: PRJLANR5L14B0235 | C24: 1ère lecture (1ère assemblée saisie) | D24: AMANR5L14SEA644420B0235P2D1N518 | E24: 2012-11-09T00:00:00Z | F24: =LEFT(E24,4) -> 2012 | G24: =RIGHT(LEFT(E24,7),2) -> 11 | H24: =F24&G24 -> 201211 | I24: Article 67 | J24: Après l’alinéa 67, insérer les quatre alinéas suivants : « 15° bis L’article L. 5211-28-1 est ainsi modifié : « a) Au premier alinéa, après la référence : « 3° », est insérée la référence : « du I » ; « b) À la deuxième phrase du troisième alinéa, après la référence : « 3° », est insérée la référence : « du I » , et à la dernière phrase du même alinéa, après le mot : « alinéa », est insérée la référence : « du II » ; « c) Au dernier alinéa, après le mot : « alinéa », est insérée la référence : « du II » ; » | K24: Amendement de coordination. | L24: /14/amendements/0235C/AN/518.pdf | M24: Discuté | N24: Pascal Terrasse | O24: SER | P24: Depute | Q24: Pascal Terrasse
A25: 14 | B25: PRJLANR5L14B0235 | C25: 1ère lecture (1ère assemblée saisie) | D25: AMANR5L14SEA644420B0235P2D1N509 | E25: 2012-11-09T00:00:00Z | F25: =LEFT(E25,4) -> 2012 | G25: =RIGHT(LEFT(E25,7),2) -> 11 | H25: =F25&G25 -> 201211 | I25: Article 67 | J25: Après l’alinéa 41, insérer l’alinéa suivant : « a bis) Au troisième alinéa du b du 1°, la première occurrence du mot : « moyen » est supprimée. ». | K25: Amendement rédactionnel. | L25: /14/amendements/0235C/AN/509.pdf | M25: Discuté | N25: Pascal Terrasse | O25: SER | P25: Depute | Q25: Pascal Terrasse
A26: 14 | B26: PRJLANR5L14B0235 | C26: 1ère lecture (1ère assemblée saisie) | D26: AMANR5L14SEA644420B0235P2D1N682 | E26: 2012-11-12T00:00:00Z | F26: =LEFT(E26,4) -> 2012 | G26: =RIGHT(LEFT(E26,7),2) -> 11 | H26: =F26&G26 -> 201211 | I26: Article 59 | J26: I.– Le I de l’article 1384 C du code général des impôts est complété par un alinéa ainsi rédigé : «Toutefois, la durée d’exonération est ramenée à quinze ans pour les logements acquis auprès des organismes visés à l’article L.411-5 du code de la construction et de l'habitation et au moyen de prêts visés à la sous-section 3 de la section 1 du chapitre unique du titre III du livre III du même code.» II.– Le I du présent article s'applique aux décisions d'octroi de subvention ou de prêt intervenues à compter du 1er janvier 2009. | K26: En novembre 2009, environ 35 000 logements locatifs étaient cédés par la société Icade, filiale cotée de la Caisse des dépôts et consignations, à un consortium de 26 bailleurs sociaux mené par la Société Nationale Immobilière. Peu avant, à la suite notamment d'une mobilisation sans précédent de 36 maires d'Ile-de-France, le gouvernement d’alors s'engageait à compenser les exonérations de taxe foncière sur les propriétés bâties accordées à ces bailleurs lors d'acquisition en PLS, en déposant un amendement, adopté à l'unanimité à l'Assemblée nationale dans le cadre de la discussion du projet de loi de finances pour 2010. Mais du fait que les différentes compensations d'exonérations sont devenues, depuis l'entrée en application de la loi de finances pour 2009, des variables d'ajustement au sein de l'enveloppe normée des concours de l'Etat, le montant de cette compensation se trouve chaque année réduit par l'application d'un coefficient déflateur cumulé. En 2012, les exonérations de taxe foncière sur les propriétés bâties liées au patrimoine Icade n’ont été compensées qu'à 62%. Cet amendement vise donc à limiter la pénalisation financière des collectivités locales qui, accueillant l’ancien patrimoine immobilier d’Icade, contribuent activement au maintien d’une offre de logements accessibles aux ménages les plus fragiles, en réduisant la durée d'exonération à 15 ans. | L26: /14/amendements/0235C/AN/682.pdf | M26: Discuté | N26: François Pupponi | O26: SER | P26: Depute | Q26: François Pupponi
A27: 14 | B27: PRJLANR5L14B0235 | C27: 1ère lecture (1ère assemblée saisie) | D27: AMANR5L14SEA644420B0235P2D1N529 | E27: 2012-11-09T00:00:00Z | F27: =LEFT(E27,4) -> 2012 | G27: =RIGHT(LEFT(E27,7),2) -> 11 | H27: =F27&G27 -> 201211 | I27: Article 67 | J27: Substituer à l’alinéa 20 les deux alinéas suivants : « d) Le sixième alinéa du 4° est ainsi rédigé : « II. – Le taux de croissance de la dotation forfaitaire est égal au taux d’évolution de la somme des composantes de cette dotation par rapport à la somme des montants versés l’année précédente en application du I, hors les montants prévus à son 3°. À compter de 2011, pour le calcul de ce taux de référence, il n’est pas tenu compte de l’évolution de la dotation forfaitaire liée aux variations de la population telle que définie par l’article L. 2334‑2, ni des évolutions liées aux éventuelles minorations des composantes de la dotation forfaitaire prévues aux 3° et 4° du I. ». | K27: Amendement rédactionnel. | L27: /14/amendements/0235C/AN/529.pdf | M27: Retiré | N27: Pascal Terrasse | O27: SER | P27: Depute | Q27: Pascal Terrasse
A28: 14 | B28: PRJLANR5L14B0235 | C28: 1ère lecture (1ère assemblée saisie) | D28: AMANR5L14SEA644420B0235P2D1N508 | E28: 2012-11-09T00:00:00Z | F28: =LEFT(E28,4) -> 2012 | G28: =RIGHT(LEFT(E28,7),2) -> 11 | H28: =F28&G28 -> 201211 | I28: Article 67 | J28: Au début de l’alinéa 36, substituer aux mots : « L’indice » les mots : « Cet indice ». | K28: Amendement rédactionnel. | L28: /14/amendements/0235C/AN/508.pdf | M28: Discuté | N28: Pascal Terrasse | O28: SER | P28: Depute | Q28: Pascal Terrasse
A29: 14 | B29: PRJLANR5L14B0235 | C29: 1ère lecture (1ère assemblée saisie) | D29: AMANR5L14SEA644420B0235P2D1N395 | E29: 2012-11-08T00:00:00Z | F29: =LEFT(E29,4) -> 2012 | G29: =RIGHT(LEFT(E29,7),2) -> 11 | H29: =F29&G29 -> 201211 | I29: Article 66 | J29: À l’alinéa 2, substituer au mot : « intérêt », le mot : « intérêts ». | K29: Amendement rédactionnel. | L29: /14/amendements/0235C/AN/395.pdf | M29: Discuté | N29: Dominique Lefebvre | O29: SER | P29: Depute | Q29: Dominique Lefebvre
A30: 14 | B30: PRJLANR5L14B0235 | C30: 1ère lecture (1ère assemblée saisie) | D30: AMANR5L14SEA644420B0235P2D1N37 | E30: 2012-10-19T00:00:00Z | F30: =LEFT(E30,4) -> 2012 | G30: =RIGHT(LEFT(E30,7),2) -> 10 | H30: =F30&G30 -> 201210 | I30: Article 59 | J30: L’article L. 581‑43 du code de l’environnement est ainsi modifié : 1° Aux premier et deuxième alinéas, les mots : « maximal de six » sont remplacés par les mots : « de deux ». 2° Le dernier alinéa est supprimé. | K30: La loi relative à la simplification du droit et à l’allègement des démarches administratives adoptée en procédure accélérée par l’Assemblée Nationale le 23 mars 2012, et que les Sénateurs n’ont pas souhaité discuter, avait modifié le délai de mise en conformité des dispositifs d’affichage. Initialement prévu à deux ans, ce délai passé à six ans avait suscité des protestations tant chez les municipalités et les riverains, qui ont vu leurs moyens de limiter la pollution visuelle se réduire, que chez les commerçants nouvellement établis qui ont ressenti une grande injustice vis-à-vis des établissements déjà en place. Il est également à préciser que les publicités sont largement rentabilisées dans des délais bien inférieurs à six ans. | L30: /14/amendements/0235C/AN/37.pdf | M30: Retiré | N30: Christophe Borgel | O30: SER | P30: Depute | Q30: Christophe Borgel
A31: 14 | B31: PRJLANR5L14B0235 | C31: 1ère lecture (1ère assemblée saisie) | D31: AMANR5L14SEA644420B0235P2D1N286 | E31: 2012-11-06T00:00:00Z | F31: =LEFT(E31,4) -> 2012 | G31: =RIGHT(LEFT(E31,7),2) -> 11 | H31: =F31&G31 -> 201211 | I31: ÉTAT B | K31: Les entreprises d’insertion et les entreprises de travail temporaire d’insertion (ETTI) accueillent 48 000 personnes éloignées de l’emploi chaque année. Le financement par l’État de l’aide au poste prévu pour 2013 s’élève à 140 millions d’euros au total pour un peu moins de 15 000 postes. Ce secteur, confronté à des coûts réels qui ont considérablement augmenté dans les dernières années, n’a pas connu de revalorisation de l’aide depuis le 1er janvier 2002. Au regard de son fort potentiel de création d’emplois, il semble aujourd’hui souhaitable de renforcer le soutien à ce secteur clé de l’insertion professionnelle des personnes éloignées de l’emploi, par une revalorisation de 10 millions d’euros de la dotation prévue, qui serait répartie entre revalorisation du montant de l’aide au poste et augmentation du nombre de poste subventionnés. Le présent amendement souhaite ainsi renforcer le soutien aux structures de l’insertion par l’activité économique (IAE), qui figurent à l’action n° 2 : « Amélioration des dispositifs en faveur de l’emploi des personnes les plus éloignées du marché du travail » du programme n° 102 : « Accès et retour à l’emploi », à hauteur de 10 millions d’euros en autorisations d’engagement et en crédits de paiement. Les crédits supplémentaires ainsi prévus sont prélevés sur l’action n° 3 : « Développement de l’emploi » du programme n° 103 : « Accompagnement des mutations économiques et développement de l’emploi », plus précisément du dispositif « aide à l’embauche pour les très petites entreprises », doté de 38,5 millions d’euros en autorisations d’engagement et en crédits de paiement. Ce dispositif, mis en place pour six mois de janvier à juin 2012, est en extinction depuis le mois de juin. Or, le nombre estimatif d’aides (26 424), pour un coût moyen unitaire de 1 434 euros, semble surévalué. Il est donc proposé de réduire les crédits alloués à ce dispositif dont la mise en place répondait à une logique opportuniste. | L31: /14/amendements/0235C/AN/286.pdf | M31: Discuté | N31: Christophe Castaner | O31: SER | P31: Depute | Q31: Christophe Castaner
A32: 14 | B32: PRJLANR5L14B0235 | C32: 1ère lecture (1ère assemblée saisie) | D32: AMANR5L14SEA644420B0235P2D1N396 | E32: 2012-11-08T00:00:00Z | F32: =LEFT(E32,4) -> 2012 | G32: =RIGHT(LEFT(E32,7),2) -> 11 | H32: =F32&G32 -> 201211 | I32: Article 66 | J32: À l’alinéa 2, supprimer les mots : « (3 CIF) ». | K32: Amendement rédactionnel. | L32: /14/amendements/0235C/AN/396.pdf | M32: Discuté | N32: Dominique Lefebvre | O32: SER | P32: Depute | Q32: Dominique Lefebvre
A33: 14 | B33: PRJLANR5L14B0235 | C33: 1ère lecture (1ère assemblée saisie) | D33: AMANR5L14SEA644420B0235P1D1N58 | E33: 2012-10-11T00:00:00Z | F33: =LEFT(E33,4) -> 2012 | G33: =RIGHT(LEFT(E33,7),2) -> 10 | H33: =F33&G33 -> 201210 | I33: Article 10 | J33: L’article 150 VC du code général des impôts est complété par un II ainsi rédigé : « II. – Les années où un bien immobilier a été déclaré vacant au sens de l’article 232 ne sont pas prises en compte pour le calcul des abattements prévus au I. » | K33: Le présent amendement a pour objet de compléter le renforcement de la taxe sur les logements vacants instauré par l’article 11, en soustrayant les années où un logement a été laissé vacant de l’abattement pour durée de détention dont bénéficient les plus-values immobilières. Le maintien de cet abattement reviendrait en effet à minorer l’efficacité de l’incitation fiscale à remettre les logements vacants sur le marché immobilier ou locatif. | L33: /14/amendements/0235A/AN/58.pdf | M33: Discuté | N33: Dominique Lefebvre | O33: SER | P33: Depute | Q33: Dominique Lefebvre
A34: 14 | B34: PRJLANR5L14B0235 | C34: 1ère lecture (1ère assemblée saisie) | D34: AMANR5L14SEA644420B0235P2D1N475 | E34: 2012-11-09T00:00:00Z | F34: =LEFT(E34,4) -> 2012 | G34: =RIGHT(LEFT(E34,7),2) -> 11 | H34: =F34&G34 -> 201211 | I34: Article 71 | J34: « Mission Egalité des territoires, Logement et Ville » I- Les dispositions de l’article 35 de la loi n° 2009-594 du 27 mai 2009 pour le développement économique des outre-mer sont remplacées par les dispositions suivantes : 1- En Guadeloupe, en Guyane, en Martinique, à la Réunion, à Mayotte et à Saint-Martin, il peut être mis en œuvre une procédure de titrement fondée sur le rassemblement et l’analyse de tous les éléments propres, d’une part, à définir les biens fonciers et immobiliers et à identifier les personnes dépourvues de titres de propriétés et permettre, d’autre part, d’établir le lien entre un bien et une personne, afin de constituer ou de reconstituer ces titres. 2- La procédure de titrement, selon les dispositions des paragraphes I et II, peut être conduite : - soit par un groupement d’intérêt public qui peut être constitué, dans chacun des territoires concernés, dans les conditions prévues au chapitre II de la loi n° 2011-525 du 17 mai 2011 de simplification et d’amélioration de la qualité du droit. Chaque groupement est constitué de l’État, de la région d’outre-mer concernée ou, selon le cas, du Département de Mayotte, de la collectivité de Saint-Martin ainsi que d’associations d’élus locaux et de représentants des officiers publics ministériels intéressés. Compte tenu des compétences spécifiques exigées par la procédure de titrement qui lui est confiée, le groupement peut, par exception aux dispositions du troisièmement de l’article 109 de la loi n° 2011-525 du 17 mai 2011 susvisée, recruter directement et en tant que de besoin, des agents contractuels de droit public ou de droit privé. - soit par un opérateur public foncier. Le statut de cet opérateur sera complété des dispositions permettant la mise en œuvre cette nouvelle mission. Les membres du ou des organes délibérants de cet opérateur seront, en tant que de besoin, complétés des personnes désignées au deuxième paragraphe». 3- L’opérateur, crée et/ou gère l’ensemble des équipements ou services d’intérêt commun, et effectue les travaux et missions connexes ou complémentaires rendus nécessaires par la conduite de la procédure de titrement. Pour l'accomplissement de sa mission, l’opérateur peut créer un fichier de données à caractère personnel dans les conditions définies par la loi n° 78-17 du 6 janvier 1978 relative à l'informatique, aux fichiers et aux libertés Sans que puisse leur être opposé le secret professionnel, l’opérateur ainsi que les personnes qu’il délègue, peuvent se faire communiquer de toute personne, physique ou morale, de droit public ou de droit privé, détentrice de tous documents et informations nécessaires à la réalisation de la procédure de titrement, y compris ceux contenus dans un système informatique ou de traitement de données à caractère personnel. Les agents de l’opérateur et les personnes qu’il délègue, sont tenus de respecter la confidentialité des informations recueillies au cours de leur mission sous peine des sanctions prévues aux articles 226-13, 226-31 et 226-32 du code pénal. Ces informations sont communiquées aux officiers publics ministériels concernés, aux représentants de l’État ainsi qu’aux responsables des exécutifs des collectivités territoriales. II- La perte de recettes pour l’État est compensée à due concurrence par la création d'une taxe additionnelle aux droits visés aux articles 575 et 575 A du code général des impôts. | K34: L’article 35 de la loi n° 2009-594 du 27 mai 2009 pour le développement économique des outre-mer prévoit la création d’un groupement d'intérêt public pour la reconstitution des titres de propriété en Guadeloupe, en Guyane, en Martinique, à la Réunion et à Saint-Martin. Il est apparu nécessaire de modifier cet article pour introduire la possibilité d’utiliser les compétences des organismes existants en leur confiant la mission de titrement afin d’éviter, autant que possible, la création d’organismes supplémentaires. Cet amendement vise ainsi à donner de la souplesse aux collectivités pour adapter l’outil aux contraintes locales, soit la création d’un GIP, soit confier la mission de titrement à un autre opérateur œuvrant dans le domaine foncier. De même, afin de tenir compte de la départementalisation de Mayotte, le projet inscrit cette collectivité dans la liste de celles qui sont autorisées à mettre en place la mission de reconstitution des titres de propriété. | L34: /14/amendements/0235C/AN/475.pdf | M34: Retiré | N34: Serge Letchimy | O34: SER | P34: Depute | Q34: Serge Letchimy
A35: 14 | B35: PRJLANR5L14B0235 | C35: 1ère lecture (1ère assemblée saisie) | D35: AMANR5L14SEA644420B0235P1D1N556 | E35: 2012-10-12T00:00:00Z | F35: =LEFT(E35,4) -> 2012 | G35: =RIGHT(LEFT(E35,7),2) -> 10 | H35: =F35&G35 -> 201210 | I35: Article 7 | J35: À la première phrase de l’alinéa 26, substituer aux mots : « , les a cédées, converties au porteur ou mises » les mots : « en les cédant, en les convertissant ou en les mettant ». | K35: Amendement de clarification. La rédaction antérieure pourrait laisser entendre que la nouvelle taxation s’appliquerait rétroactivement aussi aux donations réalisées depuis le début de l’année. Certes on peut aisément comprendre que la nouvelle fiscalité s’applique en cas de cession ou de conversion ou de mise en location, car l’assujetti serait effectivement le bénéficiaire de l’opération. Mais ce n’est pas le cas lorsqu’il y a donation, puisque la nouvelle fiscalité s’appliquerait au donateur, et non au bénéficiaire de la donation. L’amendement présenté permet de clarifier le champ de la taxation nouvelle. | L35: /14/amendements/0235A/AN/556.pdf | M35: Irrecevable | N35: Dominique Baert | O35: SER | P35: Depute | Q35: Dominique Baert
A36: 14 | B36: PRJLANR5L14B0235 | C36: 1ère lecture (1ère assemblée saisie) | D36: AMANR5L14SEA644420B0235P2D1N358 | E36: 2012-11-07T00:00:00Z | F36: =LEFT(E36,4) -> 2012 | G36: =RIGHT(LEFT(E36,7),2) -> 11 | H36: =F36&G36 -> 201211 | I36: Article 68 | J36: Après l’alinéa 17, insérer l’alinéa suivant : « III bis. – En région Île-de-France, le prélèvement dû par les ensembles intercommunaux visés au 1° du I du présent article est pris en charge en intégralité par l’établissement public de coopération intercommunale. ». | K36: En région d’Ile-de-France, les communes appelées au sein de leur bloc intercommunal à contribuer au FPIC contribuent aussi pour la grande majorité au fonds régional FSRIF. Du fait du plafonnement induit par le 3° du I. de l’article L2336-3 du Code général des collectivités territoriales, des communes « riches » au sein du bloc intercommunal peuvent se retrouver plafonnées, dès leur contribution au FSRIF. En conséquence, les autres communes de l’EPCI, aux ressources parfois modestes, se retrouvent à devoir régler le différentiel de contribution pour le reste du groupe intercommunal. Cet amendement vise à éviter cet effet contre-péréquateur en faisant peser, en région d’Ile-de-France, la contribution sur l’EPCI en tant que tel plutôt que sur ses communes membres. Cet amendement est soutenu par Paris Métropole. | L36: /14/amendements/0235C/AN/358.pdf | M36: Discuté | N36: François Pupponi | O36: SER | P36: Depute | Q36: François Pupponi
A37: 14 | B37: PRJLANR5L14B0235 | C37: 1ère lecture (1ère assemblée saisie) | D37: AMANR5L14SEA644420B0235P1D1N616 | E37: 2012-10-12T00:00:00Z | F37: =LEFT(E37,4) -> 2012 | G37: =RIGHT(LEFT(E37,7),2) -> 10 | H37: =F37&G37 -> 201210 | I37: Article 13 | J37: I. L’article 266 quater A du code des douanes, dans sa rédaction issue de l'article 88 de la loi n° 2007-1824 du 25 décembre 2007 de finances rectificative pour 2007, est abrogé. II. La perte de recettes pour l’État est compensée à due concurrence par la majoration des droits visés aux articles 575 et 575 A du code général des impôts. | K37: Le présent article a pour objet d’abroger une taxe additionnelle à la taxe spéciale de consommation sur les carburants instituée, pour la Guyane, par l’article 88 de la loi de finances rectificative pour 2007. Ce dispositif était destiné à aider d’une part la société SARA, raffinerie située en Martinique, et d’autre part les distributeurs de carburants en Guyane, à réaliser les investissements nécessaires à la mise aux normes européennes de leurs installations. L’Agence Française de Développement (AFD) avait consenti à la SARA une avance de 19,5 M€ dont le montant, intérêt compris s’élevait fin 2011 à 28 M€ environ. Cette avance devait être remboursée via la SARA par la collecte d’une taxe additionnelle à la taxe spéciale de consommation sur les carburants. Cette taxe affectée à l’AFD accordait à cette dernière la garantie de l’Etat pour le remboursement de l’avance consentie. Toutefois, pour éviter d’augmenter davantage le prix des carburants en Guyane, l’entrée en vigueur de cette taxe affectée a été reportée d’année en année et doit entrer en vigueur au 1er janvier 2013. Or, la garantie de l’État a finalement été mise en jeu en décembre 2011 et l’AFD a ainsi été remboursée de son avance à la SARA. La taxe affectée à l’AFD est, dès lors, devenue sans objet. Il est donc proposé de supprimer l’ensemble de ce dispositif dont les dispositions sont fixées à l’article 266 quater A du code des douanes. | L37: /14/amendements/0235A/AN/616.pdf | M37: Irrecevable | N37: Chantal Berthelot | O37: SER | P37: Depute | Q37: Chantal Berthelot
A38: 14 | B38: PRJLANR5L14B0235 | C38: 1ère lecture (1ère assemblée saisie) | D38: AMANR5L14SEA644420B0235P2D1N278 | E38: 2012-11-06T00:00:00Z | F38: =LEFT(E38,4) -> 2012 | G38: =RIGHT(LEFT(E38,7),2) -> 11 | H38: =F38&G38 -> 201211 | I38: ÉTAT B | K38: Les entreprises d’insertion et les entreprises de travail temporaire d’insertion (ETTI) accueillent 48 000 personnes éloignées de l’emploi chaque année. Le financement par l’État de l’aide au poste prévu pour 2013 s’élève à 140 millions d’euros au total pour un peu moins de 15 000 postes. Ce secteur, confronté à des coûts réels qui ont considérablement augmenté dans les dernières années, n’a pas connu de revalorisation de l’aide depuis le 1er janvier 2002. Au regard de son fort potentiel de création d’emplois, il semble aujourd’hui souhaitable de renforcer le soutien à ce secteur clé de l’insertion professionnelle des personnes éloignées de l’emploi, par une revalorisation de 10 millions d’euros de la dotation prévue, qui serait répartie entre revalorisation du montant de l’aide au poste et augmentation du nombre de poste subventionnés. Le présent amendement souhaite ainsi renforcer le soutien aux structures de l’insertion par l’activité économique (IAE), qui figurent à l’action n° 2 : « Amélioration des dispositifs en faveur de l’emploi des personnes les plus éloignées du marché du travail » du programme n° 102 : « Accès et retour à l’emploi », à hauteur de 10 millions d’euros en autorisations d’engagement et en crédits de paiement. Les crédits supplémentaires ainsi prévus sont prélevés sur l’action n°3 : « Développement de l’emploi » du programme 103 : « Accompagnement des mutations économiques et développement de l’emploi », et plus particulièrement sur le dispositif « zéro charge » pour l’embauche des jeunes dans les TPE, qui est un dispositif en extinction. | L38: /14/amendements/0235C/AN/278.pdf | M38: Discuté | N38: Jean-Patrick Gille | O38: SER | P38: Depute | Q38: Jean-Patrick Gille
A39: 14 | B39: PRJLANR5L14B0235 | C39: 1ère lecture (1ère assemblée saisie) | D39: AMANR5L14SEA644420B0235P1D1N235 | E39: 2012-10-12T00:00:00Z | F39: =LEFT(E39,4) -> 2012 | G39: =RIGHT(LEFT(E39,7),2) -> 10 | H39: =F39&G39 -> 201210 | I39: Article 42 | J39: Le V de l’article 43 de la loi n°99‑1172 du 30 décembre 1999 de finances pour 2000 est complété par un alinéa ainsi rédigé : « À compter du 1er juillet 2013, le montant de la redevance issue des taxes additionnelles des exploitants de la filière électronucléaire du laboratoire de Bure‑Saudron ne sera pas inférieur à 40 millions d’euros par an et par groupement d’intérêt public concerné. ». | K39: L’objectif du présent amendement est d’augmenter à compter du 1er juillet 2013, la redevance liée au versement des taxes additionnelles dues par les exploitants de la filière electronucléaire du laboratoire de Bure-Saudron. Le tableau ci-dessus sera modifié en conséquence et à compter du 1er janvier 2014, ce même tableau sera modifié afin de garantir aux Groupements d’Intérêts Publics concernés un minima de redevance à hauteur de 40 millions puis de 50 millions à compter du 1er janvier 2014. | L39: /14/amendements/0235A/AN/235.pdf | M39: Irrecevable | N39: Jean-Louis Dumont | O39: SER | P39: Depute | Q39: Jean-Louis Dumont
A40: 14 | B40: PRJLANR5L14B0235 | C40: 1ère lecture (1ère assemblée saisie) | D40: AMANR5L14SEA644420B0235P1D1N63 | E40: 2012-10-11T00:00:00Z | F40: =LEFT(E40,4) -> 2012 | G40: =RIGHT(LEFT(E40,7),2) -> 10 | H40: =F40&G40 -> 201210 | I40: Article 24 | J40: I. – L’article L. 2333‑54 du code général des collectivités territoriales est ainsi rédigé : « I. – Les établissements publics de coopération intercommunale à fiscalité propre qui réalisent des actions de promotion en faveur du tourisme peuvent instituer un prélèvement sur le produit brut des jeux dans les casinos situés sur le territoire de leurs communes membres. « Le taux maximum des prélèvements opérés par les établissements publics de coopération intercommunale à fiscalité propre sur le produit brut des jeux dans les casinos régis par le chapitre Ier du titre II du livre III du code de la sécurité intérieure en vertu des clauses des cahiers des charges de ces établissements ne doit, en aucun cas, dépasser 15 %. « Ces prélèvements s’appliquent au produit brut des jeux diminué de 25 % et, le cas échéant, des abattements supplémentaires mentionnés au I de l’article 34 de la loi n° 95‑1347 du 30 décembre 1995 de finances rectificative pour 1995. « Lorsque le taux du prélèvement intercommunal ajouté au taux du prélèvement de l’État sur la somme des éléments constitutifs du produit brut des jeux mentionnés aux 1°, 2° et 3° de l’article L. 2333‑55‑1 dépasse 80 %, le taux du prélèvement de l’État est réduit de telle façon que le total des deux prélèvements soit de 80 % « Lorsque le taux du prélèvement intercommunal ajouté au taux du prélèvement de l’État sur la somme des éléments constitutifs du produit brut des jeux mentionnés aux 4° et 5° de l’article L. 2333‑55‑1 dépasse 80 %, le taux du prélèvement de l’État est réduit de telle façon que le total des deux prélèvements soit de 80 %. « II. – Les établissements publics de coopération intercommunale à fiscalité propre peuvent, par convention, reverser tout ou partie du prélèvement à la commune siège du casino lorsqu’elle réalise des actions de promotion en faveur du tourisme. « III. – Lorsqu’un établissement public de coopération intercommunale à fiscalité propre ne réalise pas d’action de promotion en faveur du tourisme ou lorsqu’une commune n’est membre d’aucun établissement public de coopération intercommunale à fiscalité propre, le conseil municipal de la commune siège du casino peut instituer un prélèvement dans les conditions fixées au I. « Lorsqu’elles sont membres d’un syndicat mixte ou d’un groupement de communes autre qu’un établissement public de coopération intercommunale à fiscalité propre réalisant des actions de promotion en faveur du tourisme, les communes concernées doivent, par convention, lui reverser tout ou partie du prélèvement institué. » II. – L’article L. 2333‑55 du même code est ainsi rédigé : « Il est reversé à l’établissement public de coopération intercommunale à fiscalité propre 10 % du prélèvement opéré par l’État sur le produit brut des jeux réalisé par un casino régi par le chapitre Ier du titre II du livre III du code de la sécurité intérieure et situé sur le territoire d’une de ses communes membres. « À défaut, il est reversé à la commune 10 % du prélèvement opéré par l’État sur le produit brut des jeux réalisé par un casino régi par le chapitre Ier du titre II du livre III du code de la sécurité intérieure situé sur son territoire . « Le montant de ce versement ne peut toutefois avoir pour effet d’accroître de plus de 5 % le montant des recettes réelles de fonctionnement de l’établissement public de coopération intercommunale à fiscalité propre ou de la commune, ce plafond étant porté à 10 % pour les établissements publics de coopération intercommunale à fiscalité propre ou les communes dont le potentiel financier par habitant est inférieur au potentiel financier moyen par habitant de l’ensemble des communes appartenant au même groupe démographique. » III. – Au premier alinéa des articles L. 2333‑55‑1 et L. 2333‑55‑2 du même code, après le mot : « intercommunale », sont insérés les mots : « à fiscalité propre ». IV. – Les trois derniers alinéas de l’article L. 2333‑57 du même code sont remplacés par deux alinéas ainsi rédigés : « Les travaux d’investissement prévus à l’alinéa précédent peuvent être affectés, en tout ou partie, à l’équipement du casino, de ses annexes et de ses abords, après accord entre le concessionnaire des jeux et l’établissement public de coopération intercommunale à fiscalité propre ou, le cas échéant, de la commune, où est exploité le casino bénéficiaire de l’application du nouveau barème. « Un décret d’application précise les modalités d’emploi en capital ou annuités d’emprunt et les conditions dans lesquelles l’emprunt gagé par les recettes de cette nature est garanti par les collectivités territoriales ou les établissements publics de coopération intercommunale. » V. – L’article L. 5211-21-1 du même code est abrogé. VI. – La perte de recettes pour les communes concernées est compensée par la majoration à due concurrence de la dotation globale de fonctionnement, et corrélativement pour l’État par la création d’une taxe additionnelle aux droits mentionnés aux articles 575 et 575 A du code général des impôts. | K40: En dehors des dérogations en faveur de quelques communes qui possédaient déjà un casino, la loi du 15 juin 1907 (désormais codifiée au sein du code de la sécurité intérieure)a accordé, par dérogation au code pénal interdisant les jeux de hasard, aux stations classées « balnéaires », « thermales » ou « climatiques », la possibilité d’ouvrir et d’exploiter un casino. La loi n° 88-13 du 5 janvier 1988 sur l’amélioration de la décentralisation a étendu ce privilège aux villes principales de grandes agglomérations de plus de 500 000 habitants classées « stations de tourisme ». En application des articles L. 2333‑54 à L. 2333-57 du code général des collectivités territoriales (CGCT), les communes sur le territoire desquelles sont implantés des casinos peuvent actuellement bénéficier de deux ressources issues d’un prélèvement sur le produit brut des jeux : — elles bénéficient d’un reversement de 10 % du prélèvement opéré par l’État sur le produit brut des jeux réalisé par l’établissement, dont le montant est plafonné à 5 % de leur recettes réelles de fonctionnement (10 % si elles sont membres d’un EPCI à fiscalité propre) ; — elles peuvent instituer un prélèvement sur le produit brut des jeux, au taux maximal de 15 % après abattements, pour financer des actions de promotion du tourisme. Par convention, tout ou partie de ce prélèvement peut être reversé par la commune bénéficiaire à un groupement de communes ou un syndicat mixte pour mener des actions en faveur du tourisme. Selon les informations communiquées au rapporteur pour avis de la mission « Relations avec les collectivités territoriales » pour 2013, ces prélèvements effectués en 2011 sur les 196 casinos français représentaient 67,4 millions d’euros pour le reversement du prélèvement de l’État et 200,4 millions d’euros pour les prélèvements institués par les communes. Les communes sur le territoire desquelles sont implantés les casinos bénéficient par défaut de ces ressources fiscales. Elles peuvent en faire bénéficier un groupement ou un syndicat mixte dont elles sont membres, de deux façons différentes : — en application de l’article L. 5211-21-1 du CGCT, les EPCI à fiscalité propre disposant de la compétence du tourisme ou les groupements percevant la taxe de séjour ou la taxe de séjour forfaitaire (comme par exemple les syndicats mixtes) peuvent se voir transférer la compétence pour instituer le prélèvement direct sur le produit brut des jeux, sauf opposition de la commune siège du casino ; — par convention, tout ou partie de ce prélèvement peut être reversé par la commune bénéficiaire à un groupement de communes ou un syndicat mixte pour mener des actions en faveur du tourisme (sixième alinéa de l’article L. 2333-54). Ainsi, le reversement des 10 % des prélèvements de l’État ne peut être effectué qu’au profit des communes ; la faculté d’instaurer un prélèvement ou les recettes liées à celui-ci ne peuvent être transférées à un EPCI qu’avec l’accord de la commune d’implantation du casino. Selon une étude menée par l’Assemblée des communautés de France[1], 65 % des EPCI à fiscalité propre exerceraient une compétence en matière de tourisme, mais seuls 35 % en tirent pleinement la conséquence en transférant les recettes concernées (taxe de séjour essentiellement) aux EPCI. Le présent projet d’amendement vise ainsi à renforcer la solidarité locale en prévoyant de transférer aux EPCI à fiscalité propre l’intégralité du reversement de 10 % du prélèvement de l’État et d’affecter par défaut la faculté d’instaurer un prélèvement sur le produit des jeux aux EPCI à fiscalité propre, à condition qu’ils existent[2] et qu’ils exercent la compétence tourisme ; à défaut, la commune conserverait cette faculté, comme c’est le cas actuellement. [1] AdCF, Les communautés et la compétence tourisme, mai 2010. [2] la couverture intégrale du territoire par des EPCI n’est pas encore achevée : la loi de réforme des collectivités territoriales n’a prévu son achèvement par application des pouvoirs exceptionnels des préfets au plus tard le 1er juin 2013 ; les nouveaux EPCI créés ou les rattachements effectués sans l’accord des communes concernées courant 2013 ne seront effectifs qu’à partir du 1er janvier suivant, soit le 1er janvier 2014. En outre, en application des articles L. 5210-1-1 et L. 5210-1-2 du CGCT, les communes de Paris et de la petite couronne, ainsi que les « îles maritimes composées d’une seule commune », ne sont pas soumises à l’obligation de rejoindre un EPCI à fiscalité propre. | L40: /14/amendements/0235A/AN/63.pdf | M40: Irrecevable | N40: Jean-Jacques Urvoas | O40: SER | P40: Depute | Q40: Jean-Jacques Urvoas
A41: 14 | B41: PRJLANR5L14B0235 | C41: 1ère lecture (1ère assemblée saisie) | D41: AMANR5L14SEA644420B0235P2D1N462 | E41: 2012-11-09T00:00:00Z | F41: =LEFT(E41,4) -> 2012 | G41: =RIGHT(LEFT(E41,7),2) -> 11 | H41: =F41&G41 -> 201211 | I41: Article 69 | J41: Substituer aux alinéas 27 à 45 les vingt et un alinéas suivants : « Art. L. 4332‑9 – I. – Il est créé un fonds de péréquation de l’ensemble des régions et de la collectivité territoriale de Corse, portant sur leurs ressources de remplacement de fiscalité directe locale. « Sont prises en compte les ressources suivantes : « - la cotisation sur la valeur ajoutée des entreprises, perçue par les régions et la collectivité territoriale de Corse, en application de l’article 1599 bis du code général des impôts ; « - l’imposition forfaitaire sur les entreprises de réseau sur le matériel roulant ferroviaire voyageurs, perçue par les régions, en application de l’article 1599 quater A du même code ; « - l’imposition forfaitaire sur les entreprises de réseau sur la boucle locale cuivre, perçue par les régions et la collectivité territoriale de Corse, en application de l’article 1599 quater B du même code ; « - le prélèvement ou le reversement du Fonds national de garantie individuelle des ressources régionales tel que défini au 2.3 de l’article 78 de la loi n° 2009‑1673 du 30 décembre 2009 de finances pour 2010 ; « - la dotation de compensation de la réforme de la taxe professionnelle, telle que définie au 1.3 de l’article 78 de la loi du 30 décembre 2009 précitée. « II. – Chaque année, il est calculé pour chaque région et la collectivité territoriale de Corse d’une part, pour l’ensemble des régions d’autre part, le pourcentage d’évolution cumulée de ces ressources depuis 2011. « Est prise en compte pour ce calcul l’évolution entre les ressources définitives de l’année 2011 et les ressources définitives de l’année précédant la répartition du fonds. « III. – Les régions et la collectivité territoriale de Corse sont contributrices au fonds si le pourcentage d’évolution cumulée de leurs ressources telles que définies au I est supérieur au pourcentage d’évolution cumulée de ces ressources calculé pour l’ensemble des régions. « Pour chaque région ou collectivité territoriale contributrice est calculée la différence entre le montant de ses ressources telles que définies au I l’année précédant la répartition et le montant de ses ressources 2011 majoré du pourcentage d’évolution cumulée constaté pour l’ensemble des régions. « Le montant du prélèvement est égal à 70 % de cette différence. « Le montant du prélèvement ne peut excéder, pour une région ou la collectivité territoriale de Corse contributrice, 35 % du montant d’évolution cumulée depuis 2011 de ses ressources telles que définies au I. « Les régions d’outre-mer sont dispensées de prélèvement. « Les prélèvements sont effectués suivant les modalités prévues à l’article L. 4331‑2‑1 du présent code. « IV. – Les ressources du fonds sont réparties au bénéfice des régions ou de la collectivité territoriale de Corse dont le pourcentage d’évolution cumulée de leurs ressources telles que définies au I est inférieur au pourcentage d’évolution cumulée de ces ressources calculé pour l’ensemble des régions. « Pour chaque région ou collectivité territoriale bénéficiaire est calculée la différence entre le montant de ses ressources 2011 telles que définies au I majoré du pourcentage d’évolution cumulée constaté pour l’ensemble des régions et le montant de ses ressources l’année précédant la répartition. « Le montant du reversement est calculé sur 70 % de cette différence, en proportion des ressources du fonds. « Les versements sont effectués suivant les modalités prévues à l’article L. 4331‑2‑1. « V. – Ces dispositions s’appliquent jusqu’au 31 décembre 2016. « Dans cet objectif, avant le 30 juin 2016, le Gouvernement transmet à l’Assemblée nationale et au Sénat une évaluation de ce dispositif, établie avec les régions. Cette évaluation porte sur l’effet régulateur des écarts d’évolution entre régions, des ressources mentionnées au I. ». | K41: Le présent amendement vise à remplacer le dispositif de péréquation régionale de la CVAE prévu au projet de loi de finances 2013 par celui sur lequel les régions se sont accordées dans le cadre du groupe de travail constitué sur le sujet. Ce dispositif est construit sur le périmètre de l’ex- fiscalité directe locale, remplacée pour les Régions à partir de 2011 par la CVAE, les IFER, le FNGIR et la DCRTP. Il fonctionne sur le cumul d’évolution de ces ressources depuis 2011, comparativement à la moyenne. Il régule l’écart d’évolution à la moyenne : - par un écrêtement de 70 % de ce cumul de ressources au-dessus de la moyenne pour les Régions contributrices ; - par un reversement en miroir pour les Régions bénéficiaires, dans la limite du montant annuel mis en répartition. Le prélèvement est assorti de deux garanties : - chaque année, le montant du prélèvement ne peut excéder 35 % de l’évolution cumulée de la Région contributrice - les Régions prélevées ne sont que métropolitaines (dispense des Régions d’Outre-mer) Une clause de revoyure est posée pour 2016 et le projet de loi de finances pour 2017. | L41: /14/amendements/0235C/AN/462.pdf | M41: Discuté | N41: Alain Rousset | O41: SER | P41: Depute | Q41: Alain Rousset
A42: 14 | B42: PRJLANR5L14B0235 | C42: 1ère lecture (1ère assemblée saisie) | D42: AMANR5L14SEA644420B0235P2D1N547 | E42: 2012-11-09T00:00:00Z | F42: =LEFT(E42,4) -> 2012 | G42: =RIGHT(LEFT(E42,7),2) -> 11 | H42: =F42&G42 -> 201211 | I42: Article 67 | J42: À l’alinéa 11, substituer au mot : « groupement » les mots : « établissement public de coopération intercommunale ». | K42: Amendement rédactionnel. | L42: /14/amendements/0235C/AN/547.pdf | M42: Discuté | N42: Pascal Terrasse | O42: SER | P42: Depute | Q42: Pascal Terrasse
A43: 14 | B43: PRJLANR5L14B0235 | C43: 1ère lecture (1ère assemblée saisie) | D43: AMANR5L14SEA644420B0235P2D1N467 | E43: 2012-11-09T00:00:00Z | F43: =LEFT(E43,4) -> 2012 | G43: =RIGHT(LEFT(E43,7),2) -> 11 | H43: =F43&G43 -> 201211 | I43: ÉTAT B | K43: Alors que le Gouvernement a rappelé en juillet dernier que le tourisme en France est un « moteur sous exploité de la croissance économique française », Atout France, l’agence de développement du tourisme français, voit sa subvention diminuer de 10 % sur le front des interventions à laquelle s’ajoute une diminution des effectifs de 11 personnes. Afin de maintenir les crédits attribués à Atout France, il convient donc de rééquilibrer les programmes au profit de l’agence de développement touristique de la France en déplaçant 1 500 000 d’euros depuis les autorisations d’engagement et crédits de paiement de l’action 05 « soutien » du programme 220 « statistiques et études économiques » vers l’action 21 « développement du tourisme » du programme 134 « développement des entreprises et du tourisme ». Pour rappel, selon l’organisation mondiale du tourisme, le nombre de visiteurs internationaux doublera d’ici 2030, il est donc essentiel que la France conserve ses capacités à séduire de nouvelles clientèles et leur donner envie de visiter le pays. | L43: /14/amendements/0235C/AN/467.pdf | M43: Discuté | N43: Pascal Terrasse | O43: SER | P43: Depute | Q43: Pascal Terrasse
A44: 14 | B44: PRJLANR5L14B0235 | C44: 1ère lecture (1ère assemblée saisie) | D44: AMANR5L14SEA644420B0235P2D1N514 | E44: 2012-11-09T00:00:00Z | F44: =LEFT(E44,4) -> 2012 | G44: =RIGHT(LEFT(E44,7),2) -> 11 | H44: =F44&G44 -> 201211 | I44: Article 67 | J44: Après l’alinéa 52, insérer l’alinéa suivant : « 12° bis Au I de l’article L. 2573-52, après la référence : « 5° », est insérée la référence : « du I » ; » | K44: Amendement de coordination. | L44: /14/amendements/0235C/AN/514.pdf | M44: Discuté | N44: Pascal Terrasse | O44: SER | P44: Depute | Q44: Pascal Terrasse
A45: 14 | B45: PRJLANR5L14B0235 | C45: 1ère lecture (1ère assemblée saisie) | D45: AMANR5L14SEA644420B0235P2D1N287 | E45: 2012-11-06T00:00:00Z | F45: =LEFT(E45,4) -> 2012 | G45: =RIGHT(LEFT(E45,7),2) -> 11 | H45: =F45&G45 -> 201211 | I45: ÉTAT B | K45: Cet amendement propose de majorer la dotation au Fonds d’insertion professionnelle des jeunes (FIPJ) de 1,4 millions d’euros en autorisations d’engagement et en crédits de paiement, en augmentant de ce montant les crédits de l’action n°2 « Amélioration des dispositifs en faveur de l’emploi des personnes les plus éloignées du marché du travail » du programme n°102 « Accès et retour à l’emploi », sur laquelle émarge le FIPJ, et en minorant à due concurrence les crédits de l’action n° 3 : « Développement de l’emploi » du programme n° 103 : « Accompagnement des mutations économiques et développement de l’emploi », plus précisément du dispositif « aide à l’embauche pour les très petites entreprises », doté de 38,5 millions d’euros en autorisations d’engagement et en crédits de paiement. Ce dispositif, mis en place pour six mois de janvier à juin 2012, est en extinction depuis le mois de juin. Or, le nombre estimatif d’aides (26 424), pour un coût moyen unitaire de 1 434 euros, semble surévalué. Il est donc proposé de réduire les crédits alloués à ce dispositif dont la mise en place répondait à une logique opportuniste. Le Fonds d’insertion professionnelle des jeunes (FIPJ) finance des actions complémentaires à l’accompagnement personnalisé et renforcé des jeunes confrontés à des obstacles multiples qui peuvent être des freins à leur insertion professionnelle (accès au logement, au transport, charges parentales…). Il finance des actions indirectes comme l’organisation de forums de l’emploi à destination des jeunes ou encore la levée des freins à la mobilité, mais également des aides directes (aide à l’achat de vêtement, à l’accès à un logement ou à des modalités de transport, garde d’enfants, etc…). S’agissant des aides indirectes, 15 millions d’euros sont prévus pour 2013, au même niveau que pour 2012. En revanche, s’agissant des aides directes, elles seront dotées en 2013 de 3,6 millions d’euros, contre 5 millions d’euros en 2012. Au regard de la priorité donnée par le Président de la République à la jeunesse, il serait dommageable de réduire les aides directes financées par le FIPJ. | L45: /14/amendements/0235C/AN/287.pdf | M45: Discuté | N45: Christophe Castaner | O45: SER | P45: Depute | Q45: Christophe Castaner
A46: 14 | B46: PRJLANR5L14B0235 | C46: 1ère lecture (1ère assemblée saisie) | D46: AMANR5L14SEA644420B0235P2D1N502 | E46: 2012-11-09T00:00:00Z | F46: =LEFT(E46,4) -> 2012 | G46: =RIGHT(LEFT(E46,7),2) -> 11 | H46: =F46&G46 -> 201211 | I46: Article 67 | J46: À l’alinéa 18, substituer au mot : « Au » les mots : « Aux première et deuxième phrases du ». | K46: Amendement rédactionnel. | L46: /14/amendements/0235C/AN/502.pdf | M46: Discuté | N46: Pascal Terrasse | O46: SER | P46: Depute | Q46: Pascal Terrasse
A47: 14 | B47: PRJLANR5L14B0235 | C47: 1ère lecture (1ère assemblée saisie) | D47: AMANR5L14SEA644420B0235P2D1N155 | E47: 2012-10-31T00:00:00Z | F47: =LEFT(E47,4) -> 2012 | G47: =RIGHT(LEFT(E47,7),2) -> 10 | H47: =F47&G47 -> 201210 | I47: Article 57 | J47: Après l’alinéa 22, insérer l’alinéa suivant : : « Toutefois, pour les logements acquis neufs ou en l’état futur d’achèvement par le contribuable ou que celui-ci fait construire, qui font l’objet d’une demande de permis de construire entre le 1er janvier 2011 et le 31 décembre 2012, et pour les autres logements qui font l’objet, au titre des travaux mentionnés aux b), c) et d) du 2 du I, d’un dépôt d’une demande de permis de construire entre ces mêmes dates, la réduction d’impôt s’applique aux logements situés dans toutes les communes visées au X de l’article 199 septvicies. » | K47: Le texte du gouvernement prévoit de réserver l’application du présent dispositif de défiscalisation aux communes situées dans les zones A, A bis et B1, ainsi qu’à certaines communes de la zone B2 en nombre très limité. Cela pose la question de la poursuite des programmes de logements engagés avant l’année 2013, sous le régime « Scellier » dans des communes de la zone B2 exclues du dispositif, qui risquent donc d’être abandonnés avant la mise en chantier. Il est donc proposé d’introduire une solution de transition pour permettre la réalisation effective des programmes de logements engagés en 2011 et 2012 en zone B2. | L47: /14/amendements/0235C/AN/155.pdf | M47: Retiré | N47: Christophe Caresche | O47: SER | P47: Depute | Q47: Christophe Caresche
A48: 14 | B48: PRJLANR5L14B0235 | C48: 1ère lecture (1ère assemblée saisie) | D48: AMANR5L14SEA644420B0235P2D1N176 | E48: 2012-10-31T00:00:00Z | F48: =LEFT(E48,4) -> 2012 | G48: =RIGHT(LEFT(E48,7),2) -> 10 | H48: =F48&G48 -> 201210 | I48: Article 59 | J48: Relations avec les collectivités territoriales Après l’article L. 2213-6-1 du code général des collectivités territoriales, il est inséré un article L. 2213-6-2 ainsi rédigé : « Art. L. 2213-6-2. - Dès la constatation d’une occupation du domaine public viaire en infraction aux dispositions de l’article L. 2213-6 du présent code ou de l’article L. 113-2 du code de la voirie routière ou des textes pris pour leur application, et nonobstant la prescription de l’infraction ou son amnistie, le maire ou le préfet prend un arrêté ordonnant, dans un délai qu’il détermine, soit la suppression, soit la mise en conformité avec ces dispositions, des installations et matériels en cause ainsi que, le cas échéant, la remise en état des lieux. « Cet arrêté est notifié à la personne, physique ou morale, responsable de cette installation en infraction. « À l’expiration du délai fixé par l’arrêté de mise en demeure, dont le point de départ se situe au jour de la notification de l’arrêté, la personne à qui il a été notifié est redevable d’une astreinte dont le montant unique, par jour et par mètre carré en infraction, a été établi préalablement par délibération en conseil municipal. Le montant de l’astreinte ne peut dépasser 500 euros par jour et par mètre carré en infraction. « L’astreinte est recouvrée, dans les conditions prévues par les dispositions relatives aux produits communaux, au bénéfice de la commune sur le territoire de laquelle ont été commis les faits constatés. « Le maire ou le préfet peut consentir une remise ou un reversement partiel du produit de l’astreinte lorsque les travaux prescrits par l’arrêté ont été exécutés et que le redevable établit qu’il n’a pu observer le délai imposé pour l’exécution totale de ses obligations qu’en raison de cas de force majeure ou de circonstances particulières et indépendantes de sa volonté. « Sans préjudice de l’application des dispositions précédentes, le maire ou le préfet fait, en quelque lieu que ce soit, exécuter d’office les travaux prescrits par l’arrêté, s’il n’a pas été procédé à leur exécution dans le délai fixé par cet arrêté. « Les frais de l’exécution d’office sont supportés par la personne à qui a été notifié l’arrêté. « Le maire ou le préfet adresse au procureur de la République copie de l’arrêté de mise en demeure et le tient immédiatement informé de la suite qui lui a été réservée. « Pour l’application des dispositions de cet article sont habilités à procéder à toutes constatations, outre les officiers de police judiciaire : « 1° Les agents de police judiciaire mentionnés aux articles 20 et 21 du code de procédure pénale ; « 2° Les fonctionnaires et agents habilités à constater les infractions au titre II du livre VI du code du patrimoine ; « 3° Les fonctionnaires et agents habilités à constater les infractions aux dispositions du code de la voirie routière ; « 4° Les fonctionnaires et agents publics habilités à constater les infractions au code de l’urbanisme ; « 5° Les fonctionnaires et agents publics habilités à constater les infractions au titre IV du livre III et au titre VIII du livre V du code de l’environnement ; « 6° Les agents de la ville de Paris mentionnés à l’article L. 2512-16 du présent code. « Les agents et fonctionnaires ci-dessus habilités pour constater les infractions transmettent leurs procès-verbaux de constatation au procureur de la République, au maire et au préfet. » | K48: Cet amendement vise à renforcer les sanctions applicables en cas d’occupation illégales du domaine public viaire, par la mise en œuvre d’astreintes administratives en cas d’installations illicites sur la voie publique. Il s’agit de prévoir la possibilité pour le maire ou le Préfet, en cas de constatation d’une occupation du domaine public viaire illégale, de prendre un arrêté ordonnant, dans un délai qu’il détermine, soit la suppression, soit la mise en conformité des installations et matériels en cause, ainsi que, le cas échéant, la remise en état des lieux. Cette disposition vise le « domaine public viaire », et s’appliquera donc notamment aux étalages et terrasses mais également à n’importe quel objet situé sur la voie publique et non autorisé, tels que les installations des personnes exerçants une activité commerciale sur la voie publique. | L48: /14/amendements/0235C/AN/176.pdf | M48: Irrecevable | N48: Christophe Caresche | O48: SER | P48: Depute | Q48: Christophe Caresche
A49: 14 | B49: PRJLANR5L14B0235 | C49: 1ère lecture (1ère assemblée saisie) | D49: AMANR5L14SEA644420B0235P2D1N270 | E49: 2012-11-06T00:00:00Z | F49: =LEFT(E49,4) -> 2012 | G49: =RIGHT(LEFT(E49,7),2) -> 11 | H49: =F49&G49 -> 201211 | I49: Article 66 | J49: Au 4° de l’article L. 211‑2 du code des juridictions financières, l’année : « 2013 » est remplacée par l’année : « 2012. » | K49: La loi n°2011-1862 relative à la répartition des contentieux et à l’allègement de certaines procédures juridictionnelles a modifié les seuils de l’apurement administratif des comptes des collectivités locales et de quelques autres structures locales, fixées à l’article L.211-2 du code des juridictions financières. Elle a rehaussé ces seuils pour transférer davantage de petits comptes locaux à l’apurement par le comptable supérieur de l’Etat. L’objectif poursuivi est de permettre aux chambres régionales des comptes (CRC) de concentrer leurs moyens sur l’apurement des comptes les plus importants, où sont les enjeux de contrôle, en l’occurrence sur les établissements publics locaux d’enseignement (EPLE) dont le montant des ressources de fonctionnement est supérieur à trois millions d’euros. Pour autant : le juge des comptes conserve toujours la faculté d’évoquer tous les comptes pour les apurer, y compris les plus petits le seuil de l’apurement administratif est absolument sans effet sur la sphère de compétence des CRC en matière de contrôle de la gestion. Une CRC peut programmer un examen de la gestion d’une collectivité dont les comptes sont apurés par le comptable supérieur de l’Etat exactement dans les mêmes conditions que pour une collectivité dont les comptes sont apurés directement par le juge des comptes. L’objet du présent amendement est d’avancer d’un an – des comptes de l’exercice 2013 à ceux de l’exercice 2012 – le transfert à l’apurement administratif des comptes des EPLE dont le montant des ressources de fonctionnement est inférieur à trois millions d’euros. Le principe de ce transfert figure déjà dans la loi du 13 décembre 2011. Sur un total de 8087 EPLE au plan national, l’apurement administratif des comptes en concernerait 7812, dès les comptes de l’exercice 2012, les CRC en conservant 275. L’anticipation est justifiée par le fait que, tant en raison des évolutions internes à la direction générale des finances publiques (DGFiP) qu’en raison du transfert à la DGFiP d’agents issus des CRC supprimées en 2012, et formés à cette pratique de l’apurement, les centres d’apurement que la DGFiP envisage de créer seront opérationnels plus rapidement qu’initialement prévu. | L49: /14/amendements/0235C/AN/270.pdf | M49: Irrecevable | N49: Dominique Lefebvre | O49: SER | P49: Depute | Q49: Dominique Lefebvre
A50: 14 | B50: PRJLANR5L14B0235 | C50: 1ère lecture (1ère assemblée saisie) | D50: AMANR5L14SEA644420B0235P2D1N540 | E50: 2012-11-09T00:00:00Z | F50: =LEFT(E50,4) -> 2012 | G50: =RIGHT(LEFT(E50,7),2) -> 11 | H50: =F50&G50 -> 201211 | I50: Article 67 | J50: À l’alinéa 11, supprimer les mots : « de la surtaxe sur les eaux minérales prévue à l’article 1582 du code général des impôts, ». | K50: L’objet de cet amendement est d’exclure du périmètre du potentiel fiscal et donc du potentiel financier des communes la surtaxe sur les eaux minérales prévue à l’article 1582 du code général des impôts. Cette proposition est motivée par des raisons voisines de celles qui avaient conduit à exclure la taxe sur les entreprises exploitant des engins de remontées mécaniques prévue aux articles L. 2333-49 à L. 2333-53 dans le cadre de l’examen du PLF 2012. En effet, de la même manière que la taxe sur les remontées mécaniques, cette taxe n’a pas pour objet d’élargir les marges de manœuvre financières de ces communes. La surtaxe sur les eaux minérales vient en effet financer des dépenses spécifiques supportées par ces communes qui bien souvent sont en même temps siège d’activités liées au thermalisme. La loi du 25/06/1920 en avait d’ailleurs réservé l’application aux villes qui avaient la qualité de stations thermales. Les débats parlementaires qui ont précédé son adoption, notamment ceux tenus lors de la séance du Sénat du 1er juin 1920, rappellent que les communes qui disposent d’établissements thermaux peuvent se trouver en situation financière délicate en raison de charges qu’elles doivent supporter à ce titre et « qui n’incombent pas aux autres communes ». Dans l’esprit du législateur, le produit de la surtaxe avait donc bien vocation à être affecté aux équipements de ces communes afin d’accueillir en période de saison, la part flottante de la population ainsi qu’au développement de leurs infrastructures thermales, touristiques et sportives. D’une manière générale, la situation économique de ces communes n’a pas changé dans le sens d’une plus grande profitabilité de cette surtaxe pour ces stations thermales depuis 1920. Il serait donc équitable par rapport aux communes touristiques de montagne d’exclure la surtaxe sur les eaux minérales de leur potentiel fiscal car elle n’augmente pas leurs marges financières mais permet simplement de contribuer très partiellement au financement des investissements et à la charge des emprunts qu’elles ont contractés à cet effet. En outre, le maintien de cette taxe dans le potentiel financier est d’autant plus injuste que la population prise en compte au dénominateur du potentiel financier par habitant ne prend pas en considération la clientèle des stations thermales mais la seule population résidente et celle des résidences secondaires. | L50: /14/amendements/0235C/AN/540.pdf | M50: Discuté | N50: Christian Franqueville | O50: SER | P50: Depute | Q50: Christian Franqueville
A51: 14 | B51: PRJLANR5L14B0235 | C51: 1ère lecture (1ère assemblée saisie) | D51: AMANR5L14SEA644420B0235P2D1N684 | E51: 2012-11-12T00:00:00Z | F51: =LEFT(E51,4) -> 2012 | G51: =RIGHT(LEFT(E51,7),2) -> 11 | H51: =F51&G51 -> 201211 | I51: Article 59 | J51: L’article 1635‑0 quinquies du code général des impôts est complété par une phrase ainsi rédigée : « Les tarifs sont actualisés annuellement par le coefficient voté en loi de finances et codifié à l’article 1518 bis ». | K51: Le présent article vise à introduire une actualisation des tarifs des Impositions Forfaitaires des Entreprises de Réseaux (IFER) fixés, en euros par éléments physique d’assiette, lors de leur création par les lois de finances initiales 2010 et 2011. L’actualisation annuelle consiste en une indexation sur le coefficient de revalorisation des valeurs locatives voté chaque année en loi de finances, corrélé implicitement à l’hypothèse d’inflation prévisionnelle retenue dans le Budget de l’État. | L51: /14/amendements/0235C/AN/684.pdf | M51: Discuté | N51: Alain Rousset | O51: SER | P51: Depute | Q51: Alain Rousset
A52: 14 | B52: PRJLANR5L14B0235 | C52: 1ère lecture (1ère assemblée saisie) | D52: AMANR5L14SEA644420B0235P1D1N229 | E52: 2012-10-12T00:00:00Z | F52: =LEFT(E52,4) -> 2012 | G52: =RIGHT(LEFT(E52,7),2) -> 10 | H52: =F52&G52 -> 201210 | I52: Article 33 | J52: Après le nombre : « 332 » », rédiger ainsi la fin de cet article : « , « 172 » et « 160 » sont respectivement remplacés par les montants : « 419 », « 239 » et « 180 ». ». | K52: Selon les éléments présentés dans le compte d’affectation spéciale « contrôle de la circulation et du stationnement routier » (CAS) annexé aux projets de loi de finances depuis 2011, il apparait que le produit des amendes perçu par la voie de systèmes automatiques de contrôle et sanction a augmenté de 16 % en 2012 (soit +75 M€). Cette augmentation a été répartie à hauteur de 20 M€ pour les programmes 751 et 752 et de 55 M€ pour l’Agence de financement des infrastructures de transport de France (AFITF), le montant affecté aux collectivités territoriales demeurant inchangé soit 160 M€. L’article 33 du PLF 2013, prévoit une nouvelle augmentation à hauteur de 47 M€ pour les programmes 751 et 752 et de 34 M€ pour AFITF par rapport à la LFI 2012 (soit +81 M€ au total). Le montant affecté aux collectivités territoriales demeure une nouvelle fois inchangé. Si l’augmentation de la somme affectée aux programmes 751 et 752 est argumentée dans l’évaluation du projet de loi de finances pour 2013, l’augmentation de celle affectée à l’AFITF ne fait l’objet d’aucune explication. En conséquence, cet amendement propose de répercuter une partie de l’augmentation prévue en 2013 sur le montant affecté aux collectivités territoriales. Celle affectée aux programmes 751 et 752 demeurant la même que dans l’article 33 initial. EN M€ LFI 2011 LFI 2012 PLF 2013 Variation 2012/2011 Variation 2013/2012 AFITF 125,3 180,3 214 44 % 19 % Source : Projet de loi de finances pour 2013 et les documents généraux annexés – évaluations préalables de l’article 33 du PLF 2013 | L52: /14/amendements/0235A/AN/229.pdf | M52: Discuté | N52: Pascal Terrasse | O52: SER | P52: Depute | Q52: Pascal Terrasse
A53: 14 | B53: PRJLANR5L14B0235 | C53: 1ère lecture (1ère assemblée saisie) | D53: AMANR5L14SEA644420B0235P2D1N716 | E53: 2012-11-12T00:00:00Z | F53: =LEFT(E53,4) -> 2012 | G53: =RIGHT(LEFT(E53,7),2) -> 11 | H53: =F53&G53 -> 201211 | I53: Article 57 | J53: À l’alinéa 7, après le mot : « publications » insérer les mots : « payantes ». | K53: Dix ans après le vote de la première taxe sur les imprimés non sollicités, l’amendement ayant pour objet de procéder à un ultime élargissement du champ de l’éco-contribution applicable à la filière des imprimés et papiers graphiques, à l’ensemble des publications de presse et aux livres, est pertinent. Aujourd’hui seule en effet la moitié des papiers collectés séparément en vue d’un recyclage (essentiellement les imprimés gratuits et les emballages cartonnés) sont assujettis à une REP. Le traitement de l’autre moitié (constituée de journaux et magazines et livres qui ne participent pas du tout à la gestion des déchets qu’ils génèrent) est entièrement financé par les impôts locaux. Si cette mesure de cohérence permettrait donc d’envisager enfin un périmètre quasi complet pour cette filière, il s’avère toutefois nécessaire de prévoir deux dérogations : une pour les imprimés de service public découlant d’une loi ou d’un règlement, mais également une autre pour la presse politique et d’information payante. Eu égard à la situation économique du secteur de cette presse, il paraît utile de prévoir pour ce secteur une dérogation au régime proposé par l’amendement 343, qui a pour objectif d’étendre le principe de la responsabilité élargie du producteur « papier », en intégrant dans ce dispositif les livres, les magazines et les journaux gratuits. | L53: /14/amendements/0235C/AN/716.pdf | M53: Discuté | N53: Florent Boudié | O53: SER | P53: Depute | Q53: Florent Boudié
A54: 14 | B54: PRJLANR5L14B0235 | C54: 1ère lecture (1ère assemblée saisie) | D54: AMANR5L14SEA644420B0235P1D1N230 | E54: 2012-10-12T00:00:00Z | F54: =LEFT(E54,4) -> 2012 | G54: =RIGHT(LEFT(E54,7),2) -> 10 | H54: =F54&G54 -> 201210 | I54: Article 10 | J54: Après l’alinéa 19, insérer l’alinéa suivant : 1° bis Après la première phrase du premier alinéa du I, est insérée une phrase ainsi rédigée : « Ce taux augmente de 0,2 % pour chaque année supplémentaire de détention jusqu’en 2020. ». | K54: Cet amendement vise à renforcer le mécanisme de lutte contre la rétention des ressources foncières par les propriétaires à partir du 1er janvier 2015 en rendant progressif le taux forfaitaire d’imposition sur le revenu des plus-values de cessions immobilières, avec une augmentation de 0,2% pour chaque année de détention supplémentaire. Le taux forfaitaire d’imposition atteindrait ainsi 20% en 2020, date à partir de laquelle le taux cesserait alors d’augmenter. | L54: /14/amendements/0235A/AN/230.pdf | M54: Discuté | N54: Audrey Linkenheld | O54: SER | P54: Depute | Q54: Audrey Linkenheld
A55: 14 | B55: PRJLANR5L14B0235 | C55: 1ère lecture (1ère assemblée saisie) | D55: AMANR5L14SEA644420B0235P1D1N12 | E55: 2012-10-09T00:00:00Z | F55: =LEFT(E55,4) -> 2012 | G55: =RIGHT(LEFT(E55,7),2) -> 10 | H55: =F55&G55 -> 201210 | I55: Article 4 | J55: I. – Le code général des impôts est ainsi modifié : 1° À la fin du VIII de l’article 244 quater O, les mots : « jusqu’au 31 décembre 2012 » sont supprimés ; 2° À l’article 49 septies ZL, les mots : « les opérations de conception » sont remplacés par les mots :« l’étude et/ou la réalisation ». II. – Les pertes de recettes pour l’État sont compensées à due concurrence par la création d’une taxe additionnelle aux droits visés aux articles 575 et 575 A du code général des impôts. | K55: Le crédit d’impôt en faveur des métiers d’art instauré dans le cadre de la loi de finances pour 2007 et reconduit jusqu’au 31 décembre 2012 pose des difficultés d’application importantes. À l’occasion de l’examen de la prorogation de cette mesure, il semble nécessaire de rappeler que parmi les entreprises artisanales, les métiers d’art occupent une place particulière : grâce à des activités à forte valeur ajoutée appuyées sur un savoir-faire ancien et toujours pointu, elles constituent une vitrine pour l’artisanat tout entier, participent au développement local et contribuent à valoriser l’image de la France. Le champ des métiers d’art est défini par l’arrêté du 12 décembre 2003 fixant la liste des métiers de l’artisanat d’art et couvrent 19 domaines d’activité : arts graphiques, bijouterie joaillerie, orfèvrerie et horlogerie, bois, cuir, facture instrumentale, jeux, luminaire, métal, mode, patrimoine, pierre, terre, textile, tradition, verre, art floral, arts du spectacle, arts et traditions populaires, arts mécaniques, jeux et jouets. Les entreprises industrielles des secteurs de l’horlogerie, de la bijouterie, de la joaillerie, de l’orfèvrerie, de la lunetterie, des arts de la table, du jouet, de la facture instrumentale et de l’ameublement ; représentent environ 136 000 entreprises. Au niveau économique, le secteur représente 38 000 entreprises au 1er janvier 2008, dont plus de 99 % sont des PME. Ces entreprises emploient près de 95 000 personnes et ont généré un chiffre d’affaires de 8 milliards d’euros en 2007 et un chiffre d’affaires total à l’export de 637 millions d’euros. Ces métiers tiennent un rôle essentiel dans la préservation du patrimoine architectural et culturel de notre pays avec les retombées induites en matière d’activités touristiques. Il est par conséquent nécessaire de permettre à ces entreprises de poursuivre leur développement et leur rayonnement sur le monde à travers la pérennisation du dispositif du crédit d’impôt en faveur des métiers d’art. Par ailleurs, les entreprises rencontrent d’énormes difficultés dans l’obtention du crédit d’impôt en faveur des métiers d’art. De multiples questions écrites évoquant les problèmes rencontrés ont été posées depuis 2010 et n’ont reçu aucune réponse des ministères concernés. Les services de vérification remettent en cause le bénéfice du crédit d’impôt à des entreprises des secteurs visées par l’arrêté du 12 décembre 2003 précité en retenant une définition restrictive de la notion de « conception de nouveaux produits ». En méconnaissance de l’esprit du dispositif visant à soutenir les métiers d’art, c’est-à-dire les métiers intensifs en main d’œuvre et de faible implication en recherche et développement, les services de contrôle réduisent l’assiette du crédit d’impôt métiers d’art : - Aux seuls salariés en charge du « travail intellectuel » préalable à la fabrication des produits (alors que pour les métiers d’art, « l’intelligence est au bout des doigts ») ; - Aux seules entreprises réalisant des produits non pas nouveaux (c’est-à-dire spécifiques et originaux se distinguant des produits standardisés) mais innovants (alors que l’innovation est difficilement conciliable avec des métiers traditionnels basés sur un savoir-faire. Il est patent que la plupart des entreprises spécialisées dans les métiers d’art réalisent des produits qui relèvent du même registre (ex : un escaliéteur réalise des escaliers), de la même gamme, des mêmes spécialités. Mais leurs créations évoluent constamment. Toute vision restrictive de la notion de « nouveaux produits » aboutit donc à méconnaître les conditions dans lesquelles elles travaillent et s’appliquent à offrir à leurs clients des créations toujours renouvelées dans le domaine et le registre qui constituent leur spécialité – ce qui implique en conséquence des permanences et des continuités. C’est pourquoi, il conviendrait d’une manière générale de remplacer le mot « conception » par « l’étude et/ou la réalisation » afin de ne pas circonscrire à une dimension purement intellectuelle le crédit d’impôt métiers d’art qui, par essence est censé bénéficier à des entreprises de petite ou moyenne taille non dotées d’un bureau d’études. Il faudrait également ajouter la prise en compte dans l’assiette de calcul du crédit d’impôt pour dépenses d’étude et de réalisation les rémunérations allouées aux dirigeants non-salariés qui participent personnellement aux travaux portant sur la mise au point des nouveaux produits. | L55: /14/amendements/0235A/AN/12.pdf | M55: Retiré | N55: Patrick Bloche | O55: SER | P55: Depute | Q55: Patrick Bloche
A56: 14 | B56: PRJLANR5L14B0235 | C56: 1ère lecture (1ère assemblée saisie) | D56: AMANR5L14SEA644420B0235P1D1N512 | E56: 2012-10-12T00:00:00Z | F56: =LEFT(E56,4) -> 2012 | G56: =RIGHT(LEFT(E56,7),2) -> 10 | H56: =F56&G56 -> 201210 | I56: Article 36 | J56: Rédiger ainsi cet article : « I. – À la fin du IV de l’article 65 de la loi n° 2010-1657 du 29 décembre 2010 de finances pour 2011, le montant : « 35 millions d'euros » est remplacé par le montant : « 80 millions d'euros » ». « II. – Au deuxième alinéa de l’article 302 bis ZB du code général des impôts, le montant : « 7,32 € » est remplacé par le montant : « 7,92 € » ». | K56: Cet amendement vise à réécrire l’article 36 du projet de loi de finances pour 2013 relatif à l’aménagement du compte d’affectation spéciale « Services nationaux de transport conventionnés de voyageurs », en vue : – d’augmenter le produit de la taxe d’aménagement du territoire (TAT) due par les sociétés concessionnaires d’autoroutes de 60 centimes d’euros pour 1 000 kilomètres parcourus ; – d’augmenter la limite du montant du produit de la TAT affecté au compte d’affectation spéciale (taxe instituée à l’article 302 bis ZB du code général des impôts). Le produit de la TAT est à la fois affecté au compte d’affectation spéciale « Services nationaux de transport conventionnés de voyageurs » dans la limite de 35 millions en vertu du IV de l’article 65 de la loi n°2010-1657 du 29 décembre 2010 de finances pour 2011 et à l’Agence de financement des infrastructures de transport de France (AFITF), pour un montant de 555 millions d’euros, en vertu du projet de loi de finances pour 2013. Pour 2013, les prévisions d’exécution des dépenses du compte d’affectation spéciale font apparaître un surcoût de 45 millions d’euros qui s’explique par : – le maintien de certaines dessertes dont la suppression était initialement prévue par la convention ; – la réévaluation de certaines charges facturées au prix réel concernant notamment les prestations spécifiques en gares et points d’arrêt ainsi que les soldes d’emprunts et de location du matériel roulant ; – la compensation du manque à gagner pour la SNCF résultant de majorations tarifaires au 1er janvier et au 1er août 2012, inférieures aux dispositions prévues par la convention. Il est donc proposé de relever le plafond du montant du produit de la TAT versée au compte d’affectation spéciale « Services nationaux de transport conventionnés de voyageurs » de 45 millions d’euros, au lieu de relever le plafond de la taxe sur le résultat des entreprises ferroviaires (TREF), due par les entreprises de service de transport ferroviaire de voyageurs ayant des activités de transport de voyageurs et dont le chiffre d’affaires soumis à la contribution de solidarité territoriale (CST) est supérieur à 300 millions d’euros (soit, aujourd’hui la SNCF). En effet, la SNCF participe en grande majorité au financement du compte d’affectation spéciale via la CST due par les entreprises de service de transport ferroviaire de voyageurs (90 millions d’euros pour 2012) et la TREF qui a déjà été relevée dans la loi de finances initiale pour 2012 (de 80 millions d’euros, soit 155 millions). Or, le chiffres d’affaires en 2010 des six sociétés d’autoroutes françaises - APRR, ASF, Cofiroute, Escota, Sanef, SAPN - dépassait les 8 milliards d’euros. Le relèvement de 45 millions d’euros du montant du produit de la TAT affecté au compte d’affectation spéciale doit s’accompagner d’un relèvement du tarif de la TAT afin d’augmenter son produit de 45 millions d’euros et ne pas diminuer la fraction de la TAT versée à l’AFITF. Ainsi, il est proposé d’augmenter de 60 centimes d’euros pour 1 000 kilomètres le produit de la TAT. | L56: /14/amendements/0235A/AN/512.pdf | M56: Discuté | N56: Olivier Faure | O56: SER | P56: Depute | Q56: Olivier Faure
A57: 14 | B57: PRJLANR5L14B0235 | C57: 1ère lecture (1ère assemblée saisie) | D57: AMANR5L14SEA644420B0235P2D1N492 | E57: 2012-11-09T00:00:00Z | F57: =LEFT(E57,4) -> 2012 | G57: =RIGHT(LEFT(E57,7),2) -> 11 | H57: =F57&G57 -> 201211 | I57: Article 68 | J57: Compléter cet article par l’alinéa suivant : « VII. – Avant le 1er juillet 2013, le Gouvernement transmet au Parlement un rapport évaluant l’application du fonds de solidarité des communes de la région Île-de-France. Ce rapport analyse les effets péréquateurs du fonds au regard de l’objectif de réduction des écarts de ressources entre les communes de la région Île-de-France. Il propose les modifications nécessaires en particulier quant aux critères de prélèvement et au niveau du plafonnement des contributions, afin de contribuer à réduire les inégalités entre les communes de la région Île-de-France. » | K57: Cet amendement vise à demander au Gouvernement de fournir aux parlementaires un rapport qui fera le point sur les résultats du dispositif du FSRIF pour les années 2012 et 2013. Ce rapport devra analyser les situations spécifiques nécessitant des mesures de correction du dispositif afin d’assurer plus d’équité : il étudiera notamment les impacts de la prise en compte d’un critère ou d’un indice de charges dans la détermination du prélèvement, ainsi que ceux d’un relèvement du plafonnement des contributions afin de trouver un équilibre dans la dynamique de celles-ci. Cet amendement est soutenu par Paris Métropole. | L57: /14/amendements/0235C/AN/492.pdf | M57: Discuté | N57: François Pupponi | O57: SER | P57: Depute | Q57: François Pupponi
... A90: 14 | B90: PRJLANR5L14B0235 | C90: 1ère lecture (1ère assemblée saisie) | D90: AMANR5L14SEA644420B0235P1D1N742 | E90: 2012-10-12T00:00:00Z | F90: =LEFT(E90,4) -> 2012 | G90: =RIGHT(LEFT(E90,7),2) -> 10 | H90: =F90&G90 -> 201210 | I90: Article 30 | J90: Les articles 1384 A, 1384 B, 1384 C, 1384 D et 1385 du code général des impôts sont complétés par un alinéa ainsi rédigé : « Par dérogation, dans le cadre du rachat groupé en novembre 2009 des logements de la société Icade, ancienne Société Centrale Immobilière de la Caisse des dépôts et consignations, les exonérations de taxe foncière sur les propriétés bâties ne sont plus applicables à compter du 1er janvier 2013. » | K90: En novembre 2009, environ 35 000 logements locatifs étaient cédés par la société Icade, filiale cotée de la Caisse des dépôts et consignations, à un consortium de 26 bailleurs sociaux mené par la Société Nationale Immobilière. Peu avant, à la suite notamment d'une mobilisation sans précédent de 36 maires d'Ile-de-France, le gouvernement d’alors s'engageait à compenser les exonérations de taxe foncière sur les propriétés bâties accordées à ces bailleurs lors d'acquisition en PLS, en déposant un amendement, adopté à l'unanimité à l'Assemblée nationale dans le cadre de la discussion du projet de loi de finances pour 2010. Mais du fait que les différentes compensations d'exonérations sont devenues, depuis l'entrée en application de la loi de finances pour 2009, des variables d'ajustement au sein de l'enveloppe normée des concours de l'Etat, le montant de cette compensation se trouve chaque année réduit par l'application d'un coefficient déflateur cumulé. En 2012, les exonérations de taxe foncière sur les propriétés bâties liées au patrimoine Icade n’ont été compensées qu'à 62%. Cet amendement vise donc à limiter la pénalisation financière des collectivités locales qui, accueillant l’ancien patrimoine immobilier d’Icade, contribuent activement au maintien d’une offre de logements accessibles aux ménages les plus fragiles, en supprimant cette exonération. | L90: /14/amendements/0235A/AN/742.pdf | M90: Irrecevable | N90: François Pupponi | O90: SER | P90: Depute | Q90: François Pupponi
A91: 14 | B91: PRJLANR5L14B0235 | C91: 1ère lecture (1ère assemblée saisie) | D91: AMANR5L14SEA644420B0235P2D1N468 | E91: 2012-11-09T00:00:00Z | F91: =LEFT(E91,4) -> 2012 | G91: =RIGHT(LEFT(E91,7),2) -> 11 | H91: =F91&G91 -> 201211 | I91: ÉTAT B | K91: Le tourisme représente 7% du PIB français. Il est le secteur qui contribue le plus au solde positif de la balance des paiements, loin devant l’agroalimentaire et l’industrie automobile. Il doit faire l’objet de politiques publiques cohérentes et adaptées. Sa disparition de la mission économie n’est donc pas acceptable et il nous paraît nécessaire de recréer un programme tourisme qui permette de savoir quels sont les crédits attribués au secteur et leur répartition. Les actions 20 «Financement des entreprises et attractivité du territoire» et 21 «Développement du tourisme» sont dès lors incluses dans le programme «Tourisme» ce qui constitue un déplacement des autorisations d’engagement et crédits de paiement à hauteur de 64 269 064 euros du programme «Développement des entreprises» vers le programme «Tourisme». Parmi les 64 269 064 euros, 19 700 000 euros proviennent de l’action 20 «Financement des entreprises et attractivité du territoire» et 44 569 064 euros de l’action «Développement du tourisme». En conséquence aucune dépense n’est ajouté puisqu’il s’agit juste d’une division de l’ancien programme 134 en deux programmes distincts l’un de l’autre afin de promouvoir le tourisme en France. | L91: /14/amendements/0235C/AN/468.pdf | M91: Irrecevable | N91: Pascal Terrasse | O91: SER | P91: Depute | Q91: Pascal Terrasse
A92: 14 | B92: PRJLANR5L14B0235 | C92: 1ère lecture (1ère assemblée saisie) | D92: AMANR5L14SEA644420B0235P2D1N506 | E92: 2012-11-09T00:00:00Z | F92: =LEFT(E92,4) -> 2012 | G92: =RIGHT(LEFT(E92,7),2) -> 11 | H92: =F92&G92 -> 201211 | I92: Article 67 | J92: Après l’alinéa 21, insérer l’alinéa suivant : « aa) À la dernière phrase du cinquième alinéa, après la référence : « 4° » est insérée la référence : « du I » ». | K92: Amendement de coordination. | L92: /14/amendements/0235C/AN/506.pdf | M92: Discuté | N92: Pascal Terrasse | O92: SER | P92: Depute | Q92: Pascal Terrasse
A93: 14 | B93: PRJLANR5L14B0235 | C93: 1ère lecture (1ère assemblée saisie) | D93: AMANR5L14SEA644420B0235P2D1N146 | E93: 2012-10-31T00:00:00Z | F93: =LEFT(E93,4) -> 2012 | G93: =RIGHT(LEFT(E93,7),2) -> 10 | H93: =F93&G93 -> 201210 | I93: Article 57 | J93: À l'alinéa 21, supprimer le mot « important ». | K93: Le projet du Gouvernement prévoit de conditionner l’éligibilité des communes de la zone B2 à un agrément délivré par le Préfet de région après avis du CRH. Cette disposition est certes destinée à assurer une bonne sélection des communes entrant dans le dispositif de défiscalisation mais cette procédure risque d’allonger considérablement les délais au moment où la construction doit justement être soutenue. Le présent amendement a pour objectif de rendre les communes actuelles de la zone B2 éligibles au dispositif dans l’attente d’une mise à jour du zonage. | L93: /14/amendements/0235C/AN/146.pdf | M93: Retiré | N93: Christophe Caresche | O93: SER | P93: Depute | Q93: Christophe Caresche
A94: 14 | B94: PRJLANR5L14B0235 | C94: 1ère lecture (1ère assemblée saisie) | D94: AMANR5L14SEA644420B0235P2D1N410 | E94: 2012-11-08T00:00:00Z | F94: =LEFT(E94,4) -> 2012 | G94: =RIGHT(LEFT(E94,7),2) -> 11 | H94: =F94&G94 -> 201211 | I94: Article 66 | J94: À l’alinéa 3, substituer aux mots : « (en qualité de contrepartie de contrat d’échange) », les mots : « en qualité de contrepartie de contrat d’échange ». | K94: Amendement rédactionnel. | L94: /14/amendements/0235C/AN/410.pdf | M94: Discuté | N94: Dominique Lefebvre | O94: SER | P94: Depute | Q94: Dominique Lefebvre
A95: 14 | B95: PRJLANR5L14B0235 | C95: 1ère lecture (1ère assemblée saisie) | D95: AMANR5L14SEA644420B0235P2D1N250 | E95: 2012-11-05T00:00:00Z | F95: =LEFT(E95,4) -> 2012 | G95: =RIGHT(LEFT(E95,7),2) -> 11 | H95: =F95&G95 -> 201211 | I95: ÉTAT B | K95: Si le dispositif des bourses au mérite est en voie d’extinction, il serait opportun de prévoir un dispositif à finalité différente qui consisterait à permettre l’attribution de bourses aux étudiants qui dès la troisième année (L3) s’engageraient à entrer dans l’enseignement secondaire à l’issue du master. L’attribution de ces bourses qui se ferait sur sélection et pourrait varier en fonction des ressources des étudiants permettrait de porter remède à la désertion relative des concours d’enseignement tout en permettant à des étudiants issus de tous milieux de mener leurs études supérieures dans de meilleures conditions. Ce dispositif prendrait le relais des emplois d’avenir institués par la loi du 26 octobre 2012. L'augmentation de 6 millions d'euros des crédits affectés à la vie étudiante (programme 231), pour une aide moyenne d’environ 10 000 euros par an, soit 833,33 euros par mois, pour 600 étudiants serait gagée sur une réduction des crédits prévus au bénéfice des instituts d’études politiques: action n° 02 (formation initiale et continue de niveau master) pour 4,2 millions d’euros et actions n°11 (recherche universitaire en sciences de l'homme et de la société) et n°12 (recherche universitaire interdisciplinaire et transversale) pour respectivement 1,2 millions d’euros et 600 000 euros. La réduction des crédits prévus pour la formation initiale et supérieure de niveau master permettrait de retrouver une certaine maitrise dans le fonctionnement de ces établissements, tout particulièrement Sciences Po Paris, notamment concernant les rémunérations de certains dirigeants, ou bien encore le coût d'un étudiant par an. La réduction des crédits prévus pour les formations supérieures et pour la recherche universitaire en sciences de l'homme et de la société (action n° 11) et recherche universitaire interdisciplinaire et transversale (action n° 12), que le projet de loi propose d'élever respectivement à 5,453 millions d'euros et 1,884 millions d'euros par an, sans justification claire, mettrait fin à une situation sans rapport dans la période actuelle avec les besoins réels de la recherche en ces domaines. Ces réductions constitueraient un premier pas vers une rectification de la situation anormale dont bénéficient ces établissements, tout particulièrement Sciences-Po Paris, dans l’attente des décisions à tirer des conclusions définitives du rapport de la Cour des comptes. | L95: /14/amendements/0235C/AN/250.pdf | M95: Discuté | N95: Marie-Françoise Bechtel | O95: SER | P95: Depute | Q95: Marie-Françoise Bechtel
A96: 14 | B96: PRJLANR5L14B0235 | C96: 1ère lecture (1ère assemblée saisie) | D96: AMANR5L14SEA644420B0235P2D1N711 | E96: 2012-11-12T00:00:00Z | F96: =LEFT(E96,4) -> 2012 | G96: =RIGHT(LEFT(E96,7),2) -> 11 | H96: =F96&G96 -> 201211 | I96: Article 59 | J96: Après le VI de l’article 1586 sexies du code général des impôts, il est inséré un VI bis ainsi rédigé : «VI bis. – Dans les mêmes conditions qu’aux V et VI, un complément est dû par les bénéfices non commerciaux afin que leur contribution économique territoriale définitive soit au minimum égale à 1,5 % de leur valeur ajoutée. ». | K96: En l’état actuel du droit, les Bénéfices Non Commerciaux (BNC) sont redevables de la CFE et de la CVAE suivant les strictes conditions de droit commun, suite à la censure par le Conseil constitutionnel n° 2009‑599 DC du 29 décembre 2009. Or, ces dispositions censurées qui tendaient à maintenir en CVAE les spécificités du régime fiscal de taxe professionnelle de ces entreprises ont entraîné un manque à gagner évalué de quelques 600 millions d’euros. Le plancher de CFE créé en loi de finances pour 2011, outre qu’il ne constitue pas une mesure propre à compenser cette perte, présente d’importantes difficultés d’application. Par conséquent, il est proposé d’instaurer un plancher de cotisation pour les BNC, sur la CET de préférence. Le produit supplémentaire reviendra aux collectivités locales bénéficiaires de la CET. La valeur du plancher reste à déterminer, suivant les informations spécifiques que la DLF pourra fournir au parlement (situation comparée TP 2009 et CET 2010 sur un échantillon représentatif de BNC). | L96: /14/amendements/0235C/AN/711.pdf | M96: Discuté | N96: Alain Rousset | O96: SER | P96: Depute | Q96: Alain Rousset
A97: 14 | B97: PRJLANR5L14B0235 | C97: 1ère lecture (1ère assemblée saisie) | D97: AMANR5L14SEA644420B0235P2D1N465 | E97: 2012-11-09T00:00:00Z | F97: =LEFT(E97,4) -> 2012 | G97: =RIGHT(LEFT(E97,7),2) -> 11 | H97: =F97&G97 -> 201211 | I97: Article 59 | J97: Au 4° de l’article L. 211‑2 du code des juridictions financières, l’année : « 2013 » est remplacée par l’année : « 2012 ». | K97: La loi n° 2011‑1862 relative à la répartition des contentieux et à l’allègement de certaines procédures juridictionnelles a modifié les seuils de l’apurement administratif des comptes des collectivités locales et de quelques autres structures locales, fixées à l’article L. 211‑2 du code des juridictions financières. Elle a rehaussé ces seuils pour transférer davantage de petits comptes locaux à l’apurement par le comptable supérieur de l’État. L’objectif poursuivi est de permettre aux chambres régionales des comptes (CRC) de concentrer leurs moyens sur l’apurement des comptes les plus importants, où sont les enjeux de contrôle, en l’occurrence sur les établissements publics locaux d’enseignement (EPLE) dont le montant des ressources de fonctionnement est supérieur à trois millions d’euros. Pour autant : - le juge des comptes conserve toujours la faculté d’évoquer tous les comptes pour les apurer, y compris les plus petits ; - le seuil de l’apurement administratif est absolument sans effet sur la sphère de compétence des CRC en matière de contrôle de la gestion. Une CRC peut programmer un examen de la gestion d’une collectivité dont les comptes sont apurés par le comptable supérieur de l’État exactement dans les mêmes conditions que pour une collectivité dont les comptes sont apurés directement par le juge des comptes. L’objet du présent amendement est d’avancer d’un an – des comptes de l’exercice 2013 à ceux de l’exercice 2012 – le transfert à l’apurement administratif des comptes des EPLE dont le montant des ressources de fonctionnement est inférieur à trois millions d’euros. Le principe de ce transfert figure déjà dans la loi du 13 décembre 2011. Sur un total de 8087 EPLE au plan national, l’apurement administratif des comptes en concernerait 7812, dès les comptes de l’exercice 2012, les CRC en conservant 275. L’anticipation est justifiée par le fait que, tant en raison des évolutions internes à la direction générale des finances publiques (DGFiP) qu’en raison du transfert à la DGFiP d’agents issus des CRC supprimées en 2012, et formés à cette pratique de l’apurement, les centres d’apurement que la DGFiP envisage de créer seront opérationnels plus rapidement qu’initialement prévu. Une convention à ce sujet a d’ailleurs été signée entre la Cour des comptes et la DGFiP. | L97: /14/amendements/0235C/AN/465.pdf | M97: Discuté | N97: Dominique Lefebvre | O97: SER | P97: Depute | Q97: Dominique Lefebvre
A98: 14 | B98: PRJLANR5L14B0235 | C98: 1ère lecture (1ère assemblée saisie) | D98: AMANR5L14SEA644420B0235P1D1N389 | E98: 2012-10-12T00:00:00Z | F98: =LEFT(E98,4) -> 2012 | G98: =RIGHT(LEFT(E98,7),2) -> 10 | H98: =F98&G98 -> 201210 | I98: Article 20 | J98: Après l’alinéa 15, insérer les deux alinéas suivants : « d) Il est ajouté un alinéa ainsi rédigé : « En 2013, le potentiel financier utilisé pour l’application du 1° est celui calculé pour l’année 2011. » | K98: Cet amendement vise à neutraliser pour 2013 l’impact de l’utilisation du nouveau potentiel financier (tel qu’issu de la réforme de la taxe professionnelle) sur le fonds de mobilisation pour l’insertion en 2013. | L98: /14/amendements/0235A/AN/389.pdf | M98: Discuté | N98: Pascal Terrasse | O98: SER | P98: Depute | Q98: Pascal Terrasse
A99: 14 | B99: PRJLANR5L14B0235 | C99: 1ère lecture (1ère assemblée saisie) | D99: AMANR5L14SEA644420B0235P2D1N288 | E99: 2012-11-06T00:00:00Z | F99: =LEFT(E99,4) -> 2012 | G99: =RIGHT(LEFT(E99,7),2) -> 11 | H99: =F99&G99 -> 201211 | I99: ÉTAT B | K99: Cet amendement vise à permettre de renforcer les crédits affectés à la gestion prévisionnelle des emplois et des compétences (GPEC). La GPEC permet en effet de développer une gestion anticipative et préventive des ressources humaines. Elle participe à la sécurisation des parcours professionnels en permettant une meilleure maîtrise des conséquences des changements technologiques et économiques. Elle permet notamment de renforcer l’offre de formations aux compétences requises à moyen et long terme au sein d’une entreprise ou d’une branche. La GPEC participe ainsi de la prévention en amont des licenciements. Dans ce cadre, le gouvernement incite les acteurs économiques à anticiper les restructurations et favoriser la reconversion des emplois menacés. Sur les 25 millions d’euros d’autorisations d’engagement inscrits au titre de la GPEC en PLF 2013, 19 millions d’euros seront déjà mobilisés pour des actions nationales de soutien à des filières stratégiques (automobile, textile-habillement cuir, grande distribution…). Dans ce cadre, le gouvernement incite les acteurs économiques à anticiper les restructurations et favoriser la reconversion des emplois menacés. Le rapporteur spécial propose d’inscrire 15 millions d’euros supplémentaires pour ce dispositif au sein du programme 103 en autorisations d’engagement et en crédits de paiement. Ces crédits seraient redéployés de l’action n°5 Soutien du programme 155 Conception, gestion et évaluation des politiques de l’emploi et du travail vers l’action n°1 Anticipation et accompagnement des conséquences des mutations économiques sur l’emploi du programme 103 Accompagnement des mutations économiques et développement de l’emploi. Dans une période d’accélération des mutations, il convient de donner à notre pays et à ses territoires les moyens d’éviter les ajustements brutaux pour limiter les licenciements et sécuriser l’emploi. Par ailleurs, plus que dans d’autres périodes, il est essentiel de pouvoir soutenir les filières stratégiques soumises à des exigences renforcées en termes de compétences. C’est bien sur un enjeu d’emploi pour les actifs de notre pays mais également un enjeu de compétitivité majeur pour nos entreprises. Le Rapporteur spécial souhaiterait que ces crédits supplémentaires puissent profiter prioritairement aux actions territoriales engagées par l’Etat en région en soutien aux politiques d’anticipation mises en œuvre en commun avec les Régions et les partenaires sociaux. Les budgets opérationnels de programme (BOP) territorial, gérés par les Directions régionales des entreprises, de la concurrence, de la consommation, du travail et de l'emploi (DIRECCTE) pourraient être renforcés à hauteur de 10 millions d’euros. Par ailleurs, en cohérence avec le séminaire gouvernemental sur la compétitivité, 5 millions d’euros pourraient être engagés pour mettre en place une dizaine de plateformes d’accompagnement spécialisées dans l’aide aux petites entreprises, afin de les aider à mieux anticiper les évolutions des métiers et des compétences, dans les bassins d’emploi en transition. Le rapporteur spécial regrette d’être contraint d’opérer un prélèvement sur le programme 155, programme support de la mission, et préférerait que le gouvernement s’engage à redéployer des crédits en gestion interne au profit de la GPEC, notamment à partir des crédits consacrés au dispositif expérimental « zéro charges » pour les très petites entreprises au titre de l’embauche d’un apprenti. Ce dispositif, mis en place pour six mois de janvier à juin 2012, est en extinction depuis le mois de juin dernier. Or, le nombre estimatif d’aides (26 424), pour un coût moyen unitaire de 1 434 euros, semble surévalué. Il pourrait donc être utile de réduire les crédits alloués à ce dispositif dont la mise en place répondait à une logique opportuniste. | L99: /14/amendements/0235C/AN/288.pdf | M99: Discuté | N99: Christophe Castaner | O99: SER | P99: Depute | Q99: Christophe Castaner
A100: 14 | B100: PRJLANR5L14B0235 | C100: 1ère lecture (1ère assemblée saisie) | D100: AMANR5L14SEA644420B0235P2D1N505 | E100: 2012-11-09T00:00:00Z | F100: =LEFT(E100,4) -> 2012 | G100: =RIGHT(LEFT(E100,7),2) -> 11 | H100: =F100&G100 -> 201211 | I100: Article 67 | J100: Après l’alinéa 20, insérer les quatre alinéas suivants : « 5° bis L'article L. 2334-7-1 est ainsi modifié : a) Au premier alinéa, après la référence : « 1° », la référence : « 4° » et la référence : « 3° », est insérée, par trois fois, la référence : « du I » ; b) Au dernier alinéa,après la référence : « 4° » et la référence : « 3° », est insérée, par deux fois, la référence : « du I » ; « 5° ter À l'article L. 2334-9, après la référence : « 1° », est insérée la référence : « du I » ; » | K100: Amendement de coordination. | L100: /14/amendements/0235C/AN/505.pdf | M100: Discuté | N100: Pascal Terrasse | O100: SER | P100: Depute | Q100: Pascal Terrasse
A101: 14 | B101: PRJLANR5L14B0235 | C101: 1ère lecture (1ère assemblée saisie) | D101: AMANR5L14SEA644420B0235P1D1N521 | E101: 2012-10-12T00:00:00Z | F101: =LEFT(E101,4) -> 2012 | G101: =RIGHT(LEFT(E101,7),2) -> 10 | H101: =F101&G101 -> 201210 | I101: Article 26 | J101: Après l'alinéa 31, insérer l'alinéa suivant : « 20° La quarante-quatrième ligne est supprimée ». | K101: Cet amendement vise à déplafonner la fraction de la taxe sur les bureaux en île-de-France qui est affectée à la SGP. En effet, le financement de la SGP repose, au-delà des dotations et subventions qui pourront lui être accordées, sur sa capacité à rembourser des emprunts à long terme. Ce mode de financement est courant pour les projets d’infrastructure, dont la période d’usage dépasse de beaucoup la période de conception et de construction. C’est pourquoi le modèle de financement de la SGP vise à lui donner une forte crédibilité auprès des investisseurs, qu’il s’agisse d’établissements de crédits ou d’investisseurs sur les marchés financiers. Cette crédibilité repose à la fois sur un soutien de l’État et sur la dynamique propre des taxes qui ont été levées pour le financement du projet. L’écrêtement prévu par l’article 46 de la loi de finances pour 2012, quoique d’un rendement modeste à ce stade pour le budget général, créée un précédent de nature à compromettre la capacité de la SGP à lever des fonds. En outre, l’État dispose des moyens de piloter le rythme de mise en œuvre du projet, donc la montée en puissance des dépenses de la SGP, puisqu’il contrôle l’établissement à travers la majorité dont il dispose au conseil de surveillance, auquel sont notamment soumis pour approbation le budget et les opérations d’investissement, et, plus généralement, par l’exercice de sa tutelle. Le déplafonnement des taxes affectées à la SGP est donc sans incidence sur la capacité du gouvernement à restaurer l’équilibre des dépenses publiques. | L101: /14/amendements/0235A/AN/521.pdf | M101: Irrecevable | N101: Alexis Bachelay | O101: SER | P101: Depute | Q101: Alexis Bachelay
A102: 14 | B102: PRJLANR5L14B0235 | C102: 1ère lecture (1ère assemblée saisie) | D102: AMANR5L14SEA644420B0235P2D1N507 | E102: 2012-11-09T00:00:00Z | F102: =LEFT(E102,4) -> 2012 | G102: =RIGHT(LEFT(E102,7),2) -> 11 | H102: =F102&G102 -> 201211 | I102: Article 67 | J102: Substituer aux alinéas 31 et 32 les quatre alinéas suivants : « 8° L’article L. 2334‑18‑3 est ainsi modifié : « a) Le deuxième alinéa est ainsi rédigé : « « Lorsqu’une commune cesse d’être éligible à la dotation à la suite d’une baisse de sa population en deçà du seuil minimal fixé au 2° de l’article L. 2334‑16, elle perçoit, à titre de garantie pour les trois exercices suivants, une attribution égale à 90 %, 75 % puis 50 % du montant perçu l’année précédant celle au titre de laquelle elle a perdu l’éligibilité. » ; « b) Au troisième alinéa, les mots : « douzième alinéa» sont remplacés par les mots : « 1. et 2. du II » ». | K102: Amendement rédactionnel. | L102: /14/amendements/0235C/AN/507.pdf | M102: Discuté | N102: Pascal Terrasse | O102: SER | P102: Depute | Q102: Pascal Terrasse
A103: 14 | B103: PRJLANR5L14B0235 | C103: 1ère lecture (1ère assemblée saisie) | D103: AMANR5L14SEA644420B0235P2D1N746 | E103: 2012-11-14T00:00:00Z | F103: =LEFT(E103,4) -> 2012 | G103: =RIGHT(LEFT(E103,7),2) -> 11 | H103: =F103&G103 -> 201211 | I103: Article 57 | J103: I. – Après l’alinéa 3, insérer les deux alinéas suivants : « 1 bis. La durée minimale de l’engagement de location prévue au premier alinéa du 1. du I est fixée à six ans; « 1 ter. Le nombre d’années mentionné au VII ou au 6. du VIII du présent article est fixé à six; » II. – Compléter cet amendement par l’alinéa suivant : « IV. – La perte de recettes pour l’État est compensée à due concurrence par la création d’une taxe additionnelle aux droits visés aux articles 575 et 575 A du code général des impôts. » | K103: Le sous-amendement vise à compléter les dispositions introduites par l'amendement 644 de Serge Letchimy et de Jean-Claude Fruteau en réduisant la durée de location de neuf à six ans. Dans les départements et collectivités d'outre-mer,la construction de logements se heurte à des difficultés propres à ces territoires du fait d'un isolement relatif expliquant un prix élevé des matières premières, le manque de ressources des collectivités locales et la rareté du foncier. Il s'agit donc de renforcer les mécanismes visant à accroître l'attractivité du logement locatif intermédiaire neuf dont les surcoûts de la construction et l'appréciation des risques peuvent dissuader certains investissements. | L103: /14/amendements/0235C/AN/746.pdf | M103: Discuté | N103: Boinali Said | O103: SER | P103: Depute | Q103: Boinali Said
A104: 14 | B104: PRJLANR5L14B0235 | C104: 1ère lecture (1ère assemblée saisie) | D104: AMANR5L14SEA644420B0235P2D1N523 | E104: 2012-11-09T00:00:00Z | F104: =LEFT(E104,4) -> 2012 | G104: =RIGHT(LEFT(E104,7),2) -> 11 | H104: =F104&G104 -> 201211 | I104: Article 68 | J104: Substituer à l’alinéa 11 les deux alinéas suivants : « 2° bis Les cinq derniers alinéas du I sont supprimés ; « 3° Le II est remplacé par des II à IV ainsi rédigés : ». | K104: Amendement rédactionnel. | L104: /14/amendements/0235C/AN/523.pdf | M104: Discuté | N104: Pascal Terrasse | O104: SER | P104: Depute | Q104: Pascal Terrasse
