Workbook

Sheet openrefine_asso2016-2017
A1: Année | B1: nom des bénéficiaires | C1: Montant du fonds de concours ou de la subvention (numéraire) | D1: Prestations en nature
A2: 2016 | B2: OPERA NATIONAL DE BORDEAUX | C2: 16167670 | E2: =MATCH(B2,'Copy of webscraper_bordeauxasso'!B:B,0) -> #N/A
A3: 2016 | B3: ASSOCIATION DES CENTRES D'ANIMATION DE QUARTIERS DE BORDEAUX - ACAQB | C3: 8060927.5 | D3: Communication, locaux, équipements sportifs, | E3: =MATCH(B3,'Copy of webscraper_bordeauxasso'!B:B,0) -> #N/A
A4: 2016 | B4: CCAS DE BORDEAUX | C4: 7912204 | E4: =MATCH(B4,'Copy of webscraper_bordeauxasso'!B:B,0) -> #N/A
A5: 2016 | B5: ECOLE D'ENSEIGNEMENT SUPERIEUR D'ART DE BORDEAUX - ESAB | C5: 3120000 | E5: =MATCH(B5,'Copy of webscraper_bordeauxasso'!B:B,0) -> #N/A
A6: 2016 | B6: ASSOCIATION PITCHOUN | C6: 1735000 | D6: Locaux | E6: =MATCH(B6,'Copy of webscraper_bordeauxasso'!B:B,0) -> #N/A
A7: 2016 | B7: THEATRE NATIONAL DE BORDEAUX EN AQUITAINE - TNBA | C7: 1646816 | D7: Communication, locaux | E7: =MATCH(B7,'Copy of webscraper_bordeauxasso'!B:B,0) -> #N/A
A8: 2016 | B8: ASSOCIATION PETITE ENFANCE ENFANCE ET FAMILLE - APEEF | C8: 1578403 | D8: Locaux, matériel pour manifestations | E8: =MATCH(B8,'Copy of webscraper_bordeauxasso'!B:B,0) -> #N/A
A9: 2016 | B9: UNION SAINT-BRUNO | C9: 1537650 | D9: Locaux, équipements sportifs, matériel pour | E9: =MATCH(B9,'Copy of webscraper_bordeauxasso'!B:B,0) -> #N/A
A10: 2016 | B10: SPORTING CHANTECLER BORDEAUX NORD LE LAC | C10: 1128560 | D10: Locaux, équipements sportifs, matériel pour | E10: =MATCH(B10,'Copy of webscraper_bordeauxasso'!B:B,0) -> #N/A
A11: 2016 | B11: AVANT GARDE ET JEANNE D'ARC DE BORDEAUX CAUDERAN - AGJA BORDEAUX CAUDERAN | C11: 1089439 | D11: Locaux, équipements sportifs, matériel pour | E11: =MATCH(B11,'Copy of webscraper_bordeauxasso'!B:B,0) -> #N/A
A12: 2016 | B12: UNION SPORTIVE LES CHARTRONS | C12: 896350 | D12: Locaux, équipements sportifs, matériel pour | E12: =MATCH(B12,'Copy of webscraper_bordeauxasso'!B:B,0) -> #N/A
A13: 2016 | B13: LES JEUNES DE SAINT AUGUSTIN - JSA | C13: 892663 | D13: Locaux, équipements sportifs, matériel pour | E13: =MATCH(B13,'Copy of webscraper_bordeauxasso'!B:B,0) -> #N/A
A14: 2016 | B14: UNION SAINT JEAN - MAISON DE QUARTIER | C14: 879983 | D14: Locaux, équipements sportifs, matériel pour | E14: =MATCH(B14,'Copy of webscraper_bordeauxasso'!B:B,0) -> #N/A
A15: 2016 | B15: STADE BORDELAIS - ASPTT | C15: 819458 | D15: Locaux, équipements sportifs, matériel pour | E15: =MATCH(B15,'Copy of webscraper_bordeauxasso'!B:B,0) -> #N/A
A16: 2016 | B16: ARC EN REVE | C16: 752250 | D16: Communication, matériel pour manifestations, locaux | E16: =MATCH(B16,'Copy of webscraper_bordeauxasso'!B:B,0) -> #N/A
A17: 2016 | B17: MAISON DE L'EMPLOI, DE L'INSERTION ECONOMIQUE ET DE L'ENTREPRISE DE BORDEAUX | C17: 678000 | E17: =MATCH(B17,'Copy of webscraper_bordeauxasso'!B:B,0) -> #N/A
A18: 2016 | B18: CLUB PYRENEES AQUITAINE, ASSOCIATION SPORTIVE, EDUCATIVE ET CULTURELLE | C18: 634600 | D18: Locaux, équipements sportifs, matériel pour | E18: =MATCH(B18,'Copy of webscraper_bordeauxasso'!B:B,0) -> #N/A
A19: 2016 | B19: P'TIT BOUT'CHOU | C19: 567000 | D19: Matériel pour manifestations | E19: =MATCH(B19,'Copy of webscraper_bordeauxasso'!B:B,0) -> #N/A
A20: 2016 | B20: ASSOCIATION BRINS D'EVEIL | C20: 532800 | E20: =MATCH(B20,'Copy of webscraper_bordeauxasso'!B:B,0) -> #N/A
A21: 2016 | B21: ASSOCIATION DE GESTION ET D'ANIMATION DES CRECHES C.S.F. (AGEAC/CSF) | C21: 512833.33 | E21: =MATCH(B21,'Copy of webscraper_bordeauxasso'!B:B,0) -> #N/A
A22: 2016 | B22: MISSION LOCALE BORDEAUX AVENIR JEUNES | C22: 494000 | D22: Locaux, matériel pour manifestations | E22: =MATCH(B22,'Copy of webscraper_bordeauxasso'!B:B,0) -> #N/A
A23: 2016 | B23: GP INTENCITE CENTRE SOCIAL ET CULTUREL DU GRAND PARC | C23: 492222 | D23: Locaux, matériel pour manifestations | E23: =MATCH(B23,'Copy of webscraper_bordeauxasso'!B:B,0) -> #N/A
A24: 2016 | B24: INTERLUDE | C24: 478850 | D24: Locaux, matériel pour manifestations | E24: =MATCH(B24,'Copy of webscraper_bordeauxasso'!B:B,0) -> #N/A
A25: 2016 | B25: CENTRE SOCIAL ET FAMILIAL BORDEAUX NORD | C25: 461165 | D25: Locaux, équipements sportifs, matériel pour | E25: =MATCH(B25,'Copy of webscraper_bordeauxasso'!B:B,0) -> #N/A
A26: 2016 | B26: AMICALE LAIQUE DAVID JOHNSTON LAGRANGE ALBERT BARRAUD NAUJAC | C26: 450195 | D26: Equipements sportifs | E26: =MATCH(B26,'Copy of webscraper_bordeauxasso'!B:B,0) -> #N/A
A27: 2016 | B27: SASP UNION BORDEAUX BEGLES | C27: 450000 | D27: Matériel pour manifestations | E27: =MATCH(B27,'Copy of webscraper_bordeauxasso'!B:B,0) -> #N/A
A28: 2016 | B28: FOYER FRATERNEL | C28: 426565 | D28: Locaux, matériel pour manifestations | E28: =MATCH(B28,'Copy of webscraper_bordeauxasso'!B:B,0) -> #N/A
A29: 2016 | B29: FESTIVAL DES ARTS DE BORDEAUX | C29: 402000 | D29: Communication, locaux | E29: =MATCH(B29,'Copy of webscraper_bordeauxasso'!B:B,0) -> #N/A
A30: 2016 | B30: ASSOCIATION DU COMITE DES OEUVRES SOCIALES DES MUNICIPAUX DE BORDEAUX - ACOSMB | C30: 380000 | D30: Matériel pour manifestations | E30: =MATCH(B30,'Copy of webscraper_bordeauxasso'!B:B,0) -> #N/A
A31: 2016 | B31: POLE D'ENSEIGNEMENT SUPERIEUR DE LA MUSIQUE ET DE LA DANSE DE BORDEAUX AQUITAINE - PESMD | C31: 357672 | D31: Locaux | E31: =MATCH(B31,'Copy of webscraper_bordeauxasso'!B:B,0) -> #N/A
A32: 2016 | B32: AUTEUIL PETITE ENFANCE | C32: 347000 | E32: =MATCH(B32,'Copy of webscraper_bordeauxasso'!B:B,0) -> #N/A
A33: 2016 | B33: LES COQS ROUGES | C33: 343924 | D33: Equipements sportifs, matériel pour manifestations | E33: =MATCH(B33,'Copy of webscraper_bordeauxasso'!B:B,0) -> #N/A
A34: 2016 | B34: BORDEAUX GRANDS EVENEMENTS (BGE) | C34: 339500 | D34: Communication, locaux | E34: =MATCH(B34,'Copy of webscraper_bordeauxasso'!B:B,0) -> #N/A
A35: 2016 | B35: GESTION DU CENTRE DE LOISIRS DE LA POSTE ALEMA | C35: 334000 | E35: =MATCH(B35,'Copy of webscraper_bordeauxasso'!B:B,0) -> #N/A
A36: 2016 | B36: ASSOCIATION PETITS BOUCHONS | C36: 311500 | E36: =MATCH(B36,'Copy of webscraper_bordeauxasso'!B:B,0) -> #N/A
A37: 2016 | B37: ASSOCIATION POUR L'INNOVATION EN MATIERE D'INTEGRATION | C37: 300000 | E37: =MATCH(B37,'Copy of webscraper_bordeauxasso'!B:B,0) -> #N/A
A38: 2016 | B38: BOXERS DE BORDEAUX | C38: 283000 | E38: =MATCH(B38,'Copy of webscraper_bordeauxasso'!B:B,0) -> #N/A
A39: 2016 | B39: SASP JSA BORDEAUX METROPOLE | C39: 280000 | D39: Matériel pour manifestations | E39: =MATCH(B39,'Copy of webscraper_bordeauxasso'!B:B,0) -> #N/A
A40: 2016 | B40: CLUB ATHLETIQUE MUNICIPAL DE BORDEAUX - CAM | C40: 243834 | D40: Locaux, équipements sportifs, matériel pour | E40: =MATCH(B40,'Copy of webscraper_bordeauxasso'!B:B,0) -> #N/A
A41: 2016 | B41: LES ENFANTS D'OSIRIS | C41: 240000 | E41: =MATCH(B41,'Copy of webscraper_bordeauxasso'!B:B,0) -> #N/A
A42: 2016 | B42: PARALLELES ATTITUDES DIFFUSION - ROCKSCHOOL | C42: 237000 | D42: Locaux, matériel pour manifestations, matériel | E42: =MATCH(B42,'Copy of webscraper_bordeauxasso'!B:B,0) -> #N/A
A43: 2016 | B43: BORDEAUX ETUDIANTS CLUB - BEC | C43: 223734 | D43: Locaux, équipements sportifs, matériel pour | E43: =MATCH(B43,'Copy of webscraper_bordeauxasso'!B:B,0) -> #N/A
A44: 2016 | B44: EVEILLEZ LES BEBES | C44: 210000 | E44: =MATCH(B44,'Copy of webscraper_bordeauxasso'!B:B,0) -> #N/A
A45: 2016 | B45: LES PARENTS DE CAUDERAN | C45: 205000 | E45: =MATCH(B45,'Copy of webscraper_bordeauxasso'!B:B,0) -> #N/A
A46: 2016 | B46: LUCILANN | C46: 200000 | E46: =MATCH(B46,'Copy of webscraper_bordeauxasso'!B:B,0) -> #N/A
A47: 2016 | B47: BORDEAUX GIRONDE INVESTISSEMENT | C47: 198775 | D47: Matériel pour manifestations | E47: =MATCH(B47,'Copy of webscraper_bordeauxasso'!B:B,0) -> #N/A
A48: 2016 | B48: LA MANUFACTURE ATLANTIQUE | C48: 198000 | D48: Communication, locaux, matériel pour | E48: =MATCH(B48,'Copy of webscraper_bordeauxasso'!B:B,0) -> #N/A
A49: 2016 | B49: GROUPEMENT D'INTERET PUBLIC BORDEAUX MEDIATION | C49: 190000 | E49: =MATCH(B49,'Copy of webscraper_bordeauxasso'!B:B,0) -> #N/A
A50: 2016 | B50: ESCALES LITTERAIRES BORDEAUX AQUITAINE | C50: 185000 | D50: Communication, locaux, matériel pour manifestations | E50: =MATCH(B50,'Copy of webscraper_bordeauxasso'!B:B,0) -> #N/A
A51: 2016 | B51: ASSOCIATION LA COCCINELLE | C51: 180000 | E51: =MATCH(B51,'Copy of webscraper_bordeauxasso'!B:B,0) -> #N/A
A52: 2016 | B52: O'PTIMOMES LOISIRS | C52: 170592 | E52: =MATCH(B52,'Copy of webscraper_bordeauxasso'!B:B,0) -> #N/A
A53: 2016 | B53: ASTROLABE | C53: 153407 | D53: Locaux, matériel pour manifestations | E53: =MATCH(B53,'Copy of webscraper_bordeauxasso'!B:B,0) -> 82
A54: 2016 | B54: GIRONDINS DE BORDEAUX BASTIDE HANDBALL CLUB | C54: 141174 | D54: Locaux, équipements sportifs, matériel pour | E54: =MATCH(B54,'Copy of webscraper_bordeauxasso'!B:B,0) -> #N/A
A55: 2016 | B55: LES GIRONDINS DE BORDEAUX | C55: 132000 | D55: Locaux, équipements sportifs, matériel pour | E55: =MATCH(B55,'Copy of webscraper_bordeauxasso'!B:B,0) -> #N/A
A56: 2016 | B56: NUAGE BLEU | C56: 130000 | D56: Locaux | E56: =MATCH(B56,'Copy of webscraper_bordeauxasso'!B:B,0) -> #N/A
A57: 2016 | B57: OGEC LYCEE BEL ORME | C57: 120000 | E57: =MATCH(B57,'Copy of webscraper_bordeauxasso'!B:B,0) -> #N/A
A58: 2016 | B58: LA RONDE DES QUARTIERS DE BORDEAUX | C58: 119100 | D58: Communication, locaux, matériel pour manifestations | E58: =MATCH(B58,'Copy of webscraper_bordeauxasso'!B:B,0) -> 596
A59: 2016 | B59: VILLA PRIMROSE | C59: 119000 | D59: Communication, équipements sportifs, matériel pour | E59: =MATCH(B59,'Copy of webscraper_bordeauxasso'!B:B,0) -> #N/A
A60: 2016 | B60: EMULATION NAUTIQUE DE BORDEAUX | C60: 118603 | D60: Locaux, équipements sportifs, matériel pour | E60: =MATCH(B60,'Copy of webscraper_bordeauxasso'!B:B,0) -> #N/A
A61: 2016 | B61: CAISSE SOCIALE DE DEVELOPPEMENT LOCAL | C61: 115000 | E61: =MATCH(B61,'Copy of webscraper_bordeauxasso'!B:B,0) -> #N/A
A62: 2016 | B62: COS VILLA PIA - EHPAD LES DAMES DE LA FOI | C62: 115000 | D62: Matériel pour manifestations | E62: =MATCH(B62,'Copy of webscraper_bordeauxasso'!B:B,0) -> #N/A
A63: 2016 | B63: GLOB THEATRE | C63: 115000 | D63: Locaux, matériel pour manifestations | E63: =MATCH(B63,'Copy of webscraper_bordeauxasso'!B:B,0) -> #N/A
A64: 2016 | B64: MAISON DES JEUNES ET DE LA CULTURE CENTRE DE LOISIRS DES DEUX VILLES - MJC CL2V | C64: 110350 | D64: Matériel pour manifestations | E64: =MATCH(B64,'Copy of webscraper_bordeauxasso'!B:B,0) -> #N/A
A65: 2016 | B65: ECOLE SUPERIEURE DE THEATRE BORDEAUX AQUITAINE - ESTBA | C65: 109834 | E65: =MATCH(B65,'Copy of webscraper_bordeauxasso'!B:B,0) -> #N/A
A66: 2016 | B66: UNIS CITE | C66: 105000 | D66: Locaux, matériel pour manifestations | E66: =MATCH(B66,'Copy of webscraper_bordeauxasso'!B:B,0) -> #N/A
A67: 2016 | B67: FOOTBALL CLUB DES GIRONDINS DE BORDEAUX - FCGB | C67: 100000 | D67: Equipements sportifs | E67: =MATCH(B67,'Copy of webscraper_bordeauxasso'!B:B,0) -> #N/A
A68: 2016 | B68: UNION BORDEAUX METROPOLE - UBM | C68: 83680 | D68: Locaux, équipements sportifs | E68: =MATCH(B68,'Copy of webscraper_bordeauxasso'!B:B,0) -> #N/A
A69: 2016 | B69: AMICALE DES ETABLISSEMENTS SCOLAIRES LAIQUES DE BACALAN - ALB | C69: 82238 | D69: Locaux, équipements sportifs, matériel pour | E69: =MATCH(B69,'Copy of webscraper_bordeauxasso'!B:B,0) -> #N/A
A70: 2016 | B70: CAP SCIENCES | C70: 81568 | E70: =MATCH(B70,'Copy of webscraper_bordeauxasso'!B:B,0) -> 311
A71: 2016 | B71: BORDEAUX MERIGNAC VOLLEY | C71: 80000 | D71: Equipements sportifs | E71: =MATCH(B71,'Copy of webscraper_bordeauxasso'!B:B,0) -> #N/A
A72: 2016 | B72: LA HALLE DES DOUVES | C72: 80000 | D72: Locaux | E72: =MATCH(B72,'Copy of webscraper_bordeauxasso'!B:B,0) -> #N/A
A73: 2016 | B73: SOLIHA, SOLIDAIRES POUR L'HABITAT, GIRONDE | C73: 73900 | D73: Locaux | E73: =MATCH(B73,'Copy of webscraper_bordeauxasso'!B:B,0) -> #N/A
A74: 2016 | B74: SEMER LE DOUTE | C74: 73250 | D74: Communication, locaux, matériel pour | E74: =MATCH(B74,'Copy of webscraper_bordeauxasso'!B:B,0) -> #N/A
A75: 2016 | B75: HALTE 33 | C75: 66000 | E75: =MATCH(B75,'Copy of webscraper_bordeauxasso'!B:B,0) -> #N/A
A76: 2016 | B76: RESEAU PAUL BERT CENTRE SOCIAL ET CULTUREL | C76: 64000 | E76: =MATCH(B76,'Copy of webscraper_bordeauxasso'!B:B,0) -> #N/A
A77: 2016 | B77: AGENCE D'URBANISME BORDEAUX METROPOLE AQUITAINE (A'URBA) | C77: 60000 | E77: =MATCH(B77,'Copy of webscraper_bordeauxasso'!B:B,0) -> #N/A
A78: 2016 | B78: CHAHUTS | C78: 57500 | D78: Communication, locaux, matériel pour manifestations | E78: {=INDEX(MATCH(B78,'Copy of webscraper_bordeauxasso'!B:B,0),0)} -> 179 | F78: {=INDEX('Copy of webscraper_bordeauxasso'!G:G,MATCH(B78,'Copy of webscraper_bordeauxasso'!B:B,0))} -> François Pouthier
A79: 2016 | B79: LA CAISSE A OUTILS | C79: 57005 | E79: =MATCH(B79,'Copy of webscraper_bordeauxasso'!B:B,0) -> #N/A | F79: {=INDEX('Copy of webscraper_bordeauxasso'!G:G,MATCH(B79,'Copy of webscraper_bordeauxasso'!B:B,0))} -> #N/A
A80: 2016 | B80: LA MEMOIRE DE BORDEAUX METROPOLE | C80: 56105 | D80: Locaux, matériel informatique | E80: =MATCH(B80,'Copy of webscraper_bordeauxasso'!B:B,0) -> #N/A | F80: {=INDEX('Copy of webscraper_bordeauxasso'!G:G,MATCH(B80,'Copy of webscraper_bordeauxasso'!B:B,0))} -> #N/A
A81: 2016 | B81: MAISON DE L'EUROPE BORDEAUX-AQUITAINE (MEBA) | C81: 56000 | D81: Locaux | E81: =MATCH(B81,'Copy of webscraper_bordeauxasso'!B:B,0) -> #N/A | F81: {=INDEX('Copy of webscraper_bordeauxasso'!G:G,MATCH(B81,'Copy of webscraper_bordeauxasso'!B:B,0))} -> #N/A
A82: 2016 | B82: ASSOCIATION LAIQUE LE PRADO | C82: 55000 | E82: =MATCH(B82,'Copy of webscraper_bordeauxasso'!B:B,0) -> #N/A | F82: {=INDEX('Copy of webscraper_bordeauxasso'!G:G,MATCH(B82,'Copy of webscraper_bordeauxasso'!B:B,0))} -> #N/A
A83: 2016 | B83: LES PETITS DEBROUILLARDS AQUITAINE | C83: 54201 | D83: Matériel pour manifestations | E83: =MATCH(B83,'Copy of webscraper_bordeauxasso'!B:B,0) -> #N/A | F83: {=INDEX('Copy of webscraper_bordeauxasso'!G:G,MATCH(B83,'Copy of webscraper_bordeauxasso'!B:B,0))} -> #N/A
A84: 2016 | B84: FONDATION D'AUTEUIL AQUITAINE | C84: 52500 | D84: Locaux | E84: =MATCH(B84,'Copy of webscraper_bordeauxasso'!B:B,0) -> #N/A | F84: {=INDEX('Copy of webscraper_bordeauxasso'!G:G,MATCH(B84,'Copy of webscraper_bordeauxasso'!B:B,0))} -> #N/A
A85: 2016 | B85: THEATRE DU PONT TOURNANT | C85: 52250 | E85: =MATCH(B85,'Copy of webscraper_bordeauxasso'!B:B,0) -> #N/A | F85: {=INDEX('Copy of webscraper_bordeauxasso'!G:G,MATCH(B85,'Copy of webscraper_bordeauxasso'!B:B,0))} -> #N/A
A86: 2016 | B86: REGIE DE QUARTIER HABITER BACALAN | C86: 51000 | D86: Locaux | E86: =MATCH(B86,'Copy of webscraper_bordeauxasso'!B:B,0) -> #N/A | F86: {=INDEX('Copy of webscraper_bordeauxasso'!G:G,MATCH(B86,'Copy of webscraper_bordeauxasso'!B:B,0))} -> #N/A
A87: 2016 | B87: ASSOCIATION DE DEFENSE DES MUSIQUES ALTERNATIVES EN AQUITAINE - ADMAA (ALLEZ LES FILLES) | C87: 50580 | D87: Communication, matériel pour manifestations | E87: =MATCH(B87,'Copy of webscraper_bordeauxasso'!B:B,0) -> #N/A | F87: {=INDEX('Copy of webscraper_bordeauxasso'!G:G,MATCH(B87,'Copy of webscraper_bordeauxasso'!B:B,0))} -> #N/A
A88: 2016 | B88: ASSOCIATION UNION BORDEAUX BEGLES | C88: 50000 | D88: Matériel pour manifestations | F88: {=INDEX('Copy of webscraper_bordeauxasso'!G:G,MATCH(B88,'Copy of webscraper_bordeauxasso'!B:B,0))} -> #N/A
A89: 2016 | B89: LA CITE DU VIN | C89: 50000 | F89: {=INDEX('Copy of webscraper_bordeauxasso'!G:G,MATCH(B89,'Copy of webscraper_bordeauxasso'!B:B,0))} -> #N/A
A90: 2016 | B90: LE SERVICE GAGNANT | C90: 50000 | F90: {=INDEX('Copy of webscraper_bordeauxasso'!G:G,MATCH(B90,'Copy of webscraper_bordeauxasso'!B:B,0))} -> #N/A
A91: 2016 | B91: MAIRES RESPONSABLES METROPOLES FRANCOPHONES - AIMF | C91: 50000 | F91: {=INDEX('Copy of webscraper_bordeauxasso'!G:G,MATCH(B91,'Copy of webscraper_bordeauxasso'!B:B,0))} -> #N/A
A92: 2016 | B92: CENTRE D'INFORMATION JEUNESSE AQUITAINE - CIJA | C92: 49000 | D92: Locaux, matériel pour manifestations | F92: {=INDEX('Copy of webscraper_bordeauxasso'!G:G,MATCH(B92,'Copy of webscraper_bordeauxasso'!B:B,0))} -> #N/A
A93: 2016 | B93: ECOLE DE CIRQUE DE BORDEAUX, CENTRE CULTUREL DES ARTS DU CIRQUE | C93: 46500 | D93: Locaux | F93: {=INDEX('Copy of webscraper_bordeauxasso'!G:G,MATCH(B93,'Copy of webscraper_bordeauxasso'!B:B,0))} -> #N/A
A94: 2016 | B94: MAISON DE NOLAN | C94: 46000 | F94: {=INDEX('Copy of webscraper_bordeauxasso'!G:G,MATCH(B94,'Copy of webscraper_bordeauxasso'!B:B,0))} -> #N/A
A95: 2016 | B95: ASSOCIATION GIRONDINE D'EDUCATION SPECIALISEE ET DE PREVENTION SOCIALE - AGEP | C95: 45400 | D95: Locaux | F95: {=INDEX('Copy of webscraper_bordeauxasso'!G:G,MATCH(B95,'Copy of webscraper_bordeauxasso'!B:B,0))} -> #N/A
A96: 2016 | B96: ATELIER GRAPHITE | C96: 44200 | D96: Locaux | F96: {=INDEX('Copy of webscraper_bordeauxasso'!G:G,MATCH(B96,'Copy of webscraper_bordeauxasso'!B:B,0))} -> #N/A
A97: 2016 | B97: COMPAGNIE DES MARCHES DE L'ETE | C97: 41500 | D97: Communication, locaux, matériel pour manifestations | F97: {=INDEX('Copy of webscraper_bordeauxasso'!G:G,MATCH(B97,'Copy of webscraper_bordeauxasso'!B:B,0))} -> #N/A
A98: 2016 | B98: MUSIQUES DE NUIT - DIFFUSION | C98: 40700 | D98: Communication, matériel pour manifestations | F98: {=INDEX('Copy of webscraper_bordeauxasso'!G:G,MATCH(B98,'Copy of webscraper_bordeauxasso'!B:B,0))} -> #N/A
A99: 2016 | B99: CONGRES ET EXPOSITIONS DE BORDEAUX | C99: 40000 | D99: Communication, matériel pour manifestations | F99: {=INDEX('Copy of webscraper_bordeauxasso'!G:G,MATCH(B99,'Copy of webscraper_bordeauxasso'!B:B,0))} -> #N/A
A100: 2016 | B100: ASSOCIATION PROMOTION INSERTION SPORT EN AQUITAINE - APIS | C100: 37754 | D100: Equipements sportifs, matériel pour manifestations | F100: {=INDEX('Copy of webscraper_bordeauxasso'!G:G,MATCH(B100,'Copy of webscraper_bordeauxasso'!B:B,0))} -> #N/A
...

Sheet Pivot Table 1

Sheet Copy of webscraper_bordeauxasso
A1: web-scraper-start-url | B1: nom | C1: description | D1: adresse | E1: code postal | F1: telephone | G1: president | H1: site web | I1: categorie
A2: https://assos.bordeaux.fr/association/detail/1857 | B2: PERCAL TANGO | C2: Promouvoir la culture argentine à travers la musique, la danse, le théâtre. Création et vente des spectacles vivants. | D2: 86 Cours Victor Hugo | E2: 33000 | F2: 05 40 05 22 45 | G2: null | H2: null | I2: null
A3: https://assos.bordeaux.fr/association/detail/634 | B3: ARTISANS DU MONDE BORDEAUX - ADM | C3: Promouvoir le commerce équitable afin de permettre aux producteurs de pays ou régions défavorisés de vivre dignement de leur travail et être acteur de leur développement. Permettre aux consommateurs d'être informés sur les dysfonctionnements du commerce international. Contribuer à changer les mécanismes du commerce international | D3: 30 rue du Parlement Saint Pierre | E3: 33000 | F3: 05 56 44 23 33 | G3: null | H3: admbordeaux.org | I3: Entraide, solidarité, humanitaire
A4: https://assos.bordeaux.fr/association/detail/955 | B4: CERCLE PHILATÉLIQUE BORDEAUX AQUITAINE - CPBA | C4: Association philatélique (collection de timbres) et marcophile (marques postales) atteignant une dizaine d'années d'existence forte de 160 membres actifs. Cette association est ouverte à tous les philatélistes débutants ou confirmés, de tous les âges. Ses adhérents ont la possibilité de se réunir pour échanger et chercher des pièces manquantes à leurs collections, 4 samedis par mois. | D4: 8 Rue de Blois Chez M. Langella | E4: 33600 | F4: 05 56 07 24 64 | G4: Gérard Langella | H4: null | I4: Loisirs
A5: https://assos.bordeaux.fr/association/detail/588 | B5: ALLO AMIANTE | C5: Défense des victimes de l'amiante et des victimes de maladies professionnelles faisant suite à une exposition aux autres agents cancérigènes ; prévention chez les particuliers et éradication de l'amiante | D5: 5 place, Amédée St Germain | E5: 33800 | F5: 05 56 91 60 69 | G5: Georges ARNAUDEAU | H5: null | I5: Santé, bien-être
A6: https://assos.bordeaux.fr/association/detail/680 | B6: CENTRE ACCUEIL CONSULTATION INFORMATION SEXUALITÉ - CACIS | C6: Dans une démarche d’éducation populaire, le CACIS se donne pour finalité de permettre à toute personne, jeune ou adulte, de trouver les moyens de vivre sa sexualité dans notre société et d’agir contre toute forme d’exclusion liée à la santé, à la sexualité et au genre. | D6: Place de l'Europe BP 44 | E6: 33030 | F6: 05 56 39 11 69 | G6: Brigitte Tandonnet | H6: cacis-pro.fr | I6: Santé, bien-être
A7: https://assos.bordeaux.fr/association/detail/1132 | B7: HANDI CAP NOUVELLE AQUITAINE - HCNA | C7: Handi CAP Nouvelle Aquitaine est une association loi 1901 qui a pour objet d'informer les personnes touchées et concernées par le handicap ou la perte d'autonomie sur les loisirs accessibles des secteurs du tourisme, de la culture, du sport présents en Nouvelle Aquitaine. Elle fait coopérer les partenaires de ces secteurs pour collecter et organiser la diffusion de ces informations. | D7: 436 av de Verdun | E7: 33700 | F7: 05 56 12 39 39 | G7: Patrick TREINS | H7: null | I7: null
A8: https://assos.bordeaux.fr/association/detail/1394 | B8: ASSOCIATION DES SAHRAOUIS À BORDEAUX - ASB | C8: Notre association a pour but de faire connaitre et reconnaître le peuple du Sahara Occidental, son histoire, sa culture, sa vie, son territoire et ses ressources auprès de l'opinion française et internationale. Mais aussi de soutenir les sahraouis dans les difficultés matérielles quotidiennes et dans la lutte pacifique vers la résolution du problème de décolonisation de leur pays. | D8: 9 bis cours Edouard Vaillant | E8: 33300 | F8: 06 05 90 55 41 | G8: Mohamed Salem Mohamed Brahim | H8: null | I8: Culture
A9: https://assos.bordeaux.fr/association/detail/1820 | B9: LES CRAYONNEUSES | C9: Action de médiation artistique, culturelle, bien-être. Création d'ouvrages et objets papiers. | D9: 3 chemin du Grand Port | E9: 33880 | F9: 06 87 19 99 02 | G9: null | H9: lescrayonneuses.com | I9: Santé, bien-être
A10: https://assos.bordeaux.fr/association/detail/515 | B10: OPÉRA BASTIDE - OB | C10: la compagnie Opéra Bastide représentait initialement un espace de création où l'apprentissage du métier se fait immédiatement par la scène, au contact du public, en dehors du cadre institutionnel. | D10: BP 24 BP 24 | E10: 33034 | F10: 06 58 52 19 58 | G10: null | H10: null | I10: Culture
A11: https://assos.bordeaux.fr/association/detail/713 | B11: ASSOCIATION DES AMIS D’ELIANE LAVAIL - AMIDEL | D11: pas d'adresse | G11: null | H11: null | I11: null
A12: https://assos.bordeaux.fr/association/detail/615 | B12: MAM'AN LES TI'BATEAUX | C12: L’objet de l’association de maison d’assistant(e)s maternel(le)s est le suivant : Création, ouverture et gestion d'une maison d'assistant(e)s maternel(le)s (M.A.M.) avec un projet de mixité dans l'accueil d'enfants non porteurs de handicaps âgés de deux mois et demi à quatre ans et d'enfants porteurs de handicaps ou atteints d'une maladie chronique âgés de deux mois et demi à six ans. | D12: 06 Place Philippe Lebon | E12: 33300 | F12: 06 79 08 95 93 | G12: Christine MOUNIER | I12: Education - Enfance - Jeunesse - Vie étudiante
A13: https://assos.bordeaux.fr/association/detail/1405 | B13: WINE WILD WEST | C13: L'association Wine Wild West a pour objet : l’organisation et la promotion d’un rassemblement annuel de danseurs de west coast swing en région bordelaise dénommé Wine Wild West. Ce rassemblement est un festival qui comprend des cours de danse et soirées de west coast swing. De plus le festival propose des découvertes œnologiques et de spécialités Bordelaises. | D13: 10 impasse Manes Chez Mme Dubernet | E13: 33110 | F13: 06 52 06 18 13 | G13: null | H13: www.winewildwest-bordeaux.fr | I13: Culture
A14: https://assos.bordeaux.fr/association/detail/1194 | B14: UNION SAINT-BRUNO - USB | C14: Favoriser la pratique du sport sous toutes ses formes au titre du loisir et/ou de la compétition. | D14: 49 rue Brizard | E14: 33000 | F14: 05 56 96 33 53 | G14: null | H14: www.saint-bruno.org | I14: Sport
A15: https://assos.bordeaux.fr/association/detail/1053 | B15: BXA - ESPRIT VOILE - BXA EV | C15: Proposer la découverte et le perfectionnement à la voile au départ de Bordeaux sur l'estuaire de la Gironde avec le voilier habitable de l’association (7,5 m ESTE 24). Développer, promouvoir et favoriser des activités à caractère culturel et sportif dans le domaine du nautisme avec comme champ d’action les bassins à flot de Bordeaux, la ville de Bordeaux et au delà. | D15: Bld Alfred DANEY Quai ouest Bassin à flot n° 2 | E15: 33300 | F15: 07 69 17 50 70 | G15: null | H15: www.bxaespritvoile.fr | I15: Sport
A16: https://assos.bordeaux.fr/association/detail/567 | B16: ASSOCIATION PARLECOUTER | C16: Enseigner l'apprentissage d'outils de communication bienveillante et respectueuse, basés sur l'écoute active, profonde et sans jugement, sur le développement de l'empathie, pour une meilleure compréhension de l'autre et de soi. L'association vise à créer des conditions favorables à l'éducation et l'accompagnement des enfants / adolescents, à instaurer des relations plus sereines en famille et en société. | D16: 11 rue du Palais Gallien, Appt A314 | E16: 33000 | F16: 06 78 66 97 33 | G16: null | H16: parlecouter.wixsite.com/bordeaux | I16: Education - Enfance - Jeunesse - Vie étudiante
A17: https://assos.bordeaux.fr/association/detail/1441 | B17: AIDOMI | C17: AIDOMI est une association d'aide et de soins à domicile organisée en Service Polyvalent d'Aide et de Soins à Domicile (SPASAD). Nos services accompagnent 24h /24h les personnes vulnérables et les proches aidants dans le maintien à domicile à travers des missions d'aide à domicile (entretien du domicile, préparation des repas, accompagnement à la vie sociale) et des soins infirmiers et d'hygiène. | D17: 22 rue professeur lannelongue | E17: 33300 | F17: 05 56 01 91 91 | G17: null | H17: aidomi.fr | I17: Santé, bien-être
A18: https://assos.bordeaux.fr/association/detail/796 | B18: ASSOCIATION FRANCO-JAPONAISE D'ÉCHANGES CULTURELS RIVAGES - RIVAGES | C18: L'association à pour but de développer les relations culturelles franco-japonaises pour un enrichissement mutuel par des actions de diffusion de la culture, du savoir faire et de l'art japonais (exposition, conférences, cours, pratiques artistiques et de bien être). | D18: 47 rue Jean Soula | E18: 33000 | F18: 05 47 29 56 30 | G18: null | H18: www.association-rivages.org | I18: Santé, bien-être
A19: https://assos.bordeaux.fr/association/detail/1317 | B19: PROMOFEMMES | C19: Insertion sociale, professionnelle, culturelle et citoyenne des femmes d’origine étrangère et de leur famille | D19: 10 rue Carpenteyre | E19: 33800 | F19: 05 56 94 64 07 | G19: null | H19: www.promofemmes.org | I19: Entraide, solidarité, humanitaire
A20: https://assos.bordeaux.fr/association/detail/1258 | B20: LE FESTIN | C20: Depuis près de trente ans, la revue le festin permet à un large public de découvrir les richesses artistiques du Sud-Ouest. Elle est aujourd’hui reconnue comme la première publication culturelle et touristique de la région. Du local à l’universel, des monuments historiques à la création la plus contemporaine, la revue trimestrielle défend en effet une vision dynamique et originale de la culture. | D20: 176 rue Achard Zone d'activités Achard - Bât F1 | E20: 33300 | F20: 05 56 69 72 46 | G20: null | H20: null | I20: Culture
A21: https://assos.bordeaux.fr/association/detail/1227 | B21: LES DETRITIVORES - DTTV | D21: pas d'adresse | G21: null | H21: null | I21: null
A22: https://assos.bordeaux.fr/association/detail/711 | B22: FRÈRES DES HOMMES - FDH | C22: La Pépinière de la solidarité internationale (créée par Frères des Hommes) est un dispositif d’accueil et d’accompagnement ouvert à tous ceux qui veulent mener un projet de solidarité internationale. Il s’adresse également à ceux qui souhaitent accompagner un ou plusieurs porteurs de projet dans leur démarche en devenant tuteur bénévole. | D22: 2 rue de Savoie 75006 Paris | E22: 33 | F22: 01 55 42 62 62 | G22: null | H22: www.fdh.org | I22: Entraide, solidarité, humanitaire
A23: https://assos.bordeaux.fr/association/detail/974 | B23: PHILOSPHÈRES | C23: Ouvrir un espace de réflexion philosophique aux enfants, adolescents, adultes : la proposition s’adresse à tous et s’inscrit dans une démarche culturelle durable et solidaire. Ateliers à visée philosophique pour enfants, pour adultes, événements sur la place publique, projet éditorial sur la mémoire, cinéphilo, écriture & poésie... La philosophie est un « terreau » qui favorise une existence harmonieuse pour tous. | D23: 6 rue Gaspard philippe | E23: 33800 | F23: 06 77 60 53 90 | G23: null | H23: www.philospheres.org | I23: Vivre ensemble, vie quotidienne
A24: https://assos.bordeaux.fr/association/detail/1199 | B24: UNION BORDEAUX MÉTROPOLE - UBM | C24: La présente association, sans but lucratif, a pour objet la pratique et l'organisation de toutes activités sportives, éducatives, culturelles, de loisirs, bien-être, gastronomiques. L’association est ouverte aux agents de la Mairie de Bordeaux, de la Métropole de Bordeaux (EPCI), et des communes membres de la Métropole, actifs et retraités ainsi qu’à leurs ayants droit et extérieurs (article 5). | D24: Hôtel de Bordeaux métropole Esplanade Charles de Gaulle | E24: 33045 | F24: 05 57 20 70 56 | G24: MARC JOKIEL | H24: null | I24: Loisirs
A25: https://assos.bordeaux.fr/association/detail/862 | B25: LES BALADES ALTERNATIVES | C25: L'Alternative Urbaine Bordeaux propose des balades pédestres alternatives à impact positif pour le territoire. D'une part, elles sortent des sentiers touristiques habituels en mettant en valeur des quartiers dits "populaires" ; D'autre part parce que ces balades sont animées par des "éclaireurs urbains" en insertion professionnelle que nous formons et rémunérons dans le cadre d'une activité tremplin vers l'emploi. | D25: 40 rue Laffiteau Chez Astrolabe | E25: 33800 | F25: 07 67 65 24 84 | G25: null | H25: bordeaux.alternative-urbaine.com | I25: Culture
A26: https://assos.bordeaux.fr/association/detail/1503 | B26: TEST 1809 | C26: Association test | D26: Rue Claude Bonnier | E26: 33000 | F26: 05 10 10 34 64 | G26: null | H26: null | I26: Vivre ensemble, vie quotidienne
A27: https://assos.bordeaux.fr/association/detail/598 | B27: ASSOCIATION ODYSSÉE | C27: Contribuer à l'engagement et à la participation de tous, pour renforcer la citoyenneté européenne et l'émergence de « citoyens du monde » Donner des clés de lecture pour appréhender la diversité et la complexité du monde actuel et développer l'apprentissage interculturel en promouvant et en mettant en œuvre des échanges européens et internationaux Faciliter le vivre ensemble et le travailler ensemble | D27: 5 rue Marengo | E27: 33000 | F27: 06 09 46 33 14 | G27: Elisabeth SILVA | H27: www.associationodyssee.fr | I27: Education - Enfance - Jeunesse - Vie étudiante
A28: https://assos.bordeaux.fr/association/detail/782 | B28: LA CLÉ DES ONDES | C28: Ouverte à toutes et tous, la Clé des Ondes est la radio qui se mouille pour qu'il fasse beau. Elle se fait l'écho du mouvement culturel, social, associatif, environnemental. D'ici et d'ailleurs, de toutes les couleurs, de toutes les nationalités, de toutes les musiques, de tout ce qui bouge, elle ouvre ses micros aux sans-voix. Elle s'écoute sur le 90.10 en FM et sur lacdo.org. | D28: 71 cours Edouard Vaillant | E28: 33300 | F28: 05 56 39 87 57 | G28: Gilbert Hanna | H28: www.lacdo.org | I28: Vivre ensemble, vie quotidienne
A29: https://assos.bordeaux.fr/association/detail/1042 | B29: OPTIMOMES LOISIRS | C29: Favoriser l'esprit de découverte chez les jeunes en leur proposant des programmes d'activités variées (Culture, sport, nature et science) ; promouvoir la pratique des activités sportives, artistiques, scientifiques et de nature en proposant la création de structures accueils ( écoles élémentaires/maternelles,CE) ; promouvoir grâce à des pratiques ludiques, la découverte de l'environnement auprès des enfants. | D29: 10 rue de la Moulinatte | E29: 33130 | F29: 05 56 85 53 14 | G29: null | H29: optimomesloisirs.com | I29: Education - Enfance - Jeunesse - Vie étudiante
A30: https://assos.bordeaux.fr/association/detail/1275 | B30: ATELIER D'ÉCO SOLIDAIRE - ADS | C30: La Recyclerie créative de Bordeaux est depuis 2010 un des leviers de l’innovation sociale territoriale dans la réutilisation de matières, objets et mobilier dont les usagers, les entreprises et les collectivités veulent se débarrasser. Par le travail croisé de salariés, de bénévoles de tous âges et de stagiaires de tous horizons, elle alimente une expérimentation concrète et et prône un retour au « bon sens ». | D30: 7 rue la Motte Picquet | E30: 33300 | F30: 05 56 10 46 19 | G30: null | H30: null | I30: Cadre de vie environnement
A31: https://assos.bordeaux.fr/association/detail/626 | B31: HÉLIOS EVENEMENTS - O S G | C31: Cette association a pour but de promouvoir et de développer les pratiques musicales : par la production de spectacles vivants les "Mini concerts'' comprenant la participation de l’orchestre symphonique de Gironde et de son activité de diffusion d’artistes ; par l’édition de supports informatifs et pédagogiques ; par l’organisation d’actions de formation musicale en favorisant les pratiques amateurs | D31: 2 rue Frédéric Bastiat | E31: 33100 | F31: 06 11 10 03 77 | G31: null | H31: orchestresymphoniquedegironde.fr | I31: Culture
A32: https://assos.bordeaux.fr/association/detail/1410 | B32: RIRE EN-JE - CLUB DE RIRE BX | C32: Amélioration du mieux être et des relations humaines notamment en faisant connaitre la méthode du Rire sans raison du Dr Kataria afin d'apporter de la joie de vivre, de la bonne humeur, et du bien être ; en connectant les personnes à travers le rire ; en trouvant du bonheur à rendre les gens heureux et en apportant de l'amour inconditionnel. | D32: 36 allée Haussmann | E32: 33300 | F32: 06 12 29 51 96 | G32: Pascale Senon | I32: Santé, bien-être
A33: https://assos.bordeaux.fr/association/detail/1576 | B33: ASSOCIATION FRANÇAISE DE RUGBY SUBAQUATIQUE - AFRS | C33: Développer la pratique du rugby subaquatique en France et favoriser la participation à des compétitions nationales et internationales. | D33: Rue Kléber | E33: 33800 | F33: 06 24 40 80 30 | G33: Anaïs De Chaumont | H33: null | I33: Sport
A34: https://assos.bordeaux.fr/association/detail/1734 | B34: LA CASSETTE | C34: La Cassette promeut I'art & la culture, crée des échanges sociaux & culturels, organise du spectacle vivant, des expositions, aide & conseille à la production musicale et le spectacle, conseille les lieux de diffusion à la programmation, résidence artistiques, accompagnement à l'enregistrement audio, accompagnement à la réalisation de vidéos, développement de projets artistiques... | D34: 55 rue Galin | E34: 33100 | F34: 06 84 31 45 04 | G34: milos ares asian teran | H34: null | I34: Culture
A35: https://assos.bordeaux.fr/association/detail/555 | B35: PRATIKABLE - PTK | C35: L'association Pratikable a pour but de valoriser et promouvoir le handicap à travers les sports de glisse et les sports à sensation. | D35: 13 Rue Charles Perrault | E35: 33370 | F35: 06 45 86 91 69 | G35: Wilfried Panatier | H35: www.pratikable.com | I35: Sport
A36: https://assos.bordeaux.fr/association/detail/1182 | B36: CULTIVER L'ÉQUILIBRE | C36: Accompagner, transmettre et promouvoir auprès de tout public différentes pratiques et techniques ayant pour objectif d’améliorer la santé (état de bien-être total physique, mental et social) et de permettre le développement personnel des personnes. Créer une dynamique de partage, d’échange et de mise en réseau de différents professionnels proposant ces pratiques. | D36: 147 avenue de Labarde | E36: 33300 | F36: 06 62 44 90 99 | G36: null | I36: Santé, bien-être
A37: https://assos.bordeaux.fr/association/detail/949 | B37: MOUVEMENT LE CRI | C37: Le Cri a pour objet de lutter contre toute forme de violences en particulier celles liées au système prostitutionnel. Elle se fixe une triple mission de prévention, d’information et de médiation. | D37: 58, rue Schoelcher | E37: 33300 | F37: 05 56 39 05 96 | G37: null | H37: null | I37: null
A38: https://assos.bordeaux.fr/association/detail/668 | B38: FÉDÉRATION DES RADIOS ASSOCIATIVES DE LA GIRONDE - FEDERA 33 | C38: Établir des échanges entre les radios, par des rencontres avec thème (échange de programmes, nouvelles technologies et numérique, gestion administrative, fonction employeur, droits d’auteur…) et en créer les outils de mise en œuvre. Aider les radios à la constitution des nombreux dossiers administratifs. Intervenir auprès de radios en difficulté par le conseil auprès de leurs instances dirigeantes. | D38: 153 rue David Johnston | E38: 33000 | F38: 06 52 84 62 80 | G38: Nicole Teyssier | H38: www.federa33.org/la-federa33 | I38: Culture
A39: https://assos.bordeaux.fr/association/detail/511 | B39: CALIXTE COEUR DE BASTIDE | C39: l association a pour but de créer et développer des animations et événements ,mener des réflexions,pour dynamiser la place CALIXTE CAMELLE et son quartier,en renforçant le lien social.De part son objet, l association peut être emmenée à exercer des activités économiques. | D39: le pti salon 60 rue bonnefin | E39: 33100 | F39: 06 61 18 87 34 | G39: null | H39: Facebook Facebook | I39: Vivre ensemble, vie quotidienne
A40: https://assos.bordeaux.fr/association/detail/982 | B40: LES PINSONS | C40: L'association Les Pinsons gère l'Institut Pinsons (première structure passerelle d'accueil des 2/6 ans inspirée de l'approche éducative et pédagogique de Reggio Emilia et du modèle scandinave de la petite enfance) et les ateliers Let's (le meilleur des pédagogies actives - Montessori, Reggio, Fröbel - associés à nos ateliers ludo-éducatifs : Code et robotique, cuisine, jardinage, jeux de société, arts plastiques...) | D40: 6 rue Jean Bedouret | E40: 33100 | F40: 06 95 48 28 48 | G40: Adeline Charneau | H40: www.institutpinsons.com | I40: Education - Enfance - Jeunesse - Vie étudiante
A41: https://assos.bordeaux.fr/association/detail/1307 | B41: DYNAMIC KARATE BORDEAUX - DKB | C41: L'association Dynamic Karate Bordeaux a pour objet de développer le karate do shotokan et les valeurs intrinsèques liées au Dojo Kun | D41: 21 bis avenue de brivazac | E41: 33600 | F41: 06 17 64 85 32 | G41: null | I41: Sport
A42: https://assos.bordeaux.fr/association/detail/1166 | B42: ASSOCIATION EXPRESSIONS | C42: L’association Expression est un lieu de pratiques culturelles et artistiques. Elle propose des ateliers hebdomadaires et mensuels. Elle regroupe sur un même lieu la danse, le yoga, la peinture, la sophrologie, le tissage à partir de matériaux de recyclage et le travail corporel. Elle offre un espace propice à la création dans un cadre apaisant et atypique au cœur de Bordeaux, dans le quartier Fondaudège. | D42: 23 impasse Sully | E42: 33000 | F42: 05 56 01 12 41 | G42: null | H42: www.associationexpression.com | I42: Culture
A43: https://assos.bordeaux.fr/association/detail/1669 | B43: ALLIANCE 33 - ALLIANCE 33 | C43: accompagnement bénévole des personnes gravement malades ou en fin de vie et de leurs proches, dans le cadre de la loi du 9 juin 1999 sur les soins palliatifs, en vue de soulager les souffrances physiques, morales, psychologiques et spirituelles , en institution ou à domicile, ou à l'antenne pour les soutiens et suivis de deuils. | D43: 380 cours de la Somme | E43: 33800 | F43: 05 56 43 07 07 | G43: null | H43: www.alliance.asso.fr | I43: Entraide, solidarité, humanitaire
A44: https://assos.bordeaux.fr/association/detail/593 | B44: LE LABO DES HISTOIRES NOUVELLE-AQUITAINE | D44: pas d'adresse | G44: null | H44: null | I44: null
A45: https://assos.bordeaux.fr/association/detail/1072 | B45: ACTE | C45: Association d'aide au retour à l'emploi destinée principalement aux cadres sans emploi ou en reconversion professionnelle. Il s'agit d'un accompagnement individualisé et personnalisé jusqu'au retour à l'emploi. | D45: 6 rue de Ségur | E45: 33000 | F45: 05 56 81 77 59 | G45: null | H45: htpp:/www.acte-asso.fr | I45: null
A46: https://assos.bordeaux.fr/association/detail/1706 | B46: FEARLESS CULTURE | C46: Notre objectif est de venir en aide aux demandeurs d’asile et aux réfugiés grâce à l’organisation d’événements culturels dont les bénéfices sont reversés à des associations ou centres d’accueil de réfugiés. | D46: 14 rue Saint Nicolas | E46: 33800 | F46: 06 25 91 24 64 | G46: Marylou Hallaf | I46: Entraide, solidarité, humanitaire
A47: https://assos.bordeaux.fr/association/detail/678 | B47: TANGO NOMADE - TANGO NOMADE | C47: Promouvoir la connaissance de la danse et de permettre des échanges culturels par ce biais. Cette association a une finalité sportive culturelle et artistique et souhaite par ce biais lutter contre toutes formes de discriminations. Mettre en place des spectacles et à animer tous types de manifestations sportives culturelles et artistiques. | D47: 17 allée Eugène Delacroix Apt 18 | E47: 33800 | F47: 06 83 79 62 63 | G47: Perrine NIVET | H47: tangonomade.com | I47: Culture
A48: https://assos.bordeaux.fr/association/detail/1090 | B48: GRAINES DE SOLIDARITÉ | C48: Association humanitaire dont l'objectif est d'apporter une aide alimentaire aux personnes et aux familles en grande difficulté. Cette aide prend la forme de distribution de colis alimentaires hebdomadaires destinés à des personnes isolées et à des familles, de couscous en période hivernale et de maraudes dans les rues de Bordeaux. Elle aide à l'insertion par le biais d'ateliers de langue et de cuisine du monde. | D48: 48, rue Kléber | E48: 33800 | F48: 06 50 52 40 52 | G48: Hanifa MZIZOUA | H48: grainesdesolidarite.e-monsite.com | I48: Entraide, solidarité, humanitaire
A49: https://assos.bordeaux.fr/association/detail/1128 | B49: ASSOCIATION SPORT EMPLOI - AES | C49: L'Association a pour but de faciliter l'accueil, l'information, l'orientation, la formaion, l'insertion et l'emploi de tout public par le biais de la pratique sportive | D49: pas d'adresse | G49: null | H49: null | I49: null
A50: https://assos.bordeaux.fr/association/detail/1025 | B50: SO COOPÉRATION | C50: SO Coopération est le Réseau Régional Multi-Acteurs (RRMA) pour la coopération et la solidarité internationales. ​ Sous l'acronyme ce qu'il faut retenir ; c'est l'espace qui est offert aux acteurs de la Nouvelle-Aquitaine, qu'ils soient associatifs, collectivités, universités, entreprises, établissement publics ou autres, pour s'informer, échanger, entreprendre des projets de coopération et de solidarité | D50: 10 Esplanade des Antilles, Maison des Sciences de l'Homme | E50: 33607 | F50: 05 56 84 45 68 | G50: null | H50: www.socooperation.org | I50: Entraide, solidarité, humanitaire
A51: https://assos.bordeaux.fr/association/detail/1163 | B51: ASSOCIATION DE SOUTIEN AUX INVENTIONS LIBRES / BANZAÏ LAB | D51: pas d'adresse | G51: null | H51: null | I51: null
A52: https://assos.bordeaux.fr/association/detail/1172 | B52: CRÉASSEMBLE - BXGOSPELACADEMY | C52: créer, développer et soutenir des événements et des projets alternatifs, culturels, artistiques, récréatifs et ou éducatifs comme moyens d’action pour l’épanouissement de l’individu, des groupes et des sociétés dans le respect de son environnement. | D52: 26, rue Marius Olivier | E52: 33130 | F52: 06 03 30 12 02 | G52: null | H52: bordeaux-gospel-academy.com | I52: Culture
A53: https://assos.bordeaux.fr/association/detail/1479 | B53: FRENCH TECH BORDEAUX | C53: L’association French Tech Bordeaux a pour but de développer la croissance des écosystèmes de startups et d’entreprises innovantes bordelaises et néo-aquitaines, avec 3 grandes ambitions : Fédérer et animer l’écosystème au service de la croissance ; Promouvoir et représenter les startups de Bordeaux et sa région ; Porter l’excellence française du label French Tech dans le territoire et à l’international. | D53: 20 Quai Lawton CS50100 | E53: 33300 | F53: 06 35 54 25 55 | G53: Jérôme LELEU | H53: www.frenchtechbordeaux.com | I53: Economie
A54: https://assos.bordeaux.fr/association/detail/892 | B54: ASSOCIATION PRENDRE SOIN DU LIEN - APSL | C54: L'association APSL s'adresse à un public de seniors. Elle propose "Le Lien'Aînés", de l'animation à domicile en groupe. Les sorties et rencontres proposées incluent le transport, pour des personnes vivant à domicile qui ne peuvent plus sortir seules de chez elles et qui sont en recherche de nouveaux contacts pour éviter la solitude. APSL organise aussi la "Mobil'Aînés", une marche en rolateurs, intergénérationnelle. | D54: 40 Allées d'Orléans Immeuble Le Splendide | E54: 33000 | F54: 06 75 01 40 81 | G54: null | I54: Vivre ensemble, vie quotidienne
A55: https://assos.bordeaux.fr/association/detail/1171 | B55: LE CHŒUR VOYAGEUR | C55: L’association a pour but de constituer une chorale et des ensembles instrumentaux afin de se produire en France et à l'étranger, dans le cadre de simples concerts, d'interventions culturelles mais aussi d'échanges avec d'autres chorales. | D55: 148 boulevard du Président Franklin Roosevelt | E55: 33800 | F55: 06 84 84 76 80 | G55: null | H55: lechoeurvoyageur.fr | I55: Culture
A56: https://assos.bordeaux.fr/association/detail/979 | B56: UNION SPORTIVE JEUNES DE SAINT-AUGUSTIN-CLUB PYRÉNÉES AQUITAINE - US-JSA-CPA | D56: pas d'adresse | G56: null | H56: null | I56: null
A57: https://assos.bordeaux.fr/association/detail/893 | B57: ASSOCIATION NATIONALE DES ASSISTANT(E)S MATERNEL(LE)S AGREE(E)S REUNI(E)S INTER-DEPARTEMENTALE - AMARID | C57: L’Association Nationale AMARID : Défense des Intérêts de l'enfant, Information aux parents concernant la profession de l'Assistant(e) Maternel(le) Droits et Devoirs des Assistant(e) Maternel(le),Droits et Devoirs des Parents, Faire EVOLUER la Profession d'Assistant(e) Maternel(le) | D57: 8 RUE DU CHASSELAS | E57: 33370 | F57: 05 56 32 58 24 | G57: null | H57: www.amarid.fr | I57: null
A58: https://assos.bordeaux.fr/association/detail/1365 | B58: SOLID'EARTH - SE | C58: Solid’Earth est l’association de développement durable et de solidarité internationale de l’école de commerce KEDGE Business School Campus de Bordeaux. L’association compte 85 membres et est ainsi la plus grande association du campus. Elle défend des valeurs fortes telles que le respect de l’environnement et de l’être humain, la solidarité et la diversité, ou encore la consommation responsable. | D58: 680 Cours de la libération KEDGE Business School | E58: 33405 | F58: 06 80 03 24 32 | G58: null | H58: www.solidearth.fr | I58: Entraide, solidarité, humanitaire
A59: https://assos.bordeaux.fr/association/detail/1754 | B59: LA BELLA BORDEAUX | C59: Promouvoir le patrimoine ainsi que la vie artistique et culturelle de la ville de Bordeaux par le biais d'expositions, rencontres, séminaires, ateliers et d'autres animations. Créer des actions de médiation culturelle et favoriser l'émergence de nouveaux talents. Organiser des événements artistiques et des sorties culturelles collectives pour ses membres. Encourager et soutenir la diversité culturelle. | D59: 169, rue Palais Gallien | E59: 33000 | F59: 06 89 69 68 38 | G59: Luciana M. Morgera | H59: null | I59: Culture
A60: https://assos.bordeaux.fr/association/detail/1250 | B60: CHORALE CHŒUR DES ECLUSES | C60: Nous sommes une chorale dynamique aimant chanter dans la bonne humeur. Notre répertoire est la variété française. Nous recrutons toutes voix. Il n' y a pas besoin de connaitre le solfège. Nous travaillons sur support d'enregistrement. Si vous aimez chanter et partager des moments conviviaux, n’hésitez pas à venir nous rejoindre tous les lundis soirs de 20h30 à 22h30 salle Simone Noailles au Grand Parc. | D60: 8 rue Maryse Bastié apt 14 | E60: 33300 | F60: 06 60 95 25 66 | G60: Sandra BOIRON | H60: null | I60: Culture
A61: https://assos.bordeaux.fr/association/detail/1381 | B61: KLAUS COMPAGNIE | C61: Association travaillant dans la culture inclusive (valides-handicapés). Création d’œuvres chorégraphiques (ballets). Organisation du Festival Mixamum (festival pluridisciplinaire mêlant des artistes valides et handicapés). Ateliers de danse contemporaine adaptée (valides et handicapés). Ateliers ponctuels de sensibilisation de la danse adaptée (valides et handicapés) | D61: 11 rue Erik Satie | E61: 33200 | F61: 06 09 44 46 70 | G61: null | H61: www.klauscompagnie.fr | I61: Culture
A62: https://assos.bordeaux.fr/association/detail/1630 | B62: ASSOCIATION MALINE | C62: Développer des projets artistiques, quels qu'ils soient, favoriser l’émergence de nouveaux talents par le soutien de la pratique amateur,défendre la diversité culturelle en soutenant des artistes de tout horizon,favoriser dans un cadre convivial la rencontre entre les populations, les professionnels et les amateurs,permettre l’accès au plus grand nombre en pratiquant le principe de la participation libre et adaptée. | D62: 8 Rue de Barsac | E62: 33800 | F62: 06 61 98 24 24 | G62: null | H62: associationmaline.wordpress.com | I62: Culture
A63: https://assos.bordeaux.fr/association/detail/1830 | B63: PHOENIX.UNIVERSEL - PHUN | D63: pas d'adresse | G63: null | H63: null | I63: null
A64: https://assos.bordeaux.fr/association/detail/676 | B64: LE CRAYON PAPOTE | C64: L'association le Crayon Papote à pour but de partager et faire découvrir le milieu de la création artistique et de sensibiliser à l'éco-responsabilité et au développement durable. | D64: 184 rue fondaudège | E64: 33000 | F64: 06 51 03 98 24 | G64: null | H64: www.lecrayonpapote.com | I64: Loisirs
A65: https://assos.bordeaux.fr/association/detail/739 | B65: ASSOCIATION POUR LA RECHERCHE EN PRÉVENTION PSYCHIQUE PRÉCOCE EN PÉRINATALITÉ - ARPPPP | D65: pas d'adresse | G65: null | H65: null | I65: null
A66: https://assos.bordeaux.fr/association/detail/675 | B66: LA LECHE LEAGUE GROUPE DE BORDEAUX - LLL FRANCE | C66: Aider les mères dans leur chemin d'allaitement, quel que soit leur projet, pour un jour ou plus. Leur apporter soutien, entraide, information récente et pertinente, ainsi que différents outils pour vivre sereinement leur allaitement, et remettre entre les mains des parents l'accompagnement de leur enfant. | D66: Impasse du grand Barrail | E66: 33710 | F66: 07 83 00 14 06 | G66: null | H66: www.lllfrance.org | I66: Santé, bien-être
A67: https://assos.bordeaux.fr/association/detail/961 | B67: CERCLE OENOPHILE AQUITAIN - COA | C67: L'association a pour objet principal de parfaire les connaissances oenologiques des adhérents | D67: 18 rue Auguste Merillon | E67: 33000 | F67: 05 56 96 51 98 | G67: Georges Laborde | H67: null | I67: Culture
A68: https://assos.bordeaux.fr/association/detail/614 | B68: DRÔLE DE SCÈNE | C68: notre café-théâtre est un lieu simple et chaleureux grâce à nos bénévoles. Notre programmation propose soit : des soirées comédie-club, soit des one man show, ou bien des spectacles pour le jeune public.Notre but est de promouvoir le spectacle vivant et de proposer aux spectateurs même les plus jeunes une programmation qualitative, dans un petit espace où la convivialité est naturelle. | D68: 164 rue Stéhélin | E68: 33200 | F68: 06 80 28 02 40 | G68: null | I68: Culture
A69: https://assos.bordeaux.fr/association/detail/1821 | B69: DEUX BOUTS | C69: Création de réseaux d'entraide où les aidés s'engagent à devenir aidants. Notre premier réseau, EDDIE s'adresse aux SDF. Nous inscrivons notre action dans le Plan Logement d'Abord en utilisant l'intermédiation locative, l'accompagnement pluridisciplinaire et la pair-aidance pour créer un processus de réinsertion accélérée. | D69: . | E69: 33000 | F69: 07 81 50 71 09 | G69: null | H69: deuxbouts.org | I69: Entraide, solidarité, humanitaire
A70: https://assos.bordeaux.fr/association/detail/1818 | B70: CENTRE DE VOILE DE BORDEAUX-LAC - CVBL | C70: Promotion et développement de la pratique de la voile, l’initiation, le perfectionnement à la pratique de la voile. Organisation de manifestations nautiques contribuant à l’animation du Lac de Bordeaux. | D70: Boulevard Jacques Chaban-Delmas | E70: 33520 | F70: 06 86 96 13 43 | G70: null | H70: voilebordeauxlac.fr | I70: Sport
A71: https://assos.bordeaux.fr/association/detail/1442 | B71: W568925635 | D71: pas d'adresse | G71: null | H71: null | I71: null
A72: https://assos.bordeaux.fr/association/detail/531 | B72: COLLECTIF 05/15 | C72: Proposer à tous les publics des randonnées, des courts séjours à vocation pédestre, mais également des visites, dans la région. L'association propose également des ateliers confort et bien-être (sophrologie), ainsi que des ateliers cuisine vietnamienne ! | D72: 31 rue Lachassaigne chez Mme DAO DUC Sylvie | E72: 33000 | F72: 06 45 04 57 24 | G72: null | I72: Sport
A73: https://assos.bordeaux.fr/association/detail/625 | B73: ASSOCIATION DES ANGOLAIS DE BORDEAUX - AAB | C73: Créer une synergie autor des problèmes sociaux ,culturels et économiques par l'accueil;Diffuser la langue Portugaise et les langues natives de l'Angola Umbundu,Kimbundu....; Favoriser une meilleure connaissance mutuelle entre l'Angola et la France ; Cours de danse traditionnelles Angolaises ; Organisation de manifestations culturelles , théâtre ,spectacles, récitals,expositions conférences. | D73: 12 Avenue des 40 Journaux appt 162 | E73: 33300 | F73: 06 05 83 19 95 | G73: null | H73: null | I73: Sport
A74: https://assos.bordeaux.fr/association/detail/838 | B74: ASSOCIATION POUR LE DON DE SANG BENEVOLE DE BORDEAUX ET ENVIRONS | C74: Promouvoir le don de sang bénévole Accueillir et informer les donneur de sang | D74: Residence de la mairie Bat 14 apt 9 | E74: 33130 | F74: 06 88 36 66 94 | G74: Sandrine DUPLACEAU | H74: null | I74: Santé, bien-être
A75: https://assos.bordeaux.fr/association/detail/820 | B75: CLUB LOISIRS AQUITAINE CULTURE - CLAC | C75: L'association œuvre pour la découverte de notre environnement proche et pour la culture. Elle favorise les liens nature/culture en proposant des ateliers, stages, balades à destination de tous les publics. Elle s'appuie sur des approches pédagogiques créatives et innovantes, notamment celles venant des pays scandinaves. | D75: 3 rue de Tauzia | E75: 33800 | F75: 06 87 38 99 08 | G75: null | I75: Culture
A76: https://assos.bordeaux.fr/association/detail/778 | B76: SALSA WITH S - SWS | C76: L’association a pour objet l’éveil et l’expression corporelle dans les danses latines et tropicales. | D76: 62bis rue paul antin | E76: 33800 | F76: 06 87 46 12 72 | G76: carole Couture | I76: Sport
A77: https://assos.bordeaux.fr/association/detail/805 | B77: COMPAGNIE LEITMOTIV | C77: La Compagnie Leitmotiv à Bordeaux a pour vocation d'être la compagnie de toutes et de tous, permettant à tout le monde de pratiquer une activité théâtrale. Théâtre Humour ou théâtre plus traditionnel, nos cours vous sont ouverts... En scène ! | D77: 84 rue Amédée St Germain La Laiterie | E77: 33800 | F77: 06 26 39 30 40 | G77: null | H77: www.compagnie-leitmotiv.com | I77: Culture
A78: https://assos.bordeaux.fr/association/detail/1588 | B78: DÉFENSE DES RÉSIDENTS DES QUARTIERS BORDEAUX MÉTROPOLE - ADDR.DQBM | D78: pas d'adresse | G78: null | H78: null | I78: null
A79: https://assos.bordeaux.fr/association/detail/1255 | B79: WEJOB | C79: WeJOB propose des services d'insertion et de RH innovants, aux demandeurs d'emploi et aux entreprises. WeJOB associe des démarches collaboratives à de l'expertise et de l'accompagnement spécialisé. L'offre de WeJOB s'adresse aux personnes en recherche d'emploi et aux entreprises avec des programmes collectifs et individuels, des services de formation, de recrutement et de conseil. | D79: http://www.we-job.com/ | E79: 33000 | F79: 06 58 72 27 89 | G79: null | H79: www.we-job.com | I79: Emploi, insertion professionnelle, formation
A80: https://assos.bordeaux.fr/association/detail/673 | B80: ACADÉMIE KARATÉ YOGA BORDEAUX BASTIDE | C80: Association ayant pour but de promouvoir l'enseignement du karaté-do, du handi-karaté et du hatha-yoga pour tous mais aussi pour les futures mamans et les enfants, par le biais de l'activité physique sportive et du bien-être. | D80: 17 rue Calvimont Coté Cour | E80: 33100 | F80: 06 22 60 34 58 | G80: null | H80: www.hathayogasimplifie-bordeaux.fr | I80: Sport
A81: https://assos.bordeaux.fr/association/detail/1689 | B81: ENSEMBLE2GENERATIONS - E2G | C81: FAVORISER LES RELATIONS INTERGENERATIONNELLES AU TRAVERS DU LOGEMENT ET DE PARTAGES D'ACTIVITES | D81: 85 rue Camille GODARD | E81: 33000 | F81: 07 86 62 26 07 | G81: Ariane MOREAU | H81: null | I81: null
A82: https://assos.bordeaux.fr/association/detail/1149 | B82: ASTROLABE | C82: L 'association Astrolabe (Espace de Vie Sociale) propose de l'accompagnement à la scolarité, des loisirs, des activités familiales, des séjours pour tous. Elle fédère et participe à l'animation de la vie du quartier. Ses projets, activités et animations sont réalisées avec les habitants dans un esprit d'éducation populaire, d'innovation et de solidarité. | D82: 40 rue Laffiteau | E82: 33800 | F82: 05 56 85 74 59 | G82: Joël DUCOS | I82: Education - Enfance - Jeunesse - Vie étudiante
A83: https://assos.bordeaux.fr/association/detail/1827 | B83: LABO - ATELIERS & LIVRES POUR ENFANTS | D83: pas d'adresse | G83: null | H83: null | I83: null
A84: https://assos.bordeaux.fr/association/detail/1785 | B84: STUDIO CANOPÉE - SC | C84: Le Studio Canopée se donne pour mission de proposer des activités physiques douces centrées sur le thème du bien-être. Notre credo ? Proposer des cours collectifs de Pilates, Yoga et Marche Nordique en petits groupes afin de garantir un suivi et un accompagnement personnalisé pour chacun de nos adhérents. Envie d’en savoir plus ? N’hésitez pas à nous rencontrer ! | D84: 28 avenue André Reinson, Résidence Canopée, Bat F Appt 617, 4è étage | E84: 33300 | F84: 07 89 63 06 34 | G84: Matthieu Robert | H84: null | I84: Sport
A85: https://assos.bordeaux.fr/association/detail/965 | B85: ASSOCIATION DANZA EVOLUCION | C85: Danza Evolucion est une association loi 1901 qui a pour but de promouvoir la danse dans toute sa diversité sur le Bassin d'Arcachon à Biganos. Ori Tahiti (danse polynésienne) avec sa troupe Manava Ori Tahiti , Boogie-woogie, Sévillanes, Bachata Reggaeton et Ukulélé ! | D85: 106 Rue Joseph cruchon | E85: 33380 | F85: 06 44 18 51 92 | G85: Marie Christine Legrand | H85: www.danzaevolucion.fr/m | I85: Culture
A86: https://assos.bordeaux.fr/association/detail/1323 | B86: ASSOCIATION NATIONALE DES MEMBRES DE L’ORDRE NATIONAL DU MÉRITE - ANMONM | C86: Buts de l'association : assurer le rayonnement et le prestige de l’Ordre en tous lieux ; maintenir et développer les valeurs morales et civiques liées à la qualité de compagnon ; renforcer les liens de solidarité entre les membres de l’Ordre et pratiquer l’entraide ; participer au devoir national de mémoire ; développer l'esprit de la citoyenneté et du civisme. | D86: 185 Cours Balguerie Stuttenberg Appartement 124 | E86: 33300 | F86: 06 22 53 93 15 | G86: Bernard Miot | H86: null | I86: Vivre ensemble, vie quotidienne
A87: https://assos.bordeaux.fr/association/detail/1243 | B87: HANDI'CHIENS | C87: HANDI’CHIENS est une association régie, créée en 1989 et reconnue d’utilité publique en 2012. HANDI’CHIENS a pour mission d’éduquer et de remettre GRATUITEMENT des Chiens d’Assistance à des personnes en situation de handicap. Grâce à la complicité qui l’unit à l’homme et aux 50 commandes qu'il maitrise, un “handi’chien” offre à son bénéficiaire une meilleure autonomie, plus de liberté, et favorise le lien social. | D87: 13 rue l'abbé Groult 75015 PARIS | E87: 33 | F87: 01 45 86 58 88 | G87: null | H87: www.handichiens.org | I87: null
A88: https://assos.bordeaux.fr/association/detail/1161 | B88: MAISON DES SOURDS DE LA GIRONDE - MS33 | C88: Diffuser et promouvoir la culture sourd à Bordeaux et en Gironde. Aide à la personne, conférences et ateliers, cours de Langue des Signes Française. | D88: 406 boulevard du président Wilson | E88: 33000 | F88: 06 59 41 90 23 | G88: Nathalie Verny | I88: Entraide, solidarité, humanitaire
A89: https://assos.bordeaux.fr/association/detail/956 | B89: LA VIE A DOMICILE -MAISON DE LA SANTÉ ET DES AIDANTS | C89: L'association se définit comme une plateforme de services à domicile qui permet l'orientation dans une filière de soin et d'aide, intégrée et complémentaire. Elle propose une réponse graduée aux besoins des personnes fragilisées par l'âge, la dépendance, le handicap ou la maladie Elle accompagne et soutient les aidants en offrant des services innovants et de répit | D89: 412 avenue de verdun | E89: 33700 | F89: 05 56 55 04 38 | G89: null | H89: www.viesantemerignac.fr | I89: Santé, bien-être
A90: https://assos.bordeaux.fr/association/detail/613 | B90: BORDEAUX BASTIDE BASKET | C90: Pratique du Basket-ball | D90: 96, rue de la Benauge | E90: 33100 | F90: 06 61 48 03 85 | G90: null | H90: null | I90: Sport
A91: https://assos.bordeaux.fr/association/detail/618 | B91: ORCHESTRE PAPAGENO | C91: L'Orchestre Papageno a été crée en 2007 et regroupe des musiciens amateurs (cordes, bois et cuivres) de tous les âges. Le groupe est dirigé par un chef professionnel, Nicolas Piquet, et propose un répertoire varié, essentiellement de musique classique et musique de films. L'Orchestre Papageno se produit lors de 10 concerts par an environ, et collabore avec d'autres orchestres et des écoles de musique. | D91: 19 place des Basques Addeo-Orchestre Papageno | E91: 33000 | F91: 06 20 79 07 11 | G91: Richard Albiach | H91: www.orchestrepapageno.com | I91: Culture
A92: https://assos.bordeaux.fr/association/detail/996 | B92: SECOURS POPULAIRE FÉDÉRATION DE GIRONDE - SPF | C92: Le secours populaire vient en aide aux personnes en difficultés en France et dans le monde: victime de la pauvreté et de la précarité, de l'exclusion. Généraliste de la solidarité: intervention sur l'urgence alimentaire, vestimentaire, action d'accompagnement des personnes, accès aux loisirs, vacances et différentes actions mises en oeuvre par des bénévoles. | D92: fédération du secours populaire 95 quai de paludate// 6 rue Belcier | E92: 33800 | F92: 05 56 92 79 92 | G92: null | H92: www.secourspopulaire.fr/33 | I92: Entraide, solidarité, humanitaire
A93: https://assos.bordeaux.fr/association/detail/1778 | B93: LES SOURCES | C93: Cours de yoga de l'énergie | D93: 1 avenue Brémontier | E93: 33950 | F93: 06 98 99 68 71 | G93: null | H93: energieyoga.com | I93: Sport
A94: https://assos.bordeaux.fr/association/detail/1044 | B94: LES FEES PAPILLONS | C94: CENTRE BEAUTE, BIEN-ETRE, ET ESTIME DE SOI, SOLIDAIRE La finalité de l'association LES FEES PAPILLONS est d'aider des Femmes en difficulté à (re)trouver la dignité, l'estime de soi, la confiance en soi et l'énergie indispensables pour leur bien-être, et leur insertion sociale et professionnelle. Les FEES sont des professionnelles bénévoles qui offrent ces soins et ateliers aux bénéficiaires: les PAPILLONS. | D94: Résidence du Lac, Apt 289, Entrée R, Avenue Laroque | E94: 33300 | F94: 05 56 29 56 34 | G94: Patricia CHAUFFOURIER | H94: www.lesfeespapillons.fr | I94: Santé, bien-être
A95: https://assos.bordeaux.fr/association/detail/1002 | B95: GIRONDINS DE BORDEAUX BASTIDE HANDBALL CLUB - GBBHBC | C95: Le développement et la promotion du handball par la pratique de ce sport à tous niveaux, la gestion et l'animation d’activités sportives donnant lieu à l'organisation de manifestations gratuites ou payantes et versement de rémunération, l'association peut également mener toutes les actions en relation avec son objet notamment de formation au profit de sportifs, ou sociales (sur Bordeaux Bastide et/ou métropole). | D95: 96 rue de la Benauge BP 14 | E95: 33100 | F95: 05 56 67 81 06 | G95: Christian Malichecq | H95: girondins-handball.clubeo.com | I95: Sport
A96: https://assos.bordeaux.fr/association/detail/1744 | B96: ASSOCIATION IMPRIMERIE DU LOUP - TYPOGRAPHIE | D96: pas d'adresse | G96: null | H96: null | I96: null
A97: https://assos.bordeaux.fr/association/detail/1065 | B97: ASSOCIATION GÉNÉRATION DUPATY - A.G. DUPATY | C97: Favoriser l'apprentissage , accompagner les adhérents et usagers dans l'accessibilité, découvrir et animer diverses actions éducatives, culturelles, artistiques, physiques et sportives, éduquer à l'environnement, à la citoyenneté, lutter contre les discriminations et favoriser les rencontres intergénérationnelles.Organiser à côté de l'ECOLE des actions sur les temps périscolaires et postscolaires | D97: 74 rue Joséphine Ecole Dupaty | E97: 33300 | F97: 07 71 80 07 22 | G97: null | H97: null | I97: Vivre ensemble, vie quotidienne
A98: https://assos.bordeaux.fr/association/detail/685 | B98: ACT'IMAGE | C98: L’association Act'Image a pour objectif de promouvoir la création photographique, de développer des actions culturelles liées à la photographie et de favoriser sa diffusion. Les actions mises en places permettent d’alimenter le dispositif culturel du territoire afin de le valoriser et de permettre aux citoyens de trouver un épanouissement culturel au travers de la photographie. | D98: 72, rue Emile Fourcand | E98: 33000 | F98: 06 09 73 05 80 | G98: null | H98: www.act-image.fr | I98: Culture
A99: https://assos.bordeaux.fr/association/detail/1520 | B99: ASSOCIATION L'IRRÉGULIÈRE | C99: L’IRRÉGULIÈRE conçoit et organise des événements culturels qui visent à favoriser la mixité des domaines artistiques, soutenir et promouvoir des artistes et collectifs bordelais et d’origines diverses. Elle propose régulièrement des actions de médiation culturelle pour sensibiliser le public à la création (manifestations portées par l'asso, commandes ou partenariats avec différentes structures publiques ou privées). | D99: 15 place Renaudel | E99: 33800 | F99: 06 42 40 96 65 | G99: null | H99: null | I99: Culture
A100: https://assos.bordeaux.fr/association/detail/1378 | B100: COMPAGNIE ARTISTIQUE YAKKA - CIE YAKKA | C100: La compagnie artistique « Yakka » a été créée pour permettre aux artistes de la Francophonie de travailler ensemble autour de projets de création artistique mêlant différents corps de métiers existants dans l’art . La dynamique de la compagnie se base sur le désir de trouver, travailler et faire partager aux publics, des œuvres d’ auteurs issus du paysage littéraire francophone. | D100: 60 cours Aristide Briand | E100: 33000 | F100: 07 81 73 45 84 | G100: null | H100: cieyakka.com | I100: Culture
...
